Workbook
Name ACC: #REF!
Name ACC: #REF!
Name ACC: #REF!
Name ACC: #REF!
Name ACCOUNT: #REF!
Name ACCOUNT: #REF!
Name ACCOUNT: #REF!
Name ACCOUNT: #REF!
Name AKUN: #REF!
Name AKUN: #REF!
Name AKUN: #REF!
Name AKUN: #REF!
Name AKUNDUA: #REF!
Name AKUNDUA: #REF!
Name AKUNDUA: #REF!
Name AKUNDUA: #REF!
Name AKUNEMPAT: #REF!
Name AKUNEMPAT: #REF!
Name AKUNEMPAT: #REF!
Name AKUNEMPAT: #REF!
Name akunlima: [1]AKUNLIMA!$A$2:$C$310
Name AKUNTIGA: #REF!
Name AKUNTIGA: #REF!
Name AKUNTIGA: #REF!
Name AKUNTIGA: #REF!
Name asa: #REF!
Name asa: #REF!
Name JAN: #REF!
Name JAN: #REF!
Name JAN: #REF!
Name JAN: #REF!
Name OMSET: #REF!
Name OMSET: #REF!
Name OMSET: #REF!
Name OMSET: #REF!

Sheet NR
B2: NERACA
B3: K K C S
B4: TAHUN 2023 - 2026
B6: No | C6: Uraian | D6: PER | E6: PER | F6: PER | G6: PER | H6: PER | I6: No | J6: Uraian | K6: =D6 -> PER | L6: =E6 -> PER | M6: =F6 -> PER | N6: =G6 -> PER | O6: =H6 -> PER
D7: 31 Desember 2022 | E7: 31 Desember 2023 | F7: 31 Desember 2024 | G7: 31 Desember 2025 | H7: 31 Januari 2026 | K7: =D7 -> 31 Desember 2022 | L7: =E7 -> 31 Desember 2023 | M7: =F7 -> 31 Desember 2024 | N7: =G7 -> 31 Desember 2025 | O7: =H7 -> 31 Januari 2026
B8: I | C8: Aset Lancar | I8: VII | J8: Liabilitas Jangka Pendek
C9: Kas | D9: 22964481 | E9: 5751013.7 | F9: 1788563.7 | G9: 8851508.7 | H9: ='WS Trial balance'!L7 -> 8458508.7 | J9: Simpanan Sukarela I | K9: 0 | L9: 0 | M9: 0 | N9: 0 | O9: 0
C10: Bank | D10: 38487372 | E10: 53412528 | F10: 42405266 | G10: 3.0295667e+08 | H10: ='WS Trial balance'!L8 -> 3.1335738e+08 | J10: Simpanan Sukarela II | K10: 0 | L10: 0 | M10: 0 | N10: 0 | O10: 0
C11: Surat Berharga | D11: 0 | E11: 0 | F11: 0 | G11: 0 | H11: 0 | J11: Utang Anggota | K11: 0 | L11: 0 | M11: 0 | N11: 0 | O11: 0
C12: Piutang Anggota | D12: 1.5707596e+09 | E12: 1.7547836e+09 | F12: 1.9778942e+09 | G12: 1.9264197e+09 | H12: ='WS Trial balance'!L10 -> 1.9789932e+09 | J12: Utang Non Anggota | K12: 6033860000 | L12: 6164854500 | M12: 2850000000 | N12: 300000000 | O12: ='WS Trial balance'!M31 -> 300000000
C13: Piutang Non Anggota | D13: 6561449467 | E13: 6.7210876e+09 | F13: 3335823867 | G13: 643143867 | H13: ='WS Trial balance'!L11 -> 635303867
C14: Cad. Penyisihan | D14: -75000000 | E14: -155000000 | F14: -164000000 | G14: -182000000 | H14: =-'WS Trial balance'!M12 -> -183500000 | J14: Utang Pajak | K14: 0 | L14: 5244487.6 | M14: 29607286 | N14: 47686535 | O14: ='WS Trial balance'!M36 -> 47686535
C15: Biaya yg Dibayar Dimuka | D15: 0 | E15: 0 | F15: 0 | G15: 0 | H15: 0 | J15: Utang Bunga | K15: 0 | L15: 0 | M15: 0 | N15: 0 | O15: 0
C16: Uang Muka Pembelian | D16: 0 | E16: 0 | F16: 0 | G16: 0 | H16: 0 | J16: Utang Bank | K16: 0 | L16: 0 | M16: 0 | N16: 0 | O16: 0
C17: Uang Muka Operasional | D17: 0 | E17: 0 | F17: 0 | G17: 0 | H17: 0 | J17: Utang Lain-Lain | K17: 0 | L17: 0 | M17: 0 | N17: 21680000 | O17: ='WS Trial balance'!M35 -> 21680000
C18: Uang Muka Pajak | D18: 0 | E18: 0 | F18: 0 | G18: 0 | H18: 0 | J18: Biaya YMHD | K18: 0 | L18: 0 | M18: 0 | N18: 0 | O18: ='WS Trial balance'!M37 -> 28950000
C19: Total Aset Lancar : | D19: =SUM(D9:D18) -> 8.1186609e+09 | E19: =SUM(E9:E18) -> 8.3800348e+09 | F19: =SUM(F9:F18) -> 5.1939119e+09 | G19: =SUM(G9:G18) -> 2.6993717e+09 | H19: =SUM(H9:H18) -> 2.7526129e+09 | J19: Uang Muka Penjualan | K19: 0 | L19: 0 | M19: 0 | N19: 0 | O19: 0
B20: II | C20: Penyertaan Modal | D20: 0 | E20: 0 | F20: 0 | G20: 0 | H20: 0 | K20: 0 | L20: 0 | M20: 0 | N20: 0 | O20: 0
B21: III | C21: Aktiva Pajak Tangguhan | D21: 0 | E21: 0 | F21: 0 | G21: 0 | H21: 0 | K21: 0 | L21: 0 | M21: 0 | N21: 0 | O21: 0
B22: IV | C22: Aset Tetap Berwujud | J22: Grand Total Liabilitas | K22: =SUM(K9:K21) -> 6033860000 | L22: =SUM(L9:L21) -> 6.170099e+09 | M22: =SUM(M9:M21) -> 2.8796073e+09 | N22: =SUM(N9:N21) -> 3.6936654e+08 | O22: =SUM(O9:O21) -> 3.9831654e+08
C23: Tanah | D23: 0 | E23: 0 | F23: 0 | G23: 0 | H23: 0 | I23: VIII | J23: Ekuitas
C24: Bangunan dan Instalasi Listrik | D24: 0 | E24: 0 | F24: 0 | G24: 0 | H24: 0 | J24: Simpanan Pokok | K24: 10900000 | L24: 10100000 | M24: 9500000 | N24: 7900000 | O24: ='WS Trial balance'!M43 -> 7900000
C25: Kendaraan | D25: 0 | E25: 0 | F25: 0 | G25: 0 | H25: 0 | J25: Wajib | K25: 306200000 | L25: 335950000 | M25: 364570000 | N25: 339030000 | O25: =+'WS Trial balance'!M44 -> 342830000
C26: Mesin dan Peralatan | D26: 0 | E26: 0 | F26: 0 | G26: 0 | H26: 0 | J26: Hibah | K26: 0 | L26: 0 | M26: 0 | N26: 0 | O26: 0
C27: Inventaris Kantor | D27: 0 | E27: 0 | F27: 0 | G27: 0 | H27: 0 | J27: Cadangan | K27: 1623304769 | L27: 1.6810632e+09 | M27: 1.7530277e+09 | N27: 1.8279105e+09 | O27: =+'WS Trial balance'!M46 -> 1.8279105e+09
C28: Nilai Perolehan | D28: =SUM(D23:D27) -> 0 | E28: =SUM(E23:E27) -> 0 | F28: =SUM(F23:F27) -> 0 | G28: =SUM(G23:G27) -> 0 | H28: =SUM(H23:H27) -> 0 | J28: Laba Belum dicadangkan | K28: 0 | L28: 0 | M28: 0 | N28: -1.4901161e-07 | O28: =+'WS Trial balance'!M47 -> 1.5516467e+08
C29: Akumulasi Penyusutan Aktiva Tetap | D29: 0 | E29: 0 | F29: 0 | G29: 0 | H29: 0
C30: Total Aset Lancar : | D30: =D28+D29 -> 0 | E30: =E28+E29 -> 0 | F30: =F28+F29 -> 0 | G30: =G28+G29 -> 0 | H30: =H28+H29 -> 0 | J30: SHU | K30: 1.4439615e+08 | L30: 1.8282255e+08 | M30: 1.8720697e+08 | N30: 1.5516467e+08 | O30: =+'WS Trial balance'!M51 -> 20491175
B31: V | C31: Aset Tetap Tak Berwujud | J31: Total Ekuitas : | K31: =SUM(K24:K30) -> 2.0848009e+09 | L31: =SUM(L24:L30) -> 2.2099358e+09 | M31: =SUM(M24:M30) -> 2.3143047e+09 | N31: =SUM(N24:N30) -> 2.3300052e+09 | O31: =SUM(O24:O30) -> 2.3542964e+09
C32: Software Komputer | D32: 0 | E32: 0 | F32: 0 | G32: 0 | H32: 0
C33: Ak. Amrt. Software Komputer | D33: 0 | E33: 0 | F33: 0 | G33: 0 | H33: 0
C34: Total Aset Tetap Tak Berwujud : | D34: =SUM(D32:D33) -> 0 | E34: =SUM(E32:E33) -> 0 | F34: =SUM(F32:F33) -> 0 | G34: =SUM(G32:G33) -> 0 | H34: =SUM(H32:H33) -> 0
B35: VI | C35: Aset Lain-lain | D35: 0 | E35: 0 | F35: 0 | G35: 0 | H35: 0
B37: Grand Total Aset | D37: =D19+D20+D21+D30+D34+D35 -> 8.1186609e+09 | E37: =E19+E20+E21+E30+E34+E35 -> 8.3800348e+09 | F37: =F19+F20+F21+F30+F34+F35 -> 5.1939119e+09 | G37: =G19+G20+G21+G30+G34+G35 -> 2.6993717e+09 | H37: =H19+H20+H21+H30+H34+H35 -> 2.7526129e+09 | I37: Grand Total Liabilitas dan Ekuitas | K37: =K22+K31 -> 8.1186609e+09 | L37: =L22+L31 -> 8.3800348e+09 | M37: =M22+M31 -> 5.1939119e+09 | N37: =N22+N31 -> 2.6993717e+09 | O37: =O22+O31 -> 2.7526129e+09

Sheet LR
B2: LAPORAN LABA / (RUGI)
B3: K K C S
B4: =NR!B4 -> TAHUN 2023 - 2026
D5: j-k
B6: KETERANGAN | D6: JANUARI
D7: =LEFT(D6,3) -> JAN | E7: ="sd. "&D7 -> sd. JAN
C8: Pendapatan
C9: Pinjaman Rutin | D9: ='WS Trial balance'!K58-'WS Trial balance'!J58 -> 78721705 | E9: =D9 -> 78721705
C10: Pinjaman Khusus | D10: ='WS Trial balance'!K59-'WS Trial balance'!J59 -> 0 | E10: =D10 -> 0
C11: Pinjaman Lain | D11: ='WS Trial balance'!K60-'WS Trial balance'!J60 -> 525000 | E11: =D11 -> 525000
C12: HPP Pinj. Rutin | D12: =-'WS Trial balance'!J61+'WS Trial balance'!K61 -> -60419861 | E12: =D12 -> -60419861
C13: HPP Pinj. Khusus | D13: =-'WS Trial balance'!J62+'WS Trial balance'!K62 -> 0 | E13: =D13 -> 0
C14: HPP Pinj. Lain | D14: =-'WS Trial balance'!J63+'WS Trial balance'!K63 -> 0 | E14: =D14 -> 0
C15: Laba kotor | D15: =SUM(D9:D14) -> 18826844 | E15: =SUM(E9:E14) -> 18826844
C17: Beban Usaha
C18: Beban Umum dan Administrasi | D18: =-'WS Trial balance'!J64+'WS Trial balance'!K64 -> -758000 | E18: =D18 -> -758000
C19: Jumlah Beban Usaha : | D19: =SUM(D18:D18) -> -758000 | E19: =SUM(E18:E18) -> -758000
C20: Laba usaha | D20: =+D15+D19 -> 18068844 | E20: =+E15+E19 -> 18068844
C21: Pendapatan / (Beban) di luar usaha
C22: Pendapatan Lain-lain | D22: ='WS Trial balance'!K65-'WS Trial balance'!J65 -> 3918000 | E22: =D22 -> 3918000
C23: Biaya Lain-lain | D23: =-'WS Trial balance'!J66+'WS Trial balance'!K66 -> -1495669.1 | E23: =D23 -> -1495669.1
C24: Jumlah Pendapatan/(Beban) di luar usaha: | D24: =SUM(D22:D23) -> 2422330.9 | E24: =SUM(E22:E23) -> 2422330.9
C25: Laba Sebelum Pajak | D25: =+D20+D24 -> 20491175 | E25: =+E20+E24 -> 20491175
C26: Beban Pajak | D26: =-'WS Trial balance'!J67+'WS Trial balance'!K67 -> 0 | E26: =D26 -> 0
C27: Laba Setelah Pajak | D27: =SUM(D25:D26) -> 20491175 | E27: =SUM(E25:E26) -> 20491175
E29: =E27-'WS Trial balance'!L70 -> 0

Sheet WS Trial balance
C3: KOPERASI KARYAWAN CIPTA SEJAHTERA
C4: BALANCE SHEET, TAHUN 2026
C5: ACCOUNT | F5: KODE | G5: SALDO AWAL 2026 | J5: MUTASI JANUARI 2026 | L5: SALDO AKHIR JANUARI 2026
G6: DEBET | H6: KREDIT | J6: DEBET | K6: KREDIT | L6: DEBET | M6: KREDIT
D7: A01 | E7: KAS | F7: D | G7: 8851508.7 | H7: 0 | J7: =SUMIF('MUTASI 2026'!$B$5:$B$158,'WS Trial balance'!$D7,'MUTASI 2026'!$G$5:$G$158) -> 4865000 | K7: =SUMIF('MUTASI 2026'!$B$5:$B$158,'WS Trial balance'!$D7,'MUTASI 2026'!$H$5:$H$158) -> 5258000 | L7: =IF(F7="D",(G7-H7+J7-K7),0) -> 8458508.7 | M7: =IF(F7="K",(-G7+H7-J7+K7),0) -> 0
D8: A02 | E8: BANK | F8: D | G8: 3.0295667e+08 | H8: 0 | J8: =SUMIF('MUTASI 2026'!$B$5:$B$158,'WS Trial balance'!$D8,'MUTASI 2026'!$G$5:$G$158) -> 1.6096184e+08 | K8: =SUMIF('MUTASI 2026'!$B$5:$B$158,'WS Trial balance'!$D8,'MUTASI 2026'!$H$5:$H$158) -> 150561132 | L8: =IF(F8="D",(G8-H8+J8-K8),0) -> 3.1335738e+08 | M8: =IF(F8="K",(-G8+H8-J8+K8),0) -> 0
D9: A03 | E9: SURAT BERHARGA | F9: D | G9: 0 | H9: 0 | J9: =SUMIF('MUTASI 2026'!$B$5:$B$158,'WS Trial balance'!$D9,'MUTASI 2026'!$G$5:$G$158) -> 0 | K9: =SUMIF('MUTASI 2026'!$B$5:$B$158,'WS Trial balance'!$D9,'MUTASI 2026'!$H$5:$H$158) -> 0 | L9: =IF(F9="D",(G9-H9+J9-K9),0) -> 0 | M9: =IF(F9="K",(-G9+H9-J9+K9),0) -> 0
D10: A04A | E10: PIUTANG ANGGOTA | F10: D | G10: 1.9264197e+09 | H10: 0 | J10: =SUMIF('MUTASI 2026'!$B$5:$B$158,'WS Trial balance'!$D10,'MUTASI 2026'!$G$5:$G$158) -> 284500000 | K10: =SUMIF('MUTASI 2026'!$B$5:$B$158,'WS Trial balance'!$D10,'MUTASI 2026'!$H$5:$H$158) -> 2.3192654e+08 | L10: =IF(F10="D",(G10-H10+J10-K10),0) -> 1.9789932e+09 | M10: =IF(F10="K",(-G10+H10-J10+K10),0) -> 0
D11: A04B | E11: PIUTANG NON ANGGOTA | F11: D | G11: 643143867 | H11: 0 | J11: =SUMIF('MUTASI 2026'!$B$5:$B$158,'WS Trial balance'!$D11,'MUTASI 2026'!$G$5:$G$158) -> 70560000 | K11: =SUMIF('MUTASI 2026'!$B$5:$B$158,'WS Trial balance'!$D11,'MUTASI 2026'!$H$5:$H$158) -> 78400000 | L11: =IF(F11="D",(G11-H11+J11-K11),0) -> 635303867 | M11: =IF(F11="K",(-G11+H11-J11+K11),0) -> 0
D12: A05 | E12: CADANGAN PENGHAPUSAN PIUTANG USAHA | F12: K | G12: 0 | H12: 182000000 | J12: =SUMIF('MUTASI 2026'!$B$5:$B$158,'WS Trial balance'!$D12,'MUTASI 2026'!$G$5:$G$158) -> 0 | K12: =SUMIF('MUTASI 2026'!$B$5:$B$158,'WS Trial balance'!$D12,'MUTASI 2026'!$H$5:$H$158) -> 1500000 | L12: =IF(F12="D",(G12-H12+J12-K12),0) -> 0 | M12: =IF(F12="K",(-G12+H12-J12+K12),0) -> 183500000
D13: A06 | E13: PIUTANG LAIN-LAIN | F13: D | G13: 0 | H13: 0 | J13: =SUMIF('MUTASI 2026'!$B$5:$B$158,'WS Trial balance'!$D13,'MUTASI 2026'!$G$5:$G$158) -> 0 | K13: =SUMIF('MUTASI 2026'!$B$5:$B$158,'WS Trial balance'!$D13,'MUTASI 2026'!$H$5:$H$158) -> 0 | L13: =IF(F13="D",(G13-H13+J13-K13),0) -> 0 | M13: =IF(F13="K",(-G13+H13-J13+K13),0) -> 0
D14: A07 | E14: UANG MUKA PEMBELIAN | F14: D | G14: 0 | H14: 0 | J14: =SUMIF('MUTASI 2026'!$B$5:$B$158,'WS Trial balance'!$D14,'MUTASI 2026'!$G$5:$G$158) -> 0 | K14: =SUMIF('MUTASI 2026'!$B$5:$B$158,'WS Trial balance'!$D14,'MUTASI 2026'!$H$5:$H$158) -> 0 | L14: =IF(F14="D",(G14-H14+J14-K14),0) -> 0 | M14: =IF(F14="K",(-G14+H14-J14+K14),0) -> 0
D15: A08 | E15: BIAYA DIBAYAR DIMUKA | F15: D | G15: 0 | H15: 0 | J15: =SUMIF('MUTASI 2026'!$B$5:$B$158,'WS Trial balance'!$D15,'MUTASI 2026'!$G$5:$G$158) -> 0 | K15: =SUMIF('MUTASI 2026'!$B$5:$B$158,'WS Trial balance'!$D15,'MUTASI 2026'!$H$5:$H$158) -> 0 | L15: =IF(F15="D",(G15-H15+J15-K15),0) -> 0 | M15: =IF(F15="K",(-G15+H15-J15+K15),0) -> 0
D16: A09 | E16: UANG MUKA KASBON BIAYA OPERASIONAL | F16: D | G16: 0 | H16: 0 | J16: =SUMIF('MUTASI 2026'!$B$5:$B$158,'WS Trial balance'!$D16,'MUTASI 2026'!$G$5:$G$158) -> 0 | K16: =SUMIF('MUTASI 2026'!$B$5:$B$158,'WS Trial balance'!$D16,'MUTASI 2026'!$H$5:$H$158) -> 0 | L16: =IF(F16="D",(G16-H16+J16-K16),0) -> 0 | M16: =IF(F16="K",(-G16+H16-J16+K16),0) -> 0
D17: A10 | E17: UANG MUKA PAJAK | F17: D | G17: 0 | H17: 0 | J17: =SUMIF('MUTASI 2026'!$B$5:$B$158,'WS Trial balance'!$D17,'MUTASI 2026'!$G$5:$G$158) -> 0 | K17: =SUMIF('MUTASI 2026'!$B$5:$B$158,'WS Trial balance'!$D17,'MUTASI 2026'!$H$5:$H$158) -> 0 | L17: =IF(F17="D",(G17-H17+J17-K17),0) -> 0 | M17: =IF(F17="K",(-G17+H17-J17+K17),0) -> 0
D18: A11 | E18: PENYERTAAN MODAL | F18: D | G18: 0 | H18: 0 | J18: =SUMIF('MUTASI 2026'!$B$5:$B$158,'WS Trial balance'!$D18,'MUTASI 2026'!$G$5:$G$158) -> 0 | K18: =SUMIF('MUTASI 2026'!$B$5:$B$158,'WS Trial balance'!$D18,'MUTASI 2026'!$H$5:$H$158) -> 0 | L18: =IF(F18="D",(G18-H18+J18-K18),0) -> 0 | M18: =IF(F18="K",(-G18+H18-J18+K18),0) -> 0
... D48: P16 | E48: LABA / (RUGI) TAHUN BERJALAN | F48: K | G48: 0 | H48: 0 | J48: =SUMIF('MUTASI 2026'!$B$5:$B$158,'WS Trial balance'!$D48,'MUTASI 2026'!$G$5:$G$158) -> 0 | K48: =SUMIF('MUTASI 2026'!$B$5:$B$158,'WS Trial balance'!$D48,'MUTASI 2026'!$H$5:$H$158) -> 0 | L48: =IF(F48="D",(G48-H48+J48-K48),0) -> 0 | M48: =IF(F48="K",(-G48+H48-J48+K48),0) -> 0
E50: JUMLAH | G50: =SUM(G7:G29)-SUM(H7:H29) -> 2.6993717e+09 | H50: =SUM(H30:H48)-SUM(G30:G48) -> 2.6993717e+09 | J50: =SUM(J7:J49) -> 5.5857884e+08 | K50: =SUM(K7:K49) -> 5.3808767e+08 | L50: =SUM(L7:L29)-SUM(M7:M29) -> 2.7526129e+09 | M50: =SUM(M30:M48)-SUM(L30:L48) -> 2.7321217e+09
E51: LABA (RUGI) | H51: =G50-H50 -> 0 | K51: =J50-K50 -> 20491175 | M51: =L50-M50 -> 20491175
C54: =C3 -> KOPERASI KARYAWAN CIPTA SEJAHTERA
C55: PROFIT AND LOSS, TAHUN 2026
C56: ACCOUNT | F56: =F5 -> KODE | G56: =G5 -> SALDO AWAL 2026 | J56: =J5 -> MUTASI JANUARI 2026 | L56: =L5 -> SALDO AKHIR JANUARI 2026
G57: DEBET | H57: KREDIT | J57: DEBET | K57: KREDIT | L57: DEBET | M57: KREDIT
D58: LR01A | E58: PENDAPATAN PINJAMAN RUTIN | F58: K | G58: 0 | H58: 0 | J58: =SUMIF('MUTASI 2026'!$B$5:$B$158,'WS Trial balance'!$D58,'MUTASI 2026'!$G$5:$G$158) -> 0 | K58: =SUMIF('MUTASI 2026'!$B$5:$B$158,'WS Trial balance'!$D58,'MUTASI 2026'!$H$5:$H$158) -> 78721705 | L58: =IF(F58="D",(G58-H58+J58-K58),0) -> 0 | M58: =IF(F58="K",(-G58+H58-J58+K58),0) -> 78721705 | P58: =SUM(#REF!)-SUM(#REF!) -> #REF! | Q58: =+#REF!-#REF! -> #REF!
D59: LR01B | E59: PENDAPATAN PINJAMAN KHUSUS | F59: K | G59: 0 | H59: 0 | J59: =SUMIF('MUTASI 2026'!$B$5:$B$158,'WS Trial balance'!$D59,'MUTASI 2026'!$G$5:$G$158) -> 0 | K59: =SUMIF('MUTASI 2026'!$B$5:$B$158,'WS Trial balance'!$D59,'MUTASI 2026'!$H$5:$H$158) -> 0 | L59: =IF(F59="D",(G59-H59+J59-K59),0) -> 0 | M59: =IF(F59="K",(-G59+H59-J59+K59),0) -> 0
D60: LR01C | E60: PENDAPATAN PINJAMAN LAIN-LAIN | F60: K | G60: 0 | H60: 0 | J60: =SUMIF('MUTASI 2026'!$B$5:$B$158,'WS Trial balance'!$D60,'MUTASI 2026'!$G$5:$G$158) -> 0 | K60: =SUMIF('MUTASI 2026'!$B$5:$B$158,'WS Trial balance'!$D60,'MUTASI 2026'!$H$5:$H$158) -> 525000 | L60: =IF(F60="D",(G60-H60+J60-K60),0) -> 0 | M60: =IF(F60="K",(-G60+H60-J60+K60),0) -> 525000
D61: LR02A | E61: BIAYA POKOK PINJAMAN RUTIN | F61: D | G61: 0 | H61: 0 | J61: =SUMIF('MUTASI 2026'!$B$5:$B$158,'WS Trial balance'!$D61,'MUTASI 2026'!$G$5:$G$158) -> 60419861 | K61: =SUMIF('MUTASI 2026'!$B$5:$B$158,'WS Trial balance'!$D61,'MUTASI 2026'!$H$5:$H$158) -> 0 | L61: =IF(F61="D",(G61-H61+J61-K61),0) -> 60419861 | M61: =IF(F61="K",(-G61+H61-J61+K61),0) -> 0
D62: LR02B | E62: BIAYA POKOK PINJAMAN KHUSUS | F62: D | G62: 0 | H62: 0 | J62: =SUMIF('MUTASI 2026'!$B$5:$B$158,'WS Trial balance'!$D62,'MUTASI 2026'!$G$5:$G$158) -> 0 | K62: =SUMIF('MUTASI 2026'!$B$5:$B$158,'WS Trial balance'!$D62,'MUTASI 2026'!$H$5:$H$158) -> 0 | L62: =IF(F62="D",(G62-H62+J62-K62),0) -> 0 | M62: =IF(F62="K",(-G62+H62-J62+K62),0) -> 0
D63: LR02C | E63: BIAYA POKOK PINJAMAN LAIN-LAIN | F63: D | G63: 0 | H63: 0 | J63: =SUMIF('MUTASI 2026'!$B$5:$B$158,'WS Trial balance'!$D63,'MUTASI 2026'!$G$5:$G$158) -> 0 | K63: =SUMIF('MUTASI 2026'!$B$5:$B$158,'WS Trial balance'!$D63,'MUTASI 2026'!$H$5:$H$158) -> 0 | L63: =IF(F63="D",(G63-H63+J63-K63),0) -> 0 | M63: =IF(F63="K",(-G63+H63-J63+K63),0) -> 0
D64: LR05 | E64: BIAYA UMUM DAN ADMINISTRASI | F64: D | G64: 0 | H64: 0 | J64: =SUMIF('MUTASI 2026'!$B$5:$B$158,'WS Trial balance'!$D64,'MUTASI 2026'!$G$5:$G$158) -> 758000 | K64: =SUMIF('MUTASI 2026'!$B$5:$B$158,'WS Trial balance'!$D64,'MUTASI 2026'!$H$5:$H$158) -> 0 | L64: =IF(F64="D",(G64-H64+J64-K64),0) -> 758000 | M64: =IF(F64="K",(-G64+H64-J64+K64),0) -> 0
D65: LR06 | E65: PENDAPATAN DILUAR USAHA | F65: K | G65: 0 | H65: 0 | J65: =SUMIF('MUTASI 2026'!$B$5:$B$158,'WS Trial balance'!$D65,'MUTASI 2026'!$G$5:$G$158) -> 0 | K65: =SUMIF('MUTASI 2026'!$B$5:$B$158,'WS Trial balance'!$D65,'MUTASI 2026'!$H$5:$H$158) -> 3918000 | L65: =IF(F65="D",(G65-H65+J65-K65),0) -> 0 | M65: =IF(F65="K",(-G65+H65-J65+K65),0) -> 3918000
D66: LR07 | E66: BIAYA DILUAR USAHA | F66: D | G66: 0 | H66: 0 | J66: =SUMIF('MUTASI 2026'!$B$5:$B$158,'WS Trial balance'!$D66,'MUTASI 2026'!$G$5:$G$158) -> 1577093.2 | K66: =SUMIF('MUTASI 2026'!$B$5:$B$158,'WS Trial balance'!$D66,'MUTASI 2026'!$H$5:$H$158) -> 81424.12 | L66: =IF(F66="D",(G66-H66+J66-K66),0) -> 1495669.1 | M66: =IF(F66="K",(-G66+H66-J66+K66),0) -> 0
D67: LR08 | E67: BEBAN PAJAK PENGHASILAN | F67: D | G67: 0 | H67: 0 | J67: =SUMIF('MUTASI 2026'!$B$5:$B$158,'WS Trial balance'!$D67,'MUTASI 2026'!$G$5:$G$158) -> 0 | K67: =SUMIF('MUTASI 2026'!$B$5:$B$158,'WS Trial balance'!$D67,'MUTASI 2026'!$H$5:$H$158) -> 0 | L67: =IF(F67="D",(G67-H67+J67-K67),0) -> 0 | M67: =IF(F67="K",(-G67+H67-J67+K67),0) -> 0
G69: =SUM(G58:G68) -> 0 | H69: =SUM(H58:H68) -> 0 | J69: =SUM(J58:J68) -> 62754954 | K69: =SUM(K58:K68) -> 83246129 | L69: =SUM(L58:L68) -> 62673530 | M69: =SUM(M58:M68) -> 83164705
E70: LABA (RUGI) | G70: =H69-G69 -> 0 | J70: =K51 -> 20491175 | L70: =M69-L69 -> 20491175
E71: JUMLAH | G71: =G69+G70 -> 0 | H71: =H69+H70 -> 0 | J71: =J69+J70 -> 83246129 | K71: =K69+K70 -> 83246129 | L71: =L69+L70 -> 83164705 | M71: =M69+M70 -> 83164705
E72: BALANCE | K72: =J71-K71 -> -1.1920929e-07 | L72: =L71-M71 -> 0 | M72: =L50-(M50+M51) -> 0
M75: =+M58-L61 -> 18301844

Sheet MUTASI 2026
G1: =SUBTOTAL(9,G5:G1048576) -> 6.213338e+08 | H1: =SUBTOTAL(9,H5:H1048576) -> 6.213338e+08 | I1: =SUBTOTAL(9,I5:I1048576) -> 0 | J1: =+I1/I8 -> 0
I2: =-I1 -> 0
B4: Report_NR | C4: periode | D4: N.BUKTI | E4: TANGGAL | F4: ACCOUNT | G4: JMLDEB | H4: JMLKRED | I4: AMOUNT | J4: QTY | K4: SOURCE | L4: KETERANGAN | M4: Nama_Rekanan
B5: =VLOOKUP(F5,BB!$A$8:$C$152,3,0) -> A02 | C5: 202601 | D5: MDR-2601001 | E5: 46027 | F5: 02.001.0000 | G5: 0 | H5: 11608500 | I5: =IF(G5<>0,G5,-H5) -> -11608500 | J5: 0 | K5: BANK KELUAR | L5: PEMBAYARAN KE ORIX SEWA BULAN KE 42 (DES)
B6: =VLOOKUP(F6,BB!$A$8:$C$152,3,0) -> P05 | C6: =+C5 -> 202601 | D6: =+D5 -> MDR-2601001 | E6: =+E5 -> 46027 | F6: 34.000.0003 | G6: =H5 -> 11608500 | H6: 0 | I6: =IF(G6<>0,G6,-H6) -> 11608500 | J6: 0 | K6: BANK KELUAR | L6: =+L5 -> PEMBAYARAN KE ORIX SEWA BULAN KE 42 (DES)
B8: =VLOOKUP(F8,BB!$A$8:$C$152,3,0) -> A02 | C8: 202601 | D8: MDR-2601002 | E8: 46027 | F8: 02.001.0000 | G8: 0 | H8: 20000000 | I8: =IF(G8<>0,G8,-H8) -> -20000000 | J8: 0 | K8: BANK KELUAR | L8: PINJAMAN RUTIN SAFI'I, 12X
B9: =VLOOKUP(F9,BB!$A$8:$C$152,3,0) -> A04A | C9: =C8 -> 202601 | D9: =D8 -> MDR-2601002 | E9: =E8 -> 46027 | F9: 04.001.0001 | G9: =+H8 -> 20000000 | H9: 0 | I9: =IF(G9<>0,G9,-H9) -> 20000000 | J9: =-J8 -> 0 | K9: =K8 -> BANK KELUAR | L9: =L8 -> PINJAMAN RUTIN SAFI'I, 12X
B11: =VLOOKUP(F11,BB!$A$8:$C$152,3,0) -> A02 | C11: 202601 | D11: MDR-2601003 | E11: 46027 | F11: 02.001.0000 | G11: 0 | H11: 2900 | I11: =IF(G11<>0,G11,-H11) -> -2900 | J11: 0 | K11: BANK KELUAR | L11: CLEARING FEE
B12: =VLOOKUP(F12,BB!$A$8:$C$152,3,0) -> LR07 | C12: =+C11 -> 202601 | D12: =+D11 -> MDR-2601003 | E12: =+E11 -> 46027 | F12: 71.000.0300 | G12: =+H11 -> 2900 | H12: 0 | I12: =IF(G12<>0,G12,-H12) -> 2900 | J12: 0 | K12: BANK KELUAR | L12: =+L11 -> CLEARING FEE
B14: =VLOOKUP(F14,BB!$A$8:$C$152,3,0) -> A02 | C14: 202601 | D14: MDR-2601004 | E14: 46027 | F14: 02.001.0000 | G14: 0 | H14: 13333333 | I14: =IF(G14<>0,G14,-H14) -> -13333333 | J14: 0 | K14: BANK KELUAR | L14: PINJAMAN RUTIN SOLICHIN, 36X, KOMPENSASI
B15: =VLOOKUP(F15,BB!$A$8:$C$152,3,0) -> A04A | C15: =C14 -> 202601 | D15: =D14 -> MDR-2601004 | E15: =E14 -> 46027 | F15: 04.001.0001 | G15: 50000000 | H15: 0 | I15: =IF(G15<>0,G15,-H15) -> 50000000 | J15: =-J14 -> 0 | K15: =K14 -> BANK KELUAR | L15: =L14 -> PINJAMAN RUTIN SOLICHIN, 36X, KOMPENSASI
B16: =VLOOKUP(F16,BB!$A$8:$C$152,3,0) -> A04A | C16: =C15 -> 202601 | D16: =D15 -> MDR-2601004 | E16: =E15 -> 46027 | F16: 04.001.0001 | G16: 0 | H16: =G15-H14 -> 36666667 | I16: =IF(G16<>0,G16,-H16) -> -36666667 | J16: =-J15 -> 0 | K16: =K15 -> BANK KELUAR | L16: =L15 -> PINJAMAN RUTIN SOLICHIN, 36X, KOMPENSASI
B18: =VLOOKUP(F18,BB!$A$8:$C$152,3,0) -> A02 | C18: 202601 | D18: MDR-2601005 | E18: 46029 | F18: 02.001.0000 | G18: 15680000 | H18: 0 | I18: =IF(G18<>0,G18,-H18) -> 15680000 | J18: 0 | K18: BANK MASUK | L18: TERIMA DARI GCS SEWA FORKLIFT PERIODE 202511
B19: =VLOOKUP(F19,BB!$A$8:$C$152,3,0) -> A04B | C19: =C18 -> 202601 | D19: =D18 -> MDR-2601005 | E19: =E18 -> 46029 | F19: 04.002.0006 | G19: 0 | H19: =+G18 -> 15680000 | I19: =IF(G19<>0,G19,-H19) -> -15680000 | J19: 0 | K19: =K18 -> BANK MASUK | L19: =L18 -> TERIMA DARI GCS SEWA FORKLIFT PERIODE 202511
B21: =VLOOKUP(F21,BB!$A$8:$C$152,3,0) -> A02 | C21: 202601 | D21: MDR-2601006 | E21: 46031 | F21: 02.001.0000 | G21: 0 | H21: 20000000 | I21: =IF(G21<>0,G21,-H21) -> -20000000 | J21: 0 | K21: BANK KELUAR | L21: PINJAMAN RUTIN JOKO P, 24X
B22: =VLOOKUP(F22,BB!$A$8:$C$152,3,0) -> A04A | C22: =C21 -> 202601 | D22: =D21 -> MDR-2601006 | E22: =E21 -> 46031 | F22: 04.001.0001 | G22: =+H21 -> 20000000 | H22: 0 | I22: =IF(G22<>0,G22,-H22) -> 20000000 | J22: =-J21 -> 0 | K22: =K21 -> BANK KELUAR | L22: =L21 -> PINJAMAN RUTIN JOKO P, 24X
B24: =VLOOKUP(F24,BB!$A$8:$C$152,3,0) -> A02 | C24: 202601 | D24: MDR-2601007 | E24: 46035 | F24: 02.001.0000 | G24: 0 | H24: 14475000 | I24: =IF(G24<>0,G24,-H24) -> -14475000 | J24: 0 | K24: BANK KELUAR | L24: PEMBAYARAN JASA FORKLIFT ACHMAD LUTHFIE PERIODE 202511
B25: =VLOOKUP(F25,BB!$A$8:$C$152,3,0) -> P05 | C25: =C24 -> 202601 | D25: =D24 -> MDR-2601007 | E25: =E24 -> 46035 | F25: 34.000.0001 | G25: =H24 -> 14475000 | H25: =G24 -> 0 | I25: =IF(G25<>0,G25,-H25) -> 14475000 | J25: =-J24 -> 0 | K25: =K24 -> BANK KELUAR | L25: =L24 -> PEMBAYARAN JASA FORKLIFT ACHMAD LUTHFIE PERIODE 202511
B27: =VLOOKUP(F27,BB!$A$8:$C$152,3,0) -> A02 | C27: 202601 | D27: MDR-2601008 | E27: 46037 | F27: 02.001.0000 | G27: 0 | H27: 13333333 | I27: =IF(G27<>0,G27,-H27) -> -13333333 | J27: 0 | K27: BANK KELUAR | L27: PINJAMAN RUTIN SUGENG H, 36X, KOMPENSASI
B28: =VLOOKUP(F28,BB!$A$8:$C$152,3,0) -> A04A | C28: =C27 -> 202601 | D28: =D27 -> MDR-2601008 | E28: =E27 -> 46037 | F28: 04.001.0001 | G28: 30000000 | H28: 0 | I28: =IF(G28<>0,G28,-H28) -> 30000000 | J28: =-J27 -> 0 | K28: =K27 -> BANK KELUAR | L28: =L27 -> PINJAMAN RUTIN SUGENG H, 36X, KOMPENSASI
B29: =VLOOKUP(F29,BB!$A$8:$C$152,3,0) -> A04A | C29: =C28 -> 202601 | D29: =D28 -> MDR-2601008 | E29: =E28 -> 46037 | F29: 04.001.0001 | G29: 0 | H29: =G28-H27 -> 16666667 | I29: =IF(G29<>0,G29,-H29) -> -16666667 | J29: =-J28 -> 0 | K29: =K28 -> BANK KELUAR | L29: =L28 -> PINJAMAN RUTIN SUGENG H, 36X, KOMPENSASI
B31: =VLOOKUP(F31,BB!$A$8:$C$152,3,0) -> A02 | C31: 202601 | D31: MDR-2601009 | E31: 46043 | F31: 02.001.0000 | G31: 0 | H31: 8333333 | I31: =IF(G31<>0,G31,-H31) -> -8333333 | J31: 0 | K31: BANK KELUAR | L31: PINJAMAN RUTIN WIDYA NS, 60X, KOMPENSASI
B32: =VLOOKUP(F32,BB!$A$8:$C$152,3,0) -> A04A | C32: =C31 -> 202601 | D32: =D31 -> MDR-2601009 | E32: =E31 -> 46043 | F32: 04.001.0001 | G32: 50000000 | H32: 0 | I32: =IF(G32<>0,G32,-H32) -> 50000000 | J32: =-J31 -> 0 | K32: =K31 -> BANK KELUAR | L32: =L31 -> PINJAMAN RUTIN WIDYA NS, 60X, KOMPENSASI
B33: =VLOOKUP(F33,BB!$A$8:$C$152,3,0) -> A04A | C33: =C32 -> 202601 | D33: =D32 -> MDR-2601009 | E33: =E32 -> 46043 | F33: 04.001.0001 | G33: 0 | H33: =G32-H31 -> 41666667 | I33: =IF(G33<>0,G33,-H33) -> -41666667 | J33: =-J32 -> 0 | K33: =K32 -> BANK KELUAR | L33: =L32 -> PINJAMAN RUTIN WIDYA NS, 60X, KOMPENSASI
B35: =VLOOKUP(F35,BB!$A$8:$C$152,3,0) -> A02 | C35: 202601 | D35: MDR-2601010 | E35: 46045 | F35: 02.001.0000 | G35: 82521704 | H35: 0 | I35: =IF(G35<>0,G35,-H35) -> 82521704 | J35: 0 | K35: BANK MASUK | L35: TERIMA DARI GCS POTONGAN GAJI BULAN JANUARI 2026
B36: =VLOOKUP(F36,BB!$A$8:$C$152,3,0) -> A04A | C36: =C35 -> 202601 | D36: =D35 -> MDR-2601010 | E36: =E35 -> 46045 | F36: 04.001.0001 | G36: 0 | H36: 60419861 | I36: =IF(G36<>0,G36,-H36) -> -60419861 | J36: =-J35 -> 0 | K36: =K35 -> BANK MASUK | L36: ="ANGSURAN PIRUT DARI "&MID(L35,17,50) -> ANGSURAN PIRUT DARI POTONGAN GAJI BULAN JANUARI 2026
B37: =VLOOKUP(F37,BB!$A$8:$C$152,3,0) -> P12 | C37: =C36 -> 202601 | D37: =D36 -> MDR-2601010 | E37: =E36 -> 46045 | F37: 42.000.0000 | G37: 0 | H37: 3800000 | I37: =IF(G37<>0,G37,-H37) -> -3800000 | J37: =-J36 -> 0 | K37: =K36 -> BANK MASUK | L37: PENERIMAAN SIMPANAN WAJIB ANGGOTA
B38: =VLOOKUP(F38,BB!$A$8:$C$152,3,0) -> LR01A | C38: =C37 -> 202601 | D38: =D37 -> MDR-2601010 | E38: =E37 -> 46045 | F38: 50.001.0000 | G38: 0 | H38: 78721705 | I38: =IF(G38<>0,G38,-H38) -> -78721705 | J38: =-J37 -> 0 | K38: =K37 -> BANK MASUK | L38: ="PENDAPATAN PIRUT "&MID(L35,31,50) -> PENDAPATAN PIRUT BULAN JANUARI 2026
B39: =VLOOKUP(F39,BB!$A$8:$C$152,3,0) -> LR02A | C39: =C38 -> 202601 | D39: =D38 -> MDR-2601010 | E39: =E38 -> 46045 | F39: 51.001.0000 | G39: =H36 -> 60419861 | H39: 0 | I39: =IF(G39<>0,G39,-H39) -> 60419861 | J39: =-J38 -> 0 | K39: =K38 -> BANK MASUK | L39: ="HPP "&MID(L38,12,50) -> HPP PIRUT BULAN JANUARI 2026
B40: =VLOOKUP(F40,BB!$A$8:$C$152,3,0) -> LR07 | C40: =C39 -> 202601 | D40: =D39 -> MDR-2601010 | E40: =E39 -> 46045 | F40: 71.000.0900 | G40: =IF(SUM(I35:I39)<0,-SUM(I35:I39),0) -> 0.86111113 | H40: =IF(SUM(I35:I39)>0,-SUM(J35:J39),0) -> 0 | I40: =IF(G40<>0,G40,-H40) -> 0.86111113 | J40: =-J39 -> 0 | K40: =K39 -> BANK MASUK | L40: SELISIH LEBIH/KURANG TRANSFER
B42: =VLOOKUP(F42,BB!$A$8:$C$152,3,0) -> A02 | C42: 202601 | D42: MDR-2601011 | E42: 46049 | F42: 02.001.0000 | G42: 0 | H42: 10000000 | I42: =IF(G42<>0,G42,-H42) -> -10000000 | J42: 0 | K42: BANK KELUAR | L42: PINJAMAN RUTIN SUMARSONO, 24X
B43: =VLOOKUP(F43,BB!$A$8:$C$152,3,0) -> A04A | C43: =C42 -> 202601 | D43: =D42 -> MDR-2601011 | E43: =E42 -> 46049 | F43: 04.001.0001 | G43: =+H42 -> 10000000 | H43: 0 | I43: =IF(G43<>0,G43,-H43) -> 10000000 | J43: =-J42 -> 0 | K43: =K42 -> BANK KELUAR | L43: =L42 -> PINJAMAN RUTIN SUMARSONO, 24X
B45: =VLOOKUP(F45,BB!$A$8:$C$152,3,0) -> A02 | C45: 202601 | D45: MDR-2601012 | E45: 46049 | F45: 02.001.0000 | G45: 0 | H45: 11608500 | I45: =IF(G45<>0,G45,-H45) -> -11608500 | J45: 0 | K45: BANK KELUAR | L45: PEMBAYARAN KE ORIX SEWA BULAN KE 43 (JAN)
B46: =VLOOKUP(F46,BB!$A$8:$C$152,3,0) -> P05 | C46: =+C45 -> 202601 | D46: =+D45 -> MDR-2601012 | E46: =+E45 -> 46049 | F46: 34.000.0003 | G46: =+H45 -> 11608500 | H46: 0 | I46: =IF(G46<>0,G46,-H46) -> 11608500 | J46: 0 | K46: BANK KELUAR | L46: =+L45 -> PEMBAYARAN KE ORIX SEWA BULAN KE 43 (JAN)
B48: =VLOOKUP(F48,BB!$A$8:$C$152,3,0) -> A02 | C48: 202601 | D48: MDR-2601013 | E48: 46049 | F48: 02.001.0000 | G48: 0 | H48: 2900 | I48: =IF(G48<>0,G48,-H48) -> -2900 | J48: 0 | K48: BANK KELUAR | L48: CLEARING FEE
B49: =VLOOKUP(F49,BB!$A$8:$C$152,3,0) -> LR07 | C49: =+C48 -> 202601 | D49: =+D48 -> MDR-2601013 | E49: =+E48 -> 46049 | F49: 71.000.0300 | G49: =+H48 -> 2900 | H49: 0 | I49: =IF(G49<>0,G49,-H49) -> 2900 | J49: 0 | K49: BANK KELUAR | L49: =+L48 -> CLEARING FEE
B51: =VLOOKUP(F51,BB!$A$8:$C$152,3,0) -> A02 | C51: 202601 | D51: MDR-2601014 | E51: 46049 | F51: 02.001.0000 | G51: 0 | H51: 27833333 | I51: =IF(G51<>0,G51,-H51) -> -27833333 | J51: 0 | K51: BANK KELUAR | L51: PINJAMAN RUTIN DARWANTO, 60X, KOMPENSASI
B52: =VLOOKUP(F52,BB!$A$8:$C$152,3,0) -> A04A | C52: =C51 -> 202601 | D52: =D51 -> MDR-2601014 | E52: =E51 -> 46049 | F52: 04.001.0001 | G52: 100000000 | H52: 0 | I52: =IF(G52<>0,G52,-H52) -> 100000000 | J52: =-J51 -> 0 | K52: =K51 -> BANK KELUAR | L52: =L51 -> PINJAMAN RUTIN DARWANTO, 60X, KOMPENSASI
B53: =VLOOKUP(F53,BB!$A$8:$C$152,3,0) -> A04A | C53: =C52 -> 202601 | D53: =D52 -> MDR-2601014 | E53: =E52 -> 46049 | F53: 04.001.0001 | G53: 0 | H53: =G52-H51 -> 72166667 | I53: =IF(G53<>0,G53,-H53) -> -72166667 | J53: =-J52 -> 0 | K53: =K52 -> BANK KELUAR | L53: =L52 -> PINJAMAN RUTIN DARWANTO, 60X, KOMPENSASI
B55: =VLOOKUP(F55,BB!$A$8:$C$152,3,0) -> A02 | C55: 202601 | D55: MDR-2601015 | E55: 46050 | F55: 02.001.0000 | G55: 15680000 | H55: 0 | I55: =IF(G55<>0,G55,-H55) -> 15680000 | J55: 0 | K55: BANK MASUK | L55: TERIMA DARI GCS SEWA FORKLIFT PERIODE 202512
B56: =VLOOKUP(F56,BB!$A$8:$C$152,3,0) -> A04B | C56: =C55 -> 202601 | D56: =D55 -> MDR-2601015 | E56: =E55 -> 46050 | F56: 04.002.0006 | G56: 0 | H56: =+G55 -> 15680000 | I56: =IF(G56<>0,G56,-H56) -> -15680000 | J56: 0 | K56: =K55 -> BANK MASUK | L56: =L55 -> TERIMA DARI GCS SEWA FORKLIFT PERIODE 202512
B58: =VLOOKUP(F58,BB!$A$8:$C$152,3,0) -> A02 | C58: 202601 | D58: MDR-2601016 | E58: 46052 | F58: 02.001.0000 | G58: 11760000 | H58: 0 | I58: =IF(G58<>0,G58,-H58) -> 11760000 | J58: 0 | K58: BANK MASUK | L58: TERIMA SEWA KENDARAAN 1 UNIT MOBIL PERIODE BLN MEI 2025
B59: =VLOOKUP(F59,BB!$A$8:$C$152,3,0) -> A04B | C59: =C58 -> 202601 | D59: =D58 -> MDR-2601016 | E59: =E58 -> 46052 | F59: 04.002.0003 | G59: =H58 -> 0 | H59: =G58 -> 11760000 | I59: =IF(G59<>0,G59,-H59) -> -11760000 | J59: =-J58 -> 0 | K59: =K58 -> BANK MASUK | L59: =L58 -> TERIMA SEWA KENDARAAN 1 UNIT MOBIL PERIODE BLN MEI 2025
B61: =VLOOKUP(F61,BB!$A$8:$C$152,3,0) -> A02 | C61: 202601 | D61: MDR-2601017 | E61: 46052 | F61: 02.001.0000 | G61: 11760000 | H61: 0 | I61: =IF(G61<>0,G61,-H61) -> 11760000 | J61: 0 | K61: BANK MASUK | L61: TERIMA SEWA KENDARAAN 1 UNIT MOBIL PERIODE BLN JUNI 2025
B62: =VLOOKUP(F62,BB!$A$8:$C$152,3,0) -> A04B | C62: =C61 -> 202601 | D62: =D61 -> MDR-2601017 | E62: =E61 -> 46052 | F62: 04.002.0003 | G62: =H61 -> 0 | H62: =G61 -> 11760000 | I62: =IF(G62<>0,G62,-H62) -> -11760000 | J62: =-J61 -> 0 | K62: =K61 -> BANK MASUK | L62: =L61 -> TERIMA SEWA KENDARAAN 1 UNIT MOBIL PERIODE BLN JUNI 2025
B64: =VLOOKUP(F64,BB!$A$8:$C$152,3,0) -> A02 | C64: 202601 | D64: MDR-2601018 | E64: 46052 | F64: 02.001.0000 | G64: 11760000 | H64: 0 | I64: =IF(G64<>0,G64,-H64) -> 11760000 | J64: 0 | K64: BANK MASUK | L64: TERIMA SEWA KENDARAAN 1 UNIT MOBIL PERIODE BLN JULI 2025
B65: =VLOOKUP(F65,BB!$A$8:$C$152,3,0) -> A04B | C65: =C64 -> 202601 | D65: =D64 -> MDR-2601018 | E65: =E64 -> 46052 | F65: 04.002.0003 | G65: =H64 -> 0 | H65: =G64 -> 11760000 | I65: =IF(G65<>0,G65,-H65) -> -11760000 | J65: =-J64 -> 0 | K65: =K64 -> BANK MASUK | L65: =L64 -> TERIMA SEWA KENDARAAN 1 UNIT MOBIL PERIODE BLN JULI 2025
B67: =VLOOKUP(F67,BB!$A$8:$C$152,3,0) -> A02 | C67: 202601 | D67: MDR-2601019 | E67: 46052 | F67: 02.001.0000 | G67: 11760000 | H67: 0 | I67: =IF(G67<>0,G67,-H67) -> 11760000 | J67: 0 | K67: BANK MASUK | L67: TERIMA SEWA KENDARAAN 1 UNIT MOBIL PERIODE BLN AGUSTUS 2025
B68: =VLOOKUP(F68,BB!$A$8:$C$152,3,0) -> A04B | C68: =C67 -> 202601 | D68: =D67 -> MDR-2601019 | E68: =E67 -> 46052 | F68: 04.002.0003 | G68: =H67 -> 0 | H68: =G67 -> 11760000 | I68: =IF(G68<>0,G68,-H68) -> -11760000 | J68: =-J67 -> 0 | K68: =K67 -> BANK MASUK | L68: =L67 -> TERIMA SEWA KENDARAAN 1 UNIT MOBIL PERIODE BLN AGUSTUS 2025
B70: =VLOOKUP(F70,BB!$A$8:$C$152,3,0) -> A02 | C70: 202601 | D70: MDR-2601020 | E70: 46053 | F70: 02.001.0000 | G70: =IF(SUM(I71:I73)<0,-SUM(I71:I73),0) -> 40139.3 | H70: =IF(SUM(I71:I73)>0,SUM(I71:I73),0) -> 0 | I70: =IF(G70<>0,G70,-H70) -> 40139.3 | J70: =-J69 -> 0 | K70: =IF(I70>0,"BANK MASUK","BANK KELUAR") -> BANK MASUK | L70: =IF(K70="BANK MASUK","PENDAPATAN ATAS REKENING GIRO MANDIRI","BIAYA ATAS REKENING GIRO MANDIRI") -> PENDAPATAN ATAS REKENING GIRO MANDIRI
B71: =VLOOKUP(F71,BB!$A$8:$C$152,3,0) -> LR07 | C71: =C70 -> 202601 | D71: =D70 -> MDR-2601020 | E71: =E70 -> 46053 | F71: 71.000.0300 | G71: 25000 | H71: 0 | I71: =IF(G71<>0,G71,-H71) -> 25000 | J71: =-J70 -> 0 | K71: =K70 -> BANK MASUK | L71: BIAYA ADMIN GIRO
B72: =VLOOKUP(F72,BB!$A$8:$C$152,3,0) -> LR07 | C72: =C71 -> 202601 | D72: =D71 -> MDR-2601020 | E72: =E71 -> 46053 | F72: 71.000.0300 | G72: 0 | H72: 81424.12 | I72: =IF(G72<>0,G72,-H72) -> -81424.12 | J72: =-J71 -> 0 | K72: =K71 -> BANK MASUK | L72: PEND. BUNGA GIRO
B73: =VLOOKUP(F73,BB!$A$8:$C$152,3,0) -> LR07 | C73: =C72 -> 202601 | D73: =D72 -> MDR-2601020 | E73: =E72 -> 46053 | F73: 71.000.0300 | G73: 16284.82 | H73: 0 | I73: =IF(G73<>0,G73,-H73) -> 16284.82 | J73: =-J72 -> 0 | K73: =K72 -> BANK MASUK | L73: BIAYA PAJAK GIRO
B75: =VLOOKUP(F75,BB!$A$8:$C$152,3,0) -> A02 | C75: 202601 | D75: BCA-2601001 | E75: 46053 | F75: 02.002.0000 | G75: 0 | H75: 30000 | I75: =IF(G75<>0,G75,-H75) -> -30000 | J75: 0 | K75: BANK KELUAR | L75: BIAYA ADMIN GIRO
B76: =VLOOKUP(F76,BB!$A$8:$C$152,3,0) -> LR07 | C76: =C75 -> 202601 | D76: =D75 -> BCA-2601001 | E76: =E75 -> 46053 | F76: 71.000.0300 | G76: 30000 | H76: 0 | I76: =IF(G76<>0,G76,-H76) -> 30000 | J76: 0 | K76: BANK KELUAR | L76: BIAYA ADMIN GIRO
B78: =VLOOKUP(F78,BB!$A$8:$C$152,3,0) -> LR07 | C78: 202601 | D78: JRM-2601001 | E78: 46053 | F78: 71.000.0400 | G78: 1500000 | H78: 0 | I78: =IF(G78<>0,G78,-H78) -> 1500000 | J78: 0 | K78: JURNAL MANUAL | L78: PEMBEBANAN PENYISIHAN PIUTANG
B79: =VLOOKUP(F79,BB!$A$8:$C$152,3,0) -> A05 | C79: =C78 -> 202601 | D79: =D78 -> JRM-2601001 | E79: =E78 -> 46053 | F79: 05.000.0000 | G79: =H78 -> 0 | H79: =G78 -> 1500000 | I79: =IF(G79<>0,G79,-H79) -> -1500000 | J79: =-J78 -> 0 | K79: =K78 -> JURNAL MANUAL | L79: =L78 -> PEMBEBANAN PENYISIHAN PIUTANG
B81: =VLOOKUP(F81,BB!$A$8:$C$152,3,0) -> A04B | C81: 202601 | D81: JRM-2601002 | E81: 46053 | F81: 04.002.0003 | G81: =11760000 -> 11760000 | H81: 0 | I81: =IF(G81<>0,G81,-H81) -> 11760000 | J81: 0 | K81: JURNAL MANUAL | L81: JASA SEWA KENDARAAN MASA DES 2025
B82: =VLOOKUP(F82,BB!$A$8:$C$152,3,0) -> P05 | C82: =C81 -> 202601 | D82: =D81 -> JRM-2601002 | E82: =E81 -> 46053 | F82: 34.000.0003 | G82: =H81 -> 0 | H82: =11608500 -> 11608500 | I82: =IF(G82<>0,G82,-H82) -> -11608500 | J82: =-J81 -> 0 | K82: =K81 -> JURNAL MANUAL | L82: BIAYA SEWA KENDARAN MASA DES 2025
B83: =VLOOKUP(F83,BB!$A$8:$C$152,3,0) -> LR06 | C83: =+C82 -> 202601 | D83: =+D82 -> JRM-2601002 | E83: =+E82 -> 46053 | F83: 70.000.0700 | G83: 0 | H83: =+G81-H82 -> 151500 | I83: =IF(G83<>0,G83,-H83) -> -151500 | J83: 0 | K83: =+K82 -> JURNAL MANUAL | L83: LABA/RUGI DARI PENDAPATAN SEWA KENDARAAN
B85: =VLOOKUP(F85,BB!$A$8:$C$152,3,0) -> A04B | C85: 202601 | D85: JRM-2601003 | E85: 46053 | F85: 04.002.0003 | G85: =11760000 -> 11760000 | H85: 0 | I85: =IF(G85<>0,G85,-H85) -> 11760000 | J85: 0 | K85: JURNAL MANUAL | L85: JASA SEWA KENDARAAN MASA JAN 2026
B86: =VLOOKUP(F86,BB!$A$8:$C$152,3,0) -> P05 | C86: =C85 -> 202601 | D86: =D85 -> JRM-2601003 | E86: =E85 -> 46053 | F86: 34.000.0003 | G86: =H85 -> 0 | H86: =11608500 -> 11608500 | I86: =IF(G86<>0,G86,-H86) -> -11608500 | J86: =-J85 -> 0 | K86: =K85 -> JURNAL MANUAL | L86: BIAYA SEWA KENDARAN MASA JAN 2026
B87: =VLOOKUP(F87,BB!$A$8:$C$152,3,0) -> LR06 | C87: =+C86 -> 202601 | D87: =+D86 -> JRM-2601003 | E87: =+E86 -> 46053 | F87: 70.000.0700 | G87: 0 | H87: =+G85-H86 -> 151500 | I87: =IF(G87<>0,G87,-H87) -> -151500 | J87: 0 | K87: BANK KELUAR | L87: LABA/RUGI DARI PENDAPATAN SEWA KENDARAAN
B89: =VLOOKUP(F89,BB!$A$8:$C$152,3,0) -> A04B | C89: 202601 | D89: JRM-2601004 | E89: 46053 | F89: 04.002.0006 | G89: 15680000 | H89: 0 | I89: =IF(G89<>0,G89,-H89) -> 15680000 | J89: 0 | K89: JURNAL MANUAL | L89: JASA SEWA FORKLIFT MASA NOP 2025
B90: =VLOOKUP(F90,BB!$A$8:$C$152,3,0) -> P05 | C90: =C89 -> 202601 | D90: =D89 -> JRM-2601004 | E90: =E89 -> 46053 | F90: 34.000.0001 | G90: =H89 -> 0 | H90: 14475000 | I90: =IF(G90<>0,G90,-H90) -> -14475000 | J90: =-J89 -> 0 | K90: =K89 -> JURNAL MANUAL | L90: BIAYA SEWA FORKLIFT MASA NOP 2025
B91: =VLOOKUP(F91,BB!$A$8:$C$152,3,0) -> LR06 | C91: =+C90 -> 202601 | D91: =+D90 -> JRM-2601004 | E91: =+E90 -> 46053 | F91: 70.000.0800 | G91: 0 | H91: =+G89-H90 -> 1205000 | I91: =IF(G91<>0,G91,-H91) -> -1205000 | J91: 0 | K91: =+K90 -> JURNAL MANUAL | L91: LABA/RUGI DARI PENDAPATAN SEWA FORKLIFT
B93: =VLOOKUP(F93,BB!$A$8:$C$152,3,0) -> A04B | C93: 202601 | D93: JRM-2601005 | E93: 46053 | F93: 04.002.0006 | G93: 15680000 | H93: 0 | I93: =IF(G93<>0,G93,-H93) -> 15680000 | J93: 0 | K93: JURNAL MANUAL | L93: JASA SEWA FORKLIFT MASA DES 2025
B94: =VLOOKUP(F94,BB!$A$8:$C$152,3,0) -> P05 | C94: =C93 -> 202601 | D94: =D93 -> JRM-2601005 | E94: =E93 -> 46053 | F94: 34.000.0001 | G94: =H93 -> 0 | H94: 14475000 | I94: =IF(G94<>0,G94,-H94) -> -14475000 | J94: =-J93 -> 0 | K94: =K93 -> JURNAL MANUAL | L94: BIAYA SEWA FORKLIFT MASA DES 2025
B95: =VLOOKUP(F95,BB!$A$8:$C$152,3,0) -> LR06 | C95: =+C94 -> 202601 | D95: =+D94 -> JRM-2601005 | E95: =+E94 -> 46053 | F95: 70.000.0800 | G95: 0 | H95: =+G93-H94 -> 1205000 | I95: =IF(G95<>0,G95,-H95) -> -1205000 | J95: 0 | K95: =+K94 -> JURNAL MANUAL | L95: LABA/RUGI DARI PENDAPATAN SEWA FORKLIFT
B97: =VLOOKUP(F97,BB!$A$8:$C$152,3,0) -> A04B | C97: 202601 | D97: JRM-2601006 | E97: 46053 | F97: 04.002.0006 | G97: 15680000 | H97: 0 | I97: =IF(G97<>0,G97,-H97) -> 15680000 | J97: 0 | K97: JURNAL MANUAL | L97: JASA SEWA FORKLIFT MASA JAN 2026
B98: =VLOOKUP(F98,BB!$A$8:$C$152,3,0) -> P05 | C98: =C97 -> 202601 | D98: =D97 -> JRM-2601006 | E98: =E97 -> 46053 | F98: 34.000.0001 | G98: =H97 -> 0 | H98: 14475000 | I98: =IF(G98<>0,G98,-H98) -> -14475000 | J98: =-J97 -> 0 | K98: =K97 -> JURNAL MANUAL | L98: BIAYA SEWA FORKLIFT MASA JAN 2026
B99: =VLOOKUP(F99,BB!$A$8:$C$152,3,0) -> LR06 | C99: =+C98 -> 202601 | D99: =+D98 -> JRM-2601006 | E99: =+E98 -> 46053 | F99: 70.000.0800 | G99: 0 | H99: =+G97-H98 -> 1205000 | I99: =IF(G99<>0,G99,-H99) -> -1205000 | J99: 0 | K99: =+K98 -> JURNAL MANUAL | L99: LABA/RUGI DARI PENDAPATAN SEWA FORKLIFT
B101: =VLOOKUP(F101,BB!$A$8:$C$152,3,0) -> LR07 | C101: 202601 | D101: JRM-2601007 | E101: 46053 | F101: 71.000.0900 | G101: 7.5522218 | H101: 0 | I101: =IF(G101<>0,G101,-H101) -> 7.5522218 | J101: 0 | K101: JURNAL MANUAL | L101: PENYESUAIAN SELISIH PIUTANG RUTIN
B102: =VLOOKUP(F102,BB!$A$8:$C$152,3,0) -> A04A | C102: =C101 -> 202601 | D102: =D101 -> JRM-2601007 | E102: =E101 -> 46053 | F102: 04.001.0001 | G102: =H101 -> 0 | H102: =G101 -> 7.5522218 | I102: =IF(G102<>0,G102,-H102) -> -7.5522218 | J102: =-J101 -> 0 | K102: =K101 -> JURNAL MANUAL | L102: =L101 -> PENYESUAIAN SELISIH PIUTANG RUTIN
B104: =VLOOKUP(F104,BB!$A$8:$C$152,3,0) -> A01 | C104: 202601 | D104: KAS-2601001 | E104: 46028 | F104: 01.001.0000 | G104: 350000 | H104: 0 | I104: =IF(G104<>0,G104,-H104) -> 350000 | J104: 0 | K104: KAS MASUK | L104: ANGSURAN PINJAMAN LAIN AN. SOLICHIN
B105: =VLOOKUP(F105,BB!$A$8:$C$152,3,0) -> A04A | C105: =C104 -> 202601 | D105: =D104 -> KAS-2601001 | E105: =E104 -> 46028 | F105: 04.001.0004 | G105: 0 | H105: =+G104 -> 350000 | I105: =IF(G105<>0,G105,-H105) -> -350000 | J105: =-J104 -> 0 | K105: =K104 -> KAS MASUK | L105: =L104 -> ANGSURAN PINJAMAN LAIN AN. SOLICHIN
B106: =VLOOKUP(F106,BB!$A$8:$C$152,3,0) -> LR01C | C106: =C105 -> 202601 | D106: =D105 -> KAS-2601001 | E106: =E105 -> 46028 | F106: 50.003.0000 | G106: 0 | H106: =G104-H105 -> 0 | I106: =IF(G106<>0,G106,-H106) -> 0 | J106: =-J105 -> 0 | K106: =K105 -> KAS MASUK | L106: ="PENDAPATAN ATAS PINJAMAN LAIN "&MID(L105,24,20) -> PENDAPATAN ATAS PINJAMAN LAIN AN. SOLICHIN
B108: =VLOOKUP(F108,BB!$A$8:$C$152,3,0) -> A01 | C108: 202601 | D108: KAS-2601002 | E108: 46031 | F108: 01.001.0000 | G108: 425000 | H108: 0 | I108: =IF(G108<>0,G108,-H108) -> 425000 | J108: 0 | K108: KAS MASUK | L108: PELUNASAN PINJAMAN LAIN AN. ARI WIBOWO
B109: =VLOOKUP(F109,BB!$A$8:$C$152,3,0) -> A04A | C109: =C108 -> 202601 | D109: =D108 -> KAS-2601002 | E109: =E108 -> 46031 | F109: 04.001.0004 | G109: 0 | H109: 250000 | I109: =IF(G109<>0,G109,-H109) -> -250000 | J109: =-J108 -> 0 | K109: =K108 -> KAS MASUK | L109: =L108 -> PELUNASAN PINJAMAN LAIN AN. ARI WIBOWO
B110: =VLOOKUP(F110,BB!$A$8:$C$152,3,0) -> LR01C | C110: =C109 -> 202601 | D110: =D109 -> KAS-2601002 | E110: =E109 -> 46031 | F110: 50.003.0000 | G110: 0 | H110: =G108-H109 -> 175000 | I110: =IF(G110<>0,G110,-H110) -> -175000 | J110: =-J109 -> 0 | K110: =K109 -> KAS MASUK | L110: ="PENDAPATAN ATAS PINJAMAN LAIN "&MID(L109,24,20) -> PENDAPATAN ATAS PINJAMAN LAIN AN. ARI WIBOWO
B112: =VLOOKUP(F112,BB!$A$8:$C$152,3,0) -> A01 | C112: 202601 | D112: KAS-2601003 | E112: 46031 | F112: 01.001.0000 | G112: 0 | H112: 2000000 | I112: =IF(G112<>0,G112,-H112) -> -2000000 | J112: 0 | K112: KAS KELUAR | L112: PINJAMAN LAIN AN. ARI WIBOWO
B113: =VLOOKUP(F113,BB!$A$8:$C$152,3,0) -> A04A | C113: =C112 -> 202601 | D113: =D112 -> KAS-2601003 | E113: =E112 -> 46031 | F113: 04.001.0004 | G113: =H112 -> 2000000 | H113: =G112 -> 0 | I113: =IF(G113<>0,G113,-H113) -> 2000000 | J113: =-J112 -> 0 | K113: =K112 -> KAS KELUAR | L113: =L112 -> PINJAMAN LAIN AN. ARI WIBOWO
B115: =VLOOKUP(F115,BB!$A$8:$C$152,3,0) -> A01 | C115: 202601 | D115: KAS-2601004 | E115: 46031 | F115: 01.001.0000 | G115: 1700000 | H115: 0 | I115: =IF(G115<>0,G115,-H115) -> 1700000 | J115: 0 | K115: KAS MASUK | L115: PELUNASAN PINJAMAN LAIN AN. AGUS RIYANTO
B116: =VLOOKUP(F116,BB!$A$8:$C$152,3,0) -> A04A | C116: =C115 -> 202601 | D116: =D115 -> KAS-2601004 | E116: =E115 -> 46031 | F116: 04.001.0004 | G116: 0 | H116: 1350000 | I116: =IF(G116<>0,G116,-H116) -> -1350000 | J116: =-J115 -> 0 | K116: =K115 -> KAS MASUK | L116: =L115 -> PELUNASAN PINJAMAN LAIN AN. AGUS RIYANTO
B117: =VLOOKUP(F117,BB!$A$8:$C$152,3,0) -> LR01C | C117: =C116 -> 202601 | D117: =D116 -> KAS-2601004 | E117: =E116 -> 46031 | F117: 50.003.0000 | G117: 0 | H117: =G115-H116 -> 350000 | I117: =IF(G117<>0,G117,-H117) -> -350000 | J117: =-J116 -> 0 | K117: =K116 -> KAS MASUK | L117: ="PENDAPATAN ATAS PINJAMAN LAIN "&MID(L116,24,20) -> PENDAPATAN ATAS PINJAMAN LAIN AN. AGUS RIYANTO
B119: =VLOOKUP(F119,BB!$A$8:$C$152,3,0) -> A01 | C119: 202601 | D119: KAS-2601005 | E119: 46031 | F119: 01.001.0000 | G119: 0 | H119: 8000 | I119: =IF(G119<>0,G119,-H119) -> -8000 | J119: 0 | K119: KAS KELUAR | L119: ONGKIR BAJU PAK KOSA
B120: =VLOOKUP(F120,BB!$A$8:$C$152,3,0) -> LR05 | C120: =C119 -> 202601 | D120: =D119 -> KAS-2601005 | E120: =E119 -> 46031 | F120: 60.003.0200 | G120: =H119 -> 8000 | H120: =G119 -> 0 | I120: =IF(G120<>0,G120,-H120) -> 8000 | J120: =-J119 -> 0 | K120: =K119 -> KAS KELUAR | L120: =L119 -> ONGKIR BAJU PAK KOSA
B122: =VLOOKUP(F122,BB!$A$8:$C$152,3,0) -> A01 | C122: 202601 | D122: KAS-2601006 | E122: 46032 | F122: 01.001.0000 | G122: 0 | H122: 750000 | I122: =IF(G122<>0,G122,-H122) -> -750000 | J122: 0 | K122: KAS KELUAR | L122: BY REPRESENTATIF ADMIN KKCS FARID F
B123: =VLOOKUP(F123,BB!$A$8:$C$152,3,0) -> LR05 | C123: =C122 -> 202601 | D123: =D122 -> KAS-2601006 | E123: =E122 -> 46032 | F123: 60.001.0300 | G123: =H122 -> 750000 | H123: =G122 -> 0 | I123: =IF(G123<>0,G123,-H123) -> 750000 | J123: =-J122 -> 0 | K123: =K122 -> KAS KELUAR | L123: =L122 -> BY REPRESENTATIF ADMIN KKCS FARID F
B125: =VLOOKUP(F125,BB!$A$8:$C$152,3,0) -> A01 | C125: 202601 | D125: KAS-2601007 | E125: 46042 | F125: 01.001.0000 | G125: 214000 | H125: 0 | I125: =IF(G125<>0,G125,-H125) -> 214000 | J125: 0 | K125: KAS MASUK | L125: ANGSURAN PINJAMAN LAIN AN. SETYO H
B126: =VLOOKUP(F126,BB!$A$8:$C$152,3,0) -> A04A | C126: =C125 -> 202601 | D126: =D125 -> KAS-2601007 | E126: =E125 -> 46042 | F126: 04.001.0004 | G126: 0 | H126: =+G125 -> 214000 | I126: =IF(G126<>0,G126,-H126) -> -214000 | J126: =-J125 -> 0 | K126: =K125 -> KAS MASUK | L126: =L125 -> ANGSURAN PINJAMAN LAIN AN. SETYO H
B127: =VLOOKUP(F127,BB!$A$8:$C$152,3,0) -> LR01C | C127: =C126 -> 202601 | D127: =D126 -> KAS-2601007 | E127: =E126 -> 46042 | F127: 50.003.0000 | G127: 0 | H127: =G125-H126 -> 0 | I127: =IF(G127<>0,G127,-H127) -> 0 | J127: =-J126 -> 0 | K127: =K126 -> KAS MASUK | L127: ="PENDAPATAN ATAS PINJAMAN LAIN "&MID(L126,24,20) -> PENDAPATAN ATAS PINJAMAN LAIN AN. SETYO H
B129: =VLOOKUP(F129,BB!$A$8:$C$152,3,0) -> A01 | C129: 202601 | D129: KAS-2601008 | E129: 46045 | F129: 01.001.0000 | G129: 200000 | H129: 0 | I129: =IF(G129<>0,G129,-H129) -> 200000 | J129: 0 | K129: KAS MASUK | L129: ANGSURAN PINJAMAN LAIN AN. ARI WIBOWO
B130: =VLOOKUP(F130,BB!$A$8:$C$152,3,0) -> A04A | C130: =C129 -> 202601 | D130: =D129 -> KAS-2601008 | E130: =E129 -> 46045 | F130: 04.001.0004 | G130: 0 | H130: =+G129 -> 200000 | I130: =IF(G130<>0,G130,-H130) -> -200000 | J130: =-J129 -> 0 | K130: =K129 -> KAS MASUK | L130: =L129 -> ANGSURAN PINJAMAN LAIN AN. ARI WIBOWO
B131: =VLOOKUP(F131,BB!$A$8:$C$152,3,0) -> LR01C | C131: =C130 -> 202601 | D131: =D130 -> KAS-2601008 | E131: =E130 -> 46045 | F131: 50.003.0000 | G131: 0 | H131: =G129-H130 -> 0 | I131: =IF(G131<>0,G131,-H131) -> 0 | J131: =-J130 -> 0 | K131: =K130 -> KAS MASUK | L131: ="PENDAPATAN ATAS PINJAMAN LAIN "&MID(L130,24,20) -> PENDAPATAN ATAS PINJAMAN LAIN AN. ARI WIBOWO
B133: =VLOOKUP(F133,BB!$A$8:$C$152,3,0) -> A01 | C133: 202601 | D133: KAS-2601009 | E133: 46046 | F133: 01.001.0000 | G133: 267500 | H133: 0 | I133: =IF(G133<>0,G133,-H133) -> 267500 | J133: 0 | K133: KAS MASUK | L133: ANGSURAN PINJAMAN LAIN AN. HANDOKO TS
B134: =VLOOKUP(F134,BB!$A$8:$C$152,3,0) -> A04A | C134: =C133 -> 202601 | D134: =D133 -> KAS-2601009 | E134: =E133 -> 46046 | F134: 04.001.0004 | G134: 0 | H134: =+G133 -> 267500 | I134: =IF(G134<>0,G134,-H134) -> -267500 | J134: =-J133 -> 0 | K134: =K133 -> KAS MASUK | L134: =L133 -> ANGSURAN PINJAMAN LAIN AN. HANDOKO TS
B135: =VLOOKUP(F135,BB!$A$8:$C$152,3,0) -> LR01C | C135: =C134 -> 202601 | D135: =D134 -> KAS-2601009 | E135: =E134 -> 46046 | F135: 50.003.0000 | G135: 0 | H135: =G133-H134 -> 0 | I135: =IF(G135<>0,G135,-H135) -> 0 | J135: =-J134 -> 0 | K135: =K134 -> KAS MASUK | L135: ="PENDAPATAN ATAS PINJAMAN LAIN "&MID(L134,24,20) -> PENDAPATAN ATAS PINJAMAN LAIN AN. HANDOKO TS
B137: =VLOOKUP(F137,BB!$A$8:$C$152,3,0) -> A01 | C137: 202601 | D137: KAS-2601010 | E137: 46047 | F137: 01.001.0000 | G137: 321000 | H137: 0 | I137: =IF(G137<>0,G137,-H137) -> 321000 | J137: 0 | K137: KAS MASUK | L137: ANGSURAN PINJAMAN LAIN AN. BUKHORI
B138: =VLOOKUP(F138,BB!$A$8:$C$152,3,0) -> A04A | C138: =C137 -> 202601 | D138: =D137 -> KAS-2601010 | E138: =E137 -> 46047 | F138: 04.001.0004 | G138: 0 | H138: =+G137 -> 321000 | I138: =IF(G138<>0,G138,-H138) -> -321000 | J138: =-J137 -> 0 | K138: =K137 -> KAS MASUK | L138: =L137 -> ANGSURAN PINJAMAN LAIN AN. BUKHORI
...

Sheet PIRUT
D4: =SUBTOTAL(9,D8:D98) -> 1.8984218e+09 | F4: =SUBTOTAL(9,F8:F98) -> -167166668 | G4: =SUBTOTAL(9,G8:G98) -> 280000000 | H4: =SUBTOTAL(9,H8:H98) -> 0 | I4: =SUBTOTAL(9,I8:I98) -> -60419861 | J4: =SUBTOTAL(9,J8:J98) -> 1.9508353e+09
B5: N A M A | D5: SALDO AWAL TAHUN | F5: JANUARI
D6: SALDO BB | F6: KOMPENSASI | G6: UTANG | H6: BAYAR MANDIRI | I6: BAYAR POTONG | J6: SALDO BB
B7: .
B8: ABDUL RAHMAN, SE | D8: 23333333 | F8: 0 | G8: 0 | H8: 0 | I8: -833333.33 | J8: =D8+F8+G8+H8+I8 -> 22500000
B9: ABDUL ROCHIM,SP. | D9: 0 | F9: 0 | G9: 0 | H9: 0 | I9: 0 | J9: =D9+F9+G9+H9+I9 -> 0
B10: ACH. WACHYUDI | D10: 32083333 | F10: 0 | G10: 0 | H10: 0 | I10: -1666666.7 | J10: =D10+F10+G10+H10+I10 -> 30416667
B11: ADY PURNOMO | D11: 0 | F11: 0 | G11: 0 | H11: 0 | I11: 0 | J11: =D11+F11+G11+H11+I11 -> 0
B12: AENAL DARWIS | D12: 0 | F12: 0 | G12: 0 | H12: 0 | I12: 0 | J12: =D12+F12+G12+H12+I12 -> 0
B13: AGHNIA PUTRI RUSIANTO | D13: 0 | F13: 0 | G13: 0 | H13: 0 | I13: 0 | J13: =D13+F13+G13+H13+I13 -> 0
B14: AHMAD MUKHLIS K. | D14: 30333333 | F14: 0 | G14: 0 | H14: 0 | I14: -1166666.7 | J14: =D14+F14+G14+H14+I14 -> 29166667
B15: ARDHI YUNANTO | D15: 95000000 | F15: 0 | G15: 0 | H15: 0 | I15: -1666666.7 | J15: =D15+F15+G15+H15+I15 -> 93333333
B16: ARI KUNCORO | D16: 0 | F16: 0 | G16: 0 | H16: 0 | I16: 0 | J16: =D16+F16+G16+H16+I16 -> 0
B17: ARI RAHAYU | D17: 0 | F17: 0 | G17: 0 | H17: 0 | I17: 0 | J17: =D17+F17+G17+H17+I17 -> 0
B18: BAGUS ADITA | D18: 93333333 | F18: 0 | G18: 0 | H18: 0 | I18: -2000000 | J18: =D18+F18+G18+H18+I18 -> 91333333
B19: BAMBANG SYAMADJI | D19: 20277778 | F19: 0 | G19: 0 | H19: 0 | I19: -1111111.1 | J19: 19166667
B20: BURNAMA KUSUMA DR.,SE | D20: 0 | F20: 0 | G20: 0 | H20: 0 | I20: 0 | J20: =D20+F20+G20+H20+I20 -> 0
B21: CHOIRI,SE | D21: 34027778 | F21: 0 | G21: 0 | H21: 0 | I21: -972222.22 | J21: =D21+F21+G21+H21+I21 -> 33055556
B22: DANDUNG KASIATNO | D22: 40416666 | F22: 0 | G22: 0 | H22: 0 | I22: -1736111.1 | J22: =D22+F22+G22+H22+I22 -> 38680555
B23: DARWANTO | D23: 74000000 | F23: -72166667 | G23: 100000000 | H23: 0 | I23: -1833333.3 | J23: =D23+F23+G23+H23+I23 -> 1e+08
B24: DEWI FATMAWATI | D24: 0 | F24: 0 | G24: 0 | H24: 0 | I24: 0 | J24: =D24+F24+G24+H24+I24 -> 0
B25: DIAH PUSPITASARI | D25: 0 | F25: 0 | G25: 0 | H25: 0 | I25: 0 | J25: =D25+F25+G25+H25+I25 -> 0
B26: DICKY SUSANTHO | D26: 41666667 | F26: 0 | G26: 0 | H26: 0 | I26: -1388888.9 | J26: =D26+F26+G26+H26+I26 -> 40277778
B27: DWI RINI P, SE | D27: 0 | F27: 0 | G27: 0 | H27: 0 | I27: 0 | J27: =D27+F27+G27+H27+I27 -> 0
B28: ENDIN TAFRIORO | D28: 0 | F28: 0 | G28: 0 | H28: 0 | I28: 0 | J28: =D28+F28+G28+H28+I28 -> 0
B29: ERLY NURLIANTI | D29: 26250000 | F29: 0 | G29: 0 | H29: 0 | I29: -2916666.7 | J29: =D29+F29+G29+H29+I29 -> 23333333
B30: FABIAN ABDUL GAFFAR | D30: 0 | F30: 0 | G30: 0 | H30: 0 | I30: 0 | J30: =D30+F30+G30+H30+I30 -> 0
B31: FADELAN CHADARIANTO | D31: 30000000 | F31: 0 | G31: 0 | H31: 0 | I31: -1666666.7 | J31: =D31+F31+G31+H31+I31 -> 28333333
... B96: YUDISTIRA SIGIT W. | D96: 0 | F96: 0 | G96: 0 | H96: 0 | I96: 0 | J96: =D96+F96+G96+H96+I96 -> 0
D97: 0 | F97: 0 | G97: 0 | H97: 0 | I97: 0 | J97: =D97+F97+G97+H97+I97 -> 0
D98: 0 | F98: 0 | G98: 0 | H98: 0 | I98: 0 | J98: =D98+F98+G98+H98+I98 -> 0

Sheet BB
F1: AKTIVA | H1: =SUMIF($B$8:$B$152,"A",$H$8:$H$152) -> 2.6993717e+09 | I1: =+H1-NR!F37 -> -2.4945402e+09 | L1: =SUMIF($B$8:$B$152,"A",$L$8:$L$152) -> 2.7526129e+09
F2: PASIVA | H2: =SUMIF($B$8:$B$152,"P",$H$8:$H$152) -> -2.6993717e+09 | I2: =+H2+NR!M37 -> 2.4945402e+09 | L2: =SUMIF($B$8:$B$152,"P",$L$8:$L$152) -> -2.7321217e+09
F3: LR | H3: =SUMIF($B$8:$B$152,"L",$H$8:$H$152) -> 0 | L3: =SUMIF($B$8:$B$152,"L",$L$8:$L$152) -> -20491175
H4: =SUM(H1:H3) -> 0 | L4: =SUM(L1:L3) -> -3.46452e-07
F5: SUBTOTAL | H5: =SUBTOTAL(9,H8:H152) -> -2.5331974e-07 | I5: =SUBTOTAL(9,I8:I152) -> 6.213338e+08 | J5: =SUBTOTAL(9,J8:J152) -> 6.213338e+08 | K5: =SUBTOTAL(9,K8:K152) -> 1.1874363e-08 | L5: =SUBTOTAL(9,L8:L152) -> -5.9907325e-07
A7: Account | E7: Report_NR | F7: Keterangan | H7: SALDO AWAL | I7: DEBET | J7: KREDIT | K7: MUTASI | L7: SALDO AKHIR
A8: 01.000.0000 | B8: A | C8: A01 | E8: Debet | F8: KAS | H8: 0 | I8: =SUMIF('MUTASI 2026'!$F$5:$F$1048576,BB!A8,'MUTASI 2026'!$G$5:$G$1048576) -> 0 | J8: =SUMIF('MUTASI 2026'!$F$5:$F$1048576,BB!A8,'MUTASI 2026'!$H$5:$H$1048576) -> 0 | K8: =I8-J8 -> 0 | L8: =+H8+K8 -> 0
A9: 01.001.0000 | B9: A | C9: A01 | E9: Debet | F9: KAS INDUK | H9: 8851508.7 | I9: =SUMIF('MUTASI 2026'!$F$5:$F$1048576,BB!A9,'MUTASI 2026'!$G$5:$G$1048576) -> 4865000 | J9: =SUMIF('MUTASI 2026'!$F$5:$F$1048576,BB!A9,'MUTASI 2026'!$H$5:$H$1048576) -> 5258000 | K9: =I9-J9 -> -393000 | L9: =+H9+K9 -> 8458508.7
A10: 01.009.0000 | B10: A | C10: A01 | E10: Debet | F10: AYAT SILANG KAS & BANK | H10: 0 | I10: =SUMIF('MUTASI 2026'!$F$5:$F$1048576,BB!A10,'MUTASI 2026'!$G$5:$G$1048576) -> 0 | J10: =SUMIF('MUTASI 2026'!$F$5:$F$1048576,BB!A10,'MUTASI 2026'!$H$5:$H$1048576) -> 0 | K10: =I10-J10 -> 0 | L10: =+H10+K10 -> 0
A11: 02.000.0000 | B11: A | C11: A02 | E11: Debet | F11: BANK | H11: 0 | I11: =SUMIF('MUTASI 2026'!$F$5:$F$1048576,BB!A11,'MUTASI 2026'!$G$5:$G$1048576) -> 0 | J11: =SUMIF('MUTASI 2026'!$F$5:$F$1048576,BB!A11,'MUTASI 2026'!$H$5:$H$1048576) -> 0 | K11: =I11-J11 -> 0 | L11: =+H11+K11 -> 0
A12: 02.001.0000 | B12: A | C12: A02 | E12: Debet | F12: BANK MANDIRI | H12: 2.3118002e+08 | I12: =SUMIF('MUTASI 2026'!$F$5:$F$1048576,BB!A12,'MUTASI 2026'!$G$5:$G$1048576) -> 1.6096184e+08 | J12: =SUMIF('MUTASI 2026'!$F$5:$F$1048576,BB!A12,'MUTASI 2026'!$H$5:$H$1048576) -> 150531132 | K12: =I12-J12 -> 10430711 | L12: =+H12+K12 -> 2.4161073e+08
A13: 02.002.0000 | B13: A | C13: A02 | E13: Debet | F13: BANK CENTRAL ASIA (BCA) | H13: 71776656 | I13: =SUMIF('MUTASI 2026'!$F$5:$F$1048576,BB!A13,'MUTASI 2026'!$G$5:$G$1048576) -> 0 | J13: =SUMIF('MUTASI 2026'!$F$5:$F$1048576,BB!A13,'MUTASI 2026'!$H$5:$H$1048576) -> 30000 | K13: =I13-J13 -> -30000 | L13: =+H13+K13 -> 71746656
A14: 03.000.0000 | B14: A | C14: A03 | E14: Debet | F14: SURAT BERHARGA | H14: 0 | I14: =SUMIF('MUTASI 2026'!$F$5:$F$1048576,BB!A14,'MUTASI 2026'!$G$5:$G$1048576) -> 0 | J14: =SUMIF('MUTASI 2026'!$F$5:$F$1048576,BB!A14,'MUTASI 2026'!$H$5:$H$1048576) -> 0 | K14: =I14-J14 -> 0 | L14: =+H14+K14 -> 0
A15: 03.001.0000 | B15: A | C15: A03 | E15: Debet | F15: SIMPANAN INVESTASI | H15: 0 | I15: =SUMIF('MUTASI 2026'!$F$5:$F$1048576,BB!A15,'MUTASI 2026'!$G$5:$G$1048576) -> 0 | J15: =SUMIF('MUTASI 2026'!$F$5:$F$1048576,BB!A15,'MUTASI 2026'!$H$5:$H$1048576) -> 0 | K15: =I15-J15 -> 0 | L15: =+H15+K15 -> 0
A16: 03.002.0000 | B16: A | C16: A03 | E16: Debet | F16: DEPOSITO | H16: 0 | I16: =SUMIF('MUTASI 2026'!$F$5:$F$1048576,BB!A16,'MUTASI 2026'!$G$5:$G$1048576) -> 0 | J16: =SUMIF('MUTASI 2026'!$F$5:$F$1048576,BB!A16,'MUTASI 2026'!$H$5:$H$1048576) -> 0 | K16: =I16-J16 -> 0 | L16: =+H16+K16 -> 0
A17: 04.000.0000 | B17: A | C17: A04 | E17: Debet | F17: PIUTANG USAHA | H17: 0 | I17: =SUMIF('MUTASI 2026'!$F$5:$F$1048576,BB!A17,'MUTASI 2026'!$G$5:$G$1048576) -> 0 | J17: =SUMIF('MUTASI 2026'!$F$5:$F$1048576,BB!A17,'MUTASI 2026'!$H$5:$H$1048576) -> 0 | K17: =I17-J17 -> 0 | L17: =+H17+K17 -> 0
A18: 04.001.0000 | B18: A | C18: A04A | E18: Debet | F18: PIUTANG ANGGOTA | H18: 0 | I18: =SUMIF('MUTASI 2026'!$F$5:$F$1048576,BB!A18,'MUTASI 2026'!$G$5:$G$1048576) -> 0 | J18: =SUMIF('MUTASI 2026'!$F$5:$F$1048576,BB!A18,'MUTASI 2026'!$H$5:$H$1048576) -> 0 | K18: =I18-J18 -> 0 | L18: =+H18+K18 -> 0
A19: 04.001.0001 | B19: A | C19: A04A | E19: Debet | F19: PINJAMAN RUTIN | H19: 1.8984218e+09 | I19: =SUMIF('MUTASI 2026'!$F$5:$F$1048576,BB!A19,'MUTASI 2026'!$G$5:$G$1048576) -> 280000000 | J19: =SUMIF('MUTASI 2026'!$F$5:$F$1048576,BB!A19,'MUTASI 2026'!$H$5:$H$1048576) -> 2.2758654e+08 | K19: =I19-J19 -> 52413463 | L19: =+H19+K19 -> 1.9508353e+09
... A108: 46.000.0000 | B108: P | C108: P16 | E108: Kredit | F108: LABA / (RUGI) TAHUN BERJALAN | H108: 0 | I108: =SUMIF('MUTASI 2026'!$F$5:$F$1048576,BB!A108,'MUTASI 2026'!$G$5:$G$1048576) -> 0 | J108: =SUMIF('MUTASI 2026'!$F$5:$F$1048576,BB!A108,'MUTASI 2026'!$H$5:$H$1048576) -> 0 | K108: =I108-J108 -> 0 | L108: =+H108+K108 -> 0
A109: 50.000.0000 | B109: L | C109: LR01 | D109: PP | E109: Kredit | F109: PENDAPATAN | H109: 0 | I109: =SUMIF('MUTASI 2026'!$F$5:$F$1048576,BB!A109,'MUTASI 2026'!$G$5:$G$1048576) -> 0 | J109: =SUMIF('MUTASI 2026'!$F$5:$F$1048576,BB!A109,'MUTASI 2026'!$H$5:$H$1048576) -> 0 | K109: =I109-J109 -> 0 | L109: =+H109+K109 -> 0
A110: 50.001.0000 | B110: L | C110: LR01A | D110: PP | E110: Kredit | F110: PENDAPATAN PINJAMAN RUTIN | H110: 0 | I110: =SUMIF('MUTASI 2026'!$F$5:$F$1048576,BB!A110,'MUTASI 2026'!$G$5:$G$1048576) -> 0 | J110: =SUMIF('MUTASI 2026'!$F$5:$F$1048576,BB!A110,'MUTASI 2026'!$H$5:$H$1048576) -> 78721705 | K110: =I110-J110 -> -78721705 | L110: =+H110+K110 -> -78721705
A111: 50.002.0000 | B111: L | C111: LR01B | D111: PP | E111: Kredit | F111: PENDAPATAN PINJAMAN KHUSUS | H111: 0 | I111: =SUMIF('MUTASI 2026'!$F$5:$F$1048576,BB!A111,'MUTASI 2026'!$G$5:$G$1048576) -> 0 | J111: =SUMIF('MUTASI 2026'!$F$5:$F$1048576,BB!A111,'MUTASI 2026'!$H$5:$H$1048576) -> 0 | K111: =I111-J111 -> 0 | L111: =+H111+K111 -> 0
A112: 50.003.0000 | B112: L | C112: LR01C | D112: PP | E112: Kredit | F112: PENDAPATAN PINJAMAN LAIN-LAIN | H112: 0 | I112: =SUMIF('MUTASI 2026'!$F$5:$F$1048576,BB!A112,'MUTASI 2026'!$G$5:$G$1048576) -> 0 | J112: =SUMIF('MUTASI 2026'!$F$5:$F$1048576,BB!A112,'MUTASI 2026'!$H$5:$H$1048576) -> 525000 | K112: =I112-J112 -> -525000 | L112: =+H112+K112 -> -525000
A113: 51.000.0000 | B113: L | C113: LR02 | D113: PP | E113: Debet | F113: BIAYA POKOK | H113: 0 | I113: =SUMIF('MUTASI 2026'!$F$5:$F$1048576,BB!A113,'MUTASI 2026'!$G$5:$G$1048576) -> 0 | J113: =SUMIF('MUTASI 2026'!$F$5:$F$1048576,BB!A113,'MUTASI 2026'!$H$5:$H$1048576) -> 0 | K113: =I113-J113 -> 0 | L113: =+H113+K113 -> 0
A114: 51.001.0000 | B114: L | C114: LR02A | D114: PP | E114: Debet | F114: BIAYA POKOK PINJAMAN RUTIN | H114: 0 | I114: =SUMIF('MUTASI 2026'!$F$5:$F$1048576,BB!A114,'MUTASI 2026'!$G$5:$G$1048576) -> 60419861 | J114: =SUMIF('MUTASI 2026'!$F$5:$F$1048576,BB!A114,'MUTASI 2026'!$H$5:$H$1048576) -> 0 | K114: =I114-J114 -> 60419861 | L114: =+H114+K114 -> 60419861
A115: 51.002.0000 | B115: L | C115: LR02B | D115: PP | E115: Debet | F115: BIAYA POKOK PINJAMAN KHUSUS | H115: 0 | I115: =SUMIF('MUTASI 2026'!$F$5:$F$1048576,BB!A115,'MUTASI 2026'!$G$5:$G$1048576) -> 0 | J115: =SUMIF('MUTASI 2026'!$F$5:$F$1048576,BB!A115,'MUTASI 2026'!$H$5:$H$1048576) -> 0 | K115: =I115-J115 -> 0 | L115: =+H115+K115 -> 0
A116: 51.003.0000 | B116: L | C116: LR02C | D116: PP | E116: Debet | F116: BIAYA POKOK PINJAMAN LAIN-LAIN | H116: 0 | I116: =SUMIF('MUTASI 2026'!$F$5:$F$1048576,BB!A116,'MUTASI 2026'!$G$5:$G$1048576) -> 0 | J116: =SUMIF('MUTASI 2026'!$F$5:$F$1048576,BB!A116,'MUTASI 2026'!$H$5:$H$1048576) -> 0 | K116: =I116-J116 -> 0 | L116: =+H116+K116 -> 0
A117: 60.000.0000 | B117: L | C117: LR05 | D117: BO | E117: Debet | F117: BIAYA UMUM DAN ADMINISTRASI | H117: 0 | I117: =SUMIF('MUTASI 2026'!$F$5:$F$1048576,BB!A117,'MUTASI 2026'!$G$5:$G$1048576) -> 0 | J117: =SUMIF('MUTASI 2026'!$F$5:$F$1048576,BB!A117,'MUTASI 2026'!$H$5:$H$1048576) -> 0 | K117: =I117-J117 -> 0 | L117: =+H117+K117 -> 0
A118: 60.001.0000 | B118: L | C118: LR05 | D118: BO | E118: Debet | F118: BIAYA PEGAWAI | H118: 0 | I118: =SUMIF('MUTASI 2026'!$F$5:$F$1048576,BB!A118,'MUTASI 2026'!$G$5:$G$1048576) -> 0 | J118: =SUMIF('MUTASI 2026'!$F$5:$F$1048576,BB!A118,'MUTASI 2026'!$H$5:$H$1048576) -> 0 | K118: =I118-J118 -> 0 | L118: =+H118+K118 -> 0
A119: 60.001.0100 | B119: L | C119: LR05 | D119: BO | E119: Debet | F119: BIAYA GAJI | H119: 0 | I119: =SUMIF('MUTASI 2026'!$F$5:$F$1048576,BB!A119,'MUTASI 2026'!$G$5:$G$1048576) -> 0 | J119: =SUMIF('MUTASI 2026'!$F$5:$F$1048576,BB!A119,'MUTASI 2026'!$H$5:$H$1048576) -> 0 | K119: =I119-J119 -> 0 | L119: =+H119+K119 -> 0
A120: 60.001.0200 | B120: L | C120: LR05 | D120: BO | E120: Debet | F120: BIAYA INSENTIF | H120: 0 | I120: =SUMIF('MUTASI 2026'!$F$5:$F$1048576,BB!A120,'MUTASI 2026'!$G$5:$G$1048576) -> 0 | J120: =SUMIF('MUTASI 2026'!$F$5:$F$1048576,BB!A120,'MUTASI 2026'!$H$5:$H$1048576) -> 0 | K120: =I120-J120 -> 0 | L120: =+H120+K120 -> 0
... A152: 80.000.0002 | B152: L | C152: LR08 | D152: PJ | E152: Debet | F152: BEBAN PAJAK TANGGUHAN | H152: 0 | I152: =SUMIF('MUTASI 2026'!$F$5:$F$1048576,BB!A152,'MUTASI 2026'!$G$5:$G$1048576) -> 0 | J152: =SUMIF('MUTASI 2026'!$F$5:$F$1048576,BB!A152,'MUTASI 2026'!$H$5:$H$1048576) -> 0 | K152: =I152-J152 -> 0 | L152: =+H152+K152 -> 0
