Workbook
Name ACC: #REF!
Name ACC: #REF!
Name ACC: #REF!
Name ACC: #REF!
Name ACCOUNT: #REF!
Name ACCOUNT: #REF!
Name ACCOUNT: #REF!
Name ACCOUNT: #REF!
Name AKUN: #REF!
Name AKUN: #REF!
Name AKUN: #REF!
Name AKUN: #REF!
Name AKUNDUA: #REF!
Name AKUNDUA: #REF!
Name AKUNDUA: #REF!
Name AKUNDUA: #REF!
Name AKUNEMPAT: #REF!
Name AKUNEMPAT: #REF!
Name AKUNEMPAT: #REF!
Name AKUNEMPAT: #REF!
Name akunlima: [1]AKUNLIMA!$A$2:$C$310
Name AKUNTIGA: #REF!
Name AKUNTIGA: #REF!
Name AKUNTIGA: #REF!
Name AKUNTIGA: #REF!
Name asa: #REF!
Name asa: #REF!
Name JAN: #REF!
Name JAN: #REF!
Name JAN: #REF!
Name JAN: #REF!
Name OMSET: #REF!
Name OMSET: #REF!
Name OMSET: #REF!
Name OMSET: #REF!

Sheet NR
B2: NERACA
B3: K K C S
B4: TAHUN 2023 - 2026
B6: No | C6: Uraian | D6: PER | E6: PER | F6: PER | G6: PER | H6: PER | I6: No | J6: Uraian | K6: =D6 -> PER | L6: =E6 -> PER | M6: =F6 -> PER | N6: =G6 -> PER | O6: =H6 -> PER
D7: 31 Desember 2022 | E7: 31 Desember 2023 | F7: 31 Desember 2024 | G7: 31 Desember 2025 | H7: 31 Januari 2026 | K7: =D7 -> 31 Desember 2022 | L7: =E7 -> 31 Desember 2023 | M7: =F7 -> 31 Desember 2024 | N7: =G7 -> 31 Desember 2025 | O7: =H7 -> 31 Januari 2026
B8: I | C8: Aset Lancar | I8: VII | J8: Liabilitas Jangka Pendek
C9: Kas | D9: 22964481 | E9: 5751013.7 | F9: 1788563.7 | G9: 8851508.7 | H9: ='WS Trial balance'!BZ7 -> 4827416.7 | J9: Simpanan Sukarela I | K9: 0 | L9: 0 | M9: 0 | N9: 0 | O9: 0
C10: Bank | D10: 38487372 | E10: 53412528 | F10: 42405266 | G10: 3.0295667e+08 | H10: ='WS Trial balance'!BZ8 -> 1.9671383e+08 | J10: Simpanan Sukarela II | K10: 0 | L10: 0 | M10: 0 | N10: 0 | O10: 0
C11: Surat Berharga | D11: 0 | E11: 0 | F11: 0 | G11: 0 | H11: ='WS Trial balance'!CA9 -> 0 | J11: Utang Anggota | K11: 0 | L11: 0 | M11: 0 | N11: 0 | O11: 0
C12: Piutang Anggota | D12: 1.5707596e+09 | E12: 1.7547836e+09 | F12: 1.9778942e+09 | G12: 1.9264197e+09 | H12: =+'WS Trial balance'!BZ10 -> 1.979003e+09 | J12: Utang Non Anggota | K12: 6033860000 | L12: 6164854500 | M12: 2850000000 | N12: 300000000 | O12: =+'WS Trial balance'!CA31 -> 300000000
C13: Piutang Non Anggota | D13: 6561449467 | E13: 6.7210876e+09 | F13: 3335823867 | G13: 643143867 | H13: =+'WS Trial balance'!BZ11 -> 698023867
C14: Cad. Penyisihan | D14: -75000000 | E14: -155000000 | F14: -164000000 | G14: -182000000 | H14: =-'WS Trial balance'!CA12 -> -194000000 | J14: Utang Pajak | K14: 0 | L14: 5244487.6 | M14: 29607286 | N14: 47686535 | O14: =+'WS Trial balance'!CA36 -> 17636043
C15: Biaya yg Dibayar Dimuka | D15: 0 | E15: 0 | F15: 0 | G15: 0 | H15: ='WS Trial balance'!BZ15 -> 11608500 | J15: Utang Bunga | K15: 0 | L15: 0 | M15: 0 | N15: 0 | O15: 0
C16: Uang Muka Pembelian | D16: 0 | E16: 0 | F16: 0 | G16: 0 | H16: 0 | J16: Utang Bank | K16: 0 | L16: 0 | M16: 0 | N16: 0 | O16: 0
C17: Uang Muka Operasional | D17: 0 | E17: 0 | F17: 0 | G17: 0 | H17: 0 | J17: Utang Lain-Lain | K17: 0 | L17: 0 | M17: 0 | N17: 21680000 | O17: =+'WS Trial balance'!CA35 -> 21680000
C18: Uang Muka Pajak | D18: 0 | E18: 0 | F18: 0 | G18: 0 | H18: 0 | J18: Biaya YMHD | K18: 0 | L18: 0 | M18: 0 | N18: 0 | O18: =+'WS Trial balance'!CA37 -> 28950000
C19: Total Aset Lancar : | D19: =SUM(D9:D18) -> 8.1186609e+09 | E19: =SUM(E9:E18) -> 8.3800348e+09 | F19: =SUM(F9:F18) -> 5.1939119e+09 | G19: =SUM(G9:G18) -> 2.6993717e+09 | H19: =SUM(H9:H18) -> 2.6961766e+09 | J19: Uang Muka Penjualan | K19: 0 | L19: 0 | M19: 0 | N19: 0 | O19: 0
B20: II | C20: Penyertaan Modal | D20: 0 | E20: 0 | F20: 0 | G20: 0 | H20: 0 | K20: 0 | L20: 0 | M20: 0 | N20: 0 | O20: 0
B21: III | C21: Aktiva Pajak Tangguhan | D21: 0 | E21: 0 | F21: 0 | G21: 0 | H21: 0 | K21: 0 | L21: 0 | M21: 0 | N21: 0 | O21: 0
B22: IV | C22: Aset Tetap Berwujud | J22: Grand Total Liabilitas | K22: =SUM(K9:K21) -> 6033860000 | L22: =SUM(L9:L21) -> 6.170099e+09 | M22: =SUM(M9:M21) -> 2.8796073e+09 | N22: =SUM(N9:N21) -> 3.6936654e+08 | O22: =SUM(O9:O21) -> 3.6826604e+08
C23: Tanah | D23: 0 | E23: 0 | F23: 0 | G23: 0 | H23: 0 | I23: VIII | J23: Ekuitas
C24: Bangunan dan Instalasi Listrik | D24: 0 | E24: 0 | F24: 0 | G24: 0 | H24: 0 | J24: Simpanan Pokok | K24: 10900000 | L24: 10100000 | M24: 9500000 | N24: 7900000 | O24: =+'WS Trial balance'!CA43 -> 7900000
C25: Kendaraan | D25: 0 | E25: 0 | F25: 0 | G25: 0 | H25: 0 | J25: Wajib | K25: 306200000 | L25: 335950000 | M25: 364570000 | N25: 339030000 | O25: =+'WS Trial balance'!CA44 -> 354610000
C26: Mesin dan Peralatan | D26: 0 | E26: 0 | F26: 0 | G26: 0 | H26: 0 | J26: Hibah | K26: 0 | L26: 0 | M26: 0 | N26: 0 | O26: 0
C27: Inventaris Kantor | D27: 0 | E27: 0 | F27: 0 | G27: 0 | H27: 0 | J27: Cadangan | K27: 1623304769 | L27: 1.6810632e+09 | M27: 1.7530277e+09 | N27: 1.8279105e+09 | O27: =+'WS Trial balance'!CA46 -> 1.8914004e+09
C28: Nilai Perolehan | D28: =SUM(D23:D27) -> 0 | E28: =SUM(E23:E27) -> 0 | F28: =SUM(F23:F27) -> 0 | G28: =SUM(G23:G27) -> 0 | H28: =SUM(H23:H27) -> 0 | J28: Laba Belum dicadangkan | K28: 0 | L28: 0 | M28: 0 | N28: -1.4901161e-07 | O28: =+'WS Trial balance'!CA47 -> -447322.96
C29: Akumulasi Penyusutan Aktiva Tetap | D29: 0 | E29: 0 | F29: 0 | G29: 0 | H29: 0
C30: Total Aset Lancar : | D30: =D28+D29 -> 0 | E30: =E28+E29 -> 0 | F30: =F28+F29 -> 0 | G30: =G28+G29 -> 0 | H30: =H28+H29 -> 0 | J30: SHU | K30: 1.4439615e+08 | L30: 1.8282255e+08 | M30: 1.8720697e+08 | N30: 1.5516467e+08 | O30: =+'WS Trial balance'!BZ70 -> 74447522
B31: V | C31: Aset Tetap Tak Berwujud | J31: Total Ekuitas : | K31: =SUM(K24:K30) -> 2.0848009e+09 | L31: =SUM(L24:L30) -> 2.2099358e+09 | M31: =SUM(M24:M30) -> 2.3143047e+09 | N31: =SUM(N24:N30) -> 2.3300052e+09 | O31: =SUM(O24:O30) -> 2.3279106e+09
C32: Software Komputer | D32: 0 | E32: 0 | F32: 0 | G32: 0 | H32: 0
C33: Ak. Amrt. Software Komputer | D33: 0 | E33: 0 | F33: 0 | G33: 0 | H33: 0
C34: Total Aset Tetap Tak Berwujud : | D34: =SUM(D32:D33) -> 0 | E34: =SUM(E32:E33) -> 0 | F34: =SUM(F32:F33) -> 0 | G34: =SUM(G32:G33) -> 0 | H34: =SUM(H32:H33) -> 0
B35: VI | C35: Aset Lain-lain | D35: 0 | E35: 0 | F35: 0 | G35: 0 | H35: 0
B37: Grand Total Aset | D37: =D19+D20+D21+D30+D34+D35 -> 8.1186609e+09 | E37: =E19+E20+E21+E30+E34+E35 -> 8.3800348e+09 | F37: =F19+F20+F21+F30+F34+F35 -> 5.1939119e+09 | G37: =G19+G20+G21+G30+G34+G35 -> 2.6993717e+09 | H37: =H19+H20+H21+H30+H34+H35 -> 2.6961766e+09 | I37: Grand Total Liabilitas dan Ekuitas | K37: =K22+K31 -> 8.1186609e+09 | L37: =L22+L31 -> 8.3800348e+09 | M37: =M22+M31 -> 5.1939119e+09 | N37: =N22+N31 -> 2.6993717e+09 | O37: =O22+O31 -> 2.6961766e+09
K39: =+K37-D37 -> 0 | L39: =+L37-E37 -> 0 | M39: =+M37-F37 -> 0 | N39: =+N37-G37 -> 0 | O39: =+O37-H37 -> 0
L40: =L30-K30 -> 38426408 | M40: =M30-L30 -> 4384414.1 | N40: =N30-M30 -> -32042295 | O40: =O30-M30 -> -1.1275945e+08
K42: =K30*60% -> 86637688 | L42: =L30*60% -> 1.0969353e+08 | M42: =M30*60% -> 1.1232418e+08 | N42: =N30*60% -> 93098804 | O42: =O30*60% -> 44668513
K43: =K30-K42 -> 57758458 | L43: =L30-L42 -> 73129022 | M43: =M30-M42 -> 74882787 | N43: =N30-N42 -> 62065869 | O43: =O30-O42 -> 29779009

Sheet LR
B2: LAPORAN LABA / (RUGI)
B3: K K C S
B4: =NR!B4 -> TAHUN 2023 - 2026 | F4: l-m | H4: q-r | J4: s-t | L4: u-v | N4: w-x | P4: y-z | R4: aa-ab | T4: ac-ad | V4: ae-af | X4: ag-ah | Z4: ai-aj
D5: j-k | F5: o-p | H5: t-u | J5: y-z | L5: ad-ae | N5: ai-aj | P5: an-ao | R5: as-at | T5: ax-ay | V5: bc-bd | X5: bh-bi | Z5: bm-bn
B6: KETERANGAN | D6: JANUARI | F6: FEBRUARI | H6: MARET | J6: APRIL | L6: MEI | N6: JUNI | P6: JULI | R6: AGUSTUS | T6: SEPTEMBER | V6: OKTOBER | X6: NOPEMBER | Z6: DESEMBER | AC6: 2024
D7: =LEFT(D6,3) -> JAN | E7: ="sd. "&D7 -> sd. JAN | F7: =LEFT(F6,3) -> FEB | G7: ="sd. "&F7 -> sd. FEB | H7: =LEFT(H6,3) -> MAR | I7: ="sd. "&H7 -> sd. MAR | J7: =LEFT(J6,3) -> APR | K7: ="sd. "&J7 -> sd. APR | L7: =LEFT(L6,3) -> MEI | M7: ="sd. "&L7 -> sd. MEI | N7: =LEFT(N6,3) -> JUN | O7: ="sd. "&N7 -> sd. JUN | P7: =LEFT(P6,3) -> JUL | Q7: ="sd. "&P7 -> sd. JUL | R7: =LEFT(R6,5) -> AGUST | S7: ="sd. "&R7 -> sd. AGUST | T7: =LEFT(T6,4) -> SEPT | U7: ="sd. "&T7 -> sd. SEPT | V7: =LEFT(V6,3) -> OKT | W7: ="sd. "&V7 -> sd. OKT | X7: =LEFT(X6,3) -> NOP | Y7: ="sd. "&X7 -> sd. NOP | Z7: =LEFT(Z6,3) -> DES | AA7: ="sd. "&Z7 -> sd. DES
C8: Pendapatan
C9: Pinjaman Rutin | D9: ='WS Trial balance'!K58-'WS Trial balance'!J58 -> 78721705 | E9: =D9 -> 78721705 | F9: ='WS Trial balance'!P58-'WS Trial balance'!O58 -> 80206566 | G9: =E9+F9 -> 1.5892827e+08 | H9: ='WS Trial balance'!U58-'WS Trial balance'!T58 -> 81022330 | I9: =G9+H9 -> 2.399506e+08 | J9: ='WS Trial balance'!Z58-'WS Trial balance'!Y58 -> 77958441 | K9: =I9+J9 -> 3.1790904e+08 | L9: ='WS Trial balance'!AE58-'WS Trial balance'!AD58 -> 81143163 | M9: =K9+L9 -> 3.990522e+08 | N9: ='WS Trial balance'!AJ58-'WS Trial balance'!AI58 -> 82725663 | O9: =M9+N9 -> 4.8177787e+08 | P9: ='WS Trial balance'!AO58-'WS Trial balance'!AN58 -> 84316497 | Q9: =O9+P9 -> 5.6609436e+08 | R9: ='WS Trial balance'!AT58-'WS Trial balance'!AS58 -> 84316497 | S9: =Q9+R9 -> 6.5041086e+08 | T9: ='WS Trial balance'!AY58-'WS Trial balance'!AX58 -> 0 | U9: =S9+T9 -> 6.5041086e+08 | V9: ='WS Trial balance'!BD58-'WS Trial balance'!BC58 -> 0 | W9: =U9+V9 -> 6.5041086e+08 | X9: ='WS Trial balance'!BI58-'WS Trial balance'!BH58 -> 0 | Y9: =W9+X9 -> 6.5041086e+08 | Z9: ='WS Trial balance'!BN58-'WS Trial balance'!BM58 -> 0 | AA9: =Y9+Z9 -> 6.5041086e+08 | AB9: =AA9-AC9 -> 0 | AC9: =D9+F9+H9+J9+L9+N9+P9+R9+T9+V9+X9+Z9 -> 6.5041086e+08
C10: Pinjaman Khusus | D10: ='WS Trial balance'!K59-'WS Trial balance'!J59 -> 0 | E10: =D10 -> 0 | F10: ='WS Trial balance'!P59-'WS Trial balance'!O59 -> 0 | G10: =E10+F10 -> 0 | H10: ='WS Trial balance'!U59-'WS Trial balance'!T59 -> 0 | I10: =G10+H10 -> 0 | J10: ='WS Trial balance'!Z59-'WS Trial balance'!Y59 -> 0 | K10: =I10+J10 -> 0 | L10: ='WS Trial balance'!AE59-'WS Trial balance'!AD59 -> 0 | M10: =K10+L10 -> 0 | N10: ='WS Trial balance'!AJ59-'WS Trial balance'!AI59 -> 0 | O10: =M10+N10 -> 0 | P10: ='WS Trial balance'!AO59-'WS Trial balance'!AN59 -> 0 | Q10: =O10+P10 -> 0 | R10: ='WS Trial balance'!AT59-'WS Trial balance'!AS59 -> 0 | S10: =Q10+R10 -> 0 | T10: ='WS Trial balance'!AY59-'WS Trial balance'!AX59 -> 0 | U10: =S10+T10 -> 0 | V10: ='WS Trial balance'!BD59-'WS Trial balance'!BC59 -> 0 | W10: =U10+V10 -> 0 | X10: ='WS Trial balance'!BI59-'WS Trial balance'!BH59 -> 0 | Y10: =W10+X10 -> 0 | Z10: ='WS Trial balance'!BN59-'WS Trial balance'!BM59 -> 0 | AA10: =Y10+Z10 -> 0 | AB10: =AA10-AC10 -> 0 | AC10: =D10+F10+H10+J10+L10+N10+P10+R10+T10+V10+X10+Z10 -> 0
C11: Pinjaman Lain | D11: ='WS Trial balance'!K60-'WS Trial balance'!J60 -> 525000 | E11: =D11 -> 525000 | F11: ='WS Trial balance'!P60-'WS Trial balance'!O60 -> 350000 | G11: =E11+F11 -> 875000 | H11: ='WS Trial balance'!U60-'WS Trial balance'!T60 -> -92500 | I11: =G11+H11 -> 782500 | J11: ='WS Trial balance'!Z60-'WS Trial balance'!Y60 -> 385000 | K11: =I11+J11 -> 1167500 | L11: ='WS Trial balance'!AE60-'WS Trial balance'!AD60 -> 630000 | M11: =K11+L11 -> 1797500 | N11: ='WS Trial balance'!AJ60-'WS Trial balance'!AI60 -> 221500 | O11: =M11+N11 -> 2019000 | P11: ='WS Trial balance'!AO60-'WS Trial balance'!AN60 -> 0 | Q11: =O11+P11 -> 2019000 | R11: ='WS Trial balance'!AT60-'WS Trial balance'!AS60 -> 210000 | S11: =Q11+R11 -> 2229000 | T11: ='WS Trial balance'!AY60-'WS Trial balance'!AX60 -> 0 | U11: =S11+T11 -> 2229000 | V11: ='WS Trial balance'!BD60-'WS Trial balance'!BC60 -> 0 | W11: =U11+V11 -> 2229000 | X11: ='WS Trial balance'!BI60-'WS Trial balance'!BH60 -> 0 | Y11: =W11+X11 -> 2229000 | Z11: ='WS Trial balance'!BN60-'WS Trial balance'!BM60 -> 0 | AA11: =Y11+Z11 -> 2229000 | AB11: =AA11-AC11 -> 0 | AC11: =D11+F11+H11+J11+L11+N11+P11+R11+T11+V11+X11+Z11 -> 2229000
C12: HPP Pinj. Rutin | D12: =-'WS Trial balance'!J61+'WS Trial balance'!K61 -> -60419861 | E12: =D12 -> -60419861 | F12: =-'WS Trial balance'!O61+'WS Trial balance'!P61 -> -61858750 | G12: =E12+F12 -> -1.2227861e+08 | H12: =-'WS Trial balance'!T61+'WS Trial balance'!U61 -> -62264306 | I12: =G12+H12 -> -1.8454292e+08 | J12: =-'WS Trial balance'!Y61+'WS Trial balance'!Z61 -> -59901806 | K12: =I12+J12 -> -2.4444472e+08 | L12: =-'WS Trial balance'!AD61+'WS Trial balance'!AE61 -> -62749028 | M12: =K12+L12 -> -307193750 | N12: =-'WS Trial balance'!AI61+'WS Trial balance'!AJ61 -> -63894861 | O12: =M12+N12 -> -3.7108861e+08 | P12: =-'WS Trial balance'!AN61+'WS Trial balance'!AO61 -> -65128194 | Q12: =O12+P12 -> -4.3621681e+08 | R12: =-'WS Trial balance'!AS61+'WS Trial balance'!AT61 -> -65128194 | S12: =Q12+R12 -> -5.01345e+08 | T12: =-'WS Trial balance'!AX61+'WS Trial balance'!AY61 -> 0 | U12: =S12+T12 -> -5.01345e+08 | V12: =-'WS Trial balance'!BC61+'WS Trial balance'!BD61 -> 0 | W12: =U12+V12 -> -5.01345e+08 | X12: =-'WS Trial balance'!BH61+'WS Trial balance'!BI61 -> 0 | Y12: =W12+X12 -> -5.01345e+08 | Z12: =-'WS Trial balance'!BM61+'WS Trial balance'!BN61 -> 0 | AA12: =Y12+Z12 -> -5.01345e+08 | AB12: =AA12-AC12 -> 0 | AC12: =D12+F12+H12+J12+L12+N12+P12+R12+T12+V12+X12+Z12 -> -5.01345e+08
C13: HPP Pinj. Khusus | D13: =-'WS Trial balance'!J62+'WS Trial balance'!K62 -> 0 | E13: =D13 -> 0 | F13: =-'WS Trial balance'!O62+'WS Trial balance'!P62 -> 0 | G13: =E13+F13 -> 0 | H13: =-'WS Trial balance'!T62+'WS Trial balance'!U62 -> 0 | I13: =G13+H13 -> 0 | J13: =-'WS Trial balance'!Y62+'WS Trial balance'!Z62 -> 0 | K13: =I13+J13 -> 0 | L13: =-'WS Trial balance'!AD62+'WS Trial balance'!AE62 -> 0 | M13: =K13+L13 -> 0 | N13: =-'WS Trial balance'!AI62+'WS Trial balance'!AJ62 -> 0 | O13: =M13+N13 -> 0 | P13: =-'WS Trial balance'!AN62+'WS Trial balance'!AO62 -> 0 | Q13: =O13+P13 -> 0 | R13: =-'WS Trial balance'!AS62+'WS Trial balance'!AT62 -> 0 | S13: =Q13+R13 -> 0 | T13: =-'WS Trial balance'!AX62+'WS Trial balance'!AY62 -> 0 | U13: =S13+T13 -> 0 | V13: =-'WS Trial balance'!BC62+'WS Trial balance'!BD62 -> 0 | W13: =U13+V13 -> 0 | X13: =-'WS Trial balance'!BH62+'WS Trial balance'!BI62 -> 0 | Y13: =W13+X13 -> 0 | Z13: =-'WS Trial balance'!BM62+'WS Trial balance'!BN62 -> 0 | AA13: =Y13+Z13 -> 0 | AB13: =AA13-AC13 -> 0 | AC13: =D13+F13+H13+J13+L13+N13+P13+R13+T13+V13+X13+Z13 -> 0
C14: HPP Pinj. Lain | D14: =-'WS Trial balance'!J63+'WS Trial balance'!K63 -> 0 | E14: =D14 -> 0 | F14: =-'WS Trial balance'!O63+'WS Trial balance'!P63 -> 0 | G14: =E14+F14 -> 0 | H14: =-'WS Trial balance'!T63+'WS Trial balance'!U63 -> 0 | I14: =G14+H14 -> 0 | J14: =-'WS Trial balance'!Y63+'WS Trial balance'!Z63 -> 0 | K14: =I14+J14 -> 0 | L14: =-'WS Trial balance'!AD63+'WS Trial balance'!AE63 -> 0 | M14: =K14+L14 -> 0 | N14: =-'WS Trial balance'!AI63+'WS Trial balance'!AJ63 -> 0 | O14: =M14+N14 -> 0 | P14: =-'WS Trial balance'!AN63+'WS Trial balance'!AO63 -> 0 | Q14: =O14+P14 -> 0 | R14: =-'WS Trial balance'!AS63+'WS Trial balance'!AT63 -> 0 | S14: =Q14+R14 -> 0 | T14: =-'WS Trial balance'!AX63+'WS Trial balance'!AY63 -> 0 | U14: =S14+T14 -> 0 | V14: =-'WS Trial balance'!BC63+'WS Trial balance'!BD63 -> 0 | W14: =U14+V14 -> 0 | X14: =-'WS Trial balance'!BH63+'WS Trial balance'!BI63 -> 0 | Y14: =W14+X14 -> 0 | Z14: =-'WS Trial balance'!BM63+'WS Trial balance'!BN63 -> 0 | AA14: =Y14+Z14 -> 0 | AB14: =AA14-AC14 -> 0 | AC14: =D14+F14+H14+J14+L14+N14+P14+R14+T14+V14+X14+Z14 -> 0
C15: Laba kotor | D15: =SUM(D9:D14) -> 18826844 | E15: =SUM(E9:E14) -> 18826844 | F15: =SUM(F9:F14) -> 18697816 | G15: =SUM(G9:G14) -> 37524660 | H15: =SUM(H9:H14) -> 18665524 | I15: =SUM(I9:I14) -> 56190184 | J15: =SUM(J9:J14) -> 18441635 | K15: =SUM(K9:K14) -> 74631819 | ... AA15: =SUM(AA9:AA14) -> 1.5129486e+08 | AC15: =SUM(AC9:AC14) -> 1.5129486e+08
C17: Beban Usaha
C18: Beban Umum dan Administrasi | D18: =-'WS Trial balance'!J64+'WS Trial balance'!K64 -> -758000 | E18: =D18 -> -758000 | F18: =-'WS Trial balance'!O64+'WS Trial balance'!P64 -> -750000 | G18: =E18+F18 -> -1508000 | H18: =-'WS Trial balance'!T64+'WS Trial balance'!U64 -> -28557000 | I18: =G18+H18 -> -30065000 | J18: =-'WS Trial balance'!Y64+'WS Trial balance'!Z64 -> -750000 | K18: =I18+J18 -> -30815000 | L18: =-'WS Trial balance'!AD64+'WS Trial balance'!AE64 -> -42362600 | M18: =K18+L18 -> -73177600 | N18: =-'WS Trial balance'!AI64+'WS Trial balance'!AJ64 -> -3250000 | O18: =M18+N18 -> -76427600 | P18: =-'WS Trial balance'!AN64+'WS Trial balance'!AO64 -> -1120000 | Q18: =O18+P18 -> -77547600 | R18: =-'WS Trial balance'!AS64+'WS Trial balance'!AT64 -> -1900000 | S18: =Q18+R18 -> -79447600 | T18: =-'WS Trial balance'!AX64+'WS Trial balance'!AY64 -> 0 | U18: =S18+T18 -> -79447600 | V18: =-'WS Trial balance'!BC64+'WS Trial balance'!BD64 -> 0 | W18: =U18+V18 -> -79447600 | X18: =-'WS Trial balance'!BH64+'WS Trial balance'!BI64 -> 0 | Y18: =W18+X18 -> -79447600 | Z18: =-'WS Trial balance'!BM64+'WS Trial balance'!BN64 -> 0 | AA18: =Y18+Z18 -> -79447600 | AB18: =AA18-AC18 -> 0 | AC18: =D18+F18+H18+J18+L18+N18+P18+R18+T18+V18+X18+Z18 -> -79447600
C19: Jumlah Beban Usaha : | D19: =SUM(D18:D18) -> -758000 | E19: =SUM(E18:E18) -> -758000 | F19: =SUM(F18:F18) -> -750000 | G19: =SUM(G18:G18) -> -1508000 | H19: =SUM(H18:H18) -> -28557000 | I19: =SUM(I18:I18) -> -30065000 | J19: =SUM(J18:J18) -> -750000 | K19: =SUM(K18:K18) -> -30815000 | ... AA19: =SUM(AA18:AA18) -> -79447600 | AC19: =SUM(AC18:AC18) -> -79447600
C20: Laba usaha | D20: =+D15+D19 -> 18068844 | E20: =+E15+E19 -> 18068844 | F20: =+F15+F19 -> 17947816 | G20: =+G15+G19 -> 36016660 | H20: =+H15+H19 -> -9891475.7 | I20: =+I15+I19 -> 26125184 | J20: =+J15+J19 -> 17691635 | K20: =+K15+K19 -> 43816819 | ... AA20: =+AA15+AA19 -> 71847261 | AC20: =+AC15+AC19 -> 71847261
C21: Pendapatan / (Beban) di luar usaha
C22: Pendapatan Lain-lain | D22: ='WS Trial balance'!K65-'WS Trial balance'!J65 -> 3918000 | E22: =D22 -> 3918000 | F22: ='WS Trial balance'!P65-'WS Trial balance'!O65 -> 1423167.3 | G22: =E22+F22 -> 5341167.3 | H22: ='WS Trial balance'!U65-'WS Trial balance'!T65 -> 1356500 | I22: =G22+H22 -> 6697667.3 | J22: ='WS Trial balance'!Z65-'WS Trial balance'!Y65 -> 1356500 | K22: =I22+J22 -> 8054167.3 | L22: ='WS Trial balance'!AE65-'WS Trial balance'!AD65 -> 3146500 | M22: =K22+L22 -> 11200667 | N22: ='WS Trial balance'!AJ65-'WS Trial balance'!AI65 -> 1205000 | O22: =M22+N22 -> 12405667 | P22: ='WS Trial balance'!AO65-'WS Trial balance'!AN65 -> 1205000 | Q22: =O22+P22 -> 13610667 | R22: ='WS Trial balance'!AT65-'WS Trial balance'!AS65 -> 1205000 | S22: =Q22+R22 -> 14815667 | T22: ='WS Trial balance'!AY65-'WS Trial balance'!AX65 -> 0 | U22: =S22+T22 -> 14815667 | V22: ='WS Trial balance'!BD65-'WS Trial balance'!BC65 -> 0 | W22: =U22+V22 -> 14815667 | X22: ='WS Trial balance'!BI65-'WS Trial balance'!BH65 -> 0 | Y22: =W22+X22 -> 14815667 | Z22: ='WS Trial balance'!BN65-'WS Trial balance'!BM65 -> 0 | AA22: =Y22+Z22 -> 14815667 | AB22: =AA22-AC22 -> 0 | AC22: =D22+F22+H22+J22+L22+N22+P22+R22+T22+V22+X22+Z22 -> 14815667
C23: Biaya Lain-lain | D23: =-'WS Trial balance'!J66+'WS Trial balance'!K66 -> -1495669.1 | E23: =D23 -> -1495669.1 | F23: =-'WS Trial balance'!O66+'WS Trial balance'!P66 -> -1489907.3 | G23: =E23+F23 -> -2985576.4 | H23: =-'WS Trial balance'!T66+'WS Trial balance'!U66 -> -1541782.7 | I23: =G23+H23 -> -4527359.1 | J23: =-'WS Trial balance'!Y66+'WS Trial balance'!Z66 -> -1526806.1 | K23: =I23+J23 -> -6054165.1 | L23: =-'WS Trial balance'!AD66+'WS Trial balance'!AE66 -> -1534334.9 | M23: =K23+L23 -> -7588500 | N23: =-'WS Trial balance'!AI66+'WS Trial balance'!AJ66 -> -1552978.1 | O23: =M23+N23 -> -9141478.1 | P23: =-'WS Trial balance'!AN66+'WS Trial balance'!AO66 -> -1544455.2 | Q23: =O23+P23 -> -10685933 | R23: =-'WS Trial balance'!AS66+'WS Trial balance'!AT66 -> -1529472.7 | S23: =Q23+R23 -> -12215406 | T23: =-'WS Trial balance'!AX66+'WS Trial balance'!AY66 -> 0 | U23: =S23+T23 -> -12215406 | V23: =-'WS Trial balance'!BC66+'WS Trial balance'!BD66 -> 0 | W23: =U23+V23 -> -12215406 | X23: =-'WS Trial balance'!BH66+'WS Trial balance'!BI66 -> 0 | Y23: =W23+X23 -> -12215406 | Z23: =-'WS Trial balance'!BM66+'WS Trial balance'!BN66 -> 0 | AA23: =Y23+Z23 -> -12215406 | AB23: =AA23-AC23 -> 0 | AC23: =D23+F23+H23+J23+L23+N23+P23+R23+T23+V23+X23+Z23 -> -12215406
C24: Jumlah Pendapatan/(Beban) di luar usaha: | D24: =SUM(D22:D23) -> 2422330.9 | E24: =SUM(E22:E23) -> 2422330.9 | F24: =SUM(F22:F23) -> -66739.939 | G24: =SUM(G22:G23) -> 2355590.9 | H24: =SUM(H22:H23) -> -185282.67 | I24: =SUM(I22:I23) -> 2170308.3 | J24: =SUM(J22:J23) -> -170306.06 | K24: =SUM(K22:K23) -> 2000002.2 | ... AA24: =SUM(AA22:AA23) -> 2600261.3 | AC24: =SUM(AC22:AC23) -> 2600261.3
C25: Laba Sebelum Pajak | D25: =+D20+D24 -> 20491175 | E25: =+E20+E24 -> 20491175 | F25: =+F20+F24 -> 17881076 | G25: =+G20+G24 -> 38372251 | H25: =+H20+H24 -> -10076758 | I25: =+I20+I24 -> 28295492 | J25: =+J20+J24 -> 17521329 | K25: =+K20+K24 -> 45816822 | ... AA25: =+AA20+AA24 -> 74447522 | AC25: =+AC20+AC24 -> 74447522 | AE25: =AC25*22% -> 16378455
C26: Beban Pajak | D26: =-'WS Trial balance'!J67+'WS Trial balance'!K67 -> 0 | E26: =D26 -> 0 | F26: =-'WS Trial balance'!O67+'WS Trial balance'!P67 -> 0 | G26: =E26+F26 -> 0 | H26: =-'WS Trial balance'!T67+'WS Trial balance'!U67 -> 0 | I26: =G26+H26 -> 0 | J26: =-'WS Trial balance'!Y67+'WS Trial balance'!Z67 -> 0 | K26: =I26+J26 -> 0 | L26: =-'WS Trial balance'!AD67+'WS Trial balance'!AE67 -> 0 | M26: =K26+L26 -> 0 | N26: =-'WS Trial balance'!AI67+'WS Trial balance'!AJ67 -> 0 | O26: =M26+N26 -> 0 | P26: =-'WS Trial balance'!AN67+'WS Trial balance'!AO67 -> 0 | Q26: =O26+P26 -> 0 | R26: =-'WS Trial balance'!AS67+'WS Trial balance'!AT67 -> 0 | S26: =Q26+R26 -> 0 | T26: =-'WS Trial balance'!AX67+'WS Trial balance'!AY67 -> 0 | U26: =S26+T26 -> 0 | V26: =-'WS Trial balance'!BC67+'WS Trial balance'!BD67 -> 0 | W26: =U26+V26 -> 0 | X26: =-'WS Trial balance'!BH67+'WS Trial balance'!BI67 -> 0 | Y26: =W26+X26 -> 0 | Z26: =-'WS Trial balance'!BM67+'WS Trial balance'!BN67 -> 0 | AA26: =Y26+Z26 -> 0 | AB26: =AA26-AC26 -> 0 | AC26: =D26+F26+H26+J26+L26+N26+P26+R26+T26+V26+X26+Z26 -> 0
C27: Laba Setelah Pajak | D27: =SUM(D25:D26) -> 20491175 | E27: =SUM(E25:E26) -> 20491175 | F27: =SUM(F25:F26) -> 17881076 | G27: =SUM(G25:G26) -> 38372251 | H27: =SUM(H25:H26) -> -10076758 | I27: =SUM(I25:I26) -> 28295492 | J27: =SUM(J25:J26) -> 17521329 | K27: =SUM(K25:K26) -> 45816822 | ... AA27: =SUM(AA25:AA26) -> 74447522 | AC27: =SUM(AC25:AC26) -> 74447522
E29: =E27-'WS Trial balance'!L70 -> 0 | G29: =G27-'WS Trial balance'!Q70 -> 0 | I29: =I27-'WS Trial balance'!V70 -> 0 | K29: =K27-'WS Trial balance'!AA70 -> 0 | M29: =M27-'WS Trial balance'!AF70 -> 0 | O29: =O27-'WS Trial balance'!AK70 -> 0 | Q29: =Q27-'WS Trial balance'!AP70 -> 0 | S29: =S27-'WS Trial balance'!AU70 -> 0 | U29: =U27-'WS Trial balance'!AZ70 -> 0 | W29: =W27-'WS Trial balance'!BE70 -> 0 | Y29: =Y27-'WS Trial balance'!BJ70 -> 0 | AA29: =AA27-'WS Trial balance'!BO70 -> 0

Sheet WS Trial balance
C3: KOPERASI KARYAWAN CIPTA SEJAHTERA
C4: BALANCE SHEET, TAHUN 2026
C5: ACCOUNT | F5: KODE | G5: SALDO AWAL 2026 | J5: MUTASI JANUARI 2026 | L5: SALDO AKHIR JANUARI 2026 | O5: MUTASI FEBRUARI 2026 | Q5: SALDO AKHIR FEBRUARI 2026 | T5: MUTASI MARET 2026 | V5: SALDO AKHIR MARET 2026 | Y5: MUTASI APRIL 2026 | AA5: SALDO AKHIR APRIL 2026 | AD5: MUTASI MEI 2026 | AF5: SALDO AKHIR MEI 2026 | AI5: MUTASI JUNI 2026 | AK5: SALDO AKHIR JUNI 2026 | AN5: MUTASI JULI 2026 | AP5: SALDO AKHIR JULI 2026 | AS5: MUTASI AGUSTUS 2026 | AU5: SALDO AKHIR AGUSTUS 2026 | AX5: MUTASI SEPTEMBER 2026 | AZ5: SALDO AKHIR SEPTEMBER 2026 | BC5: MUTASI OKTOBER 2026 | BE5: SALDO AKHIR OKTOBER 2026 | BH5: MUTASI NOPEMBER 2026 | BJ5: SALDO AKHIR NOPEMBER 2026 | BM5: MUTASI DESEMBER 2026 | BO5: SALDO AKHIR DESEMBER 2026 | BT5: SALDO AWAL 2026 | BW5: MUTASI 2026 | BZ5: SALDO AKHIR 2026
G6: DEBET | H6: KREDIT | J6: DEBET | K6: KREDIT | L6: DEBET | M6: KREDIT | O6: DEBET | P6: KREDIT | Q6: DEBET | R6: KREDIT | T6: DEBET | U6: KREDIT | V6: DEBET | W6: KREDIT | Y6: DEBET | Z6: KREDIT | AA6: DEBET | AB6: KREDIT | AD6: DEBET | AE6: KREDIT | AF6: DEBET | AG6: KREDIT | AI6: DEBET | AJ6: KREDIT | AK6: DEBET | AL6: KREDIT | AN6: DEBET | AO6: KREDIT | AP6: DEBET | AQ6: KREDIT | AS6: DEBET | AT6: KREDIT | AU6: DEBET | AV6: KREDIT | AX6: DEBET | AY6: KREDIT | AZ6: DEBET | BA6: KREDIT | BC6: DEBET | BD6: KREDIT | BE6: DEBET | BF6: KREDIT | BH6: DEBET | BI6: KREDIT | BJ6: DEBET | BK6: KREDIT | BM6: DEBET | BN6: KREDIT | BO6: DEBET | BP6: KREDIT | BT6: DEBET | BU6: KREDIT | BW6: DEBET | BX6: KREDIT | BZ6: DEBET | CA6: KREDIT
D7: A01 | E7: KAS | F7: D | G7: 8851508.7 | H7: 0 | J7: =SUMIF('MUTASI 2026'!$B$5:$B$160,'WS Trial balance'!$D7,'MUTASI 2026'!$G$5:$G$160) -> 4865000 | K7: =SUMIF('MUTASI 2026'!$B$5:$B$160,'WS Trial balance'!$D7,'MUTASI 2026'!$H$5:$H$160) -> 5258000 | L7: =IF(F7="D",(G7-H7+J7-K7),0) -> 8458508.7 | M7: =IF(F7="K",(-G7+H7-J7+K7),0) -> 0 | O7: =SUMIF('MUTASI 2026'!$B$162:$B$252,'WS Trial balance'!$D7,'MUTASI 2026'!$G$162:$G$252) -> 49051500 | P7: =SUMIF('MUTASI 2026'!$B$162:$B$252,'WS Trial balance'!$D7,'MUTASI 2026'!$H$162:$H$252) -> 24350000 | Q7: =IF(F7="D",(L7-M7+O7-P7),0) -> 33160009 | R7: =IF(F7="K",(-L7+M7-O7+P7),0) -> 0 | T7: =SUMIF('MUTASI 2026'!$B$254:$B$356,'WS Trial balance'!$D7,'MUTASI 2026'!$G$254:$G$356) -> 2047000 | U7: =SUMIF('MUTASI 2026'!$B$254:$B$356,'WS Trial balance'!$D7,'MUTASI 2026'!$H$254:$H$356) -> 28557000 | V7: =IF(F7="D",(Q7-R7+T7-U7),0) -> 6650008.7 | W7: =IF(F7="K",(-Q7+R7-T7+U7),0) -> 0 | Y7: =SUMIF('MUTASI 2026'!$B$358:$B$480,'WS Trial balance'!$D7,'MUTASI 2026'!$G$358:$G$480) -> 4136000 | Z7: =SUMIF('MUTASI 2026'!$B$358:$B$480,'WS Trial balance'!$D7,'MUTASI 2026'!$H$358:$H$480) -> 6250000 | AA7: =IF(F7="D",(V7-W7+Y7-Z7),0) -> 4536008.7 | AB7: =IF(F7="K",(-V7+W7-Y7+Z7),0) -> 0 | AD7: =SUMIF('MUTASI 2026'!$B$482:$B$655,'WS Trial balance'!$D7,'MUTASI 2026'!$G$482:$G$655) -> 62358000 | AE7: =SUMIF('MUTASI 2026'!$B$482:$B$655,'WS Trial balance'!$D7,'MUTASI 2026'!$H$482:$H$655) -> 65179638 | AF7: =IF(F7="D",(AA7-AB7+AD7-AE7),0) -> 1714370.7 | AG7: =IF(F7="K",(-AA7+AB7-AD7+AE7),0) -> 0 | AI7: =SUMIF('MUTASI 2026'!$B$657:$B$748,'WS Trial balance'!$D7,'MUTASI 2026'!$G$657:$G$748) -> 12626000 | AJ7: =SUMIF('MUTASI 2026'!$B$657:$B$748,'WS Trial balance'!$D7,'MUTASI 2026'!$H$657:$H$748) -> 17250000 | AK7: =IF(F7="D",(AF7-AG7+AI7-AJ7),0) -> -2909629.3 | AL7: =IF(F7="K",(-AF7+AG7-AI7+AJ7),0) -> 0 | AN7: =SUMIF('MUTASI 2026'!$B$750:$B$851,'WS Trial balance'!$D7,'MUTASI 2026'!$G$750:$G$851) -> 12745500 | AO7: =SUMIF('MUTASI 2026'!$B$750:$B$851,'WS Trial balance'!$D7,'MUTASI 2026'!$H$750:$H$851) -> 6120000 | AP7: =IF(F7="D",(AK7-AL7+AN7-AO7),0) -> 3715870.7 | AQ7: =IF(F7="K",(-AK7+AL7-AN7+AO7),0) -> 0 | AS7: =SUMIF('MUTASI 2026'!$B$853:$B$945,'WS Trial balance'!$D7,'MUTASI 2026'!$G$853:$G$945) -> 28245000 | AT7: =SUMIF('MUTASI 2026'!$B$853:$B$945,'WS Trial balance'!$D7,'MUTASI 2026'!$H$853:$H$945) -> 27133454 | AU7: =IF(F7="D",(AP7-AQ7+AS7-AT7),0) -> 4827416.7 | AV7: =IF(F7="K",(-AP7+AQ7-AS7+AT7),0) -> 0 | AX7: =SUMIF('MUTASI 2026'!$B$1274:$B$1379,'WS Trial balance'!$D7,'MUTASI 2026'!$G$1274:$G$1379) -> 0 | AY7: =SUMIF('MUTASI 2026'!$B$1274:$B$1379,'WS Trial balance'!$D7,'MUTASI 2026'!$H$1274:$H$1379) -> 0 | AZ7: =IF(F7="D",(AU7-AV7+AX7-AY7),0) -> 4827416.7 | BA7: =IF(F7="K",(-AU7+AV7-AX7+AY7),0) -> 0 | BC7: =SUMIF('MUTASI 2026'!$B$1382:$B$1477,'WS Trial balance'!$D7,'MUTASI 2026'!$G$1382:$G$1477) -> 0 | BD7: =SUMIF('MUTASI 2026'!$B$1382:$B$1477,'WS Trial balance'!$D7,'MUTASI 2026'!$H$1382:$H$1477) -> 0 | BE7: =IF(F7="D",(AZ7-BA7+BC7-BD7),0) -> 4827416.7 | BF7: =IF(F7="K",(-AZ7+BA7-BC7+BD7),0) -> 0 | BH7: =SUMIF('MUTASI 2026'!$B$1480:$B$1600,'WS Trial balance'!$D7,'MUTASI 2026'!$G$1480:$G$1600) -> 0 | BI7: =SUMIF('MUTASI 2026'!$B$1480:$B$1600,'WS Trial balance'!$D7,'MUTASI 2026'!$H$1480:$H$1600) -> 0 | BJ7: =IF(F7="D",(BE7-BF7+BH7-BI7),0) -> 4827416.7 | BK7: =IF(F7="K",(-BE7+BF7-BH7+BI7),0) -> 0 | BM7: =SUMIF('MUTASI 2026'!$B$1603:$B$1722,'WS Trial balance'!$D7,'MUTASI 2026'!$G$1603:$G$1722) -> 0 | BN7: =SUMIF('MUTASI 2026'!$B$1603:$B$1722,'WS Trial balance'!$D7,'MUTASI 2026'!$H$1603:$H$1722) -> 0 | BO7: =IF(F7="D",(BJ7-BK7+BM7-BN7),0) -> 4827416.7 | BP7: =IF(F7="K",(-BJ7+BK7-BM7+BN7),0) -> 0 | BT7: =G7 -> 8851508.7 | BU7: =H7 -> 0 | BW7: =J7+O7+T7+Y7+AD7+AI7+AN7+AS7+AX7+BC7+BH7+BM7 -> 176074000 | BX7: =K7+P7+U7+Z7+AE7+AJ7+AO7+AT7+AY7+BD7+BI7+BN7 -> 180098092 | BZ7: =IF(F7="D",(BT7-BU7+BW7-BX7),0) -> 4827416.7 | CA7: =IF(F7="K",(-BT7+BU7-BW7+BX7),0) -> 0
D8: A02 | E8: BANK | F8: D | G8: 3.0295667e+08 | H8: 0 | J8: =SUMIF('MUTASI 2026'!$B$5:$B$160,'WS Trial balance'!$D8,'MUTASI 2026'!$G$5:$G$160) -> 1.6096184e+08 | K8: =SUMIF('MUTASI 2026'!$B$5:$B$160,'WS Trial balance'!$D8,'MUTASI 2026'!$H$5:$H$160) -> 150561132 | L8: =IF(F8="D",(G8-H8+J8-K8),0) -> 3.1335738e+08 | M8: =IF(F8="K",(-G8+H8-J8+K8),0) -> 0 | O8: =SUMIF('MUTASI 2026'!$B$162:$B$252,'WS Trial balance'!$D8,'MUTASI 2026'!$G$162:$G$252) -> 93516226 | P8: =SUMIF('MUTASI 2026'!$B$162:$B$252,'WS Trial balance'!$D8,'MUTASI 2026'!$H$162:$H$252) -> 185549733 | Q8: =IF(F8="D",(L8-M8+O8-P8),0) -> 2.2132388e+08 | R8: =IF(F8="K",(-L8+M8-O8+P8),0) -> 0 | T8: =SUMIF('MUTASI 2026'!$B$254:$B$356,'WS Trial balance'!$D8,'MUTASI 2026'!$G$254:$G$356) -> 200552329 | U8: =SUMIF('MUTASI 2026'!$B$254:$B$356,'WS Trial balance'!$D8,'MUTASI 2026'!$H$254:$H$356) -> 1.6824743e+08 | V8: =IF(F8="D",(Q8-R8+T8-U8),0) -> 2.5362878e+08 | W8: =IF(F8="K",(-Q8+R8-T8+U8),0) -> 0 | Y8: =SUMIF('MUTASI 2026'!$B$358:$B$480,'WS Trial balance'!$D8,'MUTASI 2026'!$G$358:$G$480) -> 1.3277787e+08 | Z8: =SUMIF('MUTASI 2026'!$B$358:$B$480,'WS Trial balance'!$D8,'MUTASI 2026'!$H$358:$H$480) -> 115116400 | AA8: =IF(F8="D",(V8-W8+Y8-Z8),0) -> 2.7129025e+08 | AB8: =IF(F8="K",(-V8+W8-Y8+Z8),0) -> 0 | AD8: =SUMIF('MUTASI 2026'!$B$482:$B$655,'WS Trial balance'!$D8,'MUTASI 2026'!$G$482:$G$655) -> 1.3562463e+08 | AE8: =SUMIF('MUTASI 2026'!$B$482:$B$655,'WS Trial balance'!$D8,'MUTASI 2026'!$H$482:$H$655) -> 258347801 | AF8: =IF(F8="D",(AA8-AB8+AD8-AE8),0) -> 1.4856708e+08 | AG8: =IF(F8="K",(-AA8+AB8-AD8+AE8),0) -> 0 | AI8: =SUMIF('MUTASI 2026'!$B$657:$B$748,'WS Trial balance'!$D8,'MUTASI 2026'!$G$657:$G$748) -> 262975576 | AJ8: =SUMIF('MUTASI 2026'!$B$657:$B$748,'WS Trial balance'!$D8,'MUTASI 2026'!$H$657:$H$748) -> 1.9024789e+08 | AK8: =IF(F8="D",(AF8-AG8+AI8-AJ8),0) -> 2.2129476e+08 | AL8: =IF(F8="K",(-AF8+AG8-AI8+AJ8),0) -> 0 | AN8: =SUMIF('MUTASI 2026'!$B$750:$B$851,'WS Trial balance'!$D8,'MUTASI 2026'!$G$750:$G$851) -> 119526496 | AO8: =SUMIF('MUTASI 2026'!$B$750:$B$851,'WS Trial balance'!$D8,'MUTASI 2026'!$H$750:$H$851) -> 1.0601945e+08 | AP8: =IF(F8="D",(AK8-AL8+AN8-AO8),0) -> 2.348018e+08 | AQ8: =IF(F8="K",(-AK8+AL8-AN8+AO8),0) -> 0 | AS8: =SUMIF('MUTASI 2026'!$B$853:$B$945,'WS Trial balance'!$D8,'MUTASI 2026'!$G$853:$G$945) -> 88167024 | AT8: =SUMIF('MUTASI 2026'!$B$853:$B$945,'WS Trial balance'!$D8,'MUTASI 2026'!$H$853:$H$945) -> 126255000 | AU8: =IF(F8="D",(AP8-AQ8+AS8-AT8),0) -> 1.9671383e+08 | AV8: =IF(F8="K",(-AP8+AQ8-AS8+AT8),0) -> 0 | AX8: =SUMIF('MUTASI 2026'!$B$1274:$B$1379,'WS Trial balance'!$D8,'MUTASI 2026'!$G$1274:$G$1379) -> 0 | AY8: =SUMIF('MUTASI 2026'!$B$1274:$B$1379,'WS Trial balance'!$D8,'MUTASI 2026'!$H$1274:$H$1379) -> 0 | AZ8: =IF(F8="D",(AU8-AV8+AX8-AY8),0) -> 1.9671383e+08 | BA8: =IF(F8="K",(-AU8+AV8-AX8+AY8),0) -> 0 | BC8: =SUMIF('MUTASI 2026'!$B$1382:$B$1477,'WS Trial balance'!$D8,'MUTASI 2026'!$G$1382:$G$1477) -> 0 | BD8: =SUMIF('MUTASI 2026'!$B$1382:$B$1477,'WS Trial balance'!$D8,'MUTASI 2026'!$H$1382:$H$1477) -> 0 | BE8: =IF(F8="D",(AZ8-BA8+BC8-BD8),0) -> 1.9671383e+08 | BF8: =IF(F8="K",(-AZ8+BA8-BC8+BD8),0) -> 0 | BH8: =SUMIF('MUTASI 2026'!$B$1480:$B$1600,'WS Trial balance'!$D8,'MUTASI 2026'!$G$1480:$G$1600) -> 0 | BI8: =SUMIF('MUTASI 2026'!$B$1480:$B$1600,'WS Trial balance'!$D8,'MUTASI 2026'!$H$1480:$H$1600) -> 0 | BJ8: =IF(F8="D",(BE8-BF8+BH8-BI8),0) -> 1.9671383e+08 | BK8: =IF(F8="K",(-BE8+BF8-BH8+BI8),0) -> 0 | BM8: =SUMIF('MUTASI 2026'!$B$1603:$B$1722,'WS Trial balance'!$D8,'MUTASI 2026'!$G$1603:$G$1722) -> 0 | BN8: =SUMIF('MUTASI 2026'!$B$1603:$B$1722,'WS Trial balance'!$D8,'MUTASI 2026'!$H$1603:$H$1722) -> 0 | BO8: =IF(F8="D",(BJ8-BK8+BM8-BN8),0) -> 1.9671383e+08 | BP8: =IF(F8="K",(-BJ8+BK8-BM8+BN8),0) -> 0 | BT8: =G8 -> 3.0295667e+08 | BU8: =H8 -> 0 | BW8: =J8+O8+T8+Y8+AD8+AI8+AN8+AS8+AX8+BC8+BH8+BM8 -> 1.194102e+09 | BX8: =K8+P8+U8+Z8+AE8+AJ8+AO8+AT8+AY8+BD8+BI8+BN8 -> 1.3003448e+09 | BZ8: =IF(F8="D",(BT8-BU8+BW8-BX8),0) -> 1.9671383e+08 | CA8: =IF(F8="K",(-BT8+BU8-BW8+BX8),0) -> 0
D9: A03 | E9: SURAT BERHARGA | F9: D | G9: 0 | H9: 0 | J9: =SUMIF('MUTASI 2026'!$B$5:$B$160,'WS Trial balance'!$D9,'MUTASI 2026'!$G$5:$G$160) -> 0 | K9: =SUMIF('MUTASI 2026'!$B$5:$B$160,'WS Trial balance'!$D9,'MUTASI 2026'!$H$5:$H$160) -> 0 | L9: =IF(F9="D",(G9-H9+J9-K9),0) -> 0 | M9: =IF(F9="K",(-G9+H9-J9+K9),0) -> 0 | O9: =SUMIF('MUTASI 2026'!$B$162:$B$252,'WS Trial balance'!$D9,'MUTASI 2026'!$G$162:$G$252) -> 0 | P9: =SUMIF('MUTASI 2026'!$B$162:$B$252,'WS Trial balance'!$D9,'MUTASI 2026'!$H$162:$H$252) -> 0 | Q9: =IF(F9="D",(L9-M9+O9-P9),0) -> 0 | R9: =IF(F9="K",(-L9+M9-O9+P9),0) -> 0 | T9: =SUMIF('MUTASI 2026'!$B$254:$B$356,'WS Trial balance'!$D9,'MUTASI 2026'!$G$254:$G$356) -> 0 | U9: =SUMIF('MUTASI 2026'!$B$254:$B$356,'WS Trial balance'!$D9,'MUTASI 2026'!$H$254:$H$356) -> 0 | V9: =IF(F9="D",(Q9-R9+T9-U9),0) -> 0 | W9: =IF(F9="K",(-Q9+R9-T9+U9),0) -> 0 | Y9: =SUMIF('MUTASI 2026'!$B$358:$B$480,'WS Trial balance'!$D9,'MUTASI 2026'!$G$358:$G$480) -> 0 | Z9: =SUMIF('MUTASI 2026'!$B$358:$B$480,'WS Trial balance'!$D9,'MUTASI 2026'!$H$358:$H$480) -> 0 | AA9: =IF(F9="D",(V9-W9+Y9-Z9),0) -> 0 | AB9: =IF(F9="K",(-V9+W9-Y9+Z9),0) -> 0 | AD9: =SUMIF('MUTASI 2026'!$B$482:$B$655,'WS Trial balance'!$D9,'MUTASI 2026'!$G$482:$G$655) -> 0 | AE9: =SUMIF('MUTASI 2026'!$B$482:$B$655,'WS Trial balance'!$D9,'MUTASI 2026'!$H$482:$H$655) -> 0 | AF9: =IF(F9="D",(AA9-AB9+AD9-AE9),0) -> 0 | AG9: =IF(F9="K",(-AA9+AB9-AD9+AE9),0) -> 0 | AI9: =SUMIF('MUTASI 2026'!$B$657:$B$748,'WS Trial balance'!$D9,'MUTASI 2026'!$G$657:$G$748) -> 0 | AJ9: =SUMIF('MUTASI 2026'!$B$657:$B$748,'WS Trial balance'!$D9,'MUTASI 2026'!$H$657:$H$748) -> 0 | AK9: =IF(F9="D",(AF9-AG9+AI9-AJ9),0) -> 0 | AL9: =IF(F9="K",(-AF9+AG9-AI9+AJ9),0) -> 0 | AN9: =SUMIF('MUTASI 2026'!$B$750:$B$851,'WS Trial balance'!$D9,'MUTASI 2026'!$G$750:$G$851) -> 0 | AO9: =SUMIF('MUTASI 2026'!$B$750:$B$851,'WS Trial balance'!$D9,'MUTASI 2026'!$H$750:$H$851) -> 0 | AP9: =IF(F9="D",(AK9-AL9+AN9-AO9),0) -> 0 | AQ9: =IF(F9="K",(-AK9+AL9-AN9+AO9),0) -> 0 | AS9: =SUMIF('MUTASI 2026'!$B$853:$B$945,'WS Trial balance'!$D9,'MUTASI 2026'!$G$853:$G$945) -> 0 | AT9: =SUMIF('MUTASI 2026'!$B$853:$B$945,'WS Trial balance'!$D9,'MUTASI 2026'!$H$853:$H$945) -> 0 | AU9: =IF(F9="D",(AP9-AQ9+AS9-AT9),0) -> 0 | AV9: =IF(F9="K",(-AP9+AQ9-AS9+AT9),0) -> 0 | AX9: =SUMIF('MUTASI 2026'!$B$1274:$B$1379,'WS Trial balance'!$D9,'MUTASI 2026'!$G$1274:$G$1379) -> 0 | AY9: =SUMIF('MUTASI 2026'!$B$1274:$B$1379,'WS Trial balance'!$D9,'MUTASI 2026'!$H$1274:$H$1379) -> 0 | AZ9: =IF(F9="D",(AU9-AV9+AX9-AY9),0) -> 0 | BA9: =IF(F9="K",(-AU9+AV9-AX9+AY9),0) -> 0 | BC9: =SUMIF('MUTASI 2026'!$B$1382:$B$1477,'WS Trial balance'!$D9,'MUTASI 2026'!$G$1382:$G$1477) -> 0 | BD9: =SUMIF('MUTASI 2026'!$B$1382:$B$1477,'WS Trial balance'!$D9,'MUTASI 2026'!$H$1382:$H$1477) -> 0 | BE9: =IF(F9="D",(AZ9-BA9+BC9-BD9),0) -> 0 | BF9: =IF(F9="K",(-AZ9+BA9-BC9+BD9),0) -> 0 | BH9: =SUMIF('MUTASI 2026'!$B$1480:$B$1600,'WS Trial balance'!$D9,'MUTASI 2026'!$G$1480:$G$1600) -> 0 | BI9: =SUMIF('MUTASI 2026'!$B$1480:$B$1600,'WS Trial balance'!$D9,'MUTASI 2026'!$H$1480:$H$1600) -> 0 | BJ9: =IF(F9="D",(BE9-BF9+BH9-BI9),0) -> 0 | BK9: =IF(F9="K",(-BE9+BF9-BH9+BI9),0) -> 0 | BM9: =SUMIF('MUTASI 2026'!$B$1603:$B$1722,'WS Trial balance'!$D9,'MUTASI 2026'!$G$1603:$G$1722) -> 0 | BN9: =SUMIF('MUTASI 2026'!$B$1603:$B$1722,'WS Trial balance'!$D9,'MUTASI 2026'!$H$1603:$H$1722) -> 0 | BO9: =IF(F9="D",(BJ9-BK9+BM9-BN9),0) -> 0 | BP9: =IF(F9="K",(-BJ9+BK9-BM9+BN9),0) -> 0 | BT9: =G9 -> 0 | BU9: =H9 -> 0 | BW9: =J9+O9+T9+Y9+AD9+AI9+AN9+AS9+AX9+BC9+BH9+BM9 -> 0 | BX9: =K9+P9+U9+Z9+AE9+AJ9+AO9+AT9+AY9+BD9+BI9+BN9 -> 0 | BZ9: =IF(F9="D",(BT9-BU9+BW9-BX9),0) -> 0 | CA9: =IF(F9="K",(-BT9+BU9-BW9+BX9),0) -> 0
D10: A04A | E10: PIUTANG ANGGOTA | F10: D | G10: 1.9264197e+09 | H10: 0 | J10: =SUMIF('MUTASI 2026'!$B$5:$B$160,'WS Trial balance'!$D10,'MUTASI 2026'!$G$5:$G$160) -> 284500000 | K10: =SUMIF('MUTASI 2026'!$B$5:$B$160,'WS Trial balance'!$D10,'MUTASI 2026'!$H$5:$H$160) -> 2.3192654e+08 | L10: =IF(F10="D",(G10-H10+J10-K10),0) -> 1.9789932e+09 | M10: =IF(F10="K",(-G10+H10-J10+K10),0) -> 0 | O10: =SUMIF('MUTASI 2026'!$B$162:$B$252,'WS Trial balance'!$D10,'MUTASI 2026'!$G$162:$G$252) -> 1.55e+08 | P10: =SUMIF('MUTASI 2026'!$B$162:$B$252,'WS Trial balance'!$D10,'MUTASI 2026'!$H$162:$H$252) -> 91326917 | Q10: =IF(F10="D",(L10-M10+O10-P10),0) -> 2.0426662e+09 | R10: =IF(F10="K",(-L10+M10-O10+P10),0) -> 0 | T10: =SUMIF('MUTASI 2026'!$B$254:$B$356,'WS Trial balance'!$D10,'MUTASI 2026'!$G$254:$G$356) -> 50000000 | U10: =SUMIF('MUTASI 2026'!$B$254:$B$356,'WS Trial balance'!$D10,'MUTASI 2026'!$H$254:$H$356) -> 1.6440381e+08 | V10: =IF(F10="D",(Q10-R10+T10-U10),0) -> 1.9282624e+09 | W10: =IF(F10="K",(-Q10+R10-T10+U10),0) -> 0 | Y10: =SUMIF('MUTASI 2026'!$B$358:$B$480,'WS Trial balance'!$D10,'MUTASI 2026'!$G$358:$G$480) -> 119500000 | Z10: =SUMIF('MUTASI 2026'!$B$358:$B$480,'WS Trial balance'!$D10,'MUTASI 2026'!$H$358:$H$480) -> 1.2398614e+08 | AA10: =IF(F10="D",(V10-W10+Y10-Z10),0) -> 1.9237763e+09 | AB10: =IF(F10="K",(-V10+W10-Y10+Z10),0) -> 0 | AD10: =SUMIF('MUTASI 2026'!$B$482:$B$655,'WS Trial balance'!$D10,'MUTASI 2026'!$G$482:$G$655) -> 278000000 | AE10: =SUMIF('MUTASI 2026'!$B$482:$B$655,'WS Trial balance'!$D10,'MUTASI 2026'!$H$482:$H$655) -> 2.2368703e+08 | AF10: =IF(F10="D",(AA10-AB10+AD10-AE10),0) -> 1.9780893e+09 | AG10: =IF(F10="K",(-AA10+AB10-AD10+AE10),0) -> 0 | AI10: =SUMIF('MUTASI 2026'!$B$657:$B$748,'WS Trial balance'!$D10,'MUTASI 2026'!$G$657:$G$748) -> 19000000 | AJ10: =SUMIF('MUTASI 2026'!$B$657:$B$748,'WS Trial balance'!$D10,'MUTASI 2026'!$H$657:$H$748) -> 66299361 | AK10: =IF(F10="D",(AF10-AG10+AI10-AJ10),0) -> 1.9307899e+09 | AL10: =IF(F10="K",(-AF10+AG10-AI10+AJ10),0) -> 0 | AN10: =SUMIF('MUTASI 2026'!$B$750:$B$851,'WS Trial balance'!$D10,'MUTASI 2026'!$G$750:$G$851) -> 274000000 | AO10: =SUMIF('MUTASI 2026'!$B$750:$B$851,'WS Trial balance'!$D10,'MUTASI 2026'!$H$750:$H$851) -> 2.5537369e+08 | AP10: =IF(F10="D",(AK10-AL10+AN10-AO10),0) -> 1.9494162e+09 | AQ10: =IF(F10="K",(-AK10+AL10-AN10+AO10),0) -> 0 | AS10: =SUMIF('MUTASI 2026'!$B$853:$B$945,'WS Trial balance'!$D10,'MUTASI 2026'!$G$853:$G$945) -> 125000000 | AT10: =SUMIF('MUTASI 2026'!$B$853:$B$945,'WS Trial balance'!$D10,'MUTASI 2026'!$H$853:$H$945) -> 95413194 | AU10: =IF(F10="D",(AP10-AQ10+AS10-AT10),0) -> 1.979003e+09 | AV10: =IF(F10="K",(-AP10+AQ10-AS10+AT10),0) -> 0 | AX10: =SUMIF('MUTASI 2026'!$B$1274:$B$1379,'WS Trial balance'!$D10,'MUTASI 2026'!$G$1274:$G$1379) -> 0 | AY10: =SUMIF('MUTASI 2026'!$B$1274:$B$1379,'WS Trial balance'!$D10,'MUTASI 2026'!$H$1274:$H$1379) -> 0 | AZ10: =IF(F10="D",(AU10-AV10+AX10-AY10),0) -> 1.979003e+09 | BA10: =IF(F10="K",(-AU10+AV10-AX10+AY10),0) -> 0 | BC10: =SUMIF('MUTASI 2026'!$B$1382:$B$1477,'WS Trial balance'!$D10,'MUTASI 2026'!$G$1382:$G$1477) -> 0 | BD10: =SUMIF('MUTASI 2026'!$B$1382:$B$1477,'WS Trial balance'!$D10,'MUTASI 2026'!$H$1382:$H$1477) -> 0 | BE10: =IF(F10="D",(AZ10-BA10+BC10-BD10),0) -> 1.979003e+09 | BF10: =IF(F10="K",(-AZ10+BA10-BC10+BD10),0) -> 0 | BH10: =SUMIF('MUTASI 2026'!$B$1480:$B$1600,'WS Trial balance'!$D10,'MUTASI 2026'!$G$1480:$G$1600) -> 0 | BI10: =SUMIF('MUTASI 2026'!$B$1480:$B$1600,'WS Trial balance'!$D10,'MUTASI 2026'!$H$1480:$H$1600) -> 0 | BJ10: =IF(F10="D",(BE10-BF10+BH10-BI10),0) -> 1.979003e+09 | BK10: =IF(F10="K",(-BE10+BF10-BH10+BI10),0) -> 0 | BM10: =SUMIF('MUTASI 2026'!$B$1603:$B$1722,'WS Trial balance'!$D10,'MUTASI 2026'!$G$1603:$G$1722) -> 0 | BN10: =SUMIF('MUTASI 2026'!$B$1603:$B$1722,'WS Trial balance'!$D10,'MUTASI 2026'!$H$1603:$H$1722) -> 0 | BO10: =IF(F10="D",(BJ10-BK10+BM10-BN10),0) -> 1.979003e+09 | BP10: =IF(F10="K",(-BJ10+BK10-BM10+BN10),0) -> 0 | BT10: =G10 -> 1.9264197e+09 | BU10: =H10 -> 0 | BW10: =J10+O10+T10+Y10+AD10+AI10+AN10+AS10+AX10+BC10+BH10+BM10 -> 1.305e+09 | BX10: =K10+P10+U10+Z10+AE10+AJ10+AO10+AT10+AY10+BD10+BI10+BN10 -> 1.2524167e+09 | BZ10: =IF(F10="D",(BT10-BU10+BW10-BX10),0) -> 1.979003e+09 | CA10: =IF(F10="K",(-BT10+BU10-BW10+BX10),0) -> 0
D11: A04B | E11: PIUTANG NON ANGGOTA | F11: D | G11: 643143867 | H11: 0 | J11: =SUMIF('MUTASI 2026'!$B$5:$B$160,'WS Trial balance'!$D11,'MUTASI 2026'!$G$5:$G$160) -> 70560000 | K11: =SUMIF('MUTASI 2026'!$B$5:$B$160,'WS Trial balance'!$D11,'MUTASI 2026'!$H$5:$H$160) -> 78400000 | L11: =IF(F11="D",(G11-H11+J11-K11),0) -> 635303867 | M11: =IF(F11="K",(-G11+H11-J11+K11),0) -> 0 | O11: =SUMIF('MUTASI 2026'!$B$162:$B$252,'WS Trial balance'!$D11,'MUTASI 2026'!$G$162:$G$252) -> 27440000 | P11: =SUMIF('MUTASI 2026'!$B$162:$B$252,'WS Trial balance'!$D11,'MUTASI 2026'!$H$162:$H$252) -> 0 | Q11: =IF(F11="D",(L11-M11+O11-P11),0) -> 662743867 | R11: =IF(F11="K",(-L11+M11-O11+P11),0) -> 0 | T11: =SUMIF('MUTASI 2026'!$B$254:$B$356,'WS Trial balance'!$D11,'MUTASI 2026'!$G$254:$G$356) -> 27440000 | U11: =SUMIF('MUTASI 2026'!$B$254:$B$356,'WS Trial balance'!$D11,'MUTASI 2026'!$H$254:$H$356) -> 15680000 | V11: =IF(F11="D",(Q11-R11+T11-U11),0) -> 674503867 | W11: =IF(F11="K",(-Q11+R11-T11+U11),0) -> 0 | Y11: =SUMIF('MUTASI 2026'!$B$358:$B$480,'WS Trial balance'!$D11,'MUTASI 2026'!$G$358:$G$480) -> 27440000 | Z11: =SUMIF('MUTASI 2026'!$B$358:$B$480,'WS Trial balance'!$D11,'MUTASI 2026'!$H$358:$H$480) -> 15680000 | AA11: =IF(F11="D",(V11-W11+Y11-Z11),0) -> 686263867 | AB11: =IF(F11="K",(-V11+W11-Y11+Z11),0) -> 0 | AD11: =SUMIF('MUTASI 2026'!$B$482:$B$655,'WS Trial balance'!$D11,'MUTASI 2026'!$G$482:$G$655) -> 27440000 | AE11: =SUMIF('MUTASI 2026'!$B$482:$B$655,'WS Trial balance'!$D11,'MUTASI 2026'!$H$482:$H$655) -> 15680000 | AF11: =IF(F11="D",(AA11-AB11+AD11-AE11),0) -> 698023867 | AG11: =IF(F11="K",(-AA11+AB11-AD11+AE11),0) -> 0 | AI11: =SUMIF('MUTASI 2026'!$B$657:$B$748,'WS Trial balance'!$D11,'MUTASI 2026'!$G$657:$G$748) -> 15680000 | AJ11: =SUMIF('MUTASI 2026'!$B$657:$B$748,'WS Trial balance'!$D11,'MUTASI 2026'!$H$657:$H$748) -> 15680000 | AK11: =IF(F11="D",(AF11-AG11+AI11-AJ11),0) -> 698023867 | AL11: =IF(F11="K",(-AF11+AG11-AI11+AJ11),0) -> 0 | AN11: =SUMIF('MUTASI 2026'!$B$750:$B$851,'WS Trial balance'!$D11,'MUTASI 2026'!$G$750:$G$851) -> 15680000 | AO11: =SUMIF('MUTASI 2026'!$B$750:$B$851,'WS Trial balance'!$D11,'MUTASI 2026'!$H$750:$H$851) -> 31360000 | AP11: =IF(F11="D",(AK11-AL11+AN11-AO11),0) -> 682343867 | AQ11: =IF(F11="K",(-AK11+AL11-AN11+AO11),0) -> 0 | AS11: =SUMIF('MUTASI 2026'!$B$853:$B$945,'WS Trial balance'!$D11,'MUTASI 2026'!$G$853:$G$945) -> 15680000 | AT11: =SUMIF('MUTASI 2026'!$B$853:$B$945,'WS Trial balance'!$D11,'MUTASI 2026'!$H$853:$H$945) -> 0 | AU11: =IF(F11="D",(AP11-AQ11+AS11-AT11),0) -> 698023867 | AV11: =IF(F11="K",(-AP11+AQ11-AS11+AT11),0) -> 0 | AX11: =SUMIF('MUTASI 2026'!$B$1274:$B$1379,'WS Trial balance'!$D11,'MUTASI 2026'!$G$1274:$G$1379) -> 0 | AY11: =SUMIF('MUTASI 2026'!$B$1274:$B$1379,'WS Trial balance'!$D11,'MUTASI 2026'!$H$1274:$H$1379) -> 0 | AZ11: =IF(F11="D",(AU11-AV11+AX11-AY11),0) -> 698023867 | BA11: =IF(F11="K",(-AU11+AV11-AX11+AY11),0) -> 0 | BC11: =SUMIF('MUTASI 2026'!$B$1382:$B$1477,'WS Trial balance'!$D11,'MUTASI 2026'!$G$1382:$G$1477) -> 0 | BD11: =SUMIF('MUTASI 2026'!$B$1382:$B$1477,'WS Trial balance'!$D11,'MUTASI 2026'!$H$1382:$H$1477) -> 0 | BE11: =IF(F11="D",(AZ11-BA11+BC11-BD11),0) -> 698023867 | BF11: =IF(F11="K",(-AZ11+BA11-BC11+BD11),0) -> 0 | BH11: =SUMIF('MUTASI 2026'!$B$1480:$B$1600,'WS Trial balance'!$D11,'MUTASI 2026'!$G$1480:$G$1600) -> 0 | BI11: =SUMIF('MUTASI 2026'!$B$1480:$B$1600,'WS Trial balance'!$D11,'MUTASI 2026'!$H$1480:$H$1600) -> 0 | BJ11: =IF(F11="D",(BE11-BF11+BH11-BI11),0) -> 698023867 | BK11: =IF(F11="K",(-BE11+BF11-BH11+BI11),0) -> 0 | BM11: =SUMIF('MUTASI 2026'!$B$1603:$B$1722,'WS Trial balance'!$D11,'MUTASI 2026'!$G$1603:$G$1722) -> 0 | BN11: =SUMIF('MUTASI 2026'!$B$1603:$B$1722,'WS Trial balance'!$D11,'MUTASI 2026'!$H$1603:$H$1722) -> 0 | BO11: =IF(F11="D",(BJ11-BK11+BM11-BN11),0) -> 698023867 | BP11: =IF(F11="K",(-BJ11+BK11-BM11+BN11),0) -> 0 | BT11: =G11 -> 643143867 | BU11: =H11 -> 0 | BW11: =J11+O11+T11+Y11+AD11+AI11+AN11+AS11+AX11+BC11+BH11+BM11 -> 227360000 | BX11: =K11+P11+U11+Z11+AE11+AJ11+AO11+AT11+AY11+BD11+BI11+BN11 -> 172480000 | BZ11: =IF(F11="D",(BT11-BU11+BW11-BX11),0) -> 698023867 | CA11: =IF(F11="K",(-BT11+BU11-BW11+BX11),0) -> 0
D12: A05 | E12: CADANGAN PENGHAPUSAN PIUTANG USAHA | F12: K | G12: 0 | H12: 182000000 | J12: =SUMIF('MUTASI 2026'!$B$5:$B$160,'WS Trial balance'!$D12,'MUTASI 2026'!$G$5:$G$160) -> 0 | K12: =SUMIF('MUTASI 2026'!$B$5:$B$160,'WS Trial balance'!$D12,'MUTASI 2026'!$H$5:$H$160) -> 1500000 | L12: =IF(F12="D",(G12-H12+J12-K12),0) -> 0 | M12: =IF(F12="K",(-G12+H12-J12+K12),0) -> 183500000 | O12: =SUMIF('MUTASI 2026'!$B$162:$B$252,'WS Trial balance'!$D12,'MUTASI 2026'!$G$162:$G$252) -> 0 | P12: =SUMIF('MUTASI 2026'!$B$162:$B$252,'WS Trial balance'!$D12,'MUTASI 2026'!$H$162:$H$252) -> 1500000 | Q12: =IF(F12="D",(L12-M12+O12-P12),0) -> 0 | R12: =IF(F12="K",(-L12+M12-O12+P12),0) -> 185000000 | T12: =SUMIF('MUTASI 2026'!$B$254:$B$356,'WS Trial balance'!$D12,'MUTASI 2026'!$G$254:$G$356) -> 0 | U12: =SUMIF('MUTASI 2026'!$B$254:$B$356,'WS Trial balance'!$D12,'MUTASI 2026'!$H$254:$H$356) -> 1500000 | V12: =IF(F12="D",(Q12-R12+T12-U12),0) -> 0 | W12: =IF(F12="K",(-Q12+R12-T12+U12),0) -> 186500000 | Y12: =SUMIF('MUTASI 2026'!$B$358:$B$480,'WS Trial balance'!$D12,'MUTASI 2026'!$G$358:$G$480) -> 0 | Z12: =SUMIF('MUTASI 2026'!$B$358:$B$480,'WS Trial balance'!$D12,'MUTASI 2026'!$H$358:$H$480) -> 1500000 | AA12: =IF(F12="D",(V12-W12+Y12-Z12),0) -> 0 | AB12: =IF(F12="K",(-V12+W12-Y12+Z12),0) -> 188000000 | AD12: =SUMIF('MUTASI 2026'!$B$482:$B$655,'WS Trial balance'!$D12,'MUTASI 2026'!$G$482:$G$655) -> 0 | AE12: =SUMIF('MUTASI 2026'!$B$482:$B$655,'WS Trial balance'!$D12,'MUTASI 2026'!$H$482:$H$655) -> 1500000 | AF12: =IF(F12="D",(AA12-AB12+AD12-AE12),0) -> 0 | AG12: =IF(F12="K",(-AA12+AB12-AD12+AE12),0) -> 189500000 | AI12: =SUMIF('MUTASI 2026'!$B$657:$B$748,'WS Trial balance'!$D12,'MUTASI 2026'!$G$657:$G$748) -> 0 | AJ12: =SUMIF('MUTASI 2026'!$B$657:$B$748,'WS Trial balance'!$D12,'MUTASI 2026'!$H$657:$H$748) -> 1500000 | AK12: =IF(F12="D",(AF12-AG12+AI12-AJ12),0) -> 0 | AL12: =IF(F12="K",(-AF12+AG12-AI12+AJ12),0) -> 191000000 | AN12: =SUMIF('MUTASI 2026'!$B$750:$B$851,'WS Trial balance'!$D12,'MUTASI 2026'!$G$750:$G$851) -> 0 | AO12: =SUMIF('MUTASI 2026'!$B$750:$B$851,'WS Trial balance'!$D12,'MUTASI 2026'!$H$750:$H$851) -> 1500000 | AP12: =IF(F12="D",(AK12-AL12+AN12-AO12),0) -> 0 | AQ12: =IF(F12="K",(-AK12+AL12-AN12+AO12),0) -> 192500000 | AS12: =SUMIF('MUTASI 2026'!$B$853:$B$945,'WS Trial balance'!$D12,'MUTASI 2026'!$G$853:$G$945) -> 0 | AT12: =SUMIF('MUTASI 2026'!$B$853:$B$945,'WS Trial balance'!$D12,'MUTASI 2026'!$H$853:$H$945) -> 1500000 | AU12: =IF(F12="D",(AP12-AQ12+AS12-AT12),0) -> 0 | AV12: =IF(F12="K",(-AP12+AQ12-AS12+AT12),0) -> 194000000 | AX12: =SUMIF('MUTASI 2026'!$B$1274:$B$1379,'WS Trial balance'!$D12,'MUTASI 2026'!$G$1274:$G$1379) -> 0 | AY12: =SUMIF('MUTASI 2026'!$B$1274:$B$1379,'WS Trial balance'!$D12,'MUTASI 2026'!$H$1274:$H$1379) -> 0 | AZ12: =IF(F12="D",(AU12-AV12+AX12-AY12),0) -> 0 | BA12: =IF(F12="K",(-AU12+AV12-AX12+AY12),0) -> 194000000 | BC12: =SUMIF('MUTASI 2026'!$B$1382:$B$1477,'WS Trial balance'!$D12,'MUTASI 2026'!$G$1382:$G$1477) -> 0 | BD12: =SUMIF('MUTASI 2026'!$B$1382:$B$1477,'WS Trial balance'!$D12,'MUTASI 2026'!$H$1382:$H$1477) -> 0 | BE12: =IF(F12="D",(AZ12-BA12+BC12-BD12),0) -> 0 | BF12: =IF(F12="K",(-AZ12+BA12-BC12+BD12),0) -> 194000000 | BH12: =SUMIF('MUTASI 2026'!$B$1480:$B$1600,'WS Trial balance'!$D12,'MUTASI 2026'!$G$1480:$G$1600) -> 0 | BI12: =SUMIF('MUTASI 2026'!$B$1480:$B$1600,'WS Trial balance'!$D12,'MUTASI 2026'!$H$1480:$H$1600) -> 0 | BJ12: =IF(F12="D",(BE12-BF12+BH12-BI12),0) -> 0 | BK12: =IF(F12="K",(-BE12+BF12-BH12+BI12),0) -> 194000000 | BM12: =SUMIF('MUTASI 2026'!$B$1603:$B$1722,'WS Trial balance'!$D12,'MUTASI 2026'!$G$1603:$G$1722) -> 0 | BN12: =SUMIF('MUTASI 2026'!$B$1603:$B$1722,'WS Trial balance'!$D12,'MUTASI 2026'!$H$1603:$H$1722) -> 0 | BO12: =IF(F12="D",(BJ12-BK12+BM12-BN12),0) -> 0 | BP12: =IF(F12="K",(-BJ12+BK12-BM12+BN12),0) -> 194000000 | BT12: =G12 -> 0 | BU12: =H12 -> 182000000 | BW12: =J12+O12+T12+Y12+AD12+AI12+AN12+AS12+AX12+BC12+BH12+BM12 -> 0 | BX12: =K12+P12+U12+Z12+AE12+AJ12+AO12+AT12+AY12+BD12+BI12+BN12 -> 12000000 | BZ12: =IF(F12="D",(BT12-BU12+BW12-BX12),0) -> 0 | CA12: =IF(F12="K",(-BT12+BU12-BW12+BX12),0) -> 194000000
D13: A06 | E13: PIUTANG LAIN-LAIN | F13: D | G13: 0 | H13: 0 | J13: =SUMIF('MUTASI 2026'!$B$5:$B$160,'WS Trial balance'!$D13,'MUTASI 2026'!$G$5:$G$160) -> 0 | K13: =SUMIF('MUTASI 2026'!$B$5:$B$160,'WS Trial balance'!$D13,'MUTASI 2026'!$H$5:$H$160) -> 0 | L13: =IF(F13="D",(G13-H13+J13-K13),0) -> 0 | M13: =IF(F13="K",(-G13+H13-J13+K13),0) -> 0 | O13: =SUMIF('MUTASI 2026'!$B$162:$B$252,'WS Trial balance'!$D13,'MUTASI 2026'!$G$162:$G$252) -> 0 | P13: =SUMIF('MUTASI 2026'!$B$162:$B$252,'WS Trial balance'!$D13,'MUTASI 2026'!$H$162:$H$252) -> 0 | Q13: =IF(F13="D",(L13-M13+O13-P13),0) -> 0 | R13: =IF(F13="K",(-L13+M13-O13+P13),0) -> 0 | T13: =SUMIF('MUTASI 2026'!$B$254:$B$356,'WS Trial balance'!$D13,'MUTASI 2026'!$G$254:$G$356) -> 0 | U13: =SUMIF('MUTASI 2026'!$B$254:$B$356,'WS Trial balance'!$D13,'MUTASI 2026'!$H$254:$H$356) -> 0 | V13: =IF(F13="D",(Q13-R13+T13-U13),0) -> 0 | W13: =IF(F13="K",(-Q13+R13-T13+U13),0) -> 0 | Y13: =SUMIF('MUTASI 2026'!$B$358:$B$480,'WS Trial balance'!$D13,'MUTASI 2026'!$G$358:$G$480) -> 0 | Z13: =SUMIF('MUTASI 2026'!$B$358:$B$480,'WS Trial balance'!$D13,'MUTASI 2026'!$H$358:$H$480) -> 0 | AA13: =IF(F13="D",(V13-W13+Y13-Z13),0) -> 0 | AB13: =IF(F13="K",(-V13+W13-Y13+Z13),0) -> 0 | AD13: =SUMIF('MUTASI 2026'!$B$482:$B$655,'WS Trial balance'!$D13,'MUTASI 2026'!$G$482:$G$655) -> 0 | AE13: =SUMIF('MUTASI 2026'!$B$482:$B$655,'WS Trial balance'!$D13,'MUTASI 2026'!$H$482:$H$655) -> 0 | AF13: =IF(F13="D",(AA13-AB13+AD13-AE13),0) -> 0 | AG13: =IF(F13="K",(-AA13+AB13-AD13+AE13),0) -> 0 | AI13: =SUMIF('MUTASI 2026'!$B$657:$B$748,'WS Trial balance'!$D13,'MUTASI 2026'!$G$657:$G$748) -> 0 | AJ13: =SUMIF('MUTASI 2026'!$B$657:$B$748,'WS Trial balance'!$D13,'MUTASI 2026'!$H$657:$H$748) -> 0 | AK13: =IF(F13="D",(AF13-AG13+AI13-AJ13),0) -> 0 | AL13: =IF(F13="K",(-AF13+AG13-AI13+AJ13),0) -> 0 | AN13: =SUMIF('MUTASI 2026'!$B$750:$B$851,'WS Trial balance'!$D13,'MUTASI 2026'!$G$750:$G$851) -> 0 | AO13: =SUMIF('MUTASI 2026'!$B$750:$B$851,'WS Trial balance'!$D13,'MUTASI 2026'!$H$750:$H$851) -> 0 | AP13: =IF(F13="D",(AK13-AL13+AN13-AO13),0) -> 0 | AQ13: =IF(F13="K",(-AK13+AL13-AN13+AO13),0) -> 0 | AS13: =SUMIF('MUTASI 2026'!$B$853:$B$945,'WS Trial balance'!$D13,'MUTASI 2026'!$G$853:$G$945) -> 0 | AT13: =SUMIF('MUTASI 2026'!$B$853:$B$945,'WS Trial balance'!$D13,'MUTASI 2026'!$H$853:$H$945) -> 0 | AU13: =IF(F13="D",(AP13-AQ13+AS13-AT13),0) -> 0 | AV13: =IF(F13="K",(-AP13+AQ13-AS13+AT13),0) -> 0 | AX13: =SUMIF('MUTASI 2026'!$B$1274:$B$1379,'WS Trial balance'!$D13,'MUTASI 2026'!$G$1274:$G$1379) -> 0 | AY13: =SUMIF('MUTASI 2026'!$B$1274:$B$1379,'WS Trial balance'!$D13,'MUTASI 2026'!$H$1274:$H$1379) -> 0 | AZ13: =IF(F13="D",(AU13-AV13+AX13-AY13),0) -> 0 | BA13: =IF(F13="K",(-AU13+AV13-AX13+AY13),0) -> 0 | BC13: =SUMIF('MUTASI 2026'!$B$1382:$B$1477,'WS Trial balance'!$D13,'MUTASI 2026'!$G$1382:$G$1477) -> 0 | BD13: =SUMIF('MUTASI 2026'!$B$1382:$B$1477,'WS Trial balance'!$D13,'MUTASI 2026'!$H$1382:$H$1477) -> 0 | BE13: =IF(F13="D",(AZ13-BA13+BC13-BD13),0) -> 0 | BF13: =IF(F13="K",(-AZ13+BA13-BC13+BD13),0) -> 0 | BH13: =SUMIF('MUTASI 2026'!$B$1480:$B$1600,'WS Trial balance'!$D13,'MUTASI 2026'!$G$1480:$G$1600) -> 0 | BI13: =SUMIF('MUTASI 2026'!$B$1480:$B$1600,'WS Trial balance'!$D13,'MUTASI 2026'!$H$1480:$H$1600) -> 0 | BJ13: =IF(F13="D",(BE13-BF13+BH13-BI13),0) -> 0 | BK13: =IF(F13="K",(-BE13+BF13-BH13+BI13),0) -> 0 | BM13: =SUMIF('MUTASI 2026'!$B$1603:$B$1722,'WS Trial balance'!$D13,'MUTASI 2026'!$G$1603:$G$1722) -> 0 | BN13: =SUMIF('MUTASI 2026'!$B$1603:$B$1722,'WS Trial balance'!$D13,'MUTASI 2026'!$H$1603:$H$1722) -> 0 | BO13: =IF(F13="D",(BJ13-BK13+BM13-BN13),0) -> 0 | BP13: =IF(F13="K",(-BJ13+BK13-BM13+BN13),0) -> 0 | BT13: =G13 -> 0 | BU13: =H13 -> 0 | BW13: =J13+O13+T13+Y13+AD13+AI13+AN13+AS13+AX13+BC13+BH13+BM13 -> 0 | BX13: =K13+P13+U13+Z13+AE13+AJ13+AO13+AT13+AY13+BD13+BI13+BN13 -> 0 | BZ13: =IF(F13="D",(BT13-BU13+BW13-BX13),0) -> 0 | CA13: =IF(F13="K",(-BT13+BU13-BW13+BX13),0) -> 0
D14: A07 | E14: UANG MUKA PEMBELIAN | F14: D | G14: 0 | H14: 0 | J14: =SUMIF('MUTASI 2026'!$B$5:$B$160,'WS Trial balance'!$D14,'MUTASI 2026'!$G$5:$G$160) -> 0 | K14: =SUMIF('MUTASI 2026'!$B$5:$B$160,'WS Trial balance'!$D14,'MUTASI 2026'!$H$5:$H$160) -> 0 | L14: =IF(F14="D",(G14-H14+J14-K14),0) -> 0 | M14: =IF(F14="K",(-G14+H14-J14+K14),0) -> 0 | O14: =SUMIF('MUTASI 2026'!$B$162:$B$252,'WS Trial balance'!$D14,'MUTASI 2026'!$G$162:$G$252) -> 0 | P14: =SUMIF('MUTASI 2026'!$B$162:$B$252,'WS Trial balance'!$D14,'MUTASI 2026'!$H$162:$H$252) -> 0 | Q14: =IF(F14="D",(L14-M14+O14-P14),0) -> 0 | R14: =IF(F14="K",(-L14+M14-O14+P14),0) -> 0 | T14: =SUMIF('MUTASI 2026'!$B$254:$B$356,'WS Trial balance'!$D14,'MUTASI 2026'!$G$254:$G$356) -> 0 | U14: =SUMIF('MUTASI 2026'!$B$254:$B$356,'WS Trial balance'!$D14,'MUTASI 2026'!$H$254:$H$356) -> 0 | V14: =IF(F14="D",(Q14-R14+T14-U14),0) -> 0 | W14: =IF(F14="K",(-Q14+R14-T14+U14),0) -> 0 | Y14: =SUMIF('MUTASI 2026'!$B$358:$B$480,'WS Trial balance'!$D14,'MUTASI 2026'!$G$358:$G$480) -> 0 | Z14: =SUMIF('MUTASI 2026'!$B$358:$B$480,'WS Trial balance'!$D14,'MUTASI 2026'!$H$358:$H$480) -> 0 | AA14: =IF(F14="D",(V14-W14+Y14-Z14),0) -> 0 | AB14: =IF(F14="K",(-V14+W14-Y14+Z14),0) -> 0 | AD14: =SUMIF('MUTASI 2026'!$B$482:$B$655,'WS Trial balance'!$D14,'MUTASI 2026'!$G$482:$G$655) -> 0 | AE14: =SUMIF('MUTASI 2026'!$B$482:$B$655,'WS Trial balance'!$D14,'MUTASI 2026'!$H$482:$H$655) -> 0 | AF14: =IF(F14="D",(AA14-AB14+AD14-AE14),0) -> 0 | AG14: =IF(F14="K",(-AA14+AB14-AD14+AE14),0) -> 0 | AI14: =SUMIF('MUTASI 2026'!$B$657:$B$748,'WS Trial balance'!$D14,'MUTASI 2026'!$G$657:$G$748) -> 0 | AJ14: =SUMIF('MUTASI 2026'!$B$657:$B$748,'WS Trial balance'!$D14,'MUTASI 2026'!$H$657:$H$748) -> 0 | AK14: =IF(F14="D",(AF14-AG14+AI14-AJ14),0) -> 0 | AL14: =IF(F14="K",(-AF14+AG14-AI14+AJ14),0) -> 0 | AN14: =SUMIF('MUTASI 2026'!$B$750:$B$851,'WS Trial balance'!$D14,'MUTASI 2026'!$G$750:$G$851) -> 0 | AO14: =SUMIF('MUTASI 2026'!$B$750:$B$851,'WS Trial balance'!$D14,'MUTASI 2026'!$H$750:$H$851) -> 0 | AP14: =IF(F14="D",(AK14-AL14+AN14-AO14),0) -> 0 | AQ14: =IF(F14="K",(-AK14+AL14-AN14+AO14),0) -> 0 | AS14: =SUMIF('MUTASI 2026'!$B$853:$B$945,'WS Trial balance'!$D14,'MUTASI 2026'!$G$853:$G$945) -> 0 | AT14: =SUMIF('MUTASI 2026'!$B$853:$B$945,'WS Trial balance'!$D14,'MUTASI 2026'!$H$853:$H$945) -> 0 | AU14: =IF(F14="D",(AP14-AQ14+AS14-AT14),0) -> 0 | AV14: =IF(F14="K",(-AP14+AQ14-AS14+AT14),0) -> 0 | AX14: =SUMIF('MUTASI 2026'!$B$1274:$B$1379,'WS Trial balance'!$D14,'MUTASI 2026'!$G$1274:$G$1379) -> 0 | AY14: =SUMIF('MUTASI 2026'!$B$1274:$B$1379,'WS Trial balance'!$D14,'MUTASI 2026'!$H$1274:$H$1379) -> 0 | AZ14: =IF(F14="D",(AU14-AV14+AX14-AY14),0) -> 0 | BA14: =IF(F14="K",(-AU14+AV14-AX14+AY14),0) -> 0 | BC14: =SUMIF('MUTASI 2026'!$B$1382:$B$1477,'WS Trial balance'!$D14,'MUTASI 2026'!$G$1382:$G$1477) -> 0 | BD14: =SUMIF('MUTASI 2026'!$B$1382:$B$1477,'WS Trial balance'!$D14,'MUTASI 2026'!$H$1382:$H$1477) -> 0 | BE14: =IF(F14="D",(AZ14-BA14+BC14-BD14),0) -> 0 | BF14: =IF(F14="K",(-AZ14+BA14-BC14+BD14),0) -> 0 | BH14: =SUMIF('MUTASI 2026'!$B$1480:$B$1600,'WS Trial balance'!$D14,'MUTASI 2026'!$G$1480:$G$1600) -> 0 | BI14: =SUMIF('MUTASI 2026'!$B$1480:$B$1600,'WS Trial balance'!$D14,'MUTASI 2026'!$H$1480:$H$1600) -> 0 | BJ14: =IF(F14="D",(BE14-BF14+BH14-BI14),0) -> 0 | BK14: =IF(F14="K",(-BE14+BF14-BH14+BI14),0) -> 0 | BM14: =SUMIF('MUTASI 2026'!$B$1603:$B$1722,'WS Trial balance'!$D14,'MUTASI 2026'!$G$1603:$G$1722) -> 0 | BN14: =SUMIF('MUTASI 2026'!$B$1603:$B$1722,'WS Trial balance'!$D14,'MUTASI 2026'!$H$1603:$H$1722) -> 0 | BO14: =IF(F14="D",(BJ14-BK14+BM14-BN14),0) -> 0 | BP14: =IF(F14="K",(-BJ14+BK14-BM14+BN14),0) -> 0 | BT14: =G14 -> 0 | BU14: =H14 -> 0 | BW14: =J14+O14+T14+Y14+AD14+AI14+AN14+AS14+AX14+BC14+BH14+BM14 -> 0 | BX14: =K14+P14+U14+Z14+AE14+AJ14+AO14+AT14+AY14+BD14+BI14+BN14 -> 0 | BZ14: =IF(F14="D",(BT14-BU14+BW14-BX14),0) -> 0 | CA14: =IF(F14="K",(-BT14+BU14-BW14+BX14),0) -> 0
D15: A08 | E15: BIAYA DIBAYAR DIMUKA | F15: D | G15: 0 | H15: 0 | J15: =SUMIF('MUTASI 2026'!$B$5:$B$160,'WS Trial balance'!$D15,'MUTASI 2026'!$G$5:$G$160) -> 0 | K15: =SUMIF('MUTASI 2026'!$B$5:$B$160,'WS Trial balance'!$D15,'MUTASI 2026'!$H$5:$H$160) -> 0 | L15: =IF(F15="D",(G15-H15+J15-K15),0) -> 0 | M15: =IF(F15="K",(-G15+H15-J15+K15),0) -> 0 | O15: =SUMIF('MUTASI 2026'!$B$162:$B$252,'WS Trial balance'!$D15,'MUTASI 2026'!$G$162:$G$252) -> 0 | P15: =SUMIF('MUTASI 2026'!$B$162:$B$252,'WS Trial balance'!$D15,'MUTASI 2026'!$H$162:$H$252) -> 0 | Q15: =IF(F15="D",(L15-M15+O15-P15),0) -> 0 | R15: =IF(F15="K",(-L15+M15-O15+P15),0) -> 0 | T15: =SUMIF('MUTASI 2026'!$B$254:$B$356,'WS Trial balance'!$D15,'MUTASI 2026'!$G$254:$G$356) -> 0 | U15: =SUMIF('MUTASI 2026'!$B$254:$B$356,'WS Trial balance'!$D15,'MUTASI 2026'!$H$254:$H$356) -> 0 | V15: =IF(F15="D",(Q15-R15+T15-U15),0) -> 0 | W15: =IF(F15="K",(-Q15+R15-T15+U15),0) -> 0 | Y15: =SUMIF('MUTASI 2026'!$B$358:$B$480,'WS Trial balance'!$D15,'MUTASI 2026'!$G$358:$G$480) -> 0 | Z15: =SUMIF('MUTASI 2026'!$B$358:$B$480,'WS Trial balance'!$D15,'MUTASI 2026'!$H$358:$H$480) -> 0 | AA15: =IF(F15="D",(V15-W15+Y15-Z15),0) -> 0 | AB15: =IF(F15="K",(-V15+W15-Y15+Z15),0) -> 0 | AD15: =SUMIF('MUTASI 2026'!$B$482:$B$655,'WS Trial balance'!$D15,'MUTASI 2026'!$G$482:$G$655) -> 11608500 | AE15: =SUMIF('MUTASI 2026'!$B$482:$B$655,'WS Trial balance'!$D15,'MUTASI 2026'!$H$482:$H$655) -> 0 | AF15: =IF(F15="D",(AA15-AB15+AD15-AE15),0) -> 11608500 | AG15: =IF(F15="K",(-AA15+AB15-AD15+AE15),0) -> 0 | AI15: =SUMIF('MUTASI 2026'!$B$657:$B$748,'WS Trial balance'!$D15,'MUTASI 2026'!$G$657:$G$748) -> 0 | AJ15: =SUMIF('MUTASI 2026'!$B$657:$B$748,'WS Trial balance'!$D15,'MUTASI 2026'!$H$657:$H$748) -> 0 | AK15: =IF(F15="D",(AF15-AG15+AI15-AJ15),0) -> 11608500 | AL15: =IF(F15="K",(-AF15+AG15-AI15+AJ15),0) -> 0 | AN15: =SUMIF('MUTASI 2026'!$B$750:$B$851,'WS Trial balance'!$D15,'MUTASI 2026'!$G$750:$G$851) -> 0 | AO15: =SUMIF('MUTASI 2026'!$B$750:$B$851,'WS Trial balance'!$D15,'MUTASI 2026'!$H$750:$H$851) -> 0 | AP15: =IF(F15="D",(AK15-AL15+AN15-AO15),0) -> 11608500 | AQ15: =IF(F15="K",(-AK15+AL15-AN15+AO15),0) -> 0 | AS15: =SUMIF('MUTASI 2026'!$B$853:$B$945,'WS Trial balance'!$D15,'MUTASI 2026'!$G$853:$G$945) -> 0 | AT15: =SUMIF('MUTASI 2026'!$B$853:$B$945,'WS Trial balance'!$D15,'MUTASI 2026'!$H$853:$H$945) -> 0 | AU15: =IF(F15="D",(AP15-AQ15+AS15-AT15),0) -> 11608500 | AV15: =IF(F15="K",(-AP15+AQ15-AS15+AT15),0) -> 0 | AX15: =SUMIF('MUTASI 2026'!$B$1274:$B$1379,'WS Trial balance'!$D15,'MUTASI 2026'!$G$1274:$G$1379) -> 0 | AY15: =SUMIF('MUTASI 2026'!$B$1274:$B$1379,'WS Trial balance'!$D15,'MUTASI 2026'!$H$1274:$H$1379) -> 0 | AZ15: =IF(F15="D",(AU15-AV15+AX15-AY15),0) -> 11608500 | BA15: =IF(F15="K",(-AU15+AV15-AX15+AY15),0) -> 0 | BC15: =SUMIF('MUTASI 2026'!$B$1382:$B$1477,'WS Trial balance'!$D15,'MUTASI 2026'!$G$1382:$G$1477) -> 0 | BD15: =SUMIF('MUTASI 2026'!$B$1382:$B$1477,'WS Trial balance'!$D15,'MUTASI 2026'!$H$1382:$H$1477) -> 0 | BE15: =IF(F15="D",(AZ15-BA15+BC15-BD15),0) -> 11608500 | BF15: =IF(F15="K",(-AZ15+BA15-BC15+BD15),0) -> 0 | BH15: =SUMIF('MUTASI 2026'!$B$1480:$B$1600,'WS Trial balance'!$D15,'MUTASI 2026'!$G$1480:$G$1600) -> 0 | BI15: =SUMIF('MUTASI 2026'!$B$1480:$B$1600,'WS Trial balance'!$D15,'MUTASI 2026'!$H$1480:$H$1600) -> 0 | BJ15: =IF(F15="D",(BE15-BF15+BH15-BI15),0) -> 11608500 | BK15: =IF(F15="K",(-BE15+BF15-BH15+BI15),0) -> 0 | BM15: =SUMIF('MUTASI 2026'!$B$1603:$B$1722,'WS Trial balance'!$D15,'MUTASI 2026'!$G$1603:$G$1722) -> 0 | BN15: =SUMIF('MUTASI 2026'!$B$1603:$B$1722,'WS Trial balance'!$D15,'MUTASI 2026'!$H$1603:$H$1722) -> 0 | BO15: =IF(F15="D",(BJ15-BK15+BM15-BN15),0) -> 11608500 | BP15: =IF(F15="K",(-BJ15+BK15-BM15+BN15),0) -> 0 | BT15: =G15 -> 0 | BU15: =H15 -> 0 | BW15: =J15+O15+T15+Y15+AD15+AI15+AN15+AS15+AX15+BC15+BH15+BM15 -> 11608500 | BX15: =K15+P15+U15+Z15+AE15+AJ15+AO15+AT15+AY15+BD15+BI15+BN15 -> 0 | BZ15: =IF(F15="D",(BT15-BU15+BW15-BX15),0) -> 11608500 | CA15: =IF(F15="K",(-BT15+BU15-BW15+BX15),0) -> 0
D16: A09 | E16: UANG MUKA KASBON BIAYA OPERASIONAL | F16: D | G16: 0 | H16: 0 | J16: =SUMIF('MUTASI 2026'!$B$5:$B$160,'WS Trial balance'!$D16,'MUTASI 2026'!$G$5:$G$160) -> 0 | K16: =SUMIF('MUTASI 2026'!$B$5:$B$160,'WS Trial balance'!$D16,'MUTASI 2026'!$H$5:$H$160) -> 0 | L16: =IF(F16="D",(G16-H16+J16-K16),0) -> 0 | M16: =IF(F16="K",(-G16+H16-J16+K16),0) -> 0 | O16: =SUMIF('MUTASI 2026'!$B$162:$B$252,'WS Trial balance'!$D16,'MUTASI 2026'!$G$162:$G$252) -> 0 | P16: =SUMIF('MUTASI 2026'!$B$162:$B$252,'WS Trial balance'!$D16,'MUTASI 2026'!$H$162:$H$252) -> 0 | Q16: =IF(F16="D",(L16-M16+O16-P16),0) -> 0 | R16: =IF(F16="K",(-L16+M16-O16+P16),0) -> 0 | T16: =SUMIF('MUTASI 2026'!$B$254:$B$356,'WS Trial balance'!$D16,'MUTASI 2026'!$G$254:$G$356) -> 0 | U16: =SUMIF('MUTASI 2026'!$B$254:$B$356,'WS Trial balance'!$D16,'MUTASI 2026'!$H$254:$H$356) -> 0 | V16: =IF(F16="D",(Q16-R16+T16-U16),0) -> 0 | W16: =IF(F16="K",(-Q16+R16-T16+U16),0) -> 0 | Y16: =SUMIF('MUTASI 2026'!$B$358:$B$480,'WS Trial balance'!$D16,'MUTASI 2026'!$G$358:$G$480) -> 0 | Z16: =SUMIF('MUTASI 2026'!$B$358:$B$480,'WS Trial balance'!$D16,'MUTASI 2026'!$H$358:$H$480) -> 0 | AA16: =IF(F16="D",(V16-W16+Y16-Z16),0) -> 0 | AB16: =IF(F16="K",(-V16+W16-Y16+Z16),0) -> 0 | AD16: =SUMIF('MUTASI 2026'!$B$482:$B$655,'WS Trial balance'!$D16,'MUTASI 2026'!$G$482:$G$655) -> 0 | AE16: =SUMIF('MUTASI 2026'!$B$482:$B$655,'WS Trial balance'!$D16,'MUTASI 2026'!$H$482:$H$655) -> 0 | AF16: =IF(F16="D",(AA16-AB16+AD16-AE16),0) -> 0 | AG16: =IF(F16="K",(-AA16+AB16-AD16+AE16),0) -> 0 | AI16: =SUMIF('MUTASI 2026'!$B$657:$B$748,'WS Trial balance'!$D16,'MUTASI 2026'!$G$657:$G$748) -> 0 | AJ16: =SUMIF('MUTASI 2026'!$B$657:$B$748,'WS Trial balance'!$D16,'MUTASI 2026'!$H$657:$H$748) -> 0 | AK16: =IF(F16="D",(AF16-AG16+AI16-AJ16),0) -> 0 | AL16: =IF(F16="K",(-AF16+AG16-AI16+AJ16),0) -> 0 | AN16: =SUMIF('MUTASI 2026'!$B$750:$B$851,'WS Trial balance'!$D16,'MUTASI 2026'!$G$750:$G$851) -> 0 | AO16: =SUMIF('MUTASI 2026'!$B$750:$B$851,'WS Trial balance'!$D16,'MUTASI 2026'!$H$750:$H$851) -> 0 | AP16: =IF(F16="D",(AK16-AL16+AN16-AO16),0) -> 0 | AQ16: =IF(F16="K",(-AK16+AL16-AN16+AO16),0) -> 0 | AS16: =SUMIF('MUTASI 2026'!$B$853:$B$945,'WS Trial balance'!$D16,'MUTASI 2026'!$G$853:$G$945) -> 0 | AT16: =SUMIF('MUTASI 2026'!$B$853:$B$945,'WS Trial balance'!$D16,'MUTASI 2026'!$H$853:$H$945) -> 0 | AU16: =IF(F16="D",(AP16-AQ16+AS16-AT16),0) -> 0 | AV16: =IF(F16="K",(-AP16+AQ16-AS16+AT16),0) -> 0 | AX16: =SUMIF('MUTASI 2026'!$B$1274:$B$1379,'WS Trial balance'!$D16,'MUTASI 2026'!$G$1274:$G$1379) -> 0 | AY16: =SUMIF('MUTASI 2026'!$B$1274:$B$1379,'WS Trial balance'!$D16,'MUTASI 2026'!$H$1274:$H$1379) -> 0 | AZ16: =IF(F16="D",(AU16-AV16+AX16-AY16),0) -> 0 | BA16: =IF(F16="K",(-AU16+AV16-AX16+AY16),0) -> 0 | BC16: =SUMIF('MUTASI 2026'!$B$1382:$B$1477,'WS Trial balance'!$D16,'MUTASI 2026'!$G$1382:$G$1477) -> 0 | BD16: =SUMIF('MUTASI 2026'!$B$1382:$B$1477,'WS Trial balance'!$D16,'MUTASI 2026'!$H$1382:$H$1477) -> 0 | BE16: =IF(F16="D",(AZ16-BA16+BC16-BD16),0) -> 0 | BF16: =IF(F16="K",(-AZ16+BA16-BC16+BD16),0) -> 0 | BH16: =SUMIF('MUTASI 2026'!$B$1480:$B$1600,'WS Trial balance'!$D16,'MUTASI 2026'!$G$1480:$G$1600) -> 0 | BI16: =SUMIF('MUTASI 2026'!$B$1480:$B$1600,'WS Trial balance'!$D16,'MUTASI 2026'!$H$1480:$H$1600) -> 0 | BJ16: =IF(F16="D",(BE16-BF16+BH16-BI16),0) -> 0 | BK16: =IF(F16="K",(-BE16+BF16-BH16+BI16),0) -> 0 | BM16: =SUMIF('MUTASI 2026'!$B$1603:$B$1722,'WS Trial balance'!$D16,'MUTASI 2026'!$G$1603:$G$1722) -> 0 | BN16: =SUMIF('MUTASI 2026'!$B$1603:$B$1722,'WS Trial balance'!$D16,'MUTASI 2026'!$H$1603:$H$1722) -> 0 | BO16: =IF(F16="D",(BJ16-BK16+BM16-BN16),0) -> 0 | BP16: =IF(F16="K",(-BJ16+BK16-BM16+BN16),0) -> 0 | BT16: =G16 -> 0 | BU16: =H16 -> 0 | BW16: =J16+O16+T16+Y16+AD16+AI16+AN16+AS16+AX16+BC16+BH16+BM16 -> 0 | BX16: =K16+P16+U16+Z16+AE16+AJ16+AO16+AT16+AY16+BD16+BI16+BN16 -> 0 | BZ16: =IF(F16="D",(BT16-BU16+BW16-BX16),0) -> 0 | CA16: =IF(F16="K",(-BT16+BU16-BW16+BX16),0) -> 0
D17: A10 | E17: UANG MUKA PAJAK | F17: D | G17: 0 | H17: 0 | J17: =SUMIF('MUTASI 2026'!$B$5:$B$160,'WS Trial balance'!$D17,'MUTASI 2026'!$G$5:$G$160) -> 0 | K17: =SUMIF('MUTASI 2026'!$B$5:$B$160,'WS Trial balance'!$D17,'MUTASI 2026'!$H$5:$H$160) -> 0 | L17: =IF(F17="D",(G17-H17+J17-K17),0) -> 0 | M17: =IF(F17="K",(-G17+H17-J17+K17),0) -> 0 | O17: =SUMIF('MUTASI 2026'!$B$162:$B$252,'WS Trial balance'!$D17,'MUTASI 2026'!$G$162:$G$252) -> 0 | P17: =SUMIF('MUTASI 2026'!$B$162:$B$252,'WS Trial balance'!$D17,'MUTASI 2026'!$H$162:$H$252) -> 0 | Q17: =IF(F17="D",(L17-M17+O17-P17),0) -> 0 | R17: =IF(F17="K",(-L17+M17-O17+P17),0) -> 0 | T17: =SUMIF('MUTASI 2026'!$B$254:$B$356,'WS Trial balance'!$D17,'MUTASI 2026'!$G$254:$G$356) -> 0 | U17: =SUMIF('MUTASI 2026'!$B$254:$B$356,'WS Trial balance'!$D17,'MUTASI 2026'!$H$254:$H$356) -> 0 | V17: =IF(F17="D",(Q17-R17+T17-U17),0) -> 0 | W17: =IF(F17="K",(-Q17+R17-T17+U17),0) -> 0 | Y17: =SUMIF('MUTASI 2026'!$B$358:$B$480,'WS Trial balance'!$D17,'MUTASI 2026'!$G$358:$G$480) -> 0 | Z17: =SUMIF('MUTASI 2026'!$B$358:$B$480,'WS Trial balance'!$D17,'MUTASI 2026'!$H$358:$H$480) -> 0 | AA17: =IF(F17="D",(V17-W17+Y17-Z17),0) -> 0 | AB17: =IF(F17="K",(-V17+W17-Y17+Z17),0) -> 0 | AD17: =SUMIF('MUTASI 2026'!$B$482:$B$655,'WS Trial balance'!$D17,'MUTASI 2026'!$G$482:$G$655) -> 0 | AE17: =SUMIF('MUTASI 2026'!$B$482:$B$655,'WS Trial balance'!$D17,'MUTASI 2026'!$H$482:$H$655) -> 0 | AF17: =IF(F17="D",(AA17-AB17+AD17-AE17),0) -> 0 | AG17: =IF(F17="K",(-AA17+AB17-AD17+AE17),0) -> 0 | AI17: =SUMIF('MUTASI 2026'!$B$657:$B$748,'WS Trial balance'!$D17,'MUTASI 2026'!$G$657:$G$748) -> 0 | AJ17: =SUMIF('MUTASI 2026'!$B$657:$B$748,'WS Trial balance'!$D17,'MUTASI 2026'!$H$657:$H$748) -> 0 | AK17: =IF(F17="D",(AF17-AG17+AI17-AJ17),0) -> 0 | AL17: =IF(F17="K",(-AF17+AG17-AI17+AJ17),0) -> 0 | AN17: =SUMIF('MUTASI 2026'!$B$750:$B$851,'WS Trial balance'!$D17,'MUTASI 2026'!$G$750:$G$851) -> 0 | AO17: =SUMIF('MUTASI 2026'!$B$750:$B$851,'WS Trial balance'!$D17,'MUTASI 2026'!$H$750:$H$851) -> 0 | AP17: =IF(F17="D",(AK17-AL17+AN17-AO17),0) -> 0 | AQ17: =IF(F17="K",(-AK17+AL17-AN17+AO17),0) -> 0 | AS17: =SUMIF('MUTASI 2026'!$B$853:$B$945,'WS Trial balance'!$D17,'MUTASI 2026'!$G$853:$G$945) -> 0 | AT17: =SUMIF('MUTASI 2026'!$B$853:$B$945,'WS Trial balance'!$D17,'MUTASI 2026'!$H$853:$H$945) -> 0 | AU17: =IF(F17="D",(AP17-AQ17+AS17-AT17),0) -> 0 | AV17: =IF(F17="K",(-AP17+AQ17-AS17+AT17),0) -> 0 | AX17: =SUMIF('MUTASI 2026'!$B$1274:$B$1379,'WS Trial balance'!$D17,'MUTASI 2026'!$G$1274:$G$1379) -> 0 | AY17: =SUMIF('MUTASI 2026'!$B$1274:$B$1379,'WS Trial balance'!$D17,'MUTASI 2026'!$H$1274:$H$1379) -> 0 | AZ17: =IF(F17="D",(AU17-AV17+AX17-AY17),0) -> 0 | BA17: =IF(F17="K",(-AU17+AV17-AX17+AY17),0) -> 0 | BC17: =SUMIF('MUTASI 2026'!$B$1382:$B$1477,'WS Trial balance'!$D17,'MUTASI 2026'!$G$1382:$G$1477) -> 0 | BD17: =SUMIF('MUTASI 2026'!$B$1382:$B$1477,'WS Trial balance'!$D17,'MUTASI 2026'!$H$1382:$H$1477) -> 0 | BE17: =IF(F17="D",(AZ17-BA17+BC17-BD17),0) -> 0 | BF17: =IF(F17="K",(-AZ17+BA17-BC17+BD17),0) -> 0 | BH17: =SUMIF('MUTASI 2026'!$B$1480:$B$1600,'WS Trial balance'!$D17,'MUTASI 2026'!$G$1480:$G$1600) -> 0 | BI17: =SUMIF('MUTASI 2026'!$B$1480:$B$1600,'WS Trial balance'!$D17,'MUTASI 2026'!$H$1480:$H$1600) -> 0 | BJ17: =IF(F17="D",(BE17-BF17+BH17-BI17),0) -> 0 | BK17: =IF(F17="K",(-BE17+BF17-BH17+BI17),0) -> 0 | BM17: =SUMIF('MUTASI 2026'!$B$1603:$B$1722,'WS Trial balance'!$D17,'MUTASI 2026'!$G$1603:$G$1722) -> 0 | BN17: =SUMIF('MUTASI 2026'!$B$1603:$B$1722,'WS Trial balance'!$D17,'MUTASI 2026'!$H$1603:$H$1722) -> 0 | BO17: =IF(F17="D",(BJ17-BK17+BM17-BN17),0) -> 0 | BP17: =IF(F17="K",(-BJ17+BK17-BM17+BN17),0) -> 0 | BT17: =G17 -> 0 | BU17: =H17 -> 0 | BW17: =J17+O17+T17+Y17+AD17+AI17+AN17+AS17+AX17+BC17+BH17+BM17 -> 0 | BX17: =K17+P17+U17+Z17+AE17+AJ17+AO17+AT17+AY17+BD17+BI17+BN17 -> 0 | BZ17: =IF(F17="D",(BT17-BU17+BW17-BX17),0) -> 0 | CA17: =IF(F17="K",(-BT17+BU17-BW17+BX17),0) -> 0
D18: A11 | E18: PENYERTAAN MODAL | F18: D | G18: 0 | H18: 0 | J18: =SUMIF('MUTASI 2026'!$B$5:$B$160,'WS Trial balance'!$D18,'MUTASI 2026'!$G$5:$G$160) -> 0 | K18: =SUMIF('MUTASI 2026'!$B$5:$B$160,'WS Trial balance'!$D18,'MUTASI 2026'!$H$5:$H$160) -> 0 | L18: =IF(F18="D",(G18-H18+J18-K18),0) -> 0 | M18: =IF(F18="K",(-G18+H18-J18+K18),0) -> 0 | O18: =SUMIF('MUTASI 2026'!$B$162:$B$252,'WS Trial balance'!$D18,'MUTASI 2026'!$G$162:$G$252) -> 0 | P18: =SUMIF('MUTASI 2026'!$B$162:$B$252,'WS Trial balance'!$D18,'MUTASI 2026'!$H$162:$H$252) -> 0 | Q18: =IF(F18="D",(L18-M18+O18-P18),0) -> 0 | R18: =IF(F18="K",(-L18+M18-O18+P18),0) -> 0 | T18: =SUMIF('MUTASI 2026'!$B$254:$B$356,'WS Trial balance'!$D18,'MUTASI 2026'!$G$254:$G$356) -> 0 | U18: =SUMIF('MUTASI 2026'!$B$254:$B$356,'WS Trial balance'!$D18,'MUTASI 2026'!$H$254:$H$356) -> 0 | V18: =IF(F18="D",(Q18-R18+T18-U18),0) -> 0 | W18: =IF(F18="K",(-Q18+R18-T18+U18),0) -> 0 | Y18: =SUMIF('MUTASI 2026'!$B$358:$B$480,'WS Trial balance'!$D18,'MUTASI 2026'!$G$358:$G$480) -> 0 | Z18: =SUMIF('MUTASI 2026'!$B$358:$B$480,'WS Trial balance'!$D18,'MUTASI 2026'!$H$358:$H$480) -> 0 | AA18: =IF(F18="D",(V18-W18+Y18-Z18),0) -> 0 | AB18: =IF(F18="K",(-V18+W18-Y18+Z18),0) -> 0 | AD18: =SUMIF('MUTASI 2026'!$B$482:$B$655,'WS Trial balance'!$D18,'MUTASI 2026'!$G$482:$G$655) -> 0 | AE18: =SUMIF('MUTASI 2026'!$B$482:$B$655,'WS Trial balance'!$D18,'MUTASI 2026'!$H$482:$H$655) -> 0 | AF18: =IF(F18="D",(AA18-AB18+AD18-AE18),0) -> 0 | AG18: =IF(F18="K",(-AA18+AB18-AD18+AE18),0) -> 0 | AI18: =SUMIF('MUTASI 2026'!$B$657:$B$748,'WS Trial balance'!$D18,'MUTASI 2026'!$G$657:$G$748) -> 0 | AJ18: =SUMIF('MUTASI 2026'!$B$657:$B$748,'WS Trial balance'!$D18,'MUTASI 2026'!$H$657:$H$748) -> 0 | AK18: =IF(F18="D",(AF18-AG18+AI18-AJ18),0) -> 0 | AL18: =IF(F18="K",(-AF18+AG18-AI18+AJ18),0) -> 0 | AN18: =SUMIF('MUTASI 2026'!$B$750:$B$851,'WS Trial balance'!$D18,'MUTASI 2026'!$G$750:$G$851) -> 0 | AO18: =SUMIF('MUTASI 2026'!$B$750:$B$851,'WS Trial balance'!$D18,'MUTASI 2026'!$H$750:$H$851) -> 0 | AP18: =IF(F18="D",(AK18-AL18+AN18-AO18),0) -> 0 | AQ18: =IF(F18="K",(-AK18+AL18-AN18+AO18),0) -> 0 | AS18: =SUMIF('MUTASI 2026'!$B$853:$B$945,'WS Trial balance'!$D18,'MUTASI 2026'!$G$853:$G$945) -> 0 | AT18: =SUMIF('MUTASI 2026'!$B$853:$B$945,'WS Trial balance'!$D18,'MUTASI 2026'!$H$853:$H$945) -> 0 | AU18: =IF(F18="D",(AP18-AQ18+AS18-AT18),0) -> 0 | AV18: =IF(F18="K",(-AP18+AQ18-AS18+AT18),0) -> 0 | AX18: =SUMIF('MUTASI 2026'!$B$1274:$B$1379,'WS Trial balance'!$D18,'MUTASI 2026'!$G$1274:$G$1379) -> 0 | AY18: =SUMIF('MUTASI 2026'!$B$1274:$B$1379,'WS Trial balance'!$D18,'MUTASI 2026'!$H$1274:$H$1379) -> 0 | AZ18: =IF(F18="D",(AU18-AV18+AX18-AY18),0) -> 0 | BA18: =IF(F18="K",(-AU18+AV18-AX18+AY18),0) -> 0 | BC18: =SUMIF('MUTASI 2026'!$B$1382:$B$1477,'WS Trial balance'!$D18,'MUTASI 2026'!$G$1382:$G$1477) -> 0 | BD18: =SUMIF('MUTASI 2026'!$B$1382:$B$1477,'WS Trial balance'!$D18,'MUTASI 2026'!$H$1382:$H$1477) -> 0 | BE18: =IF(F18="D",(AZ18-BA18+BC18-BD18),0) -> 0 | BF18: =IF(F18="K",(-AZ18+BA18-BC18+BD18),0) -> 0 | BH18: =SUMIF('MUTASI 2026'!$B$1480:$B$1600,'WS Trial balance'!$D18,'MUTASI 2026'!$G$1480:$G$1600) -> 0 | BI18: =SUMIF('MUTASI 2026'!$B$1480:$B$1600,'WS Trial balance'!$D18,'MUTASI 2026'!$H$1480:$H$1600) -> 0 | BJ18: =IF(F18="D",(BE18-BF18+BH18-BI18),0) -> 0 | BK18: =IF(F18="K",(-BE18+BF18-BH18+BI18),0) -> 0 | BM18: =SUMIF('MUTASI 2026'!$B$1603:$B$1722,'WS Trial balance'!$D18,'MUTASI 2026'!$G$1603:$G$1722) -> 0 | BN18: =SUMIF('MUTASI 2026'!$B$1603:$B$1722,'WS Trial balance'!$D18,'MUTASI 2026'!$H$1603:$H$1722) -> 0 | BO18: =IF(F18="D",(BJ18-BK18+BM18-BN18),0) -> 0 | BP18: =IF(F18="K",(-BJ18+BK18-BM18+BN18),0) -> 0 | BT18: =G18 -> 0 | BU18: =H18 -> 0 | BW18: =J18+O18+T18+Y18+AD18+AI18+AN18+AS18+AX18+BC18+BH18+BM18 -> 0 | BX18: =K18+P18+U18+Z18+AE18+AJ18+AO18+AT18+AY18+BD18+BI18+BN18 -> 0 | BZ18: =IF(F18="D",(BT18-BU18+BW18-BX18),0) -> 0 | CA18: =IF(F18="K",(-BT18+BU18-BW18+BX18),0) -> 0
... D48: P16 | E48: LABA / (RUGI) TAHUN BERJALAN | F48: K | G48: 0 | H48: 0 | J48: =SUMIF('MUTASI 2026'!$B$5:$B$160,'WS Trial balance'!$D48,'MUTASI 2026'!$G$5:$G$160) -> 0 | K48: =SUMIF('MUTASI 2026'!$B$5:$B$160,'WS Trial balance'!$D48,'MUTASI 2026'!$H$5:$H$160) -> 0 | L48: =IF(F48="D",(G48-H48+J48-K48),0) -> 0 | M48: =IF(F48="K",(-G48+H48-J48+K48),0) -> 0 | O48: =SUMIF('MUTASI 2026'!$B$162:$B$252,'WS Trial balance'!$D48,'MUTASI 2026'!$G$162:$G$252) -> 0 | P48: =SUMIF('MUTASI 2026'!$B$162:$B$252,'WS Trial balance'!$D48,'MUTASI 2026'!$H$162:$H$252) -> 0 | Q48: =IF(F48="D",(L48-M48+O48-P48),0) -> 0 | R48: =IF(F48="K",(-L48+M48-O48+P48),0) -> 0 | T48: =SUMIF('MUTASI 2026'!$B$254:$B$356,'WS Trial balance'!$D48,'MUTASI 2026'!$G$254:$G$356) -> 0 | U48: =SUMIF('MUTASI 2026'!$B$254:$B$356,'WS Trial balance'!$D48,'MUTASI 2026'!$H$254:$H$356) -> 0 | V48: =IF(F48="D",(Q48-R48+T48-U48),0) -> 0 | W48: =IF(F48="K",(-Q48+R48-T48+U48),0) -> 0 | Y48: =SUMIF('MUTASI 2026'!$B$358:$B$480,'WS Trial balance'!$D48,'MUTASI 2026'!$G$358:$G$480) -> 0 | Z48: =SUMIF('MUTASI 2026'!$B$358:$B$480,'WS Trial balance'!$D48,'MUTASI 2026'!$H$358:$H$480) -> 0 | AA48: =IF(F48="D",(V48-W48+Y48-Z48),0) -> 0 | AB48: =IF(F48="K",(-V48+W48-Y48+Z48),0) -> 0 | AD48: =SUMIF('MUTASI 2026'!$B$482:$B$655,'WS Trial balance'!$D48,'MUTASI 2026'!$G$482:$G$655) -> 0 | AE48: =SUMIF('MUTASI 2026'!$B$482:$B$655,'WS Trial balance'!$D48,'MUTASI 2026'!$H$482:$H$655) -> 0 | AF48: =IF(F48="D",(AA48-AB48+AD48-AE48),0) -> 0 | AG48: =IF(F48="K",(-AA48+AB48-AD48+AE48),0) -> 0 | AI48: =SUMIF('MUTASI 2026'!$B$657:$B$748,'WS Trial balance'!$D48,'MUTASI 2026'!$G$657:$G$748) -> 0 | AJ48: =SUMIF('MUTASI 2026'!$B$657:$B$748,'WS Trial balance'!$D48,'MUTASI 2026'!$H$657:$H$748) -> 0 | AK48: =IF(F48="D",(AF48-AG48+AI48-AJ48),0) -> 0 | AL48: =IF(F48="K",(-AF48+AG48-AI48+AJ48),0) -> 0 | AN48: =SUMIF('MUTASI 2026'!$B$750:$B$851,'WS Trial balance'!$D48,'MUTASI 2026'!$G$750:$G$851) -> 0 | AO48: =SUMIF('MUTASI 2026'!$B$750:$B$851,'WS Trial balance'!$D48,'MUTASI 2026'!$H$750:$H$851) -> 0 | AP48: =IF(F48="D",(AK48-AL48+AN48-AO48),0) -> 0 | AQ48: =IF(F48="K",(-AK48+AL48-AN48+AO48),0) -> 0 | AS48: =SUMIF('MUTASI 2026'!$B$853:$B$945,'WS Trial balance'!$D48,'MUTASI 2026'!$G$853:$G$945) -> 0 | AT48: =SUMIF('MUTASI 2026'!$B$853:$B$945,'WS Trial balance'!$D48,'MUTASI 2026'!$H$853:$H$945) -> 0 | AU48: =IF(F48="D",(AP48-AQ48+AS48-AT48),0) -> 0 | AV48: =IF(F48="K",(-AP48+AQ48-AS48+AT48),0) -> 0 | AX48: =SUMIF('MUTASI 2026'!$B$1274:$B$1379,'WS Trial balance'!$D48,'MUTASI 2026'!$G$1274:$G$1379) -> 0 | AY48: =SUMIF('MUTASI 2026'!$B$1274:$B$1379,'WS Trial balance'!$D48,'MUTASI 2026'!$H$1274:$H$1379) -> 0 | AZ48: =IF(F48="D",(AU48-AV48+AX48-AY48),0) -> 0 | BA48: =IF(F48="K",(-AU48+AV48-AX48+AY48),0) -> 0 | BC48: =SUMIF('MUTASI 2026'!$B$1382:$B$1477,'WS Trial balance'!$D48,'MUTASI 2026'!$G$1382:$G$1477) -> 0 | BD48: =SUMIF('MUTASI 2026'!$B$1382:$B$1477,'WS Trial balance'!$D48,'MUTASI 2026'!$H$1382:$H$1477) -> 0 | BE48: =IF(F48="D",(AZ48-BA48+BC48-BD48),0) -> 0 | BF48: =IF(F48="K",(-AZ48+BA48-BC48+BD48),0) -> 0 | BH48: =SUMIF('MUTASI 2026'!$B$1480:$B$1600,'WS Trial balance'!$D48,'MUTASI 2026'!$G$1480:$G$1600) -> 0 | BI48: =SUMIF('MUTASI 2026'!$B$1480:$B$1600,'WS Trial balance'!$D48,'MUTASI 2026'!$H$1480:$H$1600) -> 0 | BJ48: =IF(F48="D",(BE48-BF48+BH48-BI48),0) -> 0 | BK48: =IF(F48="K",(-BE48+BF48-BH48+BI48),0) -> 0 | BM48: =SUMIF('MUTASI 2026'!$B$1603:$B$1722,'WS Trial balance'!$D48,'MUTASI 2026'!$G$1603:$G$1722) -> 0 | BN48: =SUMIF('MUTASI 2026'!$B$1603:$B$1722,'WS Trial balance'!$D48,'MUTASI 2026'!$H$1603:$H$1722) -> 0 | BO48: =IF(F48="D",(BJ48-BK48+BM48-BN48),0) -> 0 | BP48: =IF(F48="K",(-BJ48+BK48-BM48+BN48),0) -> 0 | BT48: =G48 -> 0 | BU48: =H48 -> 0 | BW48: =J48+O48+T48+Y48+AD48+AI48+AN48+AS48+AX48+BC48+BH48+BM48 -> 0 | BX48: =K48+P48+U48+Z48+AE48+AJ48+AO48+AT48+AY48+BD48+BI48+BN48 -> 0 | BZ48: =IF(F48="D",(BT48-BU48+BW48-BX48),0) -> 0 | CA48: =IF(F48="K",(-BT48+BU48-BW48+BX48),0) -> 0
E50: JUMLAH | G50: =SUM(G7:G29)-SUM(H7:H29) -> 2.6993717e+09 | H50: =SUM(H30:H48)-SUM(G30:G48) -> 2.6993717e+09 | J50: =SUM(J7:J49) -> 5.5857884e+08 | K50: =SUM(K7:K49) -> 5.3808767e+08 | L50: =SUM(L7:L29)-SUM(M7:M29) -> 2.7526129e+09 | M50: =SUM(M30:M48)-SUM(L30:L48) -> 2.7321217e+09 | O50: =SUM(O7:O49) -> 3.5109123e+08 | P50: =SUM(P7:P49) -> 333210150 | Q50: =SUM(Q7:Q29)-SUM(R7:R29) -> 2.774894e+09 | R50: =SUM(R30:R48)-SUM(Q30:Q48) -> 2.7365217e+09 | T50: =SUM(T7:T49) -> 4.6173483e+08 | U50: =SUM(U7:U49) -> 4.7181158e+08 | V50: =SUM(V7:V29)-SUM(W7:W29) -> 2.6765451e+09 | W50: =SUM(W30:W48)-SUM(V30:V48) -> 2.6482496e+09 | Y50: =SUM(Y7:Y49) -> 3.0993737e+08 | Z50: =SUM(Z7:Z49) -> 2.9241604e+08 | AA50: =SUM(AA7:AA29)-SUM(AB7:AB29) -> 2.6978664e+09 | AB50: =SUM(AB30:AB48)-SUM(AA30:AA48) -> 2.6520496e+09 | AD50: =SUM(AD7:AD49) -> 6.0755167e+08 | AE50: =SUM(AE7:AE49) -> 6.2927797e+08 | AF50: =SUM(AF7:AF29)-SUM(AG7:AG29) -> 2.6485031e+09 | AG50: =SUM(AG30:AG48)-SUM(AF30:AF48) -> 2.6244126e+09 | AI50: =SUM(AI7:AI49) -> 485476489 | AJ50: =SUM(AJ7:AJ49) -> 4.7002217e+08 | AK50: =SUM(AK7:AK29)-SUM(AL7:AL29) -> 2.6678074e+09 | AL50: =SUM(AL30:AL48)-SUM(AK30:AK48) -> 2.6282626e+09 | AN50: =SUM(AN7:AN49) -> 436426996 | AO50: =SUM(AO7:AO49) -> 4.1869815e+08 | AP50: =SUM(AP7:AP29)-SUM(AQ7:AQ29) -> 2.6893863e+09 | AQ50: =SUM(AQ30:AQ48)-SUM(AP30:AP48) -> 2.6321126e+09 | AS50: =SUM(AS7:AS49) -> 2.8580048e+08 | AT50: =SUM(AT7:AT49) -> 2.6862665e+08 | AU50: =SUM(AU7:AU29)-SUM(AV7:AV29) -> 2.6961766e+09 | AV50: =SUM(AV30:AV48)-SUM(AU30:AU48) -> 2.6217291e+09 | AX50: =SUM(AX7:AX49) -> 0 | AY50: =SUM(AY7:AY49) -> 0 | AZ50: =SUM(AZ7:AZ29)-SUM(BA7:BA29) -> 2.6961766e+09 | BA50: =SUM(BA30:BA48)-SUM(AZ30:AZ48) -> 2.6217291e+09 | BC50: =SUM(BC7:BC49) -> 0 | BD50: =SUM(BD7:BD49) -> 0 | BE50: =SUM(BE7:BE29)-SUM(BF7:BF29) -> 2.6961766e+09 | BF50: =SUM(BF30:BF48)-SUM(BE30:BE48) -> 2.6217291e+09 | BH50: =SUM(BH7:BH49) -> 0 | BI50: =SUM(BI7:BI49) -> 0 | BJ50: =SUM(BJ7:BJ29)-SUM(BK7:BK29) -> 2.6961766e+09 | BK50: =SUM(BK30:BK48)-SUM(BJ30:BJ48) -> 2.6217291e+09 | BM50: =SUM(BM7:BM49) -> 0 | BN50: =SUM(BN7:BN49) -> 0 | BO50: =SUM(BO7:BO29)-SUM(BP7:BP29) -> 2.6961766e+09 | BP50: =SUM(BP30:BP48)-SUM(BO30:BO48) -> 2.6217291e+09 | BT50: =SUM(BT7:BT29)-SUM(BU7:BU29) -> 2.6993717e+09 | BU50: =SUM(BU30:BU48)-SUM(BT30:BT48) -> 2.6993717e+09 | BW50: =SUM(BW7:BW49) -> 3.4965979e+09 | BX50: =SUM(BX7:BX49) -> 3.4221504e+09 | BZ50: =SUM(BZ7:BZ29)-SUM(CA7:CA29) -> 2.6961766e+09 | CA50: =SUM(CA30:CA48)-SUM(BZ30:BZ48) -> 2.6217291e+09
E51: LABA (RUGI) | H51: =G50-H50 -> 0 | K51: =J50-K50 -> 20491175 | M51: =L50-M50 -> 20491175 | P51: =O50-P50 -> 17881076 | R51: =Q50-R50 -> 38372251 | U51: =T50-U50 -> -10076758 | W51: =V50-W50 -> 28295492 | Z51: =Y50-Z50 -> 17521329 | AB51: =AA50-AB50 -> 45816822 | AE51: =AD50-AE50 -> -21726299 | AG51: =AF50-AG50 -> 24090522 | AJ51: =AI50-AJ50 -> 15454324 | AL51: =AK50-AL50 -> 39544846 | AO51: =AN50-AO50 -> 17728847 | AQ51: =AP50-AQ50 -> 57273693 | AT51: =AS50-AT50 -> 17173829 | AV51: =AU50-AV50 -> 74447522 | AY51: =AX50-AY50 -> 0 | BA51: =AZ50-BA50 -> 74447522 | BD51: =BC50-BD50 -> 0 | BF51: =BE50-BF50 -> 74447522 | BI51: =BH50-BI50 -> 0 | BK51: =BJ50-BK50 -> 74447522 | BN51: =BM50-BN50 -> 0 | BP51: =BO50-BP50 -> 74447522 | BU51: =BT50-BU50 -> 0 | BX51: =BW50-BX50 -> 74447522 | CA51: =BZ50-CA50 -> 74447522
C54: =C3 -> KOPERASI KARYAWAN CIPTA SEJAHTERA
C55: PROFIT AND LOSS, TAHUN 2026
C56: ACCOUNT | F56: =F5 -> KODE | G56: =G5 -> SALDO AWAL 2026 | J56: =J5 -> MUTASI JANUARI 2026 | L56: =L5 -> SALDO AKHIR JANUARI 2026 | O56: =O5 -> MUTASI FEBRUARI 2026 | Q56: =Q5 -> SALDO AKHIR FEBRUARI 2026 | T56: =T5 -> MUTASI MARET 2026 | V56: =V5 -> SALDO AKHIR MARET 2026 | Y56: =Y5 -> MUTASI APRIL 2026 | AA56: =AA5 -> SALDO AKHIR APRIL 2026 | AD56: =AD5 -> MUTASI MEI 2026 | AF56: =AF5 -> SALDO AKHIR MEI 2026 | AI56: =AI5 -> MUTASI JUNI 2026 | AK56: =AK5 -> SALDO AKHIR JUNI 2026 | AN56: =AN5 -> MUTASI JULI 2026 | AP56: =AP5 -> SALDO AKHIR JULI 2026 | AS56: =AS5 -> MUTASI AGUSTUS 2026 | AU56: =AU5 -> SALDO AKHIR AGUSTUS 2026 | AX56: =AX5 -> MUTASI SEPTEMBER 2026 | AZ56: =AZ5 -> SALDO AKHIR SEPTEMBER 2026 | BC56: =BC5 -> MUTASI OKTOBER 2026 | BE56: =BE5 -> SALDO AKHIR OKTOBER 2026 | BH56: =BH5 -> MUTASI NOPEMBER 2026 | BJ56: =BJ5 -> SALDO AKHIR NOPEMBER 2026 | BM56: =BM5 -> MUTASI DESEMBER 2026 | BO56: =BO5 -> SALDO AKHIR DESEMBER 2026 | BT56: =BT5 -> SALDO AWAL 2026 | BW56: =BW5 -> MUTASI 2026 | BZ56: =BZ5 -> SALDO AKHIR 2026
G57: DEBET | H57: KREDIT | J57: DEBET | K57: KREDIT | L57: DEBET | M57: KREDIT | O57: DEBET | P57: KREDIT | Q57: DEBET | R57: KREDIT | T57: DEBET | U57: KREDIT | V57: DEBET | W57: KREDIT | Y57: DEBET | Z57: KREDIT | AA57: DEBET | AB57: KREDIT | AD57: DEBET | AE57: KREDIT | AF57: DEBET | AG57: KREDIT | AI57: DEBET | AJ57: KREDIT | AK57: DEBET | AL57: KREDIT | AN57: DEBET | AO57: KREDIT | AP57: DEBET | AQ57: KREDIT | AS57: DEBET | AT57: KREDIT | AU57: DEBET | AV57: KREDIT | AX57: DEBET | AY57: KREDIT | AZ57: DEBET | BA57: KREDIT | BC57: DEBET | BD57: KREDIT | BE57: DEBET | BF57: KREDIT | BH57: DEBET | BI57: KREDIT | BJ57: DEBET | BK57: KREDIT | BM57: DEBET | BN57: KREDIT | BO57: DEBET | BP57: KREDIT | BT57: DEBET | BU57: KREDIT | BW57: DEBET | BX57: KREDIT | BZ57: DEBET | CA57: KREDIT
D58: LR01A | E58: PENDAPATAN PINJAMAN RUTIN | F58: K | G58: 0 | H58: 0 | J58: =SUMIF('MUTASI 2026'!$B$5:$B$160,'WS Trial balance'!$D58,'MUTASI 2026'!$G$5:$G$160) -> 0 | K58: =SUMIF('MUTASI 2026'!$B$5:$B$160,'WS Trial balance'!$D58,'MUTASI 2026'!$H$5:$H$160) -> 78721705 | L58: =IF(F58="D",(G58-H58+J58-K58),0) -> 0 | M58: =IF(F58="K",(-G58+H58-J58+K58),0) -> 78721705 | O58: =SUMIF('MUTASI 2026'!$B$162:$B$252,'WS Trial balance'!$D58,'MUTASI 2026'!$G$162:$G$252) -> 0 | P58: =SUMIF('MUTASI 2026'!$B$162:$B$252,'WS Trial balance'!$D58,'MUTASI 2026'!$H$162:$H$252) -> 80206566 | Q58: =IF(F58="D",(L58-M58+O58-P58),0) -> 0 | R58: =IF(F58="K",(-L58+M58-O58+P58),0) -> 1.5892827e+08 | T58: =SUMIF('MUTASI 2026'!$B$254:$B$356,'WS Trial balance'!$D58,'MUTASI 2026'!$G$254:$G$356) -> 0 | U58: =SUMIF('MUTASI 2026'!$B$254:$B$356,'WS Trial balance'!$D58,'MUTASI 2026'!$H$254:$H$356) -> 81022330 | V58: =IF(F58="D",(Q58-R58+T58-U58),0) -> 0 | W58: =IF(F58="K",(-Q58+R58-T58+U58),0) -> 2.399506e+08 | Y58: =SUMIF('MUTASI 2026'!$B$358:$B$480,'WS Trial balance'!$D58,'MUTASI 2026'!$G$358:$G$480) -> 0 | Z58: =SUMIF('MUTASI 2026'!$B$358:$B$480,'WS Trial balance'!$D58,'MUTASI 2026'!$H$358:$H$480) -> 77958441 | AA58: =IF(F58="D",(V58-W58+Y58-Z58),0) -> 0 | AB58: =IF(F58="K",(-V58+W58-Y58+Z58),0) -> 3.1790904e+08 | AD58: =SUMIF('MUTASI 2026'!$B$482:$B$655,'WS Trial balance'!$D58,'MUTASI 2026'!$G$482:$G$655) -> 0 | AE58: =SUMIF('MUTASI 2026'!$B$482:$B$655,'WS Trial balance'!$D58,'MUTASI 2026'!$H$482:$H$655) -> 81143163 | AF58: =IF(F58="D",(AA58-AB58+AD58-AE58),0) -> 0 | AG58: =IF(F58="K",(-AA58+AB58-AD58+AE58),0) -> 3.990522e+08 | AI58: =SUMIF('MUTASI 2026'!$B$657:$B$748,'WS Trial balance'!$D58,'MUTASI 2026'!$G$657:$G$748) -> 0 | AJ58: =SUMIF('MUTASI 2026'!$B$657:$B$748,'WS Trial balance'!$D58,'MUTASI 2026'!$H$657:$H$748) -> 82725663 | AK58: =IF(F58="D",(AF58-AG58+AI58-AJ58),0) -> 0 | AL58: =IF(F58="K",(-AF58+AG58-AI58+AJ58),0) -> 4.8177787e+08 | AN58: =SUMIF('MUTASI 2026'!$B$750:$B$851,'WS Trial balance'!$D58,'MUTASI 2026'!$G$750:$G$851) -> 0 | AO58: =SUMIF('MUTASI 2026'!$B$750:$B$851,'WS Trial balance'!$D58,'MUTASI 2026'!$H$750:$H$851) -> 84316497 | AP58: =IF(F58="D",(AK58-AL58+AN58-AO58),0) -> 0 | AQ58: =IF(F58="K",(-AK58+AL58-AN58+AO58),0) -> 5.6609436e+08 | AS58: =SUMIF('MUTASI 2026'!$B$853:$B$945,'WS Trial balance'!$D58,'MUTASI 2026'!$G$853:$G$945) -> 0 | AT58: =SUMIF('MUTASI 2026'!$B$853:$B$945,'WS Trial balance'!$D58,'MUTASI 2026'!$H$853:$H$945) -> 84316497 | AU58: =IF(F58="D",(AP58-AQ58+AS58-AT58),0) -> 0 | AV58: =IF(F58="K",(-AP58+AQ58-AS58+AT58),0) -> 6.5041086e+08 | AX58: =SUMIF('MUTASI 2026'!$B$1274:$B$1379,'WS Trial balance'!$D58,'MUTASI 2026'!$G$1274:$G$1379) -> 0 | AY58: =SUMIF('MUTASI 2026'!$B$1274:$B$1379,'WS Trial balance'!$D58,'MUTASI 2026'!$H$1274:$H$1379) -> 0 | AZ58: =IF(F58="D",(AU58-AV58+AX58-AY58),0) -> 0 | BA58: =IF(F58="K",(-AU58+AV58-AX58+AY58),0) -> 6.5041086e+08 | BC58: =SUMIF('MUTASI 2026'!$B$1382:$B$1477,'WS Trial balance'!$D58,'MUTASI 2026'!$G$1382:$G$1477) -> 0 | BD58: =SUMIF('MUTASI 2026'!$B$1382:$B$1477,'WS Trial balance'!$D58,'MUTASI 2026'!$H$1382:$H$1477) -> 0 | BE58: =IF(F58="D",(AZ58-BA58+BC58-BD58),0) -> 0 | BF58: =IF(F58="K",(-AZ58+BA58-BC58+BD58),0) -> 6.5041086e+08 | BH58: =SUMIF('MUTASI 2026'!$B$1480:$B$1600,'WS Trial balance'!$D58,'MUTASI 2026'!$G$1480:$G$1600) -> 0 | BI58: =SUMIF('MUTASI 2026'!$B$1480:$B$1600,'WS Trial balance'!$D58,'MUTASI 2026'!$H$1480:$H$1600) -> 0 | BJ58: =IF(F58="D",(BE58-BF58+BH58-BI58),0) -> 0 | BK58: =IF(F58="K",(-BE58+BF58-BH58+BI58),0) -> 6.5041086e+08 | BM58: =SUMIF('MUTASI 2026'!$B$1603:$B$1722,'WS Trial balance'!$D58,'MUTASI 2026'!$G$1603:$G$1722) -> 0 | BN58: =SUMIF('MUTASI 2026'!$B$1603:$B$1722,'WS Trial balance'!$D58,'MUTASI 2026'!$H$1603:$H$1722) -> 0 | BO58: =IF(F58="D",(BJ58-BK58+BM58-BN58),0) -> 0 | BP58: =IF(F58="K",(-BJ58+BK58-BM58+BN58),0) -> 6.5041086e+08 | BT58: =G58 -> 0 | BU58: =H58 -> 0 | BW58: =J58+O58+T58+Y58+AD58+AI58+AN58+AS58+AX58+BC58+BH58+BM58 -> 0 | BX58: =K58+P58+U58+Z58+AE58+AJ58+AO58+AT58+AY58+BD58+BI58+BN58 -> 6.5041086e+08 | BZ58: =IF(F58="D",(BT58-BU58+BW58-BX58),0) -> 0 | CA58: =IF(F58="K",(-BT58+BU58-BW58+BX58),0) -> 6.5041086e+08 | CE58: =SUM(CA58:CA60)-SUM(BZ61:BZ63) -> 1.5129486e+08 | CF58: =+CA58-BZ61 -> 1.4906586e+08
D59: LR01B | E59: PENDAPATAN PINJAMAN KHUSUS | F59: K | G59: 0 | H59: 0 | J59: =SUMIF('MUTASI 2026'!$B$5:$B$160,'WS Trial balance'!$D59,'MUTASI 2026'!$G$5:$G$160) -> 0 | K59: =SUMIF('MUTASI 2026'!$B$5:$B$160,'WS Trial balance'!$D59,'MUTASI 2026'!$H$5:$H$160) -> 0 | L59: =IF(F59="D",(G59-H59+J59-K59),0) -> 0 | M59: =IF(F59="K",(-G59+H59-J59+K59),0) -> 0 | O59: =SUMIF('MUTASI 2026'!$B$162:$B$252,'WS Trial balance'!$D59,'MUTASI 2026'!$G$162:$G$252) -> 0 | P59: =SUMIF('MUTASI 2026'!$B$162:$B$252,'WS Trial balance'!$D59,'MUTASI 2026'!$H$162:$H$252) -> 0 | Q59: =IF(F59="D",(L59-M59+O59-P59),0) -> 0 | R59: =IF(F59="K",(-L59+M59-O59+P59),0) -> 0 | T59: =SUMIF('MUTASI 2026'!$B$254:$B$356,'WS Trial balance'!$D59,'MUTASI 2026'!$G$254:$G$356) -> 0 | U59: =SUMIF('MUTASI 2026'!$B$254:$B$356,'WS Trial balance'!$D59,'MUTASI 2026'!$H$254:$H$356) -> 0 | V59: =IF(F59="D",(Q59-R59+T59-U59),0) -> 0 | W59: =IF(F59="K",(-Q59+R59-T59+U59),0) -> 0 | Y59: =SUMIF('MUTASI 2026'!$B$358:$B$480,'WS Trial balance'!$D59,'MUTASI 2026'!$G$358:$G$480) -> 0 | Z59: =SUMIF('MUTASI 2026'!$B$358:$B$480,'WS Trial balance'!$D59,'MUTASI 2026'!$H$358:$H$480) -> 0 | AA59: =IF(F59="D",(V59-W59+Y59-Z59),0) -> 0 | AB59: =IF(F59="K",(-V59+W59-Y59+Z59),0) -> 0 | AD59: =SUMIF('MUTASI 2026'!$B$482:$B$655,'WS Trial balance'!$D59,'MUTASI 2026'!$G$482:$G$655) -> 0 | AE59: =SUMIF('MUTASI 2026'!$B$482:$B$655,'WS Trial balance'!$D59,'MUTASI 2026'!$H$482:$H$655) -> 0 | AF59: =IF(F59="D",(AA59-AB59+AD59-AE59),0) -> 0 | AG59: =IF(F59="K",(-AA59+AB59-AD59+AE59),0) -> 0 | AI59: =SUMIF('MUTASI 2026'!$B$657:$B$748,'WS Trial balance'!$D59,'MUTASI 2026'!$G$657:$G$748) -> 0 | AJ59: =SUMIF('MUTASI 2026'!$B$657:$B$748,'WS Trial balance'!$D59,'MUTASI 2026'!$H$657:$H$748) -> 0 | AK59: =IF(F59="D",(AF59-AG59+AI59-AJ59),0) -> 0 | AL59: =IF(F59="K",(-AF59+AG59-AI59+AJ59),0) -> 0 | AN59: =SUMIF('MUTASI 2026'!$B$750:$B$851,'WS Trial balance'!$D59,'MUTASI 2026'!$G$750:$G$851) -> 0 | AO59: =SUMIF('MUTASI 2026'!$B$750:$B$851,'WS Trial balance'!$D59,'MUTASI 2026'!$H$750:$H$851) -> 0 | AP59: =IF(F59="D",(AK59-AL59+AN59-AO59),0) -> 0 | AQ59: =IF(F59="K",(-AK59+AL59-AN59+AO59),0) -> 0 | AS59: =SUMIF('MUTASI 2026'!$B$853:$B$945,'WS Trial balance'!$D59,'MUTASI 2026'!$G$853:$G$945) -> 0 | AT59: =SUMIF('MUTASI 2026'!$B$853:$B$945,'WS Trial balance'!$D59,'MUTASI 2026'!$H$853:$H$945) -> 0 | AU59: =IF(F59="D",(AP59-AQ59+AS59-AT59),0) -> 0 | AV59: =IF(F59="K",(-AP59+AQ59-AS59+AT59),0) -> 0 | AX59: =SUMIF('MUTASI 2026'!$B$1274:$B$1379,'WS Trial balance'!$D59,'MUTASI 2026'!$G$1274:$G$1379) -> 0 | AY59: =SUMIF('MUTASI 2026'!$B$1274:$B$1379,'WS Trial balance'!$D59,'MUTASI 2026'!$H$1274:$H$1379) -> 0 | AZ59: =IF(F59="D",(AU59-AV59+AX59-AY59),0) -> 0 | BA59: =IF(F59="K",(-AU59+AV59-AX59+AY59),0) -> 0 | BC59: =SUMIF('MUTASI 2026'!$B$1382:$B$1477,'WS Trial balance'!$D59,'MUTASI 2026'!$G$1382:$G$1477) -> 0 | BD59: =SUMIF('MUTASI 2026'!$B$1382:$B$1477,'WS Trial balance'!$D59,'MUTASI 2026'!$H$1382:$H$1477) -> 0 | BE59: =IF(F59="D",(AZ59-BA59+BC59-BD59),0) -> 0 | BF59: =IF(F59="K",(-AZ59+BA59-BC59+BD59),0) -> 0 | BH59: =SUMIF('MUTASI 2026'!$B$1480:$B$1600,'WS Trial balance'!$D59,'MUTASI 2026'!$G$1480:$G$1600) -> 0 | BI59: =SUMIF('MUTASI 2026'!$B$1480:$B$1600,'WS Trial balance'!$D59,'MUTASI 2026'!$H$1480:$H$1600) -> 0 | BJ59: =IF(F59="D",(BE59-BF59+BH59-BI59),0) -> 0 | BK59: =IF(F59="K",(-BE59+BF59-BH59+BI59),0) -> 0 | BM59: =SUMIF('MUTASI 2026'!$B$1603:$B$1722,'WS Trial balance'!$D59,'MUTASI 2026'!$G$1603:$G$1722) -> 0 | BN59: =SUMIF('MUTASI 2026'!$B$1603:$B$1722,'WS Trial balance'!$D59,'MUTASI 2026'!$H$1603:$H$1722) -> 0 | BO59: =IF(F59="D",(BJ59-BK59+BM59-BN59),0) -> 0 | BP59: =IF(F59="K",(-BJ59+BK59-BM59+BN59),0) -> 0 | BT59: =G59 -> 0 | BU59: =H59 -> 0 | BW59: =J59+O59+T59+Y59+AD59+AI59+AN59+AS59+AX59+BC59+BH59+BM59 -> 0 | BX59: =K59+P59+U59+Z59+AE59+AJ59+AO59+AT59+AY59+BD59+BI59+BN59 -> 0 | BZ59: =IF(F59="D",(BT59-BU59+BW59-BX59),0) -> 0 | CA59: =IF(F59="K",(-BT59+BU59-BW59+BX59),0) -> 0
D60: LR01C | E60: PENDAPATAN PINJAMAN LAIN-LAIN | F60: K | G60: 0 | H60: 0 | J60: =SUMIF('MUTASI 2026'!$B$5:$B$160,'WS Trial balance'!$D60,'MUTASI 2026'!$G$5:$G$160) -> 0 | K60: =SUMIF('MUTASI 2026'!$B$5:$B$160,'WS Trial balance'!$D60,'MUTASI 2026'!$H$5:$H$160) -> 525000 | L60: =IF(F60="D",(G60-H60+J60-K60),0) -> 0 | M60: =IF(F60="K",(-G60+H60-J60+K60),0) -> 525000 | O60: =SUMIF('MUTASI 2026'!$B$162:$B$252,'WS Trial balance'!$D60,'MUTASI 2026'!$G$162:$G$252) -> 0 | P60: =SUMIF('MUTASI 2026'!$B$162:$B$252,'WS Trial balance'!$D60,'MUTASI 2026'!$H$162:$H$252) -> 350000 | Q60: =IF(F60="D",(L60-M60+O60-P60),0) -> 0 | R60: =IF(F60="K",(-L60+M60-O60+P60),0) -> 875000 | T60: =SUMIF('MUTASI 2026'!$B$254:$B$356,'WS Trial balance'!$D60,'MUTASI 2026'!$G$254:$G$356) -> 92500 | U60: =SUMIF('MUTASI 2026'!$B$254:$B$356,'WS Trial balance'!$D60,'MUTASI 2026'!$H$254:$H$356) -> 0 | V60: =IF(F60="D",(Q60-R60+T60-U60),0) -> 0 | W60: =IF(F60="K",(-Q60+R60-T60+U60),0) -> 782500 | Y60: =SUMIF('MUTASI 2026'!$B$358:$B$480,'WS Trial balance'!$D60,'MUTASI 2026'!$G$358:$G$480) -> 0 | Z60: =SUMIF('MUTASI 2026'!$B$358:$B$480,'WS Trial balance'!$D60,'MUTASI 2026'!$H$358:$H$480) -> 385000 | AA60: =IF(F60="D",(V60-W60+Y60-Z60),0) -> 0 | AB60: =IF(F60="K",(-V60+W60-Y60+Z60),0) -> 1167500 | AD60: =SUMIF('MUTASI 2026'!$B$482:$B$655,'WS Trial balance'!$D60,'MUTASI 2026'!$G$482:$G$655) -> 0 | AE60: =SUMIF('MUTASI 2026'!$B$482:$B$655,'WS Trial balance'!$D60,'MUTASI 2026'!$H$482:$H$655) -> 630000 | AF60: =IF(F60="D",(AA60-AB60+AD60-AE60),0) -> 0 | AG60: =IF(F60="K",(-AA60+AB60-AD60+AE60),0) -> 1797500 | AI60: =SUMIF('MUTASI 2026'!$B$657:$B$748,'WS Trial balance'!$D60,'MUTASI 2026'!$G$657:$G$748) -> 0 | AJ60: =SUMIF('MUTASI 2026'!$B$657:$B$748,'WS Trial balance'!$D60,'MUTASI 2026'!$H$657:$H$748) -> 221500 | AK60: =IF(F60="D",(AF60-AG60+AI60-AJ60),0) -> 0 | AL60: =IF(F60="K",(-AF60+AG60-AI60+AJ60),0) -> 2019000 | AN60: =SUMIF('MUTASI 2026'!$B$750:$B$851,'WS Trial balance'!$D60,'MUTASI 2026'!$G$750:$G$851) -> 0 | AO60: =SUMIF('MUTASI 2026'!$B$750:$B$851,'WS Trial balance'!$D60,'MUTASI 2026'!$H$750:$H$851) -> 0 | AP60: =IF(F60="D",(AK60-AL60+AN60-AO60),0) -> 0 | AQ60: =IF(F60="K",(-AK60+AL60-AN60+AO60),0) -> 2019000 | AS60: =SUMIF('MUTASI 2026'!$B$853:$B$945,'WS Trial balance'!$D60,'MUTASI 2026'!$G$853:$G$945) -> 0 | AT60: =SUMIF('MUTASI 2026'!$B$853:$B$945,'WS Trial balance'!$D60,'MUTASI 2026'!$H$853:$H$945) -> 210000 | AU60: =IF(F60="D",(AP60-AQ60+AS60-AT60),0) -> 0 | AV60: =IF(F60="K",(-AP60+AQ60-AS60+AT60),0) -> 2229000 | AX60: =SUMIF('MUTASI 2026'!$B$1274:$B$1379,'WS Trial balance'!$D60,'MUTASI 2026'!$G$1274:$G$1379) -> 0 | AY60: =SUMIF('MUTASI 2026'!$B$1274:$B$1379,'WS Trial balance'!$D60,'MUTASI 2026'!$H$1274:$H$1379) -> 0 | AZ60: =IF(F60="D",(AU60-AV60+AX60-AY60),0) -> 0 | BA60: =IF(F60="K",(-AU60+AV60-AX60+AY60),0) -> 2229000 | BC60: =SUMIF('MUTASI 2026'!$B$1382:$B$1477,'WS Trial balance'!$D60,'MUTASI 2026'!$G$1382:$G$1477) -> 0 | BD60: =SUMIF('MUTASI 2026'!$B$1382:$B$1477,'WS Trial balance'!$D60,'MUTASI 2026'!$H$1382:$H$1477) -> 0 | BE60: =IF(F60="D",(AZ60-BA60+BC60-BD60),0) -> 0 | BF60: =IF(F60="K",(-AZ60+BA60-BC60+BD60),0) -> 2229000 | BH60: =SUMIF('MUTASI 2026'!$B$1480:$B$1600,'WS Trial balance'!$D60,'MUTASI 2026'!$G$1480:$G$1600) -> 0 | BI60: =SUMIF('MUTASI 2026'!$B$1480:$B$1600,'WS Trial balance'!$D60,'MUTASI 2026'!$H$1480:$H$1600) -> 0 | BJ60: =IF(F60="D",(BE60-BF60+BH60-BI60),0) -> 0 | BK60: =IF(F60="K",(-BE60+BF60-BH60+BI60),0) -> 2229000 | BM60: =SUMIF('MUTASI 2026'!$B$1603:$B$1722,'WS Trial balance'!$D60,'MUTASI 2026'!$G$1603:$G$1722) -> 0 | BN60: =SUMIF('MUTASI 2026'!$B$1603:$B$1722,'WS Trial balance'!$D60,'MUTASI 2026'!$H$1603:$H$1722) -> 0 | BO60: =IF(F60="D",(BJ60-BK60+BM60-BN60),0) -> 0 | BP60: =IF(F60="K",(-BJ60+BK60-BM60+BN60),0) -> 2229000 | BT60: =G60 -> 0 | BU60: =H60 -> 0 | BW60: =J60+O60+T60+Y60+AD60+AI60+AN60+AS60+AX60+BC60+BH60+BM60 -> 92500 | BX60: =K60+P60+U60+Z60+AE60+AJ60+AO60+AT60+AY60+BD60+BI60+BN60 -> 2321500 | BZ60: =IF(F60="D",(BT60-BU60+BW60-BX60),0) -> 0 | CA60: =IF(F60="K",(-BT60+BU60-BW60+BX60),0) -> 2229000
D61: LR02A | E61: BIAYA POKOK PINJAMAN RUTIN | F61: D | G61: 0 | H61: 0 | J61: =SUMIF('MUTASI 2026'!$B$5:$B$160,'WS Trial balance'!$D61,'MUTASI 2026'!$G$5:$G$160) -> 60419861 | K61: =SUMIF('MUTASI 2026'!$B$5:$B$160,'WS Trial balance'!$D61,'MUTASI 2026'!$H$5:$H$160) -> 0 | L61: =IF(F61="D",(G61-H61+J61-K61),0) -> 60419861 | M61: =IF(F61="K",(-G61+H61-J61+K61),0) -> 0 | O61: =SUMIF('MUTASI 2026'!$B$162:$B$252,'WS Trial balance'!$D61,'MUTASI 2026'!$G$162:$G$252) -> 61858750 | P61: =SUMIF('MUTASI 2026'!$B$162:$B$252,'WS Trial balance'!$D61,'MUTASI 2026'!$H$162:$H$252) -> 0 | Q61: =IF(F61="D",(L61-M61+O61-P61),0) -> 1.2227861e+08 | R61: =IF(F61="K",(-L61+M61-O61+P61),0) -> 0 | T61: =SUMIF('MUTASI 2026'!$B$254:$B$356,'WS Trial balance'!$D61,'MUTASI 2026'!$G$254:$G$356) -> 62264306 | U61: =SUMIF('MUTASI 2026'!$B$254:$B$356,'WS Trial balance'!$D61,'MUTASI 2026'!$H$254:$H$356) -> 0 | V61: =IF(F61="D",(Q61-R61+T61-U61),0) -> 1.8454292e+08 | W61: =IF(F61="K",(-Q61+R61-T61+U61),0) -> 0 | Y61: =SUMIF('MUTASI 2026'!$B$358:$B$480,'WS Trial balance'!$D61,'MUTASI 2026'!$G$358:$G$480) -> 59901806 | Z61: =SUMIF('MUTASI 2026'!$B$358:$B$480,'WS Trial balance'!$D61,'MUTASI 2026'!$H$358:$H$480) -> 0 | AA61: =IF(F61="D",(V61-W61+Y61-Z61),0) -> 2.4444472e+08 | AB61: =IF(F61="K",(-V61+W61-Y61+Z61),0) -> 0 | AD61: =SUMIF('MUTASI 2026'!$B$482:$B$655,'WS Trial balance'!$D61,'MUTASI 2026'!$G$482:$G$655) -> 62749028 | AE61: =SUMIF('MUTASI 2026'!$B$482:$B$655,'WS Trial balance'!$D61,'MUTASI 2026'!$H$482:$H$655) -> 0 | AF61: =IF(F61="D",(AA61-AB61+AD61-AE61),0) -> 307193750 | AG61: =IF(F61="K",(-AA61+AB61-AD61+AE61),0) -> 0 | AI61: =SUMIF('MUTASI 2026'!$B$657:$B$748,'WS Trial balance'!$D61,'MUTASI 2026'!$G$657:$G$748) -> 63894861 | AJ61: =SUMIF('MUTASI 2026'!$B$657:$B$748,'WS Trial balance'!$D61,'MUTASI 2026'!$H$657:$H$748) -> 0 | AK61: =IF(F61="D",(AF61-AG61+AI61-AJ61),0) -> 3.7108861e+08 | AL61: =IF(F61="K",(-AF61+AG61-AI61+AJ61),0) -> 0 | AN61: =SUMIF('MUTASI 2026'!$B$750:$B$851,'WS Trial balance'!$D61,'MUTASI 2026'!$G$750:$G$851) -> 65128194 | AO61: =SUMIF('MUTASI 2026'!$B$750:$B$851,'WS Trial balance'!$D61,'MUTASI 2026'!$H$750:$H$851) -> 0 | AP61: =IF(F61="D",(AK61-AL61+AN61-AO61),0) -> 4.3621681e+08 | AQ61: =IF(F61="K",(-AK61+AL61-AN61+AO61),0) -> 0 | AS61: =SUMIF('MUTASI 2026'!$B$853:$B$945,'WS Trial balance'!$D61,'MUTASI 2026'!$G$853:$G$945) -> 65128194 | AT61: =SUMIF('MUTASI 2026'!$B$853:$B$945,'WS Trial balance'!$D61,'MUTASI 2026'!$H$853:$H$945) -> 0 | AU61: =IF(F61="D",(AP61-AQ61+AS61-AT61),0) -> 5.01345e+08 | AV61: =IF(F61="K",(-AP61+AQ61-AS61+AT61),0) -> 0 | AX61: =SUMIF('MUTASI 2026'!$B$1274:$B$1379,'WS Trial balance'!$D61,'MUTASI 2026'!$G$1274:$G$1379) -> 0 | AY61: =SUMIF('MUTASI 2026'!$B$1274:$B$1379,'WS Trial balance'!$D61,'MUTASI 2026'!$H$1274:$H$1379) -> 0 | AZ61: =IF(F61="D",(AU61-AV61+AX61-AY61),0) -> 5.01345e+08 | BA61: =IF(F61="K",(-AU61+AV61-AX61+AY61),0) -> 0 | BC61: =SUMIF('MUTASI 2026'!$B$1382:$B$1477,'WS Trial balance'!$D61,'MUTASI 2026'!$G$1382:$G$1477) -> 0 | BD61: =SUMIF('MUTASI 2026'!$B$1382:$B$1477,'WS Trial balance'!$D61,'MUTASI 2026'!$H$1382:$H$1477) -> 0 | BE61: =IF(F61="D",(AZ61-BA61+BC61-BD61),0) -> 5.01345e+08 | BF61: =IF(F61="K",(-AZ61+BA61-BC61+BD61),0) -> 0 | BH61: =SUMIF('MUTASI 2026'!$B$1480:$B$1600,'WS Trial balance'!$D61,'MUTASI 2026'!$G$1480:$G$1600) -> 0 | BI61: =SUMIF('MUTASI 2026'!$B$1480:$B$1600,'WS Trial balance'!$D61,'MUTASI 2026'!$H$1480:$H$1600) -> 0 | BJ61: =IF(F61="D",(BE61-BF61+BH61-BI61),0) -> 5.01345e+08 | BK61: =IF(F61="K",(-BE61+BF61-BH61+BI61),0) -> 0 | BM61: =SUMIF('MUTASI 2026'!$B$1603:$B$1722,'WS Trial balance'!$D61,'MUTASI 2026'!$G$1603:$G$1722) -> 0 | BN61: =SUMIF('MUTASI 2026'!$B$1603:$B$1722,'WS Trial balance'!$D61,'MUTASI 2026'!$H$1603:$H$1722) -> 0 | BO61: =IF(F61="D",(BJ61-BK61+BM61-BN61),0) -> 5.01345e+08 | BP61: =IF(F61="K",(-BJ61+BK61-BM61+BN61),0) -> 0 | BT61: =G61 -> 0 | BU61: =H61 -> 0 | BW61: =J61+O61+T61+Y61+AD61+AI61+AN61+AS61+AX61+BC61+BH61+BM61 -> 5.01345e+08 | BX61: =K61+P61+U61+Z61+AE61+AJ61+AO61+AT61+AY61+BD61+BI61+BN61 -> 0 | BZ61: =IF(F61="D",(BT61-BU61+BW61-BX61),0) -> 5.01345e+08 | CA61: =IF(F61="K",(-BT61+BU61-BW61+BX61),0) -> 0
D62: LR02B | E62: BIAYA POKOK PINJAMAN KHUSUS | F62: D | G62: 0 | H62: 0 | J62: =SUMIF('MUTASI 2026'!$B$5:$B$160,'WS Trial balance'!$D62,'MUTASI 2026'!$G$5:$G$160) -> 0 | K62: =SUMIF('MUTASI 2026'!$B$5:$B$160,'WS Trial balance'!$D62,'MUTASI 2026'!$H$5:$H$160) -> 0 | L62: =IF(F62="D",(G62-H62+J62-K62),0) -> 0 | M62: =IF(F62="K",(-G62+H62-J62+K62),0) -> 0 | O62: =SUMIF('MUTASI 2026'!$B$162:$B$252,'WS Trial balance'!$D62,'MUTASI 2026'!$G$162:$G$252) -> 0 | P62: =SUMIF('MUTASI 2026'!$B$162:$B$252,'WS Trial balance'!$D62,'MUTASI 2026'!$H$162:$H$252) -> 0 | Q62: =IF(F62="D",(L62-M62+O62-P62),0) -> 0 | R62: =IF(F62="K",(-L62+M62-O62+P62),0) -> 0 | T62: =SUMIF('MUTASI 2026'!$B$254:$B$356,'WS Trial balance'!$D62,'MUTASI 2026'!$G$254:$G$356) -> 0 | U62: =SUMIF('MUTASI 2026'!$B$254:$B$356,'WS Trial balance'!$D62,'MUTASI 2026'!$H$254:$H$356) -> 0 | V62: =IF(F62="D",(Q62-R62+T62-U62),0) -> 0 | W62: =IF(F62="K",(-Q62+R62-T62+U62),0) -> 0 | Y62: =SUMIF('MUTASI 2026'!$B$358:$B$480,'WS Trial balance'!$D62,'MUTASI 2026'!$G$358:$G$480) -> 0 | Z62: =SUMIF('MUTASI 2026'!$B$358:$B$480,'WS Trial balance'!$D62,'MUTASI 2026'!$H$358:$H$480) -> 0 | AA62: =IF(F62="D",(V62-W62+Y62-Z62),0) -> 0 | AB62: =IF(F62="K",(-V62+W62-Y62+Z62),0) -> 0 | AD62: =SUMIF('MUTASI 2026'!$B$482:$B$655,'WS Trial balance'!$D62,'MUTASI 2026'!$G$482:$G$655) -> 0 | AE62: =SUMIF('MUTASI 2026'!$B$482:$B$655,'WS Trial balance'!$D62,'MUTASI 2026'!$H$482:$H$655) -> 0 | AF62: =IF(F62="D",(AA62-AB62+AD62-AE62),0) -> 0 | AG62: =IF(F62="K",(-AA62+AB62-AD62+AE62),0) -> 0 | AI62: =SUMIF('MUTASI 2026'!$B$657:$B$748,'WS Trial balance'!$D62,'MUTASI 2026'!$G$657:$G$748) -> 0 | AJ62: =SUMIF('MUTASI 2026'!$B$657:$B$748,'WS Trial balance'!$D62,'MUTASI 2026'!$H$657:$H$748) -> 0 | AK62: =IF(F62="D",(AF62-AG62+AI62-AJ62),0) -> 0 | AL62: =IF(F62="K",(-AF62+AG62-AI62+AJ62),0) -> 0 | AN62: =SUMIF('MUTASI 2026'!$B$750:$B$851,'WS Trial balance'!$D62,'MUTASI 2026'!$G$750:$G$851) -> 0 | AO62: =SUMIF('MUTASI 2026'!$B$750:$B$851,'WS Trial balance'!$D62,'MUTASI 2026'!$H$750:$H$851) -> 0 | AP62: =IF(F62="D",(AK62-AL62+AN62-AO62),0) -> 0 | AQ62: =IF(F62="K",(-AK62+AL62-AN62+AO62),0) -> 0 | AS62: =SUMIF('MUTASI 2026'!$B$853:$B$945,'WS Trial balance'!$D62,'MUTASI 2026'!$G$853:$G$945) -> 0 | AT62: =SUMIF('MUTASI 2026'!$B$853:$B$945,'WS Trial balance'!$D62,'MUTASI 2026'!$H$853:$H$945) -> 0 | AU62: =IF(F62="D",(AP62-AQ62+AS62-AT62),0) -> 0 | AV62: =IF(F62="K",(-AP62+AQ62-AS62+AT62),0) -> 0 | AX62: =SUMIF('MUTASI 2026'!$B$1274:$B$1379,'WS Trial balance'!$D62,'MUTASI 2026'!$G$1274:$G$1379) -> 0 | AY62: =SUMIF('MUTASI 2026'!$B$1274:$B$1379,'WS Trial balance'!$D62,'MUTASI 2026'!$H$1274:$H$1379) -> 0 | AZ62: =IF(F62="D",(AU62-AV62+AX62-AY62),0) -> 0 | BA62: =IF(F62="K",(-AU62+AV62-AX62+AY62),0) -> 0 | BC62: =SUMIF('MUTASI 2026'!$B$1382:$B$1477,'WS Trial balance'!$D62,'MUTASI 2026'!$G$1382:$G$1477) -> 0 | BD62: =SUMIF('MUTASI 2026'!$B$1382:$B$1477,'WS Trial balance'!$D62,'MUTASI 2026'!$H$1382:$H$1477) -> 0 | BE62: =IF(F62="D",(AZ62-BA62+BC62-BD62),0) -> 0 | BF62: =IF(F62="K",(-AZ62+BA62-BC62+BD62),0) -> 0 | BH62: =SUMIF('MUTASI 2026'!$B$1480:$B$1600,'WS Trial balance'!$D62,'MUTASI 2026'!$G$1480:$G$1600) -> 0 | BI62: =SUMIF('MUTASI 2026'!$B$1480:$B$1600,'WS Trial balance'!$D62,'MUTASI 2026'!$H$1480:$H$1600) -> 0 | BJ62: =IF(F62="D",(BE62-BF62+BH62-BI62),0) -> 0 | BK62: =IF(F62="K",(-BE62+BF62-BH62+BI62),0) -> 0 | BM62: =SUMIF('MUTASI 2026'!$B$1603:$B$1722,'WS Trial balance'!$D62,'MUTASI 2026'!$G$1603:$G$1722) -> 0 | BN62: =SUMIF('MUTASI 2026'!$B$1603:$B$1722,'WS Trial balance'!$D62,'MUTASI 2026'!$H$1603:$H$1722) -> 0 | BO62: =IF(F62="D",(BJ62-BK62+BM62-BN62),0) -> 0 | BP62: =IF(F62="K",(-BJ62+BK62-BM62+BN62),0) -> 0 | BT62: =G62 -> 0 | BU62: =H62 -> 0 | BW62: =J62+O62+T62+Y62+AD62+AI62+AN62+AS62+AX62+BC62+BH62+BM62 -> 0 | BX62: =K62+P62+U62+Z62+AE62+AJ62+AO62+AT62+AY62+BD62+BI62+BN62 -> 0 | BZ62: =IF(F62="D",(BT62-BU62+BW62-BX62),0) -> 0 | CA62: =IF(F62="K",(-BT62+BU62-BW62+BX62),0) -> 0
D63: LR02C | E63: BIAYA POKOK PINJAMAN LAIN-LAIN | F63: D | G63: 0 | H63: 0 | J63: =SUMIF('MUTASI 2026'!$B$5:$B$160,'WS Trial balance'!$D63,'MUTASI 2026'!$G$5:$G$160) -> 0 | K63: =SUMIF('MUTASI 2026'!$B$5:$B$160,'WS Trial balance'!$D63,'MUTASI 2026'!$H$5:$H$160) -> 0 | L63: =IF(F63="D",(G63-H63+J63-K63),0) -> 0 | M63: =IF(F63="K",(-G63+H63-J63+K63),0) -> 0 | O63: =SUMIF('MUTASI 2026'!$B$162:$B$252,'WS Trial balance'!$D63,'MUTASI 2026'!$G$162:$G$252) -> 0 | P63: =SUMIF('MUTASI 2026'!$B$162:$B$252,'WS Trial balance'!$D63,'MUTASI 2026'!$H$162:$H$252) -> 0 | Q63: =IF(F63="D",(L63-M63+O63-P63),0) -> 0 | R63: =IF(F63="K",(-L63+M63-O63+P63),0) -> 0 | T63: =SUMIF('MUTASI 2026'!$B$254:$B$356,'WS Trial balance'!$D63,'MUTASI 2026'!$G$254:$G$356) -> 0 | U63: =SUMIF('MUTASI 2026'!$B$254:$B$356,'WS Trial balance'!$D63,'MUTASI 2026'!$H$254:$H$356) -> 0 | V63: =IF(F63="D",(Q63-R63+T63-U63),0) -> 0 | W63: =IF(F63="K",(-Q63+R63-T63+U63),0) -> 0 | Y63: =SUMIF('MUTASI 2026'!$B$358:$B$480,'WS Trial balance'!$D63,'MUTASI 2026'!$G$358:$G$480) -> 0 | Z63: =SUMIF('MUTASI 2026'!$B$358:$B$480,'WS Trial balance'!$D63,'MUTASI 2026'!$H$358:$H$480) -> 0 | AA63: =IF(F63="D",(V63-W63+Y63-Z63),0) -> 0 | AB63: =IF(F63="K",(-V63+W63-Y63+Z63),0) -> 0 | AD63: =SUMIF('MUTASI 2026'!$B$482:$B$655,'WS Trial balance'!$D63,'MUTASI 2026'!$G$482:$G$655) -> 0 | AE63: =SUMIF('MUTASI 2026'!$B$482:$B$655,'WS Trial balance'!$D63,'MUTASI 2026'!$H$482:$H$655) -> 0 | AF63: =IF(F63="D",(AA63-AB63+AD63-AE63),0) -> 0 | AG63: =IF(F63="K",(-AA63+AB63-AD63+AE63),0) -> 0 | AI63: =SUMIF('MUTASI 2026'!$B$657:$B$748,'WS Trial balance'!$D63,'MUTASI 2026'!$G$657:$G$748) -> 0 | AJ63: =SUMIF('MUTASI 2026'!$B$657:$B$748,'WS Trial balance'!$D63,'MUTASI 2026'!$H$657:$H$748) -> 0 | AK63: =IF(F63="D",(AF63-AG63+AI63-AJ63),0) -> 0 | AL63: =IF(F63="K",(-AF63+AG63-AI63+AJ63),0) -> 0 | AN63: =SUMIF('MUTASI 2026'!$B$750:$B$851,'WS Trial balance'!$D63,'MUTASI 2026'!$G$750:$G$851) -> 0 | AO63: =SUMIF('MUTASI 2026'!$B$750:$B$851,'WS Trial balance'!$D63,'MUTASI 2026'!$H$750:$H$851) -> 0 | AP63: =IF(F63="D",(AK63-AL63+AN63-AO63),0) -> 0 | AQ63: =IF(F63="K",(-AK63+AL63-AN63+AO63),0) -> 0 | AS63: =SUMIF('MUTASI 2026'!$B$853:$B$945,'WS Trial balance'!$D63,'MUTASI 2026'!$G$853:$G$945) -> 0 | AT63: =SUMIF('MUTASI 2026'!$B$853:$B$945,'WS Trial balance'!$D63,'MUTASI 2026'!$H$853:$H$945) -> 0 | AU63: =IF(F63="D",(AP63-AQ63+AS63-AT63),0) -> 0 | AV63: =IF(F63="K",(-AP63+AQ63-AS63+AT63),0) -> 0 | AX63: =SUMIF('MUTASI 2026'!$B$1274:$B$1379,'WS Trial balance'!$D63,'MUTASI 2026'!$G$1274:$G$1379) -> 0 | AY63: =SUMIF('MUTASI 2026'!$B$1274:$B$1379,'WS Trial balance'!$D63,'MUTASI 2026'!$H$1274:$H$1379) -> 0 | AZ63: =IF(F63="D",(AU63-AV63+AX63-AY63),0) -> 0 | BA63: =IF(F63="K",(-AU63+AV63-AX63+AY63),0) -> 0 | BC63: =SUMIF('MUTASI 2026'!$B$1382:$B$1477,'WS Trial balance'!$D63,'MUTASI 2026'!$G$1382:$G$1477) -> 0 | BD63: =SUMIF('MUTASI 2026'!$B$1382:$B$1477,'WS Trial balance'!$D63,'MUTASI 2026'!$H$1382:$H$1477) -> 0 | BE63: =IF(F63="D",(AZ63-BA63+BC63-BD63),0) -> 0 | BF63: =IF(F63="K",(-AZ63+BA63-BC63+BD63),0) -> 0 | BH63: =SUMIF('MUTASI 2026'!$B$1480:$B$1600,'WS Trial balance'!$D63,'MUTASI 2026'!$G$1480:$G$1600) -> 0 | BI63: =SUMIF('MUTASI 2026'!$B$1480:$B$1600,'WS Trial balance'!$D63,'MUTASI 2026'!$H$1480:$H$1600) -> 0 | BJ63: =IF(F63="D",(BE63-BF63+BH63-BI63),0) -> 0 | BK63: =IF(F63="K",(-BE63+BF63-BH63+BI63),0) -> 0 | BM63: =SUMIF('MUTASI 2026'!$B$1603:$B$1722,'WS Trial balance'!$D63,'MUTASI 2026'!$G$1603:$G$1722) -> 0 | BN63: =SUMIF('MUTASI 2026'!$B$1603:$B$1722,'WS Trial balance'!$D63,'MUTASI 2026'!$H$1603:$H$1722) -> 0 | BO63: =IF(F63="D",(BJ63-BK63+BM63-BN63),0) -> 0 | BP63: =IF(F63="K",(-BJ63+BK63-BM63+BN63),0) -> 0 | BT63: =G63 -> 0 | BU63: =H63 -> 0 | BW63: =J63+O63+T63+Y63+AD63+AI63+AN63+AS63+AX63+BC63+BH63+BM63 -> 0 | BX63: =K63+P63+U63+Z63+AE63+AJ63+AO63+AT63+AY63+BD63+BI63+BN63 -> 0 | BZ63: =IF(F63="D",(BT63-BU63+BW63-BX63),0) -> 0 | CA63: =IF(F63="K",(-BT63+BU63-BW63+BX63),0) -> 0
D64: LR05 | E64: BIAYA UMUM DAN ADMINISTRASI | F64: D | G64: 0 | H64: 0 | J64: =SUMIF('MUTASI 2026'!$B$5:$B$160,'WS Trial balance'!$D64,'MUTASI 2026'!$G$5:$G$160) -> 758000 | K64: =SUMIF('MUTASI 2026'!$B$5:$B$160,'WS Trial balance'!$D64,'MUTASI 2026'!$H$5:$H$160) -> 0 | L64: =IF(F64="D",(G64-H64+J64-K64),0) -> 758000 | M64: =IF(F64="K",(-G64+H64-J64+K64),0) -> 0 | O64: =SUMIF('MUTASI 2026'!$B$162:$B$252,'WS Trial balance'!$D64,'MUTASI 2026'!$G$162:$G$252) -> 750000 | P64: =SUMIF('MUTASI 2026'!$B$162:$B$252,'WS Trial balance'!$D64,'MUTASI 2026'!$H$162:$H$252) -> 0 | Q64: =IF(F64="D",(L64-M64+O64-P64),0) -> 1508000 | R64: =IF(F64="K",(-L64+M64-O64+P64),0) -> 0 | T64: =SUMIF('MUTASI 2026'!$B$254:$B$356,'WS Trial balance'!$D64,'MUTASI 2026'!$G$254:$G$356) -> 28557000 | U64: =SUMIF('MUTASI 2026'!$B$254:$B$356,'WS Trial balance'!$D64,'MUTASI 2026'!$H$254:$H$356) -> 0 | V64: =IF(F64="D",(Q64-R64+T64-U64),0) -> 30065000 | W64: =IF(F64="K",(-Q64+R64-T64+U64),0) -> 0 | Y64: =SUMIF('MUTASI 2026'!$B$358:$B$480,'WS Trial balance'!$D64,'MUTASI 2026'!$G$358:$G$480) -> 750000 | Z64: =SUMIF('MUTASI 2026'!$B$358:$B$480,'WS Trial balance'!$D64,'MUTASI 2026'!$H$358:$H$480) -> 0 | AA64: =IF(F64="D",(V64-W64+Y64-Z64),0) -> 30815000 | AB64: =IF(F64="K",(-V64+W64-Y64+Z64),0) -> 0 | AD64: =SUMIF('MUTASI 2026'!$B$482:$B$655,'WS Trial balance'!$D64,'MUTASI 2026'!$G$482:$G$655) -> 42362600 | AE64: =SUMIF('MUTASI 2026'!$B$482:$B$655,'WS Trial balance'!$D64,'MUTASI 2026'!$H$482:$H$655) -> 0 | AF64: =IF(F64="D",(AA64-AB64+AD64-AE64),0) -> 73177600 | AG64: =IF(F64="K",(-AA64+AB64-AD64+AE64),0) -> 0 | AI64: =SUMIF('MUTASI 2026'!$B$657:$B$748,'WS Trial balance'!$D64,'MUTASI 2026'!$G$657:$G$748) -> 3250000 | AJ64: =SUMIF('MUTASI 2026'!$B$657:$B$748,'WS Trial balance'!$D64,'MUTASI 2026'!$H$657:$H$748) -> 0 | AK64: =IF(F64="D",(AF64-AG64+AI64-AJ64),0) -> 76427600 | AL64: =IF(F64="K",(-AF64+AG64-AI64+AJ64),0) -> 0 | AN64: =SUMIF('MUTASI 2026'!$B$750:$B$851,'WS Trial balance'!$D64,'MUTASI 2026'!$G$750:$G$851) -> 1120000 | AO64: =SUMIF('MUTASI 2026'!$B$750:$B$851,'WS Trial balance'!$D64,'MUTASI 2026'!$H$750:$H$851) -> 0 | AP64: =IF(F64="D",(AK64-AL64+AN64-AO64),0) -> 77547600 | AQ64: =IF(F64="K",(-AK64+AL64-AN64+AO64),0) -> 0 | AS64: =SUMIF('MUTASI 2026'!$B$853:$B$945,'WS Trial balance'!$D64,'MUTASI 2026'!$G$853:$G$945) -> 1900000 | AT64: =SUMIF('MUTASI 2026'!$B$853:$B$945,'WS Trial balance'!$D64,'MUTASI 2026'!$H$853:$H$945) -> 0 | AU64: =IF(F64="D",(AP64-AQ64+AS64-AT64),0) -> 79447600 | AV64: =IF(F64="K",(-AP64+AQ64-AS64+AT64),0) -> 0 | AX64: =SUMIF('MUTASI 2026'!$B$1274:$B$1379,'WS Trial balance'!$D64,'MUTASI 2026'!$G$1274:$G$1379) -> 0 | AY64: =SUMIF('MUTASI 2026'!$B$1274:$B$1379,'WS Trial balance'!$D64,'MUTASI 2026'!$H$1274:$H$1379) -> 0 | AZ64: =IF(F64="D",(AU64-AV64+AX64-AY64),0) -> 79447600 | BA64: =IF(F64="K",(-AU64+AV64-AX64+AY64),0) -> 0 | BC64: =SUMIF('MUTASI 2026'!$B$1382:$B$1477,'WS Trial balance'!$D64,'MUTASI 2026'!$G$1382:$G$1477) -> 0 | BD64: =SUMIF('MUTASI 2026'!$B$1382:$B$1477,'WS Trial balance'!$D64,'MUTASI 2026'!$H$1382:$H$1477) -> 0 | BE64: =IF(F64="D",(AZ64-BA64+BC64-BD64),0) -> 79447600 | BF64: =IF(F64="K",(-AZ64+BA64-BC64+BD64),0) -> 0 | BH64: =SUMIF('MUTASI 2026'!$B$1480:$B$1600,'WS Trial balance'!$D64,'MUTASI 2026'!$G$1480:$G$1600) -> 0 | BI64: =SUMIF('MUTASI 2026'!$B$1480:$B$1600,'WS Trial balance'!$D64,'MUTASI 2026'!$H$1480:$H$1600) -> 0 | BJ64: =IF(F64="D",(BE64-BF64+BH64-BI64),0) -> 79447600 | BK64: =IF(F64="K",(-BE64+BF64-BH64+BI64),0) -> 0 | BM64: =SUMIF('MUTASI 2026'!$B$1603:$B$1722,'WS Trial balance'!$D64,'MUTASI 2026'!$G$1603:$G$1722) -> 0 | BN64: =SUMIF('MUTASI 2026'!$B$1603:$B$1722,'WS Trial balance'!$D64,'MUTASI 2026'!$H$1603:$H$1722) -> 0 | BO64: =IF(F64="D",(BJ64-BK64+BM64-BN64),0) -> 79447600 | BP64: =IF(F64="K",(-BJ64+BK64-BM64+BN64),0) -> 0 | BT64: =G64 -> 0 | BU64: =H64 -> 0 | BW64: =J64+O64+T64+Y64+AD64+AI64+AN64+AS64+AX64+BC64+BH64+BM64 -> 79447600 | BX64: =K64+P64+U64+Z64+AE64+AJ64+AO64+AT64+AY64+BD64+BI64+BN64 -> 0 | BZ64: =IF(F64="D",(BT64-BU64+BW64-BX64),0) -> 79447600 | CA64: =IF(F64="K",(-BT64+BU64-BW64+BX64),0) -> 0
D65: LR06 | E65: PENDAPATAN DILUAR USAHA | F65: K | G65: 0 | H65: 0 | J65: =SUMIF('MUTASI 2026'!$B$5:$B$160,'WS Trial balance'!$D65,'MUTASI 2026'!$G$5:$G$160) -> 0 | K65: =SUMIF('MUTASI 2026'!$B$5:$B$160,'WS Trial balance'!$D65,'MUTASI 2026'!$H$5:$H$160) -> 3918000 | L65: =IF(F65="D",(G65-H65+J65-K65),0) -> 0 | M65: =IF(F65="K",(-G65+H65-J65+K65),0) -> 3918000 | O65: =SUMIF('MUTASI 2026'!$B$162:$B$252,'WS Trial balance'!$D65,'MUTASI 2026'!$G$162:$G$252) -> 0 | P65: =SUMIF('MUTASI 2026'!$B$162:$B$252,'WS Trial balance'!$D65,'MUTASI 2026'!$H$162:$H$252) -> 1423167.3 | Q65: =IF(F65="D",(L65-M65+O65-P65),0) -> 0 | R65: =IF(F65="K",(-L65+M65-O65+P65),0) -> 5341167.3 | T65: =SUMIF('MUTASI 2026'!$B$254:$B$356,'WS Trial balance'!$D65,'MUTASI 2026'!$G$254:$G$356) -> 0 | U65: =SUMIF('MUTASI 2026'!$B$254:$B$356,'WS Trial balance'!$D65,'MUTASI 2026'!$H$254:$H$356) -> 1356500 | V65: =IF(F65="D",(Q65-R65+T65-U65),0) -> 0 | W65: =IF(F65="K",(-Q65+R65-T65+U65),0) -> 6697667.3 | Y65: =SUMIF('MUTASI 2026'!$B$358:$B$480,'WS Trial balance'!$D65,'MUTASI 2026'!$G$358:$G$480) -> 0 | Z65: =SUMIF('MUTASI 2026'!$B$358:$B$480,'WS Trial balance'!$D65,'MUTASI 2026'!$H$358:$H$480) -> 1356500 | AA65: =IF(F65="D",(V65-W65+Y65-Z65),0) -> 0 | AB65: =IF(F65="K",(-V65+W65-Y65+Z65),0) -> 8054167.3 | AD65: =SUMIF('MUTASI 2026'!$B$482:$B$655,'WS Trial balance'!$D65,'MUTASI 2026'!$G$482:$G$655) -> 0 | AE65: =SUMIF('MUTASI 2026'!$B$482:$B$655,'WS Trial balance'!$D65,'MUTASI 2026'!$H$482:$H$655) -> 3146500 | AF65: =IF(F65="D",(AA65-AB65+AD65-AE65),0) -> 0 | AG65: =IF(F65="K",(-AA65+AB65-AD65+AE65),0) -> 11200667 | AI65: =SUMIF('MUTASI 2026'!$B$657:$B$748,'WS Trial balance'!$D65,'MUTASI 2026'!$G$657:$G$748) -> 0 | AJ65: =SUMIF('MUTASI 2026'!$B$657:$B$748,'WS Trial balance'!$D65,'MUTASI 2026'!$H$657:$H$748) -> 1205000 | AK65: =IF(F65="D",(AF65-AG65+AI65-AJ65),0) -> 0 | AL65: =IF(F65="K",(-AF65+AG65-AI65+AJ65),0) -> 12405667 | AN65: =SUMIF('MUTASI 2026'!$B$750:$B$851,'WS Trial balance'!$D65,'MUTASI 2026'!$G$750:$G$851) -> 0 | AO65: =SUMIF('MUTASI 2026'!$B$750:$B$851,'WS Trial balance'!$D65,'MUTASI 2026'!$H$750:$H$851) -> 1205000 | AP65: =IF(F65="D",(AK65-AL65+AN65-AO65),0) -> 0 | AQ65: =IF(F65="K",(-AK65+AL65-AN65+AO65),0) -> 13610667 | AS65: =SUMIF('MUTASI 2026'!$B$853:$B$945,'WS Trial balance'!$D65,'MUTASI 2026'!$G$853:$G$945) -> 0 | AT65: =SUMIF('MUTASI 2026'!$B$853:$B$945,'WS Trial balance'!$D65,'MUTASI 2026'!$H$853:$H$945) -> 1205000 | AU65: =IF(F65="D",(AP65-AQ65+AS65-AT65),0) -> 0 | AV65: =IF(F65="K",(-AP65+AQ65-AS65+AT65),0) -> 14815667 | AX65: =SUMIF('MUTASI 2026'!$B$1274:$B$1379,'WS Trial balance'!$D65,'MUTASI 2026'!$G$1274:$G$1379) -> 0 | AY65: =SUMIF('MUTASI 2026'!$B$1274:$B$1379,'WS Trial balance'!$D65,'MUTASI 2026'!$H$1274:$H$1379) -> 0 | AZ65: =IF(F65="D",(AU65-AV65+AX65-AY65),0) -> 0 | BA65: =IF(F65="K",(-AU65+AV65-AX65+AY65),0) -> 14815667 | BC65: =SUMIF('MUTASI 2026'!$B$1382:$B$1477,'WS Trial balance'!$D65,'MUTASI 2026'!$G$1382:$G$1477) -> 0 | BD65: =SUMIF('MUTASI 2026'!$B$1382:$B$1477,'WS Trial balance'!$D65,'MUTASI 2026'!$H$1382:$H$1477) -> 0 | BE65: =IF(F65="D",(AZ65-BA65+BC65-BD65),0) -> 0 | BF65: =IF(F65="K",(-AZ65+BA65-BC65+BD65),0) -> 14815667 | BH65: =SUMIF('MUTASI 2026'!$B$1480:$B$1600,'WS Trial balance'!$D65,'MUTASI 2026'!$G$1480:$G$1600) -> 0 | BI65: =SUMIF('MUTASI 2026'!$B$1480:$B$1600,'WS Trial balance'!$D65,'MUTASI 2026'!$H$1480:$H$1600) -> 0 | BJ65: =IF(F65="D",(BE65-BF65+BH65-BI65),0) -> 0 | BK65: =IF(F65="K",(-BE65+BF65-BH65+BI65),0) -> 14815667 | BM65: =SUMIF('MUTASI 2026'!$B$1603:$B$1722,'WS Trial balance'!$D65,'MUTASI 2026'!$G$1603:$G$1722) -> 0 | BN65: =SUMIF('MUTASI 2026'!$B$1603:$B$1722,'WS Trial balance'!$D65,'MUTASI 2026'!$H$1603:$H$1722) -> 0 | BO65: =IF(F65="D",(BJ65-BK65+BM65-BN65),0) -> 0 | BP65: =IF(F65="K",(-BJ65+BK65-BM65+BN65),0) -> 14815667 | BT65: =G65 -> 0 | BU65: =H65 -> 0 | BW65: =J65+O65+T65+Y65+AD65+AI65+AN65+AS65+AX65+BC65+BH65+BM65 -> 0 | BX65: =K65+P65+U65+Z65+AE65+AJ65+AO65+AT65+AY65+BD65+BI65+BN65 -> 14815667 | BZ65: =IF(F65="D",(BT65-BU65+BW65-BX65),0) -> 0 | CA65: =IF(F65="K",(-BT65+BU65-BW65+BX65),0) -> 14815667
D66: LR07 | E66: BIAYA DILUAR USAHA | F66: D | G66: 0 | H66: 0 | J66: =SUMIF('MUTASI 2026'!$B$5:$B$160,'WS Trial balance'!$D66,'MUTASI 2026'!$G$5:$G$160) -> 1577093.2 | K66: =SUMIF('MUTASI 2026'!$B$5:$B$160,'WS Trial balance'!$D66,'MUTASI 2026'!$H$5:$H$160) -> 81424.12 | L66: =IF(F66="D",(G66-H66+J66-K66),0) -> 1495669.1 | M66: =IF(F66="K",(-G66+H66-J66+K66),0) -> 0 | O66: =SUMIF('MUTASI 2026'!$B$162:$B$252,'WS Trial balance'!$D66,'MUTASI 2026'!$G$162:$G$252) -> 1574899.4 | P66: =SUMIF('MUTASI 2026'!$B$162:$B$252,'WS Trial balance'!$D66,'MUTASI 2026'!$H$162:$H$252) -> 84992.13 | Q66: =IF(F66="D",(L66-M66+O66-P66),0) -> 2985576.4 | R66: =IF(F66="K",(-L66+M66-O66+P66),0) -> 0 | T66: =SUMIF('MUTASI 2026'!$B$254:$B$356,'WS Trial balance'!$D66,'MUTASI 2026'!$G$254:$G$356) -> 1565556.3 | U66: =SUMIF('MUTASI 2026'!$B$254:$B$356,'WS Trial balance'!$D66,'MUTASI 2026'!$H$254:$H$356) -> 23773.58 | V66: =IF(F66="D",(Q66-R66+T66-U66),0) -> 4527359.1 | W66: =IF(F66="K",(-Q66+R66-T66+U66),0) -> 0 | Y66: =SUMIF('MUTASI 2026'!$B$358:$B$480,'WS Trial balance'!$D66,'MUTASI 2026'!$G$358:$G$480) -> 1565675.1 | Z66: =SUMIF('MUTASI 2026'!$B$358:$B$480,'WS Trial balance'!$D66,'MUTASI 2026'!$H$358:$H$480) -> 38869.06 | AA66: =IF(F66="D",(V66-W66+Y66-Z66),0) -> 6054165.1 | AB66: =IF(F66="K",(-V66+W66-Y66+Z66),0) -> 0 | AD66: =SUMIF('MUTASI 2026'!$B$482:$B$655,'WS Trial balance'!$D66,'MUTASI 2026'!$G$482:$G$655) -> 1567416.5 | AE66: =SUMIF('MUTASI 2026'!$B$482:$B$655,'WS Trial balance'!$D66,'MUTASI 2026'!$H$482:$H$655) -> 33081.63 | AF66: =IF(F66="D",(AA66-AB66+AD66-AE66),0) -> 7588500 | AG66: =IF(F66="K",(-AA66+AB66-AD66+AE66),0) -> 0 | AI66: =SUMIF('MUTASI 2026'!$B$657:$B$748,'WS Trial balance'!$D66,'MUTASI 2026'!$G$657:$G$748) -> 1559130.7 | AJ66: =SUMIF('MUTASI 2026'!$B$657:$B$748,'WS Trial balance'!$D66,'MUTASI 2026'!$H$657:$H$748) -> 6152.63 | AK66: =IF(F66="D",(AF66-AG66+AI66-AJ66),0) -> 9141478.1 | AL66: =IF(F66="K",(-AF66+AG66-AI66+AJ66),0) -> 0 | AN66: =SUMIF('MUTASI 2026'!$B$750:$B$851,'WS Trial balance'!$D66,'MUTASI 2026'!$G$750:$G$851) -> 1557636.8 | AO66: =SUMIF('MUTASI 2026'!$B$750:$B$851,'WS Trial balance'!$D66,'MUTASI 2026'!$H$750:$H$851) -> 13181.61 | AP66: =IF(F66="D",(AK66-AL66+AN66-AO66),0) -> 10685933 | AQ66: =IF(F66="K",(-AK66+AL66-AN66+AO66),0) -> 0 | AS66: =SUMIF('MUTASI 2026'!$B$853:$B$945,'WS Trial balance'!$D66,'MUTASI 2026'!$G$853:$G$945) -> 1561382.5 | AT66: =SUMIF('MUTASI 2026'!$B$853:$B$945,'WS Trial balance'!$D66,'MUTASI 2026'!$H$853:$H$945) -> 31909.74 | AU66: =IF(F66="D",(AP66-AQ66+AS66-AT66),0) -> 12215406 | AV66: =IF(F66="K",(-AP66+AQ66-AS66+AT66),0) -> 0 | AX66: =SUMIF('MUTASI 2026'!$B$1274:$B$1379,'WS Trial balance'!$D66,'MUTASI 2026'!$G$1274:$G$1379) -> 0 | AY66: =SUMIF('MUTASI 2026'!$B$1274:$B$1379,'WS Trial balance'!$D66,'MUTASI 2026'!$H$1274:$H$1379) -> 0 | AZ66: =IF(F66="D",(AU66-AV66+AX66-AY66),0) -> 12215406 | BA66: =IF(F66="K",(-AU66+AV66-AX66+AY66),0) -> 0 | BC66: =SUMIF('MUTASI 2026'!$B$1382:$B$1477,'WS Trial balance'!$D66,'MUTASI 2026'!$G$1382:$G$1477) -> 0 | BD66: =SUMIF('MUTASI 2026'!$B$1382:$B$1477,'WS Trial balance'!$D66,'MUTASI 2026'!$H$1382:$H$1477) -> 0 | BE66: =IF(F66="D",(AZ66-BA66+BC66-BD66),0) -> 12215406 | BF66: =IF(F66="K",(-AZ66+BA66-BC66+BD66),0) -> 0 | BH66: =SUMIF('MUTASI 2026'!$B$1480:$B$1600,'WS Trial balance'!$D66,'MUTASI 2026'!$G$1480:$G$1600) -> 0 | BI66: =SUMIF('MUTASI 2026'!$B$1480:$B$1600,'WS Trial balance'!$D66,'MUTASI 2026'!$H$1480:$H$1600) -> 0 | BJ66: =IF(F66="D",(BE66-BF66+BH66-BI66),0) -> 12215406 | BK66: =IF(F66="K",(-BE66+BF66-BH66+BI66),0) -> 0 | BM66: =SUMIF('MUTASI 2026'!$B$1603:$B$1722,'WS Trial balance'!$D66,'MUTASI 2026'!$G$1603:$G$1722) -> 0 | BN66: =SUMIF('MUTASI 2026'!$B$1603:$B$1722,'WS Trial balance'!$D66,'MUTASI 2026'!$H$1603:$H$1722) -> 0 | BO66: =IF(F66="D",(BJ66-BK66+BM66-BN66),0) -> 12215406 | BP66: =IF(F66="K",(-BJ66+BK66-BM66+BN66),0) -> 0 | BT66: =G66 -> 0 | BU66: =H66 -> 0 | BW66: =J66+O66+T66+Y66+AD66+AI66+AN66+AS66+AX66+BC66+BH66+BM66 -> 12528791 | BX66: =K66+P66+U66+Z66+AE66+AJ66+AO66+AT66+AY66+BD66+BI66+BN66 -> 313384.5 | BZ66: =IF(F66="D",(BT66-BU66+BW66-BX66),0) -> 12215406 | CA66: =IF(F66="K",(-BT66+BU66-BW66+BX66),0) -> 0
D67: LR08 | E67: BEBAN PAJAK PENGHASILAN | F67: D | G67: 0 | H67: 0 | J67: =SUMIF('MUTASI 2026'!$B$5:$B$160,'WS Trial balance'!$D67,'MUTASI 2026'!$G$5:$G$160) -> 0 | K67: =SUMIF('MUTASI 2026'!$B$5:$B$160,'WS Trial balance'!$D67,'MUTASI 2026'!$H$5:$H$160) -> 0 | L67: =IF(F67="D",(G67-H67+J67-K67),0) -> 0 | M67: =IF(F67="K",(-G67+H67-J67+K67),0) -> 0 | O67: =SUMIF('MUTASI 2026'!$B$162:$B$252,'WS Trial balance'!$D67,'MUTASI 2026'!$G$162:$G$252) -> 0 | P67: =SUMIF('MUTASI 2026'!$B$162:$B$252,'WS Trial balance'!$D67,'MUTASI 2026'!$H$162:$H$252) -> 0 | Q67: =IF(F67="D",(L67-M67+O67-P67),0) -> 0 | R67: =IF(F67="K",(-L67+M67-O67+P67),0) -> 0 | T67: =SUMIF('MUTASI 2026'!$B$254:$B$356,'WS Trial balance'!$D67,'MUTASI 2026'!$G$254:$G$356) -> 0 | U67: =SUMIF('MUTASI 2026'!$B$254:$B$356,'WS Trial balance'!$D67,'MUTASI 2026'!$H$254:$H$356) -> 0 | V67: =IF(F67="D",(Q67-R67+T67-U67),0) -> 0 | W67: =IF(F67="K",(-Q67+R67-T67+U67),0) -> 0 | Y67: =SUMIF('MUTASI 2026'!$B$358:$B$480,'WS Trial balance'!$D67,'MUTASI 2026'!$G$358:$G$480) -> 0 | Z67: =SUMIF('MUTASI 2026'!$B$358:$B$480,'WS Trial balance'!$D67,'MUTASI 2026'!$H$358:$H$480) -> 0 | AA67: =IF(F67="D",(V67-W67+Y67-Z67),0) -> 0 | AB67: =IF(F67="K",(-V67+W67-Y67+Z67),0) -> 0 | AD67: =SUMIF('MUTASI 2026'!$B$482:$B$655,'WS Trial balance'!$D67,'MUTASI 2026'!$G$482:$G$655) -> 0 | AE67: =SUMIF('MUTASI 2026'!$B$482:$B$655,'WS Trial balance'!$D67,'MUTASI 2026'!$H$482:$H$655) -> 0 | AF67: =IF(F67="D",(AA67-AB67+AD67-AE67),0) -> 0 | AG67: =IF(F67="K",(-AA67+AB67-AD67+AE67),0) -> 0 | AI67: =SUMIF('MUTASI 2026'!$B$657:$B$748,'WS Trial balance'!$D67,'MUTASI 2026'!$G$657:$G$748) -> 0 | AJ67: =SUMIF('MUTASI 2026'!$B$657:$B$748,'WS Trial balance'!$D67,'MUTASI 2026'!$H$657:$H$748) -> 0 | AK67: =IF(F67="D",(AF67-AG67+AI67-AJ67),0) -> 0 | AL67: =IF(F67="K",(-AF67+AG67-AI67+AJ67),0) -> 0 | AN67: =SUMIF('MUTASI 2026'!$B$750:$B$851,'WS Trial balance'!$D67,'MUTASI 2026'!$G$750:$G$851) -> 0 | AO67: =SUMIF('MUTASI 2026'!$B$750:$B$851,'WS Trial balance'!$D67,'MUTASI 2026'!$H$750:$H$851) -> 0 | AP67: =IF(F67="D",(AK67-AL67+AN67-AO67),0) -> 0 | AQ67: =IF(F67="K",(-AK67+AL67-AN67+AO67),0) -> 0 | AS67: =SUMIF('MUTASI 2026'!$B$853:$B$945,'WS Trial balance'!$D67,'MUTASI 2026'!$G$853:$G$945) -> 0 | AT67: =SUMIF('MUTASI 2026'!$B$853:$B$945,'WS Trial balance'!$D67,'MUTASI 2026'!$H$853:$H$945) -> 0 | AU67: =IF(F67="D",(AP67-AQ67+AS67-AT67),0) -> 0 | AV67: =IF(F67="K",(-AP67+AQ67-AS67+AT67),0) -> 0 | AX67: =SUMIF('MUTASI 2026'!$B$1274:$B$1379,'WS Trial balance'!$D67,'MUTASI 2026'!$G$1274:$G$1379) -> 0 | AY67: =SUMIF('MUTASI 2026'!$B$1274:$B$1379,'WS Trial balance'!$D67,'MUTASI 2026'!$H$1274:$H$1379) -> 0 | AZ67: =IF(F67="D",(AU67-AV67+AX67-AY67),0) -> 0 | BA67: =IF(F67="K",(-AU67+AV67-AX67+AY67),0) -> 0 | BC67: =SUMIF('MUTASI 2026'!$B$1382:$B$1477,'WS Trial balance'!$D67,'MUTASI 2026'!$G$1382:$G$1477) -> 0 | BD67: =SUMIF('MUTASI 2026'!$B$1382:$B$1477,'WS Trial balance'!$D67,'MUTASI 2026'!$H$1382:$H$1477) -> 0 | BE67: =IF(F67="D",(AZ67-BA67+BC67-BD67),0) -> 0 | BF67: =IF(F67="K",(-AZ67+BA67-BC67+BD67),0) -> 0 | BH67: =SUMIF('MUTASI 2026'!$B$1480:$B$1600,'WS Trial balance'!$D67,'MUTASI 2026'!$G$1480:$G$1600) -> 0 | BI67: =SUMIF('MUTASI 2026'!$B$1480:$B$1600,'WS Trial balance'!$D67,'MUTASI 2026'!$H$1480:$H$1600) -> 0 | BJ67: =IF(F67="D",(BE67-BF67+BH67-BI67),0) -> 0 | BK67: =IF(F67="K",(-BE67+BF67-BH67+BI67),0) -> 0 | BM67: =SUMIF('MUTASI 2026'!$B$1603:$B$1722,'WS Trial balance'!$D67,'MUTASI 2026'!$G$1603:$G$1722) -> 0 | BN67: =SUMIF('MUTASI 2026'!$B$1603:$B$1722,'WS Trial balance'!$D67,'MUTASI 2026'!$H$1603:$H$1722) -> 0 | BO67: =IF(F67="D",(BJ67-BK67+BM67-BN67),0) -> 0 | BP67: =IF(F67="K",(-BJ67+BK67-BM67+BN67),0) -> 0 | BT67: =G67 -> 0 | BU67: =H67 -> 0 | BW67: =J67+O67+T67+Y67+AD67+AI67+AN67+AS67+AX67+BC67+BH67+BM67 -> 0 | BX67: =K67+P67+U67+Z67+AE67+AJ67+AO67+AT67+AY67+BD67+BI67+BN67 -> 0 | BZ67: =IF(F67="D",(BT67-BU67+BW67-BX67),0) -> 0 | CA67: =IF(F67="K",(-BT67+BU67-BW67+BX67),0) -> 0
G69: =SUM(G58:G68) -> 0 | H69: =SUM(H58:H68) -> 0 | J69: =SUM(J58:J68) -> 62754954 | K69: =SUM(K58:K68) -> 83246129 | L69: =SUM(L58:L68) -> 62673530 | M69: =SUM(M58:M68) -> 83164705 | O69: =SUM(O58:O68) -> 64183649 | P69: =SUM(P58:P68) -> 82064725 | Q69: =SUM(Q58:Q68) -> 1.2677219e+08 | R69: =SUM(R58:R68) -> 1.6514444e+08 | T69: =SUM(T58:T68) -> 92479362 | U69: =SUM(U58:U68) -> 82402603 | V69: =SUM(V58:V68) -> 2.1913528e+08 | W69: =SUM(W58:W68) -> 2.4743077e+08 | Y69: =SUM(Y58:Y68) -> 62217481 | Z69: =SUM(Z58:Z68) -> 79738810 | AA69: =SUM(AA58:AA68) -> 2.8131389e+08 | AB69: =SUM(AB58:AB68) -> 3.2713071e+08 | AD69: =SUM(AD58:AD68) -> 1.0667904e+08 | AE69: =SUM(AE58:AE68) -> 84952745 | AF69: =SUM(AF58:AF68) -> 3.8795985e+08 | AG69: =SUM(AG58:AG68) -> 4.1205037e+08 | AI69: =SUM(AI58:AI68) -> 68703992 | AJ69: =SUM(AJ58:AJ68) -> 84158316 | AK69: =SUM(AK58:AK68) -> 4.5665769e+08 | AL69: =SUM(AL58:AL68) -> 4.9620254e+08 | AN69: =SUM(AN58:AN68) -> 67805831 | AO69: =SUM(AO58:AO68) -> 85534678 | AP69: =SUM(AP58:AP68) -> 5.2445034e+08 | AQ69: =SUM(AQ58:AQ68) -> 5.8172403e+08 | AS69: =SUM(AS58:AS68) -> 68589577 | AT69: =SUM(AT58:AT68) -> 85763406 | AU69: =SUM(AU58:AU68) -> 5.9300801e+08 | AV69: =SUM(AV58:AV68) -> 6.6745553e+08 | AX69: =SUM(AX58:AX68) -> 0 | AY69: =SUM(AY58:AY68) -> 0 | AZ69: =SUM(AZ58:AZ68) -> 5.9300801e+08 | BA69: =SUM(BA58:BA68) -> 6.6745553e+08 | BC69: =SUM(BC58:BC68) -> 0 | BD69: =SUM(BD58:BD68) -> 0 | BE69: =SUM(BE58:BE68) -> 5.9300801e+08 | BF69: =SUM(BF58:BF68) -> 6.6745553e+08 | BH69: =SUM(BH58:BH68) -> 0 | BI69: =SUM(BI58:BI68) -> 0 | BJ69: =SUM(BJ58:BJ68) -> 5.9300801e+08 | BK69: =SUM(BK58:BK68) -> 6.6745553e+08 | BM69: =SUM(BM58:BM68) -> 0 | BN69: =SUM(BN58:BN68) -> 0 | BO69: =SUM(BO58:BO68) -> 5.9300801e+08 | BP69: =SUM(BP58:BP68) -> 6.6745553e+08 | BT69: =SUM(BT58:BT68) -> 0 | BU69: =SUM(BU58:BU68) -> 0 | BW69: =SUM(BW58:BW68) -> 5.9341389e+08 | BX69: =SUM(BX58:BX68) -> 6.6786141e+08 | BZ69: =SUM(BZ58:BZ68) -> 5.9300801e+08 | CA69: =SUM(CA58:CA68) -> 6.6745553e+08
E70: LABA (RUGI) | G70: =H69-G69 -> 0 | J70: =K51 -> 20491175 | L70: =M69-L69 -> 20491175 | O70: =P51 -> 17881076 | Q70: =R69-Q69 -> 38372251 | T70: =U51 -> -10076758 | V70: =W69-V69 -> 28295492 | Y70: =Z51 -> 17521329 | AA70: =AB69-AA69 -> 45816822 | AD70: =AE51 -> -21726299 | AF70: =AG69-AF69 -> 24090522 | AI70: =AJ51 -> 15454324 | AK70: =AL69-AK69 -> 39544846 | AN70: =AO51 -> 17728847 | AP70: =AQ69-AP69 -> 57273693 | AS70: =AT51 -> 17173829 | AU70: =AV69-AU69 -> 74447522 | AX70: =AY51 -> 0 | AZ70: =BA69-AZ69 -> 74447522 | BC70: =BD51 -> 0 | BE70: =BF69-BE69 -> 74447522 | BH70: =BI51 -> 0 | BJ70: =BK69-BJ69 -> 74447522 | BM70: =BN51 -> 0 | BO70: =BP69-BO69 -> 74447522 | BT70: =BU69-BT69 -> 0 | BW70: =BX51 -> 74447522 | BZ70: =CA69-BZ69 -> 74447522
E71: JUMLAH | G71: =G69+G70 -> 0 | H71: =H69+H70 -> 0 | J71: =J69+J70 -> 83246129 | K71: =K69+K70 -> 83246129 | L71: =L69+L70 -> 83164705 | M71: =M69+M70 -> 83164705 | O71: =O69+O70 -> 82064725 | P71: =P69+P70 -> 82064725 | Q71: =Q69+Q70 -> 1.6514444e+08 | R71: =R69+R70 -> 1.6514444e+08 | T71: =T69+T70 -> 82402603 | U71: =U69+U70 -> 82402603 | V71: =V69+V70 -> 2.4743077e+08 | W71: =W69+W70 -> 2.4743077e+08 | Y71: =Y69+Y70 -> 79738810 | Z71: =Z69+Z70 -> 79738810 | AA71: =AA69+AA70 -> 3.2713071e+08 | AB71: =AB69+AB70 -> 3.2713071e+08 | AD71: =AD69+AD70 -> 84952745 | AE71: =AE69+AE70 -> 84952745 | AF71: =AF69+AF70 -> 4.1205037e+08 | AG71: =AG69+AG70 -> 4.1205037e+08 | AI71: =AI69+AI70 -> 84158316 | AJ71: =AJ69+AJ70 -> 84158316 | AK71: =AK69+AK70 -> 4.9620254e+08 | AL71: =AL69+AL70 -> 4.9620254e+08 | AN71: =AN69+AN70 -> 85534678 | AO71: =AO69+AO70 -> 85534678 | AP71: =AP69+AP70 -> 5.8172403e+08 | AQ71: =AQ69+AQ70 -> 5.8172403e+08 | AS71: =AS69+AS70 -> 85763406 | AT71: =AT69+AT70 -> 85763406 | AU71: =AU69+AU70 -> 6.6745553e+08 | AV71: =AV69+AV70 -> 6.6745553e+08 | AX71: =AX69+AX70 -> 0 | AY71: =AY69+AY70 -> 0 | AZ71: =AZ69+AZ70 -> 6.6745553e+08 | BA71: =BA69+BA70 -> 6.6745553e+08 | BC71: =BC69+BC70 -> 0 | BD71: =BD69+BD70 -> 0 | BE71: =BE69+BE70 -> 6.6745553e+08 | BF71: =BF69+BF70 -> 6.6745553e+08 | BH71: =BH69+BH70 -> 0 | BI71: =BI69+BI70 -> 0 | BJ71: =BJ69+BJ70 -> 6.6745553e+08 | BK71: =BK69+BK70 -> 6.6745553e+08 | BM71: =BM69+BM70 -> 0 | BN71: =BN69+BN70 -> 0 | BO71: =BO69+BO70 -> 6.6745553e+08 | BP71: =BP69+BP70 -> 6.6745553e+08 | BT71: =BT69+BT70 -> 0 | BU71: =BU69+BU70 -> 0 | BW71: =BW69+BW70 -> 6.6786141e+08 | BX71: =BX69+BX70 -> 6.6786141e+08 | BZ71: =BZ69+BZ70 -> 6.6745553e+08 | CA71: =CA69+CA70 -> 6.6745553e+08
E72: BALANCE | K72: =J71-K71 -> -1.1920929e-07 | L72: =L71-M71 -> 0 | M72: =L50-(M50+M51) -> 0 | P72: =O71-P71 -> 0 | Q72: =Q71-R71 -> 0 | R72: =Q50-(R50+R51) -> 0 | U72: =T71-U71 -> 0 | V72: =V71-W71 -> 0 | W72: =V50-(W50+W51) -> 0 | Z72: =Y71-Z71 -> 0 | AA72: =AA71-AB71 -> 0 | AB72: =AA50-(AB50+AB51) -> 0 | AE72: =AD71-AE71 -> 0 | AF72: =AF71-AG71 -> 0 | AG72: =AF50-(AG50+AG51) -> 0 | AJ72: =AI71-AJ71 -> 0 | AK72: =AK71-AL71 -> 0 | AL72: =AK50-(AL50+AL51) -> 0 | AO72: =AN71-AO71 -> 0 | AP72: =AP71-AQ71 -> 0 | AQ72: =AP50-(AQ50+AQ51) -> 0 | AT72: =AS71-AT71 -> 0 | AU72: =AU71-AV71 -> 0 | AV72: =AU50-(AV50+AV51) -> 0 | AY72: =AX71-AY71 -> 0 | AZ72: =AZ71-BA71 -> 0 | BA72: =AZ50-(BA50+BA51) -> 0 | BD72: =BC71-BD71 -> 0 | BE72: =BE71-BF71 -> 0 | BF72: =BE50-(BF50+BF51) -> 0 | BI72: =BH71-BI71 -> 0 | BJ72: =BJ71-BK71 -> 0 | BK72: =BJ50-(BK50+BK51) -> 0 | BN72: =BM71-BN71 -> 0 | BO72: =BO71-BP71 -> 0 | BP72: =BO50-(BP50+BP51) -> 0 | BX72: =BW71-BX71 -> 0 | BZ72: =BZ71-CA71 -> 0 | CA72: =BZ50-(CA50+CA51) -> 0
M75: =+M58-L61 -> 18301844 | R75: =+R58-Q61 -> 36649660 | W75: =+W58-V61 -> 55407684 | AB75: =+AB58-AA61 -> 73464319 | AG75: =+AG58-AF61 -> 91858455 | AL75: =+AL58-AK61 -> 1.1068926e+08 | AQ75: =+AQ58-AP61 -> 1.2987756e+08 | AV75: =+AV58-AU61 -> 1.4906586e+08 | BA75: =+BA58-AZ61 -> 1.4906586e+08 | BF75: =+BF58-BE61 -> 1.4906586e+08 | BK75: =+BK58-BJ61 -> 1.4906586e+08 | BP75: =+BP58-BO61 -> 1.4906586e+08
R76: =+R75-M75 -> 18347816 | W76: =+W75-R75 -> 18758024 | AB76: =+AB75-W75 -> 18056635 | AG76: =+AG75-AB75 -> 18394135 | AL76: =+AL75-AG75 -> 18830802 | AQ76: =+AQ75-AL75 -> 19188302 | AV76: =+AV75-AQ75 -> 19188302 | BA76: =+BA75-AV75 -> 0 | BF76: =+BF75-BA75 -> 0 | BK76: =+BK75-BF75 -> 0 | BP76: =+BP75-BK75 -> 0

Sheet MUTASI 2026
G1: =SUBTOTAL(9,G5:G1048576) -> 4.0900118e+09 | H1: =SUBTOTAL(9,H5:H1048576) -> 4.0900118e+09 | I1: =SUBTOTAL(9,I5:I1048576) -> 0 | J1: =+I1/I8 -> 0
I2: =-I1 -> 0
B4: Report_NR | C4: periode | D4: N.BUKTI | E4: TANGGAL | F4: ACCOUNT | G4: JMLDEB | H4: JMLKRED | I4: AMOUNT | J4: QTY | K4: SOURCE | L4: KETERANGAN | M4: Nama_Rekanan
B5: =VLOOKUP(F5,BB!$A$8:$C$152,3,0) -> A02 | C5: 202601 | D5: MDR-2601001 | E5: 46027 | F5: 02.001.0000 | G5: 0 | H5: 11608500 | I5: =IF(G5<>0,G5,-H5) -> -11608500 | J5: 0 | K5: BANK KELUAR | L5: PEMBAYARAN KE ORIX SEWA BULAN KE 42 (DES)
B6: =VLOOKUP(F6,BB!$A$8:$C$152,3,0) -> P05 | C6: =+C5 -> 202601 | D6: =+D5 -> MDR-2601001 | E6: =+E5 -> 46027 | F6: 34.000.0003 | G6: =H5 -> 11608500 | H6: 0 | I6: =IF(G6<>0,G6,-H6) -> 11608500 | J6: 0 | K6: BANK KELUAR | L6: =+L5 -> PEMBAYARAN KE ORIX SEWA BULAN KE 42 (DES)
B8: =VLOOKUP(F8,BB!$A$8:$C$152,3,0) -> A02 | C8: 202601 | D8: MDR-2601002 | E8: 46027 | F8: 02.001.0000 | G8: 0 | H8: 20000000 | I8: =IF(G8<>0,G8,-H8) -> -20000000 | J8: 0 | K8: BANK KELUAR | L8: PINJAMAN RUTIN SAFI'I, 12X
B9: =VLOOKUP(F9,BB!$A$8:$C$152,3,0) -> A04A | C9: =C8 -> 202601 | D9: =D8 -> MDR-2601002 | E9: =E8 -> 46027 | F9: 04.001.0001 | G9: =+H8 -> 20000000 | H9: 0 | I9: =IF(G9<>0,G9,-H9) -> 20000000 | J9: =-J8 -> 0 | K9: =K8 -> BANK KELUAR | L9: =L8 -> PINJAMAN RUTIN SAFI'I, 12X
B11: =VLOOKUP(F11,BB!$A$8:$C$152,3,0) -> A02 | C11: 202601 | D11: MDR-2601003 | E11: 46027 | F11: 02.001.0000 | G11: 0 | H11: 2900 | I11: =IF(G11<>0,G11,-H11) -> -2900 | J11: 0 | K11: BANK KELUAR | L11: CLEARING FEE
B12: =VLOOKUP(F12,BB!$A$8:$C$152,3,0) -> LR07 | C12: =+C11 -> 202601 | D12: =+D11 -> MDR-2601003 | E12: =+E11 -> 46027 | F12: 71.000.0300 | G12: =+H11 -> 2900 | H12: 0 | I12: =IF(G12<>0,G12,-H12) -> 2900 | J12: 0 | K12: BANK KELUAR | L12: =+L11 -> CLEARING FEE
B14: =VLOOKUP(F14,BB!$A$8:$C$152,3,0) -> A02 | C14: 202601 | D14: MDR-2601004 | E14: 46027 | F14: 02.001.0000 | G14: 0 | H14: 13333333 | I14: =IF(G14<>0,G14,-H14) -> -13333333 | J14: 0 | K14: BANK KELUAR | L14: PINJAMAN RUTIN SOLICHIN, 36X, KOMPENSASI
B15: =VLOOKUP(F15,BB!$A$8:$C$152,3,0) -> A04A | C15: =C14 -> 202601 | D15: =D14 -> MDR-2601004 | E15: =E14 -> 46027 | F15: 04.001.0001 | G15: 50000000 | H15: 0 | I15: =IF(G15<>0,G15,-H15) -> 50000000 | J15: =-J14 -> 0 | K15: =K14 -> BANK KELUAR | L15: =L14 -> PINJAMAN RUTIN SOLICHIN, 36X, KOMPENSASI
B16: =VLOOKUP(F16,BB!$A$8:$C$152,3,0) -> A04A | C16: =C15 -> 202601 | D16: =D15 -> MDR-2601004 | E16: =E15 -> 46027 | F16: 04.001.0001 | G16: 0 | H16: =G15-H14 -> 36666667 | I16: =IF(G16<>0,G16,-H16) -> -36666667 | J16: =-J15 -> 0 | K16: =K15 -> BANK KELUAR | L16: =L15 -> PINJAMAN RUTIN SOLICHIN, 36X, KOMPENSASI
B18: =VLOOKUP(F18,BB!$A$8:$C$152,3,0) -> A02 | C18: 202601 | D18: MDR-2601005 | E18: 46029 | F18: 02.001.0000 | G18: 15680000 | H18: 0 | I18: =IF(G18<>0,G18,-H18) -> 15680000 | J18: 0 | K18: BANK MASUK | L18: TERIMA DARI GCS SEWA FORKLIFT PERIODE 202511
B19: =VLOOKUP(F19,BB!$A$8:$C$152,3,0) -> A04B | C19: =C18 -> 202601 | D19: =D18 -> MDR-2601005 | E19: =E18 -> 46029 | F19: 04.002.0006 | G19: 0 | H19: =+G18 -> 15680000 | I19: =IF(G19<>0,G19,-H19) -> -15680000 | J19: 0 | K19: =K18 -> BANK MASUK | L19: =L18 -> TERIMA DARI GCS SEWA FORKLIFT PERIODE 202511
B21: =VLOOKUP(F21,BB!$A$8:$C$152,3,0) -> A02 | C21: 202601 | D21: MDR-2601006 | E21: 46031 | F21: 02.001.0000 | G21: 0 | H21: 20000000 | I21: =IF(G21<>0,G21,-H21) -> -20000000 | J21: 0 | K21: BANK KELUAR | L21: PINJAMAN RUTIN JOKO P, 24X
B22: =VLOOKUP(F22,BB!$A$8:$C$152,3,0) -> A04A | C22: =C21 -> 202601 | D22: =D21 -> MDR-2601006 | E22: =E21 -> 46031 | F22: 04.001.0001 | G22: =+H21 -> 20000000 | H22: 0 | I22: =IF(G22<>0,G22,-H22) -> 20000000 | J22: =-J21 -> 0 | K22: =K21 -> BANK KELUAR | L22: =L21 -> PINJAMAN RUTIN JOKO P, 24X
B24: =VLOOKUP(F24,BB!$A$8:$C$152,3,0) -> A02 | C24: 202601 | D24: MDR-2601007 | E24: 46035 | F24: 02.001.0000 | G24: 0 | H24: 14475000 | I24: =IF(G24<>0,G24,-H24) -> -14475000 | J24: 0 | K24: BANK KELUAR | L24: PEMBAYARAN JASA FORKLIFT ACHMAD LUTHFIE PERIODE 202511
B25: =VLOOKUP(F25,BB!$A$8:$C$152,3,0) -> P05 | C25: =C24 -> 202601 | D25: =D24 -> MDR-2601007 | E25: =E24 -> 46035 | F25: 34.000.0001 | G25: =H24 -> 14475000 | H25: =G24 -> 0 | I25: =IF(G25<>0,G25,-H25) -> 14475000 | J25: =-J24 -> 0 | K25: =K24 -> BANK KELUAR | L25: =L24 -> PEMBAYARAN JASA FORKLIFT ACHMAD LUTHFIE PERIODE 202511
B27: =VLOOKUP(F27,BB!$A$8:$C$152,3,0) -> A02 | C27: 202601 | D27: MDR-2601008 | E27: 46037 | F27: 02.001.0000 | G27: 0 | H27: 13333333 | I27: =IF(G27<>0,G27,-H27) -> -13333333 | J27: 0 | K27: BANK KELUAR | L27: PINJAMAN RUTIN SUGENG H, 36X, KOMPENSASI
B28: =VLOOKUP(F28,BB!$A$8:$C$152,3,0) -> A04A | C28: =C27 -> 202601 | D28: =D27 -> MDR-2601008 | E28: =E27 -> 46037 | F28: 04.001.0001 | G28: 30000000 | H28: 0 | I28: =IF(G28<>0,G28,-H28) -> 30000000 | J28: =-J27 -> 0 | K28: =K27 -> BANK KELUAR | L28: =L27 -> PINJAMAN RUTIN SUGENG H, 36X, KOMPENSASI
B29: =VLOOKUP(F29,BB!$A$8:$C$152,3,0) -> A04A | C29: =C28 -> 202601 | D29: =D28 -> MDR-2601008 | E29: =E28 -> 46037 | F29: 04.001.0001 | G29: 0 | H29: =G28-H27 -> 16666667 | I29: =IF(G29<>0,G29,-H29) -> -16666667 | J29: =-J28 -> 0 | K29: =K28 -> BANK KELUAR | L29: =L28 -> PINJAMAN RUTIN SUGENG H, 36X, KOMPENSASI
B31: =VLOOKUP(F31,BB!$A$8:$C$152,3,0) -> A02 | C31: 202601 | D31: MDR-2601009 | E31: 46043 | F31: 02.001.0000 | G31: 0 | H31: 8333333 | I31: =IF(G31<>0,G31,-H31) -> -8333333 | J31: 0 | K31: BANK KELUAR | L31: PINJAMAN RUTIN WIDYA NS, 60X, KOMPENSASI
B32: =VLOOKUP(F32,BB!$A$8:$C$152,3,0) -> A04A | C32: =C31 -> 202601 | D32: =D31 -> MDR-2601009 | E32: =E31 -> 46043 | F32: 04.001.0001 | G32: 50000000 | H32: 0 | I32: =IF(G32<>0,G32,-H32) -> 50000000 | J32: =-J31 -> 0 | K32: =K31 -> BANK KELUAR | L32: =L31 -> PINJAMAN RUTIN WIDYA NS, 60X, KOMPENSASI
B33: =VLOOKUP(F33,BB!$A$8:$C$152,3,0) -> A04A | C33: =C32 -> 202601 | D33: =D32 -> MDR-2601009 | E33: =E32 -> 46043 | F33: 04.001.0001 | G33: 0 | H33: =G32-H31 -> 41666667 | I33: =IF(G33<>0,G33,-H33) -> -41666667 | J33: =-J32 -> 0 | K33: =K32 -> BANK KELUAR | L33: =L32 -> PINJAMAN RUTIN WIDYA NS, 60X, KOMPENSASI
B35: =VLOOKUP(F35,BB!$A$8:$C$152,3,0) -> A02 | C35: 202601 | D35: MDR-2601010 | E35: 46045 | F35: 02.001.0000 | G35: 82521704 | H35: 0 | I35: =IF(G35<>0,G35,-H35) -> 82521704 | J35: 0 | K35: BANK MASUK | L35: TERIMA DARI GCS POTONGAN GAJI BULAN JANUARI 2026
B36: =VLOOKUP(F36,BB!$A$8:$C$152,3,0) -> A04A | C36: =C35 -> 202601 | D36: =D35 -> MDR-2601010 | E36: =E35 -> 46045 | F36: 04.001.0001 | G36: 0 | H36: 60419861 | I36: =IF(G36<>0,G36,-H36) -> -60419861 | J36: =-J35 -> 0 | K36: =K35 -> BANK MASUK | L36: ="ANGSURAN PIRUT DARI "&MID(L35,17,50) -> ANGSURAN PIRUT DARI POTONGAN GAJI BULAN JANUARI 2026
B37: =VLOOKUP(F37,BB!$A$8:$C$152,3,0) -> P12 | C37: =C36 -> 202601 | D37: =D36 -> MDR-2601010 | E37: =E36 -> 46045 | F37: 42.000.0000 | G37: 0 | H37: 3800000 | I37: =IF(G37<>0,G37,-H37) -> -3800000 | J37: =-J36 -> 0 | K37: =K36 -> BANK MASUK | L37: PENERIMAAN SIMPANAN WAJIB ANGGOTA
B38: =VLOOKUP(F38,BB!$A$8:$C$152,3,0) -> LR01A | C38: =C37 -> 202601 | D38: =D37 -> MDR-2601010 | E38: =E37 -> 46045 | F38: 50.001.0000 | G38: 0 | H38: 78721705 | I38: =IF(G38<>0,G38,-H38) -> -78721705 | J38: =-J37 -> 0 | K38: =K37 -> BANK MASUK | L38: ="PENDAPATAN PIRUT "&MID(L35,31,50) -> PENDAPATAN PIRUT BULAN JANUARI 2026
B39: =VLOOKUP(F39,BB!$A$8:$C$152,3,0) -> LR02A | C39: =C38 -> 202601 | D39: =D38 -> MDR-2601010 | E39: =E38 -> 46045 | F39: 51.001.0000 | G39: =H36 -> 60419861 | H39: 0 | I39: =IF(G39<>0,G39,-H39) -> 60419861 | J39: =-J38 -> 0 | K39: =K38 -> BANK MASUK | L39: ="HPP "&MID(L38,12,50) -> HPP PIRUT BULAN JANUARI 2026
B40: =VLOOKUP(F40,BB!$A$8:$C$152,3,0) -> LR07 | C40: =C39 -> 202601 | D40: =D39 -> MDR-2601010 | E40: =E39 -> 46045 | F40: 71.000.0900 | G40: =IF(SUM(I35:I39)<0,-SUM(I35:I39),0) -> 0.86111113 | H40: =IF(SUM(I35:I39)>0,-SUM(J35:J39),0) -> 0 | I40: =IF(G40<>0,G40,-H40) -> 0.86111113 | J40: =-J39 -> 0 | K40: =K39 -> BANK MASUK | L40: SELISIH LEBIH/KURANG TRANSFER
B42: =VLOOKUP(F42,BB!$A$8:$C$152,3,0) -> A02 | C42: 202601 | D42: MDR-2601011 | E42: 46049 | F42: 02.001.0000 | G42: 0 | H42: 10000000 | I42: =IF(G42<>0,G42,-H42) -> -10000000 | J42: 0 | K42: BANK KELUAR | L42: PINJAMAN RUTIN SUMARSONO, 24X
B43: =VLOOKUP(F43,BB!$A$8:$C$152,3,0) -> A04A | C43: =C42 -> 202601 | D43: =D42 -> MDR-2601011 | E43: =E42 -> 46049 | F43: 04.001.0001 | G43: =+H42 -> 10000000 | H43: 0 | I43: =IF(G43<>0,G43,-H43) -> 10000000 | J43: =-J42 -> 0 | K43: =K42 -> BANK KELUAR | L43: =L42 -> PINJAMAN RUTIN SUMARSONO, 24X
B45: =VLOOKUP(F45,BB!$A$8:$C$152,3,0) -> A02 | C45: 202601 | D45: MDR-2601012 | E45: 46049 | F45: 02.001.0000 | G45: 0 | H45: 11608500 | I45: =IF(G45<>0,G45,-H45) -> -11608500 | J45: 0 | K45: BANK KELUAR | L45: PEMBAYARAN KE ORIX SEWA BULAN KE 43 (JAN)
B46: =VLOOKUP(F46,BB!$A$8:$C$152,3,0) -> P05 | C46: =+C45 -> 202601 | D46: =+D45 -> MDR-2601012 | E46: =+E45 -> 46049 | F46: 34.000.0003 | G46: =+H45 -> 11608500 | H46: 0 | I46: =IF(G46<>0,G46,-H46) -> 11608500 | J46: 0 | K46: BANK KELUAR | L46: =+L45 -> PEMBAYARAN KE ORIX SEWA BULAN KE 43 (JAN)
B48: =VLOOKUP(F48,BB!$A$8:$C$152,3,0) -> A02 | C48: 202601 | D48: MDR-2601013 | E48: 46049 | F48: 02.001.0000 | G48: 0 | H48: 2900 | I48: =IF(G48<>0,G48,-H48) -> -2900 | J48: 0 | K48: BANK KELUAR | L48: CLEARING FEE
B49: =VLOOKUP(F49,BB!$A$8:$C$152,3,0) -> LR07 | C49: =+C48 -> 202601 | D49: =+D48 -> MDR-2601013 | E49: =+E48 -> 46049 | F49: 71.000.0300 | G49: =+H48 -> 2900 | H49: 0 | I49: =IF(G49<>0,G49,-H49) -> 2900 | J49: 0 | K49: BANK KELUAR | L49: =+L48 -> CLEARING FEE
B51: =VLOOKUP(F51,BB!$A$8:$C$152,3,0) -> A02 | C51: 202601 | D51: MDR-2601014 | E51: 46049 | F51: 02.001.0000 | G51: 0 | H51: 27833333 | I51: =IF(G51<>0,G51,-H51) -> -27833333 | J51: 0 | K51: BANK KELUAR | L51: PINJAMAN RUTIN DARWANTO, 60X, KOMPENSASI
B52: =VLOOKUP(F52,BB!$A$8:$C$152,3,0) -> A04A | C52: =C51 -> 202601 | D52: =D51 -> MDR-2601014 | E52: =E51 -> 46049 | F52: 04.001.0001 | G52: 100000000 | H52: 0 | I52: =IF(G52<>0,G52,-H52) -> 100000000 | J52: =-J51 -> 0 | K52: =K51 -> BANK KELUAR | L52: =L51 -> PINJAMAN RUTIN DARWANTO, 60X, KOMPENSASI
B53: =VLOOKUP(F53,BB!$A$8:$C$152,3,0) -> A04A | C53: =C52 -> 202601 | D53: =D52 -> MDR-2601014 | E53: =E52 -> 46049 | F53: 04.001.0001 | G53: 0 | H53: =G52-H51 -> 72166667 | I53: =IF(G53<>0,G53,-H53) -> -72166667 | J53: =-J52 -> 0 | K53: =K52 -> BANK KELUAR | L53: =L52 -> PINJAMAN RUTIN DARWANTO, 60X, KOMPENSASI
B55: =VLOOKUP(F55,BB!$A$8:$C$152,3,0) -> A02 | C55: 202601 | D55: MDR-2601015 | E55: 46050 | F55: 02.001.0000 | G55: 15680000 | H55: 0 | I55: =IF(G55<>0,G55,-H55) -> 15680000 | J55: 0 | K55: BANK MASUK | L55: TERIMA DARI GCS SEWA FORKLIFT PERIODE 202512
B56: =VLOOKUP(F56,BB!$A$8:$C$152,3,0) -> A04B | C56: =C55 -> 202601 | D56: =D55 -> MDR-2601015 | E56: =E55 -> 46050 | F56: 04.002.0006 | G56: 0 | H56: =+G55 -> 15680000 | I56: =IF(G56<>0,G56,-H56) -> -15680000 | J56: 0 | K56: =K55 -> BANK MASUK | L56: =L55 -> TERIMA DARI GCS SEWA FORKLIFT PERIODE 202512
B58: =VLOOKUP(F58,BB!$A$8:$C$152,3,0) -> A02 | C58: 202601 | D58: MDR-2601016 | E58: 46052 | F58: 02.001.0000 | G58: 11760000 | H58: 0 | I58: =IF(G58<>0,G58,-H58) -> 11760000 | J58: 0 | K58: BANK MASUK | L58: TERIMA SEWA KENDARAAN 1 UNIT MOBIL PERIODE BLN MEI 2025
B59: =VLOOKUP(F59,BB!$A$8:$C$152,3,0) -> A04B | C59: =C58 -> 202601 | D59: =D58 -> MDR-2601016 | E59: =E58 -> 46052 | F59: 04.002.0003 | G59: =H58 -> 0 | H59: =G58 -> 11760000 | I59: =IF(G59<>0,G59,-H59) -> -11760000 | J59: =-J58 -> 0 | K59: =K58 -> BANK MASUK | L59: =L58 -> TERIMA SEWA KENDARAAN 1 UNIT MOBIL PERIODE BLN MEI 2025
B61: =VLOOKUP(F61,BB!$A$8:$C$152,3,0) -> A02 | C61: 202601 | D61: MDR-2601017 | E61: 46052 | F61: 02.001.0000 | G61: 11760000 | H61: 0 | I61: =IF(G61<>0,G61,-H61) -> 11760000 | J61: 0 | K61: BANK MASUK | L61: TERIMA SEWA KENDARAAN 1 UNIT MOBIL PERIODE BLN JUNI 2025
B62: =VLOOKUP(F62,BB!$A$8:$C$152,3,0) -> A04B | C62: =C61 -> 202601 | D62: =D61 -> MDR-2601017 | E62: =E61 -> 46052 | F62: 04.002.0003 | G62: =H61 -> 0 | H62: =G61 -> 11760000 | I62: =IF(G62<>0,G62,-H62) -> -11760000 | J62: =-J61 -> 0 | K62: =K61 -> BANK MASUK | L62: =L61 -> TERIMA SEWA KENDARAAN 1 UNIT MOBIL PERIODE BLN JUNI 2025
B64: =VLOOKUP(F64,BB!$A$8:$C$152,3,0) -> A02 | C64: 202601 | D64: MDR-2601018 | E64: 46052 | F64: 02.001.0000 | G64: 11760000 | H64: 0 | I64: =IF(G64<>0,G64,-H64) -> 11760000 | J64: 0 | K64: BANK MASUK | L64: TERIMA SEWA KENDARAAN 1 UNIT MOBIL PERIODE BLN JULI 2025
B65: =VLOOKUP(F65,BB!$A$8:$C$152,3,0) -> A04B | C65: =C64 -> 202601 | D65: =D64 -> MDR-2601018 | E65: =E64 -> 46052 | F65: 04.002.0003 | G65: =H64 -> 0 | H65: =G64 -> 11760000 | I65: =IF(G65<>0,G65,-H65) -> -11760000 | J65: =-J64 -> 0 | K65: =K64 -> BANK MASUK | L65: =L64 -> TERIMA SEWA KENDARAAN 1 UNIT MOBIL PERIODE BLN JULI 2025
B67: =VLOOKUP(F67,BB!$A$8:$C$152,3,0) -> A02 | C67: 202601 | D67: MDR-2601019 | E67: 46052 | F67: 02.001.0000 | G67: 11760000 | H67: 0 | I67: =IF(G67<>0,G67,-H67) -> 11760000 | J67: 0 | K67: BANK MASUK | L67: TERIMA SEWA KENDARAAN 1 UNIT MOBIL PERIODE BLN AGUSTUS 2025
B68: =VLOOKUP(F68,BB!$A$8:$C$152,3,0) -> A04B | C68: =C67 -> 202601 | D68: =D67 -> MDR-2601019 | E68: =E67 -> 46052 | F68: 04.002.0003 | G68: =H67 -> 0 | H68: =G67 -> 11760000 | I68: =IF(G68<>0,G68,-H68) -> -11760000 | J68: =-J67 -> 0 | K68: =K67 -> BANK MASUK | L68: =L67 -> TERIMA SEWA KENDARAAN 1 UNIT MOBIL PERIODE BLN AGUSTUS 2025
B70: =VLOOKUP(F70,BB!$A$8:$C$152,3,0) -> A02 | C70: 202601 | D70: MDR-2601020 | E70: 46053 | F70: 02.001.0000 | G70: =IF(SUM(I71:I73)<0,-SUM(I71:I73),0) -> 40139.3 | H70: =IF(SUM(I71:I73)>0,SUM(I71:I73),0) -> 0 | I70: =IF(G70<>0,G70,-H70) -> 40139.3 | J70: =-J69 -> 0 | K70: =IF(I70>0,"BANK MASUK","BANK KELUAR") -> BANK MASUK | L70: =IF(K70="BANK MASUK","PENDAPATAN ATAS REKENING GIRO MANDIRI","BIAYA ATAS REKENING GIRO MANDIRI") -> PENDAPATAN ATAS REKENING GIRO MANDIRI
B71: =VLOOKUP(F71,BB!$A$8:$C$152,3,0) -> LR07 | C71: =C70 -> 202601 | D71: =D70 -> MDR-2601020 | E71: =E70 -> 46053 | F71: 71.000.0300 | G71: 25000 | H71: 0 | I71: =IF(G71<>0,G71,-H71) -> 25000 | J71: =-J70 -> 0 | K71: =K70 -> BANK MASUK | L71: BIAYA ADMIN GIRO
B72: =VLOOKUP(F72,BB!$A$8:$C$152,3,0) -> LR07 | C72: =C71 -> 202601 | D72: =D71 -> MDR-2601020 | E72: =E71 -> 46053 | F72: 71.000.0300 | G72: 0 | H72: 81424.12 | I72: =IF(G72<>0,G72,-H72) -> -81424.12 | J72: =-J71 -> 0 | K72: =K71 -> BANK MASUK | L72: PEND. BUNGA GIRO
B73: =VLOOKUP(F73,BB!$A$8:$C$152,3,0) -> LR07 | C73: =C72 -> 202601 | D73: =D72 -> MDR-2601020 | E73: =E72 -> 46053 | F73: 71.000.0300 | G73: 16284.82 | H73: 0 | I73: =IF(G73<>0,G73,-H73) -> 16284.82 | J73: =-J72 -> 0 | K73: =K72 -> BANK MASUK | L73: BIAYA PAJAK GIRO
B75: =VLOOKUP(F75,BB!$A$8:$C$152,3,0) -> A02 | C75: 202601 | D75: BCA-2601001 | E75: 46053 | F75: 02.002.0000 | G75: 0 | H75: 30000 | I75: =IF(G75<>0,G75,-H75) -> -30000 | J75: 0 | K75: BANK KELUAR | L75: BIAYA ADMIN GIRO
B76: =VLOOKUP(F76,BB!$A$8:$C$152,3,0) -> LR07 | C76: =C75 -> 202601 | D76: =D75 -> BCA-2601001 | E76: =E75 -> 46053 | F76: 71.000.0300 | G76: 30000 | H76: 0 | I76: =IF(G76<>0,G76,-H76) -> 30000 | J76: 0 | K76: BANK KELUAR | L76: BIAYA ADMIN GIRO
B78: =VLOOKUP(F78,BB!$A$8:$C$152,3,0) -> A01 | C78: 202601 | D78: KAS-2601001 | E78: 46028 | F78: 01.001.0000 | G78: 350000 | H78: 0 | I78: =IF(G78<>0,G78,-H78) -> 350000 | J78: 0 | K78: KAS MASUK | L78: ANGSURAN PINJAMAN LAIN AN. SOLICHIN
B79: =VLOOKUP(F79,BB!$A$8:$C$152,3,0) -> A04A | C79: =C78 -> 202601 | D79: =D78 -> KAS-2601001 | E79: =E78 -> 46028 | F79: 04.001.0004 | G79: 0 | H79: =+G78 -> 350000 | I79: =IF(G79<>0,G79,-H79) -> -350000 | J79: =-J78 -> 0 | K79: =K78 -> KAS MASUK | L79: =L78 -> ANGSURAN PINJAMAN LAIN AN. SOLICHIN
B80: =VLOOKUP(F80,BB!$A$8:$C$152,3,0) -> LR01C | C80: =C79 -> 202601 | D80: =D79 -> KAS-2601001 | E80: =E79 -> 46028 | F80: 50.003.0000 | G80: 0 | H80: =G78-H79 -> 0 | I80: =IF(G80<>0,G80,-H80) -> 0 | J80: =-J79 -> 0 | K80: =K79 -> KAS MASUK | L80: ="PENDAPATAN ATAS PINJAMAN LAIN "&MID(L79,24,20) -> PENDAPATAN ATAS PINJAMAN LAIN AN. SOLICHIN
B82: =VLOOKUP(F82,BB!$A$8:$C$152,3,0) -> A01 | C82: 202601 | D82: KAS-2601002 | E82: 46031 | F82: 01.001.0000 | G82: 425000 | H82: 0 | I82: =IF(G82<>0,G82,-H82) -> 425000 | J82: 0 | K82: KAS MASUK | L82: PELUNASAN PINJAMAN LAIN AN. ARI WIBOWO
B83: =VLOOKUP(F83,BB!$A$8:$C$152,3,0) -> A04A | C83: =C82 -> 202601 | D83: =D82 -> KAS-2601002 | E83: =E82 -> 46031 | F83: 04.001.0004 | G83: 0 | H83: 250000 | I83: =IF(G83<>0,G83,-H83) -> -250000 | J83: =-J82 -> 0 | K83: =K82 -> KAS MASUK | L83: =L82 -> PELUNASAN PINJAMAN LAIN AN. ARI WIBOWO
B84: =VLOOKUP(F84,BB!$A$8:$C$152,3,0) -> LR01C | C84: =C83 -> 202601 | D84: =D83 -> KAS-2601002 | E84: =E83 -> 46031 | F84: 50.003.0000 | G84: 0 | H84: =G82-H83 -> 175000 | I84: =IF(G84<>0,G84,-H84) -> -175000 | J84: =-J83 -> 0 | K84: =K83 -> KAS MASUK | L84: ="PENDAPATAN ATAS PINJAMAN LAIN "&MID(L83,24,20) -> PENDAPATAN ATAS PINJAMAN LAIN AN. ARI WIBOWO
B86: =VLOOKUP(F86,BB!$A$8:$C$152,3,0) -> A01 | C86: 202601 | D86: KAS-2601003 | E86: 46031 | F86: 01.001.0000 | G86: 0 | H86: 2000000 | I86: =IF(G86<>0,G86,-H86) -> -2000000 | J86: 0 | K86: KAS KELUAR | L86: PINJAMAN LAIN AN. ARI WIBOWO
B87: =VLOOKUP(F87,BB!$A$8:$C$152,3,0) -> A04A | C87: =C86 -> 202601 | D87: =D86 -> KAS-2601003 | E87: =E86 -> 46031 | F87: 04.001.0004 | G87: =H86 -> 2000000 | H87: =G86 -> 0 | I87: =IF(G87<>0,G87,-H87) -> 2000000 | J87: =-J86 -> 0 | K87: =K86 -> KAS KELUAR | L87: =L86 -> PINJAMAN LAIN AN. ARI WIBOWO
B89: =VLOOKUP(F89,BB!$A$8:$C$152,3,0) -> A01 | C89: 202601 | D89: KAS-2601004 | E89: 46031 | F89: 01.001.0000 | G89: 1700000 | H89: 0 | I89: =IF(G89<>0,G89,-H89) -> 1700000 | J89: 0 | K89: KAS MASUK | L89: PELUNASAN PINJAMAN LAIN AN. AGUS RIYANTO
B90: =VLOOKUP(F90,BB!$A$8:$C$152,3,0) -> A04A | C90: =C89 -> 202601 | D90: =D89 -> KAS-2601004 | E90: =E89 -> 46031 | F90: 04.001.0004 | G90: 0 | H90: 1350000 | I90: =IF(G90<>0,G90,-H90) -> -1350000 | J90: =-J89 -> 0 | K90: =K89 -> KAS MASUK | L90: =L89 -> PELUNASAN PINJAMAN LAIN AN. AGUS RIYANTO
B91: =VLOOKUP(F91,BB!$A$8:$C$152,3,0) -> LR01C | C91: =C90 -> 202601 | D91: =D90 -> KAS-2601004 | E91: =E90 -> 46031 | F91: 50.003.0000 | G91: 0 | H91: =G89-H90 -> 350000 | I91: =IF(G91<>0,G91,-H91) -> -350000 | J91: =-J90 -> 0 | K91: =K90 -> KAS MASUK | L91: ="PENDAPATAN ATAS PINJAMAN LAIN "&MID(L90,24,20) -> PENDAPATAN ATAS PINJAMAN LAIN AN. AGUS RIYANTO
B93: =VLOOKUP(F93,BB!$A$8:$C$152,3,0) -> A01 | C93: 202601 | D93: KAS-2601005 | E93: 46031 | F93: 01.001.0000 | G93: 0 | H93: 8000 | I93: =IF(G93<>0,G93,-H93) -> -8000 | J93: 0 | K93: KAS KELUAR | L93: ONGKIR BAJU PAK KOSA
B94: =VLOOKUP(F94,BB!$A$8:$C$152,3,0) -> LR05 | C94: =C93 -> 202601 | D94: =D93 -> KAS-2601005 | E94: =E93 -> 46031 | F94: 60.003.0200 | G94: =H93 -> 8000 | H94: =G93 -> 0 | I94: =IF(G94<>0,G94,-H94) -> 8000 | J94: =-J93 -> 0 | K94: =K93 -> KAS KELUAR | L94: =L93 -> ONGKIR BAJU PAK KOSA
B96: =VLOOKUP(F96,BB!$A$8:$C$152,3,0) -> A01 | C96: 202601 | D96: KAS-2601006 | E96: 46032 | F96: 01.001.0000 | G96: 0 | H96: 750000 | I96: =IF(G96<>0,G96,-H96) -> -750000 | J96: 0 | K96: KAS KELUAR | L96: BY REPRESENTATIF ADMIN KKCS FARID F
B97: =VLOOKUP(F97,BB!$A$8:$C$152,3,0) -> LR05 | C97: =C96 -> 202601 | D97: =D96 -> KAS-2601006 | E97: =E96 -> 46032 | F97: 60.001.0300 | G97: =H96 -> 750000 | H97: =G96 -> 0 | I97: =IF(G97<>0,G97,-H97) -> 750000 | J97: =-J96 -> 0 | K97: =K96 -> KAS KELUAR | L97: =L96 -> BY REPRESENTATIF ADMIN KKCS FARID F
B99: =VLOOKUP(F99,BB!$A$8:$C$152,3,0) -> A01 | C99: 202601 | D99: KAS-2601007 | E99: 46042 | F99: 01.001.0000 | G99: 214000 | H99: 0 | I99: =IF(G99<>0,G99,-H99) -> 214000 | J99: 0 | K99: KAS MASUK | L99: ANGSURAN PINJAMAN LAIN AN. SETYO H
B100: =VLOOKUP(F100,BB!$A$8:$C$152,3,0) -> A04A | C100: =C99 -> 202601 | D100: =D99 -> KAS-2601007 | E100: =E99 -> 46042 | F100: 04.001.0004 | G100: 0 | H100: =+G99 -> 214000 | I100: =IF(G100<>0,G100,-H100) -> -214000 | J100: =-J99 -> 0 | K100: =K99 -> KAS MASUK | L100: =L99 -> ANGSURAN PINJAMAN LAIN AN. SETYO H
B101: =VLOOKUP(F101,BB!$A$8:$C$152,3,0) -> LR01C | C101: =C100 -> 202601 | D101: =D100 -> KAS-2601007 | E101: =E100 -> 46042 | F101: 50.003.0000 | G101: 0 | H101: =G99-H100 -> 0 | I101: =IF(G101<>0,G101,-H101) -> 0 | J101: =-J100 -> 0 | K101: =K100 -> KAS MASUK | L101: ="PENDAPATAN ATAS PINJAMAN LAIN "&MID(L100,24,20) -> PENDAPATAN ATAS PINJAMAN LAIN AN. SETYO H
B103: =VLOOKUP(F103,BB!$A$8:$C$152,3,0) -> A01 | C103: 202601 | D103: KAS-2601008 | E103: 46045 | F103: 01.001.0000 | G103: 200000 | H103: 0 | I103: =IF(G103<>0,G103,-H103) -> 200000 | J103: 0 | K103: KAS MASUK | L103: ANGSURAN PINJAMAN LAIN AN. ARI WIBOWO
B104: =VLOOKUP(F104,BB!$A$8:$C$152,3,0) -> A04A | C104: =C103 -> 202601 | D104: =D103 -> KAS-2601008 | E104: =E103 -> 46045 | F104: 04.001.0004 | G104: 0 | H104: =+G103 -> 200000 | I104: =IF(G104<>0,G104,-H104) -> -200000 | J104: =-J103 -> 0 | K104: =K103 -> KAS MASUK | L104: =L103 -> ANGSURAN PINJAMAN LAIN AN. ARI WIBOWO
B105: =VLOOKUP(F105,BB!$A$8:$C$152,3,0) -> LR01C | C105: =C104 -> 202601 | D105: =D104 -> KAS-2601008 | E105: =E104 -> 46045 | F105: 50.003.0000 | G105: 0 | H105: =G103-H104 -> 0 | I105: =IF(G105<>0,G105,-H105) -> 0 | J105: =-J104 -> 0 | K105: =K104 -> KAS MASUK | L105: ="PENDAPATAN ATAS PINJAMAN LAIN "&MID(L104,24,20) -> PENDAPATAN ATAS PINJAMAN LAIN AN. ARI WIBOWO
B107: =VLOOKUP(F107,BB!$A$8:$C$152,3,0) -> A01 | C107: 202601 | D107: KAS-2601009 | E107: 46046 | F107: 01.001.0000 | G107: 267500 | H107: 0 | I107: =IF(G107<>0,G107,-H107) -> 267500 | J107: 0 | K107: KAS MASUK | L107: ANGSURAN PINJAMAN LAIN AN. HANDOKO TS
B108: =VLOOKUP(F108,BB!$A$8:$C$152,3,0) -> A04A | C108: =C107 -> 202601 | D108: =D107 -> KAS-2601009 | E108: =E107 -> 46046 | F108: 04.001.0004 | G108: 0 | H108: =+G107 -> 267500 | I108: =IF(G108<>0,G108,-H108) -> -267500 | J108: =-J107 -> 0 | K108: =K107 -> KAS MASUK | L108: =L107 -> ANGSURAN PINJAMAN LAIN AN. HANDOKO TS
B109: =VLOOKUP(F109,BB!$A$8:$C$152,3,0) -> LR01C | C109: =C108 -> 202601 | D109: =D108 -> KAS-2601009 | E109: =E108 -> 46046 | F109: 50.003.0000 | G109: 0 | H109: =G107-H108 -> 0 | I109: =IF(G109<>0,G109,-H109) -> 0 | J109: =-J108 -> 0 | K109: =K108 -> KAS MASUK | L109: ="PENDAPATAN ATAS PINJAMAN LAIN "&MID(L108,24,20) -> PENDAPATAN ATAS PINJAMAN LAIN AN. HANDOKO TS
B111: =VLOOKUP(F111,BB!$A$8:$C$152,3,0) -> A01 | C111: 202601 | D111: KAS-2601010 | E111: 46047 | F111: 01.001.0000 | G111: 321000 | H111: 0 | I111: =IF(G111<>0,G111,-H111) -> 321000 | J111: 0 | K111: KAS MASUK | L111: ANGSURAN PINJAMAN LAIN AN. BUKHORI
B112: =VLOOKUP(F112,BB!$A$8:$C$152,3,0) -> A04A | C112: =C111 -> 202601 | D112: =D111 -> KAS-2601010 | E112: =E111 -> 46047 | F112: 04.001.0004 | G112: 0 | H112: =+G111 -> 321000 | I112: =IF(G112<>0,G112,-H112) -> -321000 | J112: =-J111 -> 0 | K112: =K111 -> KAS MASUK | L112: =L111 -> ANGSURAN PINJAMAN LAIN AN. BUKHORI
B113: =VLOOKUP(F113,BB!$A$8:$C$152,3,0) -> LR01C | C113: =C112 -> 202601 | D113: =D112 -> KAS-2601010 | E113: =E112 -> 46047 | F113: 50.003.0000 | G113: 0 | H113: =G111-H112 -> 0 | I113: =IF(G113<>0,G113,-H113) -> 0 | J113: =-J112 -> 0 | K113: =K112 -> KAS MASUK | L113: ="PENDAPATAN ATAS PINJAMAN LAIN "&MID(L112,24,20) -> PENDAPATAN ATAS PINJAMAN LAIN AN. BUKHORI
B115: =VLOOKUP(F115,BB!$A$8:$C$152,3,0) -> A01 | C115: 202601 | D115: KAS-2601011 | E115: 46048 | F115: 01.001.0000 | G115: 0 | H115: 2500000 | I115: =IF(G115<>0,G115,-H115) -> -2500000 | J115: 0 | K115: KAS KELUAR | L115: PINJAMAN LAIN AN. AGUS R
B116: =VLOOKUP(F116,BB!$A$8:$C$152,3,0) -> A04A | C116: =C115 -> 202601 | D116: =D115 -> KAS-2601011 | E116: =E115 -> 46048 | F116: 04.001.0004 | G116: =H115 -> 2500000 | H116: =G115 -> 0 | I116: =IF(G116<>0,G116,-H116) -> 2500000 | J116: =-J115 -> 0 | K116: =K115 -> KAS KELUAR | L116: =L115 -> PINJAMAN LAIN AN. AGUS R
B118: =VLOOKUP(F118,BB!$A$8:$C$152,3,0) -> A01 | C118: 202601 | D118: KAS-2601012 | E118: 46050 | F118: 01.001.0000 | G118: 267500 | H118: 0 | I118: =IF(G118<>0,G118,-H118) -> 267500 | J118: 0 | K118: KAS MASUK | L118: ANGSURAN PINJAMAN LAIN AN. AGUS S
B119: =VLOOKUP(F119,BB!$A$8:$C$152,3,0) -> A04A | C119: =C118 -> 202601 | D119: =D118 -> KAS-2601012 | E119: =E118 -> 46050 | F119: 04.001.0004 | G119: 0 | H119: =+G118 -> 267500 | I119: =IF(G119<>0,G119,-H119) -> -267500 | J119: =-J118 -> 0 | K119: =K118 -> KAS MASUK | L119: =L118 -> ANGSURAN PINJAMAN LAIN AN. AGUS S
B120: =VLOOKUP(F120,BB!$A$8:$C$152,3,0) -> LR01C | C120: =C119 -> 202601 | D120: =D119 -> KAS-2601012 | E120: =E119 -> 46050 | F120: 50.003.0000 | G120: 0 | H120: =G118-H119 -> 0 | I120: =IF(G120<>0,G120,-H120) -> 0 | J120: =-J119 -> 0 | K120: =K119 -> KAS MASUK | L120: ="PENDAPATAN ATAS PINJAMAN LAIN "&MID(L119,24,20) -> PENDAPATAN ATAS PINJAMAN LAIN AN. AGUS S
B122: =VLOOKUP(F122,BB!$A$8:$C$152,3,0) -> A01 | C122: 202601 | D122: KAS-2601013 | E122: 46050 | F122: 01.001.0000 | G122: 500000 | H122: 0 | I122: =IF(G122<>0,G122,-H122) -> 500000 | J122: 0 | K122: KAS MASUK | L122: ANGSURAN PINJAMAN LAIN AN. ISFAK
B123: =VLOOKUP(F123,BB!$A$8:$C$152,3,0) -> A04A | C123: =C122 -> 202601 | D123: =D122 -> KAS-2601013 | E123: =E122 -> 46050 | F123: 04.001.0004 | G123: 0 | H123: =+G122 -> 500000 | I123: =IF(G123<>0,G123,-H123) -> -500000 | J123: =-J122 -> 0 | K123: =K122 -> KAS MASUK | L123: =L122 -> ANGSURAN PINJAMAN LAIN AN. ISFAK
B124: =VLOOKUP(F124,BB!$A$8:$C$152,3,0) -> LR01C | C124: =C123 -> 202601 | D124: =D123 -> KAS-2601013 | E124: =E123 -> 46050 | F124: 50.003.0000 | G124: 0 | H124: =G122-H123 -> 0 | I124: =IF(G124<>0,G124,-H124) -> 0 | J124: =-J123 -> 0 | K124: =K123 -> KAS MASUK | L124: ="PENDAPATAN ATAS PINJAMAN LAIN "&MID(L123,24,20) -> PENDAPATAN ATAS PINJAMAN LAIN AN. ISFAK
B126: =VLOOKUP(F126,BB!$A$8:$C$152,3,0) -> A01 | C126: 202601 | D126: KAS-2601014 | E126: 46051 | F126: 01.001.0000 | G126: 300000 | H126: 0 | I126: =IF(G126<>0,G126,-H126) -> 300000 | J126: 0 | K126: KAS MASUK | L126: ANGSURAN PINJAMAN LAIN AN. SOLICHIN
B127: =VLOOKUP(F127,BB!$A$8:$C$152,3,0) -> A04A | C127: =C126 -> 202601 | D127: =D126 -> KAS-2601014 | E127: =E126 -> 46051 | F127: 04.001.0004 | G127: 0 | H127: =+G126 -> 300000 | I127: =IF(G127<>0,G127,-H127) -> -300000 | J127: =-J126 -> 0 | K127: =K126 -> KAS MASUK | L127: =L126 -> ANGSURAN PINJAMAN LAIN AN. SOLICHIN
B128: =VLOOKUP(F128,BB!$A$8:$C$152,3,0) -> LR01C | C128: =C127 -> 202601 | D128: =D127 -> KAS-2601014 | E128: =E127 -> 46051 | F128: 50.003.0000 | G128: 0 | H128: =G126-H127 -> 0 | I128: =IF(G128<>0,G128,-H128) -> 0 | J128: =-J127 -> 0 | K128: =K127 -> KAS MASUK | L128: ="PENDAPATAN ATAS PINJAMAN LAIN "&MID(L127,24,20) -> PENDAPATAN ATAS PINJAMAN LAIN AN. SOLICHIN
B130: =VLOOKUP(F130,BB!$A$8:$C$152,3,0) -> A01 | C130: 202601 | D130: KAS-2601015 | E130: 46052 | F130: 01.001.0000 | G130: 320000 | H130: 0 | I130: =IF(G130<>0,G130,-H130) -> 320000 | J130: 0 | K130: KAS MASUK | L130: ANGSURAN PINJAMAN LAIN AN. FADELAN
B131: =VLOOKUP(F131,BB!$A$8:$C$152,3,0) -> A04A | C131: =C130 -> 202601 | D131: =D130 -> KAS-2601015 | E131: =E130 -> 46052 | F131: 04.001.0004 | G131: 0 | H131: =+G130 -> 320000 | I131: =IF(G131<>0,G131,-H131) -> -320000 | J131: =-J130 -> 0 | K131: =K130 -> KAS MASUK | L131: =L130 -> ANGSURAN PINJAMAN LAIN AN. FADELAN
B132: =VLOOKUP(F132,BB!$A$8:$C$152,3,0) -> LR01C | C132: =C131 -> 202601 | D132: =D131 -> KAS-2601015 | E132: =E131 -> 46052 | F132: 50.003.0000 | G132: 0 | H132: =G130-H131 -> 0 | I132: =IF(G132<>0,G132,-H132) -> 0 | J132: =-J131 -> 0 | K132: =K131 -> KAS MASUK | L132: ="PENDAPATAN ATAS PINJAMAN LAIN "&MID(L131,24,20) -> PENDAPATAN ATAS PINJAMAN LAIN AN. FADELAN
B134: =VLOOKUP(F134,BB!$A$8:$C$152,3,0) -> LR07 | C134: 202601 | D134: JRM-2601001 | E134: 46053 | F134: 71.000.0400 | G134: 1500000 | H134: 0 | I134: =IF(G134<>0,G134,-H134) -> 1500000 | J134: 0 | K134: JURNAL MANUAL | L134: PEMBEBANAN PENYISIHAN PIUTANG
B135: =VLOOKUP(F135,BB!$A$8:$C$152,3,0) -> A05 | C135: =C134 -> 202601 | D135: =D134 -> JRM-2601001 | E135: =E134 -> 46053 | F135: 05.000.0000 | G135: =H134 -> 0 | H135: =G134 -> 1500000 | I135: =IF(G135<>0,G135,-H135) -> -1500000 | J135: =-J134 -> 0 | K135: =K134 -> JURNAL MANUAL | L135: =L134 -> PEMBEBANAN PENYISIHAN PIUTANG
B137: =VLOOKUP(F137,BB!$A$8:$C$152,3,0) -> A04B | C137: 202601 | D137: JRM-2601002 | E137: 46053 | F137: 04.002.0003 | G137: =11760000 -> 11760000 | H137: 0 | I137: =IF(G137<>0,G137,-H137) -> 11760000 | J137: 0 | K137: JURNAL MANUAL | L137: JASA SEWA KENDARAAN MASA DES 2025
B138: =VLOOKUP(F138,BB!$A$8:$C$152,3,0) -> P05 | C138: =C137 -> 202601 | D138: =D137 -> JRM-2601002 | E138: =E137 -> 46053 | F138: 34.000.0003 | G138: =H137 -> 0 | H138: =11608500 -> 11608500 | I138: =IF(G138<>0,G138,-H138) -> -11608500 | J138: =-J137 -> 0 | K138: =K137 -> JURNAL MANUAL | L138: BIAYA SEWA KENDARAN MASA DES 2025
...

Sheet BB
F1: AKTIVA | H1: =SUMIF($B$8:$B$152,"A",$H$8:$H$152) -> 2.6993717e+09 | I1: =+H1-NR!F37 -> -2.4945402e+09 | K1: =+L1-NR!H37 -> 0 | L1: =SUMIF($B$8:$B$152,"A",$L$8:$L$152) -> 2.6961766e+09
F2: PASIVA | H2: =SUMIF($B$8:$B$152,"P",$H$8:$H$152) -> -2.6993717e+09 | I2: =+H2+NR!M37 -> 2.4945402e+09 | K2: =+L2+NR!O37 -> 74447522 | L2: =SUMIF($B$8:$B$152,"P",$L$8:$L$152) -> -2.6217291e+09 | N2: =L3+'WS Trial balance'!BO70 -> 0
F3: LR | H3: =SUMIF($B$8:$B$152,"L",$H$8:$H$152) -> 0 | K3: =+L3+NR!O30 -> 0 | L3: =SUMIF($B$8:$B$152,"L",$L$8:$L$152) -> -74447522
H4: =SUM(H1:H3) -> 0 | L4: =SUM(L1:L3) -> -7.0035458e-07 | M4: =-(K110+K111+K112+K134+K139+K140+K141+K142)*0.5% -> 3337277.6 | N4: <<-- PPH (ga berlaku) | O4: =SUM(O8:O142)*0.5% -> 74078.337
F5: SUBTOTAL | H5: =SUBTOTAL(9,H8:H152) -> -4.4703484e-07 | I5: =SUBTOTAL(9,I8:I152) -> 4.0900118e+09 | J5: =SUBTOTAL(9,J8:J152) -> 4.0900118e+09 | K5: =SUBTOTAL(9,K8:K152) -> 1.8626451e-08 | L5: =SUBTOTAL(9,L8:L152) -> -6.9662929e-07 | M5: =M4-O4 -> 3263199.3
A7: Account | E7: Report_NR | F7: Keterangan | H7: SALDO AWAL | I7: DEBET | J7: KREDIT | K7: MUTASI | L7: SALDO AKHIR
A8: 01.000.0000 | B8: A | C8: A01 | E8: Debet | F8: KAS | H8: 0 | I8: =SUMIF('MUTASI 2026'!$F$5:$F$1048576,BB!A8,'MUTASI 2026'!$G$5:$G$1048576) -> 0 | J8: =SUMIF('MUTASI 2026'!$F$5:$F$1048576,BB!A8,'MUTASI 2026'!$H$5:$H$1048576) -> 0 | K8: =I8-J8 -> 0 | L8: =+H8+K8 -> 0
A9: 01.001.0000 | B9: A | C9: A01 | E9: Debet | F9: KAS INDUK | H9: 8851508.7 | I9: =SUMIF('MUTASI 2026'!$F$5:$F$1048576,BB!A9,'MUTASI 2026'!$G$5:$G$1048576) -> 103474000 | J9: =SUMIF('MUTASI 2026'!$F$5:$F$1048576,BB!A9,'MUTASI 2026'!$H$5:$H$1048576) -> 107498092 | K9: =I9-J9 -> -4024092 | L9: =+H9+K9 -> 4827416.7 | M9: 4827416.7 | N9: =L9-M9 -> 0
A10: 01.009.0000 | B10: A | C10: A01 | E10: Debet | F10: AYAT SILANG KAS & BANK | H10: 0 | I10: =SUMIF('MUTASI 2026'!$F$5:$F$1048576,BB!A10,'MUTASI 2026'!$G$5:$G$1048576) -> 72600000 | J10: =SUMIF('MUTASI 2026'!$F$5:$F$1048576,BB!A10,'MUTASI 2026'!$H$5:$H$1048576) -> 72600000 | K10: =I10-J10 -> 0 | L10: =+H10+K10 -> 0
A11: 02.000.0000 | B11: A | C11: A02 | E11: Debet | F11: BANK | H11: 0 | I11: =SUMIF('MUTASI 2026'!$F$5:$F$1048576,BB!A11,'MUTASI 2026'!$G$5:$G$1048576) -> 0 | J11: =SUMIF('MUTASI 2026'!$F$5:$F$1048576,BB!A11,'MUTASI 2026'!$H$5:$H$1048576) -> 0 | K11: =I11-J11 -> 0 | L11: =+H11+K11 -> 0
A12: 02.001.0000 | B12: A | C12: A02 | E12: Debet | F12: BANK MANDIRI | H12: 2.3118002e+08 | I12: =SUMIF('MUTASI 2026'!$F$5:$F$1048576,BB!A12,'MUTASI 2026'!$G$5:$G$1048576) -> 1.194102e+09 | J12: =SUMIF('MUTASI 2026'!$F$5:$F$1048576,BB!A12,'MUTASI 2026'!$H$5:$H$1048576) -> 1.3001048e+09 | K12: =I12-J12 -> -1.0600285e+08 | L12: =+H12+K12 -> 1.2517717e+08 | M12: 1.2517717e+08 | N12: =L12-M12 -> -4.9173832e-07
A13: 02.002.0000 | B13: A | C13: A02 | E13: Debet | F13: BANK CENTRAL ASIA (BCA) | H13: 71776656 | I13: =SUMIF('MUTASI 2026'!$F$5:$F$1048576,BB!A13,'MUTASI 2026'!$G$5:$G$1048576) -> 0 | J13: =SUMIF('MUTASI 2026'!$F$5:$F$1048576,BB!A13,'MUTASI 2026'!$H$5:$H$1048576) -> 240000 | K13: =I13-J13 -> -240000 | L13: =+H13+K13 -> 71536656 | M13: 71536656 | N13: =L13-M13 -> 0
A14: 03.000.0000 | B14: A | C14: A03 | E14: Debet | F14: SURAT BERHARGA | H14: 0 | I14: =SUMIF('MUTASI 2026'!$F$5:$F$1048576,BB!A14,'MUTASI 2026'!$G$5:$G$1048576) -> 0 | J14: =SUMIF('MUTASI 2026'!$F$5:$F$1048576,BB!A14,'MUTASI 2026'!$H$5:$H$1048576) -> 0 | K14: =I14-J14 -> 0 | L14: =+H14+K14 -> 0
A15: 03.001.0000 | B15: A | C15: A03 | E15: Debet | F15: SIMPANAN INVESTASI | H15: 0 | I15: =SUMIF('MUTASI 2026'!$F$5:$F$1048576,BB!A15,'MUTASI 2026'!$G$5:$G$1048576) -> 0 | J15: =SUMIF('MUTASI 2026'!$F$5:$F$1048576,BB!A15,'MUTASI 2026'!$H$5:$H$1048576) -> 0 | K15: =I15-J15 -> 0 | L15: =+H15+K15 -> 0
A16: 03.002.0000 | B16: A | C16: A03 | E16: Debet | F16: DEPOSITO | H16: 0 | I16: =SUMIF('MUTASI 2026'!$F$5:$F$1048576,BB!A16,'MUTASI 2026'!$G$5:$G$1048576) -> 0 | J16: =SUMIF('MUTASI 2026'!$F$5:$F$1048576,BB!A16,'MUTASI 2026'!$H$5:$H$1048576) -> 0 | K16: =I16-J16 -> 0 | L16: =+H16+K16 -> 0
A17: 04.000.0000 | B17: A | C17: A04 | E17: Debet | F17: PIUTANG USAHA | H17: 0 | I17: =SUMIF('MUTASI 2026'!$F$5:$F$1048576,BB!A17,'MUTASI 2026'!$G$5:$G$1048576) -> 0 | J17: =SUMIF('MUTASI 2026'!$F$5:$F$1048576,BB!A17,'MUTASI 2026'!$H$5:$H$1048576) -> 0 | K17: =I17-J17 -> 0 | L17: =+H17+K17 -> 0
A18: 04.001.0000 | B18: A | C18: A04A | E18: Debet | F18: PIUTANG ANGGOTA | H18: 0 | I18: =SUMIF('MUTASI 2026'!$F$5:$F$1048576,BB!A18,'MUTASI 2026'!$G$5:$G$1048576) -> 0 | J18: =SUMIF('MUTASI 2026'!$F$5:$F$1048576,BB!A18,'MUTASI 2026'!$H$5:$H$1048576) -> 0 | K18: =I18-J18 -> 0 | L18: =+H18+K18 -> 0
A19: 04.001.0001 | B19: A | C19: A04A | E19: Debet | F19: PINJAMAN RUTIN | H19: 1.8984218e+09 | I19: =SUMIF('MUTASI 2026'!$F$5:$F$1048576,BB!A19,'MUTASI 2026'!$G$5:$G$1048576) -> 1.279e+09 | J19: =SUMIF('MUTASI 2026'!$F$5:$F$1048576,BB!A19,'MUTASI 2026'!$H$5:$H$1048576) -> 1.2235617e+09 | K19: =I19-J19 -> 55438325 | L19: =+H19+K19 -> 1.9538601e+09 | M19: 1.9538601e+09 | N19: =L19-M19 -> 0
A20: 04.001.0002 | B20: A | C20: A04A | E20: Debet | F20: PUTB | H20: 0 | I20: =SUMIF('MUTASI 2026'!$F$5:$F$1048576,BB!A20,'MUTASI 2026'!$G$5:$G$1048576) -> 0 | J20: =SUMIF('MUTASI 2026'!$F$5:$F$1048576,BB!A20,'MUTASI 2026'!$H$5:$H$1048576) -> 0 | K20: =I20-J20 -> 0 | L20: =+H20+K20 -> 0
A21: 04.001.0003 | B21: A | C21: A04A | E21: Debet | F21: PINJAMAN KHUSUS | H21: 0 | I21: =SUMIF('MUTASI 2026'!$F$5:$F$1048576,BB!A21,'MUTASI 2026'!$G$5:$G$1048576) -> 0 | J21: =SUMIF('MUTASI 2026'!$F$5:$F$1048576,BB!A21,'MUTASI 2026'!$H$5:$H$1048576) -> 0 | K21: =I21-J21 -> 0 | L21: =+H21+K21 -> 0
A22: 04.001.0004 | B22: A | C22: A04A | E22: Debet | F22: PINJAMAN UMUM | H22: 27997882 | I22: =SUMIF('MUTASI 2026'!$F$5:$F$1048576,BB!A22,'MUTASI 2026'!$G$5:$G$1048576) -> 26000000 | J22: =SUMIF('MUTASI 2026'!$F$5:$F$1048576,BB!A22,'MUTASI 2026'!$H$5:$H$1048576) -> 28855000 | K22: =I22-J22 -> -2855000 | L22: =+H22+K22 -> 25142882 | M22: 25142882 | N22: =L22-M22 -> 0
A23: 04.002.0000 | B23: A | C23: A04B | E23: Debet | F23: PIUTANG NON ANGGOTA | H23: 0 | I23: =SUMIF('MUTASI 2026'!$F$5:$F$1048576,BB!A23,'MUTASI 2026'!$G$5:$G$1048576) -> 0 | J23: =SUMIF('MUTASI 2026'!$F$5:$F$1048576,BB!A23,'MUTASI 2026'!$H$5:$H$1048576) -> 0 | K23: =I23-J23 -> 0 | L23: =+H23+K23 -> 0
A24: 04.002.0001 | B24: A | C24: A04B | E24: Debet | F24: ABABYL | H24: 560823867 | I24: =SUMIF('MUTASI 2026'!$F$5:$F$1048576,BB!A24,'MUTASI 2026'!$G$5:$G$1048576) -> 0 | J24: =SUMIF('MUTASI 2026'!$F$5:$F$1048576,BB!A24,'MUTASI 2026'!$H$5:$H$1048576) -> 0 | K24: =I24-J24 -> 0 | L24: =+H24+K24 -> 560823867
A25: 04.002.0002 | B25: A | C25: A04B | E25: Debet | F25: GCS - SIMPANAN INVESTASI | H25: 0 | I25: =SUMIF('MUTASI 2026'!$F$5:$F$1048576,BB!A25,'MUTASI 2026'!$G$5:$G$1048576) -> 0 | J25: =SUMIF('MUTASI 2026'!$F$5:$F$1048576,BB!A25,'MUTASI 2026'!$H$5:$H$1048576) -> 0 | K25: =I25-J25 -> 0 | L25: =+H25+K25 -> 0
A26: 04.002.0003 | B26: A | C26: A04B | E26: Debet | F26: GCS - SEWA MOBIL | H26: 82320000 | I26: =SUMIF('MUTASI 2026'!$F$5:$F$1048576,BB!A26,'MUTASI 2026'!$G$5:$G$1048576) -> 70560000 | J26: =SUMIF('MUTASI 2026'!$F$5:$F$1048576,BB!A26,'MUTASI 2026'!$H$5:$H$1048576) -> 47040000 | K26: =I26-J26 -> 23520000 | L26: =+H26+K26 -> 105840000 | M26: =+L26/11760000 -> 9
A27: 04.002.0004 | B27: A | C27: A04B | E27: Debet | F27: BP. AGUNG | H27: 0 | I27: =SUMIF('MUTASI 2026'!$F$5:$F$1048576,BB!A27,'MUTASI 2026'!$G$5:$G$1048576) -> 0 | J27: =SUMIF('MUTASI 2026'!$F$5:$F$1048576,BB!A27,'MUTASI 2026'!$H$5:$H$1048576) -> 0 | K27: =I27-J27 -> 0 | L27: =+H27+K27 -> 0
A28: 04.002.0005 | B28: A | C28: A04B | E28: Debet | F28: BP YANTO SEWA MOBIL | H28: 0 | I28: =SUMIF('MUTASI 2026'!$F$5:$F$1048576,BB!A28,'MUTASI 2026'!$G$5:$G$1048576) -> 0 | J28: =SUMIF('MUTASI 2026'!$F$5:$F$1048576,BB!A28,'MUTASI 2026'!$H$5:$H$1048576) -> 0 | K28: =I28-J28 -> 0 | L28: =+H28+K28 -> 0
A29: 04.002.0006 | B29: A | C29: A04B | E29: Debet | F29: GCS - SEWA FORKLIFT | H29: 0 | I29: =SUMIF('MUTASI 2026'!$F$5:$F$1048576,BB!A29,'MUTASI 2026'!$G$5:$G$1048576) -> 156800000 | J29: =SUMIF('MUTASI 2026'!$F$5:$F$1048576,BB!A29,'MUTASI 2026'!$H$5:$H$1048576) -> 125440000 | K29: =I29-J29 -> 31360000 | L29: =+H29+K29 -> 31360000 | M29: =+L29/15680000 -> 2
A30: 04.002.0007 | B30: A | C30: A04B | E30: Debet | F30: GCS - KSO SI | H30: 0 | I30: =SUMIF('MUTASI 2026'!$F$5:$F$1048576,BB!A30,'MUTASI 2026'!$G$5:$G$1048576) -> 0 | J30: =SUMIF('MUTASI 2026'!$F$5:$F$1048576,BB!A30,'MUTASI 2026'!$H$5:$H$1048576) -> 0 | K30: =I30-J30 -> 0 | L30: =+H30+K30 -> 0
A31: 04.002.0008 | B31: A | C31: A04B | E31: Debet | F31: GCS - PENGADAAN BARANG | H31: 0 | I31: =SUMIF('MUTASI 2026'!$F$5:$F$1048576,BB!A31,'MUTASI 2026'!$G$5:$G$1048576) -> 0 | J31: =SUMIF('MUTASI 2026'!$F$5:$F$1048576,BB!A31,'MUTASI 2026'!$H$5:$H$1048576) -> 0 | K31: =I31-J31 -> 0 | L31: =+H31+K31 -> 0
A32: 04.002.0009 | B32: A | C32: A04B | E32: Debet | F32: GCS - HAK TERAKHIR KOMPENSASI | H32: 0 | I32: =SUMIF('MUTASI 2026'!$F$5:$F$1048576,BB!A32,'MUTASI 2026'!$G$5:$G$1048576) -> 0 | J32: =SUMIF('MUTASI 2026'!$F$5:$F$1048576,BB!A32,'MUTASI 2026'!$H$5:$H$1048576) -> 0 | K32: =I32-J32 -> 0 | L32: =+H32+K32 -> 0
A33: 05.000.0000 | B33: A | C33: A05 | E33: Kredit | F33: CADANGAN PENGHAPUSAN PIUTANG USAHA | H33: -182000000 | I33: =SUMIF('MUTASI 2026'!$F$5:$F$1048576,BB!A33,'MUTASI 2026'!$G$5:$G$1048576) -> 0 | J33: =SUMIF('MUTASI 2026'!$F$5:$F$1048576,BB!A33,'MUTASI 2026'!$H$5:$H$1048576) -> 12000000 | K33: =I33-J33 -> -12000000 | L33: =+H33+K33 -> -194000000
A34: 06.000.0000 | B34: A | C34: A06 | E34: Debet | F34: PIUTANG LAIN-LAIN | H34: 0 | I34: =SUMIF('MUTASI 2026'!$F$5:$F$1048576,BB!A34,'MUTASI 2026'!$G$5:$G$1048576) -> 0 | J34: =SUMIF('MUTASI 2026'!$F$5:$F$1048576,BB!A34,'MUTASI 2026'!$H$5:$H$1048576) -> 0 | K34: =I34-J34 -> 0 | L34: =+H34+K34 -> 0
A35: 09.000.0000 | B35: A | C35: A07 | E35: Debet | F35: UANG MUKA PEMBELIAN | H35: 0 | I35: =SUMIF('MUTASI 2026'!$F$5:$F$1048576,BB!A35,'MUTASI 2026'!$G$5:$G$1048576) -> 0 | J35: =SUMIF('MUTASI 2026'!$F$5:$F$1048576,BB!A35,'MUTASI 2026'!$H$5:$H$1048576) -> 0 | K35: =I35-J35 -> 0 | L35: =+H35+K35 -> 0
A36: 10.000.0000 | B36: A | C36: A08 | E36: Debet | F36: BIAYA DIBAYAR DIMUKA | H36: 0 | I36: =SUMIF('MUTASI 2026'!$F$5:$F$1048576,BB!A36,'MUTASI 2026'!$G$5:$G$1048576) -> 11608500 | J36: =SUMIF('MUTASI 2026'!$F$5:$F$1048576,BB!A36,'MUTASI 2026'!$H$5:$H$1048576) -> 0 | K36: =I36-J36 -> 11608500 | L36: =+H36+K36 -> 11608500
A37: 10.000.0001 | B37: A | C37: A08 | E37: Debet | F37: SEWA FORKLIFT | H37: 0 | I37: =SUMIF('MUTASI 2026'!$F$5:$F$1048576,BB!A37,'MUTASI 2026'!$G$5:$G$1048576) -> 0 | J37: =SUMIF('MUTASI 2026'!$F$5:$F$1048576,BB!A37,'MUTASI 2026'!$H$5:$H$1048576) -> 0 | K37: =I37-J37 -> 0 | L37: =+H37+K37 -> 0
A38: 10.000.0002 | B38: A | C38: A08 | E38: Debet | F38: PENGADAAN KALENDER | H38: 0 | I38: =SUMIF('MUTASI 2026'!$F$5:$F$1048576,BB!A38,'MUTASI 2026'!$G$5:$G$1048576) -> 0 | J38: =SUMIF('MUTASI 2026'!$F$5:$F$1048576,BB!A38,'MUTASI 2026'!$H$5:$H$1048576) -> 0 | K38: =I38-J38 -> 0 | L38: =+H38+K38 -> 0
A39: 10.000.0003 | B39: A | C39: A08 | E39: Debet | F39: KSO SI | H39: 0 | I39: =SUMIF('MUTASI 2026'!$F$5:$F$1048576,BB!A39,'MUTASI 2026'!$G$5:$G$1048576) -> 0 | J39: =SUMIF('MUTASI 2026'!$F$5:$F$1048576,BB!A39,'MUTASI 2026'!$H$5:$H$1048576) -> 0 | K39: =I39-J39 -> 0 | L39: =+H39+K39 -> 0
A40: 10.000.0010 | B40: A | C40: A08 | E40: Debet | F40: LAIN-LAIN | H40: 0 | I40: =SUMIF('MUTASI 2026'!$F$5:$F$1048576,BB!A40,'MUTASI 2026'!$G$5:$G$1048576) -> 0 | J40: =SUMIF('MUTASI 2026'!$F$5:$F$1048576,BB!A40,'MUTASI 2026'!$H$5:$H$1048576) -> 0 | K40: =I40-J40 -> 0 | L40: =+H40+K40 -> 0
A41: 10.001.0000 | B41: A | C41: A09 | E41: Debet | F41: UANG MUKA KASBON BIAYA OPERASIONAL | H41: 0 | I41: =SUMIF('MUTASI 2026'!$F$5:$F$1048576,BB!A41,'MUTASI 2026'!$G$5:$G$1048576) -> 0 | J41: =SUMIF('MUTASI 2026'!$F$5:$F$1048576,BB!A41,'MUTASI 2026'!$H$5:$H$1048576) -> 0 | K41: =I41-J41 -> 0 | L41: =+H41+K41 -> 0
... A93: 34.000.0000 | B93: P | C93: P05 | E93: Kredit | F93: BIAYA YANG MASIH HARUS DIBAYAR | H93: 0 | I93: =SUMIF('MUTASI 2026'!$F$5:$F$1048576,BB!A93,'MUTASI 2026'!$G$5:$G$1048576) -> 0 | J93: =SUMIF('MUTASI 2026'!$F$5:$F$1048576,BB!A93,'MUTASI 2026'!$H$5:$H$1048576) -> 0 | K93: =I93-J93 -> 0 | L93: =+H93+K93 -> 0
A94: 34.000.0001 | B94: P | C94: P05 | E94: Kredit | F94: BYMHD FORKLIFT | H94: 0 | I94: =SUMIF('MUTASI 2026'!$F$5:$F$1048576,BB!A94,'MUTASI 2026'!$G$5:$G$1048576) -> 115800000 | J94: =SUMIF('MUTASI 2026'!$F$5:$F$1048576,BB!A94,'MUTASI 2026'!$H$5:$H$1048576) -> 144750000 | K94: =I94-J94 -> -28950000 | L94: =+H94+K94 -> -28950000 | M94: =-L94/14475000 -> 2
A95: 34.000.0002 | B95: P | C95: P05 | E95: Kredit | F95: BYMHD KSO | H95: 0 | I95: =SUMIF('MUTASI 2026'!$F$5:$F$1048576,BB!A95,'MUTASI 2026'!$G$5:$G$1048576) -> 0 | J95: =SUMIF('MUTASI 2026'!$F$5:$F$1048576,BB!A95,'MUTASI 2026'!$H$5:$H$1048576) -> 0 | K95: =I95-J95 -> 0 | L95: =+H95+K95 -> 0
A96: 34.000.0003 | B96: P | C96: P05 | E96: Kredit | F96: BYMHD ORIX | H96: 0 | I96: =SUMIF('MUTASI 2026'!$F$5:$F$1048576,BB!A96,'MUTASI 2026'!$G$5:$G$1048576) -> 69651000 | J96: =SUMIF('MUTASI 2026'!$F$5:$F$1048576,BB!A96,'MUTASI 2026'!$H$5:$H$1048576) -> 69651000 | K96: =I96-J96 -> 0 | L96: =+H96+K96 -> 0
A97: 34.000.1000 | B97: P | C97: P05 | E97: Kredit | F97: LAIN-LAIN | H97: =-93098803.8810875*0 -> 0 | I97: =SUMIF('MUTASI 2026'!$F$5:$F$1048576,BB!A97,'MUTASI 2026'!$G$5:$G$1048576) -> 0 | J97: =SUMIF('MUTASI 2026'!$F$5:$F$1048576,BB!A97,'MUTASI 2026'!$H$5:$H$1048576) -> 0 | K97: =I97-J97 -> 0 | L97: =+H97+K97 -> 0
A98: 35.000.0000 | B98: P | C98: P06 | E98: Kredit | F98: UANG MUKA JAMINAN | H98: 0 | I98: =SUMIF('MUTASI 2026'!$F$5:$F$1048576,BB!A98,'MUTASI 2026'!$G$5:$G$1048576) -> 195719913 | J98: =SUMIF('MUTASI 2026'!$F$5:$F$1048576,BB!A98,'MUTASI 2026'!$H$5:$H$1048576) -> 195719913 | K98: =I98-J98 -> 0 | L98: =+H98+K98 -> 0
A99: 36.000.0000 | B99: P | C99: P07 | E99: Kredit | F99: UTANG JANGKA PANJANG TELAH JATUH TEMPO | H99: 0 | I99: =SUMIF('MUTASI 2026'!$F$5:$F$1048576,BB!A99,'MUTASI 2026'!$G$5:$G$1048576) -> 0 | J99: =SUMIF('MUTASI 2026'!$F$5:$F$1048576,BB!A99,'MUTASI 2026'!$H$5:$H$1048576) -> 0 | K99: =I99-J99 -> 0 | L99: =+H99+K99 -> 0
A100: 37.000.0000 | B100: P | C100: P08 | E100: Kredit | F100: UTANG PAJAK TANGGUHAN | H100: 0 | I100: =SUMIF('MUTASI 2026'!$F$5:$F$1048576,BB!A100,'MUTASI 2026'!$G$5:$G$1048576) -> 0 | J100: =SUMIF('MUTASI 2026'!$F$5:$F$1048576,BB!A100,'MUTASI 2026'!$H$5:$H$1048576) -> 0 | K100: =I100-J100 -> 0 | L100: =+H100+K100 -> 0
A101: 38.000.0000 | B101: P | C101: P09 | E101: Kredit | F101: UTANG INVESTASI JANGKA PANJANG | H101: 0 | I101: =SUMIF('MUTASI 2026'!$F$5:$F$1048576,BB!A101,'MUTASI 2026'!$G$5:$G$1048576) -> 0 | J101: =SUMIF('MUTASI 2026'!$F$5:$F$1048576,BB!A101,'MUTASI 2026'!$H$5:$H$1048576) -> 0 | K101: =I101-J101 -> 0 | L101: =+H101+K101 -> 0
A102: 40.000.0000 | B102: P | C102: P10 | E102: Kredit | F102: SAHAM YANG TELAH DISETOR | H102: 0 | I102: =SUMIF('MUTASI 2026'!$F$5:$F$1048576,BB!A102,'MUTASI 2026'!$G$5:$G$1048576) -> 0 | J102: =SUMIF('MUTASI 2026'!$F$5:$F$1048576,BB!A102,'MUTASI 2026'!$H$5:$H$1048576) -> 0 | K102: =I102-J102 -> 0 | L102: =+H102+K102 -> 0
A103: 41.000.0000 | B103: P | C103: P11 | E103: Kredit | F103: SIMPANAN POKOK | H103: -7900000 | I103: =SUMIF('MUTASI 2026'!$F$5:$F$1048576,BB!A103,'MUTASI 2026'!$G$5:$G$1048576) -> 300000 | J103: =SUMIF('MUTASI 2026'!$F$5:$F$1048576,BB!A103,'MUTASI 2026'!$H$5:$H$1048576) -> 300000 | K103: =I103-J103 -> 0 | L103: =+H103+K103 -> -7900000 | M103: 7900000 | N103: =+L103+M103 -> 0
A104: 42.000.0000 | B104: P | C104: P12 | E104: Kredit | F104: SIMPANAN WAJIB | H104: -339030000 | I104: =SUMIF('MUTASI 2026'!$F$5:$F$1048576,BB!A104,'MUTASI 2026'!$G$5:$G$1048576) -> 15320000 | J104: =SUMIF('MUTASI 2026'!$F$5:$F$1048576,BB!A104,'MUTASI 2026'!$H$5:$H$1048576) -> 30900000 | K104: =I104-J104 -> -15580000 | L104: =+H104+K104 -> -354610000 | M104: 354610000 | N104: =+L104+M104 -> 0
A105: 43.000.0000 | B105: P | C105: P13 | E105: Kredit | F105: HIBAH | H105: 0 | I105: =SUMIF('MUTASI 2026'!$F$5:$F$1048576,BB!A105,'MUTASI 2026'!$G$5:$G$1048576) -> 0 | J105: =SUMIF('MUTASI 2026'!$F$5:$F$1048576,BB!A105,'MUTASI 2026'!$H$5:$H$1048576) -> 0 | K105: =I105-J105 -> 0 | L105: =+H105+K105 -> 0
A106: 44.000.0000 | B106: P | C106: P14 | E106: Kredit | F106: LABA TELAH DICADANGKAN | H106: -1.8279105e+09 | I106: =SUMIF('MUTASI 2026'!$F$5:$F$1048576,BB!A106,'MUTASI 2026'!$G$5:$G$1048576) -> 0 | J106: =SUMIF('MUTASI 2026'!$F$5:$F$1048576,BB!A106,'MUTASI 2026'!$H$5:$H$1048576) -> 63489852 | K106: =I106-J106 -> -63489852 | L106: =+H106+K106 -> -1.8914004e+09
A107: 45.000.0000 | B107: P | C107: P15 | E107: Kredit | F107: LABA BELUM DICADANGKAN | H107: =-62513192.2104664-93098803.8810875 -> -1.55612e+08 | I107: =SUMIF('MUTASI 2026'!$F$5:$F$1048576,BB!A107,'MUTASI 2026'!$G$5:$G$1048576) -> 1.55612e+08 | J107: =SUMIF('MUTASI 2026'!$F$5:$F$1048576,BB!A107,'MUTASI 2026'!$H$5:$H$1048576) -> 0 | K107: =I107-J107 -> 1.55612e+08 | L107: =+H107+K107 -> 0
A108: 46.000.0000 | B108: P | C108: P16 | E108: Kredit | F108: LABA / (RUGI) TAHUN BERJALAN | H108: 0 | I108: =SUMIF('MUTASI 2026'!$F$5:$F$1048576,BB!A108,'MUTASI 2026'!$G$5:$G$1048576) -> 0 | J108: =SUMIF('MUTASI 2026'!$F$5:$F$1048576,BB!A108,'MUTASI 2026'!$H$5:$H$1048576) -> 0 | K108: =I108-J108 -> 0 | L108: =+H108+K108 -> 0
A109: 50.000.0000 | B109: L | C109: LR01 | D109: PP | E109: Kredit | F109: PENDAPATAN | H109: 0 | I109: =SUMIF('MUTASI 2026'!$F$5:$F$1048576,BB!A109,'MUTASI 2026'!$G$5:$G$1048576) -> 0 | J109: =SUMIF('MUTASI 2026'!$F$5:$F$1048576,BB!A109,'MUTASI 2026'!$H$5:$H$1048576) -> 0 | K109: =I109-J109 -> 0 | L109: =+H109+K109 -> 0
A110: 50.001.0000 | B110: L | C110: LR01A | D110: PP | E110: Kredit | F110: PENDAPATAN PINJAMAN RUTIN | H110: 0 | I110: =SUMIF('MUTASI 2026'!$F$5:$F$1048576,BB!A110,'MUTASI 2026'!$G$5:$G$1048576) -> 0 | J110: =SUMIF('MUTASI 2026'!$F$5:$F$1048576,BB!A110,'MUTASI 2026'!$H$5:$H$1048576) -> 6.5041086e+08 | K110: =I110-J110 -> -6.5041086e+08 | L110: =+H110+K110 -> -6.5041086e+08
A111: 50.002.0000 | B111: L | C111: LR01B | D111: PP | E111: Kredit | F111: PENDAPATAN PINJAMAN KHUSUS | H111: 0 | I111: =SUMIF('MUTASI 2026'!$F$5:$F$1048576,BB!A111,'MUTASI 2026'!$G$5:$G$1048576) -> 0 | J111: =SUMIF('MUTASI 2026'!$F$5:$F$1048576,BB!A111,'MUTASI 2026'!$H$5:$H$1048576) -> 0 | K111: =I111-J111 -> 0 | L111: =+H111+K111 -> 0
A112: 50.003.0000 | B112: L | C112: LR01C | D112: PP | E112: Kredit | F112: PENDAPATAN PINJAMAN LAIN-LAIN | H112: 0 | I112: =SUMIF('MUTASI 2026'!$F$5:$F$1048576,BB!A112,'MUTASI 2026'!$G$5:$G$1048576) -> 92500 | J112: =SUMIF('MUTASI 2026'!$F$5:$F$1048576,BB!A112,'MUTASI 2026'!$H$5:$H$1048576) -> 2321500 | K112: =I112-J112 -> -2229000 | L112: =+H112+K112 -> -2229000
A113: 51.000.0000 | B113: L | C113: LR02 | D113: PP | E113: Debet | F113: BIAYA POKOK | H113: 0 | I113: =SUMIF('MUTASI 2026'!$F$5:$F$1048576,BB!A113,'MUTASI 2026'!$G$5:$G$1048576) -> 0 | J113: =SUMIF('MUTASI 2026'!$F$5:$F$1048576,BB!A113,'MUTASI 2026'!$H$5:$H$1048576) -> 0 | K113: =I113-J113 -> 0 | L113: =+H113+K113 -> 0
A114: 51.001.0000 | B114: L | C114: LR02A | D114: PP | E114: Debet | F114: BIAYA POKOK PINJAMAN RUTIN | H114: 0 | I114: =SUMIF('MUTASI 2026'!$F$5:$F$1048576,BB!A114,'MUTASI 2026'!$G$5:$G$1048576) -> 5.01345e+08 | J114: =SUMIF('MUTASI 2026'!$F$5:$F$1048576,BB!A114,'MUTASI 2026'!$H$5:$H$1048576) -> 0 | K114: =I114-J114 -> 5.01345e+08 | L114: =+H114+K114 -> 5.01345e+08
A115: 51.002.0000 | B115: L | C115: LR02B | D115: PP | E115: Debet | F115: BIAYA POKOK PINJAMAN KHUSUS | H115: 0 | I115: =SUMIF('MUTASI 2026'!$F$5:$F$1048576,BB!A115,'MUTASI 2026'!$G$5:$G$1048576) -> 0 | J115: =SUMIF('MUTASI 2026'!$F$5:$F$1048576,BB!A115,'MUTASI 2026'!$H$5:$H$1048576) -> 0 | K115: =I115-J115 -> 0 | L115: =+H115+K115 -> 0
A116: 51.003.0000 | B116: L | C116: LR02C | D116: PP | E116: Debet | F116: BIAYA POKOK PINJAMAN LAIN-LAIN | H116: 0 | I116: =SUMIF('MUTASI 2026'!$F$5:$F$1048576,BB!A116,'MUTASI 2026'!$G$5:$G$1048576) -> 0 | J116: =SUMIF('MUTASI 2026'!$F$5:$F$1048576,BB!A116,'MUTASI 2026'!$H$5:$H$1048576) -> 0 | K116: =I116-J116 -> 0 | L116: =+H116+K116 -> 0
A117: 60.000.0000 | B117: L | C117: LR05 | D117: BO | E117: Debet | F117: BIAYA UMUM DAN ADMINISTRASI | H117: 0 | I117: =SUMIF('MUTASI 2026'!$F$5:$F$1048576,BB!A117,'MUTASI 2026'!$G$5:$G$1048576) -> 0 | J117: =SUMIF('MUTASI 2026'!$F$5:$F$1048576,BB!A117,'MUTASI 2026'!$H$5:$H$1048576) -> 0 | K117: =I117-J117 -> 0 | L117: =+H117+K117 -> 0
A118: 60.001.0000 | B118: L | C118: LR05 | D118: BO | E118: Debet | F118: BIAYA PEGAWAI | H118: 0 | I118: =SUMIF('MUTASI 2026'!$F$5:$F$1048576,BB!A118,'MUTASI 2026'!$G$5:$G$1048576) -> 0 | J118: =SUMIF('MUTASI 2026'!$F$5:$F$1048576,BB!A118,'MUTASI 2026'!$H$5:$H$1048576) -> 0 | K118: =I118-J118 -> 0 | L118: =+H118+K118 -> 0
A119: 60.001.0100 | B119: L | C119: LR05 | D119: BO | E119: Debet | F119: BIAYA GAJI | H119: 0 | I119: =SUMIF('MUTASI 2026'!$F$5:$F$1048576,BB!A119,'MUTASI 2026'!$G$5:$G$1048576) -> 0 | J119: =SUMIF('MUTASI 2026'!$F$5:$F$1048576,BB!A119,'MUTASI 2026'!$H$5:$H$1048576) -> 0 | K119: =I119-J119 -> 0 | L119: =+H119+K119 -> 0
A120: 60.001.0200 | B120: L | C120: LR05 | D120: BO | E120: Debet | F120: BIAYA INSENTIF | H120: 0 | I120: =SUMIF('MUTASI 2026'!$F$5:$F$1048576,BB!A120,'MUTASI 2026'!$G$5:$G$1048576) -> 0 | J120: =SUMIF('MUTASI 2026'!$F$5:$F$1048576,BB!A120,'MUTASI 2026'!$H$5:$H$1048576) -> 0 | K120: =I120-J120 -> 0 | L120: =+H120+K120 -> 0
... A133: 70.000.0100 | B133: L | C133: LR06 | D133: PL | E133: Kredit | F133: PENJUALAN LELANG | H133: 0 | I133: =SUMIF('MUTASI 2026'!$F$5:$F$1048576,BB!A133,'MUTASI 2026'!$G$5:$G$1048576) -> 0 | J133: =SUMIF('MUTASI 2026'!$F$5:$F$1048576,BB!A133,'MUTASI 2026'!$H$5:$H$1048576) -> 0 | K133: =I133-J133 -> 0 | L133: =+H133+K133 -> 0
A134: 70.000.0200 | B134: L | C134: LR06 | D134: PL | E134: Kredit | F134: PENJUALAN BARANG BEKAS | H134: 0 | I134: =SUMIF('MUTASI 2026'!$F$5:$F$1048576,BB!A134,'MUTASI 2026'!$G$5:$G$1048576) -> 0 | J134: =SUMIF('MUTASI 2026'!$F$5:$F$1048576,BB!A134,'MUTASI 2026'!$H$5:$H$1048576) -> 0 | K134: =I134-J134 -> 0 | L134: =+H134+K134 -> 0 | O134: =-K134 -> 0
A135: 70.000.0300 | B135: L | C135: LR06 | D135: PL | E135: Kredit | F135: PENDAPATAN JASA GIRO | H135: 0 | I135: =SUMIF('MUTASI 2026'!$F$5:$F$1048576,BB!A135,'MUTASI 2026'!$G$5:$G$1048576) -> 0 | J135: =SUMIF('MUTASI 2026'!$F$5:$F$1048576,BB!A135,'MUTASI 2026'!$H$5:$H$1048576) -> 0 | K135: =I135-J135 -> 0 | L135: =+H135+K135 -> 0
A136: 70.000.0400 | B136: L | C136: LR06 | D136: PL | E136: Kredit | F136: PENDAPATAN BUNGA DEPOSITO | H136: 0 | I136: =SUMIF('MUTASI 2026'!$F$5:$F$1048576,BB!A136,'MUTASI 2026'!$G$5:$G$1048576) -> 0 | J136: =SUMIF('MUTASI 2026'!$F$5:$F$1048576,BB!A136,'MUTASI 2026'!$H$5:$H$1048576) -> 0 | K136: =I136-J136 -> 0 | L136: =+H136+K136 -> 0
A137: 70.000.0500 | B137: L | C137: LR06 | D137: PL | E137: Kredit | F137: PENDAPATAN ADM SIMPANAN INVESTASI | H137: 0 | I137: =SUMIF('MUTASI 2026'!$F$5:$F$1048576,BB!A137,'MUTASI 2026'!$G$5:$G$1048576) -> 0 | J137: =SUMIF('MUTASI 2026'!$F$5:$F$1048576,BB!A137,'MUTASI 2026'!$H$5:$H$1048576) -> 0 | K137: =I137-J137 -> 0 | L137: =+H137+K137 -> 0
A138: 70.000.0600 | B138: L | C138: LR06 | D138: PL | E138: Kredit | F138: PENDAPATAN SIMPANAN INVESTASI | H138: 0 | I138: =SUMIF('MUTASI 2026'!$F$5:$F$1048576,BB!A138,'MUTASI 2026'!$G$5:$G$1048576) -> 0 | J138: =SUMIF('MUTASI 2026'!$F$5:$F$1048576,BB!A138,'MUTASI 2026'!$H$5:$H$1048576) -> 0 | K138: =I138-J138 -> 0 | L138: =+H138+K138 -> 0
A139: 70.000.0700 | B139: L | C139: LR06 | D139: PL | E139: Kredit | F139: PENDAPATAN SEWA KENDARAAN | H139: 0 | I139: =SUMIF('MUTASI 2026'!$F$5:$F$1048576,BB!A139,'MUTASI 2026'!$G$5:$G$1048576) -> 0 | J139: =SUMIF('MUTASI 2026'!$F$5:$F$1048576,BB!A139,'MUTASI 2026'!$H$5:$H$1048576) -> 909000 | K139: =I139-J139 -> -909000 | L139: =+H139+K139 -> -909000 | O139: =-K139 -> 909000
A140: 70.000.0800 | B140: L | C140: LR06 | D140: PL | E140: Kredit | F140: PENDAPATAN SEWA FORKLIFT | H140: 0 | I140: =SUMIF('MUTASI 2026'!$F$5:$F$1048576,BB!A140,'MUTASI 2026'!$G$5:$G$1048576) -> 0 | J140: =SUMIF('MUTASI 2026'!$F$5:$F$1048576,BB!A140,'MUTASI 2026'!$H$5:$H$1048576) -> 12050000 | K140: =I140-J140 -> -12050000 | L140: =+H140+K140 -> -12050000 | O140: =-K140 -> 12050000
A141: 70.000.0900 | B141: L | C141: LR06 | D141: PL | E141: Kredit | F141: PENDAPATAN PENGADAAN BARANG | H141: 0 | I141: =SUMIF('MUTASI 2026'!$F$5:$F$1048576,BB!A141,'MUTASI 2026'!$G$5:$G$1048576) -> 0 | J141: =SUMIF('MUTASI 2026'!$F$5:$F$1048576,BB!A141,'MUTASI 2026'!$H$5:$H$1048576) -> 0 | K141: =I141-J141 -> 0 | L141: =+H141+K141 -> 0 | O141: =-K141 -> 0
A142: 70.000.1000 | B142: L | C142: LR06 | D142: PL | E142: Kredit | F142: PENDAPATAN DILUAR USAHA LAINNYA | H142: 0 | I142: =SUMIF('MUTASI 2026'!$F$5:$F$1048576,BB!A142,'MUTASI 2026'!$G$5:$G$1048576) -> 0 | J142: =SUMIF('MUTASI 2026'!$F$5:$F$1048576,BB!A142,'MUTASI 2026'!$H$5:$H$1048576) -> 1856667.3 | K142: =I142-J142 -> -1856667.3 | L142: =+H142+K142 -> -1856667.3 | O142: =-K142 -> 1856667.3
A143: 70.000.1001 | B143: L | C143: LR06 | D143: PL | E143: Kredit | F143: KSO SI | H143: 0 | I143: =SUMIF('MUTASI 2026'!$F$5:$F$1048576,BB!A143,'MUTASI 2026'!$G$5:$G$1048576) -> 0 | J143: =SUMIF('MUTASI 2026'!$F$5:$F$1048576,BB!A143,'MUTASI 2026'!$H$5:$H$1048576) -> 0 | K143: =I143-J143 -> 0 | L143: =+H143+K143 -> 0
A144: 71.000.0000 | B144: L | C144: LR07 | D144: PL | E144: Debet | F144: BIAYA DILUAR USAHA | H144: 0 | I144: =SUMIF('MUTASI 2026'!$F$5:$F$1048576,BB!A144,'MUTASI 2026'!$G$5:$G$1048576) -> 0 | J144: =SUMIF('MUTASI 2026'!$F$5:$F$1048576,BB!A144,'MUTASI 2026'!$H$5:$H$1048576) -> 0 | K144: =I144-J144 -> 0 | L144: =+H144+K144 -> 0
A145: 71.000.0100 | B145: L | C145: LR07 | D145: PL | E145: Debet | F145: BIAYA LELANG | H145: 0 | I145: =SUMIF('MUTASI 2026'!$F$5:$F$1048576,BB!A145,'MUTASI 2026'!$G$5:$G$1048576) -> 0 | J145: =SUMIF('MUTASI 2026'!$F$5:$F$1048576,BB!A145,'MUTASI 2026'!$H$5:$H$1048576) -> 0 | K145: =I145-J145 -> 0 | L145: =+H145+K145 -> 0
A146: 71.000.0200 | B146: L | C146: LR07 | D146: PL | E146: Debet | F146: BIAYA BUNGA | H146: 0 | I146: =SUMIF('MUTASI 2026'!$F$5:$F$1048576,BB!A146,'MUTASI 2026'!$G$5:$G$1048576) -> 0 | J146: =SUMIF('MUTASI 2026'!$F$5:$F$1048576,BB!A146,'MUTASI 2026'!$H$5:$H$1048576) -> 0 | K146: =I146-J146 -> 0 | L146: =+H146+K146 -> 0
A147: 71.000.0300 | B147: L | C147: LR07 | D147: PL | E147: Debet | F147: BIAYA KLIRING, TRANSFER, ADM BANK | H147: 0 | I147: =SUMIF('MUTASI 2026'!$F$5:$F$1048576,BB!A147,'MUTASI 2026'!$G$5:$G$1048576) -> 528776.91 | J147: =SUMIF('MUTASI 2026'!$F$5:$F$1048576,BB!A147,'MUTASI 2026'!$H$5:$H$1048576) -> 313384.5 | K147: =I147-J147 -> 215392.41 | L147: =+H147+K147 -> 215392.41
A148: 71.000.0400 | B148: L | C148: LR07 | D148: BC | E148: Debet | F148: BIAYA PENYISIHAN PIUTANG | H148: 0 | I148: =SUMIF('MUTASI 2026'!$F$5:$F$1048576,BB!A148,'MUTASI 2026'!$G$5:$G$1048576) -> 12000000 | J148: =SUMIF('MUTASI 2026'!$F$5:$F$1048576,BB!A148,'MUTASI 2026'!$H$5:$H$1048576) -> 0 | K148: =I148-J148 -> 12000000 | L148: =+H148+K148 -> 12000000
A149: 71.000.0900 | B149: L | C149: LR07 | D149: PL | E149: Debet | F149: BIAYA DILUAR USAHA LAINNYA | H149: 0 | I149: =SUMIF('MUTASI 2026'!$F$5:$F$1048576,BB!A149,'MUTASI 2026'!$G$5:$G$1048576) -> 13.666666 | J149: =SUMIF('MUTASI 2026'!$F$5:$F$1048576,BB!A149,'MUTASI 2026'!$H$5:$H$1048576) -> 0 | K149: =I149-J149 -> 13.666666 | L149: =+H149+K149 -> 13.666666
A150: 80.000.0000 | B150: L | C150: LR08 | D150: PJ | E150: Debet | F150: BEBAN PAJAK PENGHASILAN | H150: 0 | I150: =SUMIF('MUTASI 2026'!$F$5:$F$1048576,BB!A150,'MUTASI 2026'!$G$5:$G$1048576) -> 0 | J150: =SUMIF('MUTASI 2026'!$F$5:$F$1048576,BB!A150,'MUTASI 2026'!$H$5:$H$1048576) -> 0 | K150: =I150-J150 -> 0 | L150: =+H150+K150 -> 0
A151: 80.000.0001 | B151: L | C151: LR08 | D151: PJ | E151: Debet | F151: BEBAN PAJAK TAHUN BERJALAN | H151: 0 | I151: =SUMIF('MUTASI 2026'!$F$5:$F$1048576,BB!A151,'MUTASI 2026'!$G$5:$G$1048576) -> 0 | J151: =SUMIF('MUTASI 2026'!$F$5:$F$1048576,BB!A151,'MUTASI 2026'!$H$5:$H$1048576) -> 0 | K151: =I151-J151 -> 0 | L151: =+H151+K151 -> 0
A152: 80.000.0002 | B152: L | C152: LR08 | D152: PJ | E152: Debet | F152: BEBAN PAJAK TANGGUHAN | H152: 0 | I152: =SUMIF('MUTASI 2026'!$F$5:$F$1048576,BB!A152,'MUTASI 2026'!$G$5:$G$1048576) -> 0 | J152: =SUMIF('MUTASI 2026'!$F$5:$F$1048576,BB!A152,'MUTASI 2026'!$H$5:$H$1048576) -> 0 | K152: =I152-J152 -> 0 | L152: =+H152+K152 -> 0
